{"id": "2023_EN_X_133_TENDER", "chunk_id": "0", "input_tokens": 2289, "refiner_input_tokens": 0, "total_output_tokens": 253, "text": "cl splosna bolnisnica celje oblakova ulica 5 3000 celje tel (03) 42 33 000 fax (03) 42 33 757 postopek n 133 2023 sm/ms povabilo k oddaji ponudbe predmet evidencnega narocila odprava pomanjkljivosti na dizel agregatih fg wilson poz. 1 agregat 1 model fg wilson p1000p1 letnik 2008 predvidena dela rezervni del kolicina kom vzroka zamakanja 1. | zamenjava zagonskih baterij najmanj enakovredno!! 2 kos 225 ah (c20) tab motion pasted 2. | zamenjava cevi grelca ht s silikonskimi 1 kpl 3 ; pregled izpusnega sistema in ugotovitev 1kpl poz 2 agregat 2 model fg wilson (caterpillar) p1000p1 letnik 2016 predvidena dela rezervni del kolicina kom zamenjava zagonskih baterij najmanj 225 ah (c20) enakovredno!! tab motion pasted 2 kos obrazec predracuna servisna storitev kolicina | cena na enoto | skupaj brez ddv brez ddv 1 predvidena dela agregat 1 1 781 68 781 68 model fg wilson p1000p1 letnik 2008 2 predvidena dela agregat 2 1 605 16 605 16 model fg wilson (caterpillar) p1000p1 letnik 2016 3 skupne delovne ure (poz 1 +2) 16 00 42 00 672 00 4 kilometrina stroski 1 00 162 40 162 40 prin$sis cos skupaj brez ddv 2221 24 \"meje prj6abzn skupaj z ddv 2709 92 narocnik splosna bolnisnica celje 2 zahteve e obvezna priloga veljavna listina certifikat s katero ponudnik izkazuje da je pooblascen zastopnik serviser za dizel agregate proizvajalca fg wilson v ponudbi morajo biti zajeti vsi stroski na obeh agregatih. e ponudnik mora zagotavljati originalne rezervne dele. opomba e v kolikor je za pripravo ponudbe potrebno lahko narocnik po predhodnem dogovoru doloci termin in izvede ogled postrojenja. e dela se izvedejo v terminih ki jih doloci narocnik. skrajni rok izvedbe 11. 05. 2023 e ponudba mora vsebovati vse stroske materiala dela (mozna izvedba del izven rednega delovnega casa) potne stroske popuste rabate in davek na dodano vrednost. narocnik se zavezuje naroceno ter dobavljeno blago placati v roku 60 dni od datuma uradnega prejema racuna oziroma v roku skladno z veljavno zakonodajo. merilo za izbor najnizja vrednost ponudbe v eur z ddv ob izpolnjevanju tehnicnih zahtev narocnika. kontaktni oseba s strani narocnika ; mag. matej sinko splosna bolnisnica celje elektro delavnica in medicinski plini e matej.sinko sb celje.si m 041/245 823 stane mulej dipl.ekon. sluzba za nabavo nemedicinske opreme m 041/765 324 ponudbe posljite na naslov elektronske poste nabava2(2sb celje.si z oznako n 133 2023 do najkasneje 24. 04. 2023 do 12 ure. vodja nabavne sluzbe matjaz stinek univ.dipl.ekon. $1s soo as yeni postopek ms/ms", "ner": [{"TenderOrg": "splosna bolnisnica celje"}, {"TenderTel": "(03) 42 33 000"}, {"TenderFax": "(03) 42 33 757"}, {"TenderNumber": "133"}, {"TenderYear": "2023"}, {"TenderCode": "sm/ms"}, {"TenderType": "x"}, {"TenderDeadline": "11.05.2023"}, {"TenderPerson": "matej sinko"}, {"TenderPerson": "stane mulej"}, {"TenderDeadline": "24.04.2023"}, {"TenderPerson": "matjaz stinek"}], "ner_refine": []}
{"id": "2023_EN_X_209_TENDER", "chunk_id": "0", "input_tokens": 2199, "refiner_input_tokens": 0, "total_output_tokens": 194, "text": "ci splosna bolnisnica celje oblakova ulica 5 3000 celje tel (03) 42 33 000 fax (03) 42 33 757 postopek n 209 2023 sm/ms povabilo k oddaji ponudbe predmet evidencnega narocila nabava in montaza nadomestne potopne crpalke za fekalije . kot npr. drg 750/4/150 noft ts (zenit) tehnicne zahteve potopne crpalke za fekalije delovna napetost 400v 50hz nazivna moc min 5 50kw izvedba trofazna vrtljaji najmanj 1400 1/min v isina crpanja najmanj 14m minimalna kolicina crpanja 290 m3/h razred izolacije h prikljucki sesanje/praznjenje dn 150 stopnja zascite ip ip 68 garancija 12 mesecev ostale zahteve splosne zahteve predmeta 1. osnova za realizacijo dobave je prejem pisnega narocila strani narocnika. ponudbe zbiramo informativno za predlozitev v presojo odobritve. v kolikor bomo prejeli odobritev s strani pristojnih bomo realizacijo izvedli pri najugodnejsemu ponudniku ki bo izpolnjeval tehnicne zahteve. 2. demontaza obstojece in montaza nove crpalke se vrsi v crpaliscu fekalij (glazija) 3. ponudnik mora imeti dokazilo da je pooblascen serviser za dobavljeno crpalko. 4. v kolikor je za pripravo ponudbe potrebno lahko narocnik po predhodnem dogovoru doloci termin in izvede ogled crpalisca glazija. zbirno mesto za odhod na lokacijo objekta je sluzba za nabavo nemedicinske opreme. kontaktna oseba narocnika za ogled je g. matej sinko narocnik splosna bolnisnica celje 2 5. izvajalec mora pred izvedbo zacetka del podati narocniku okvirni nacrt popisa del z casovnim obsegom. terminski nacrt se posreduje kontaktni osebi narocnika. 6. izvajalec je dolzan odstraniti vso odpadno embalazo na lastne stroske. narocnik nima nobenih stroskov odvoza unicenja ali drugih stroskov. narocnik se zavezuje naroceno ter dobavljeno blago placati v roku kot ga doloca veljavna zakonodaja. pogoj za placilo racuna je uspesna primopredaja izvedenih del ki vkljucuje s strani narocnika podpisano porocilo izvajalca o izvedenem obsegu del v obliki delovnega naloga z natancnim opisom izvedenih storitev in zamenjavi materiala. pristojna oseba narocnika za podpis je mag. matej sinko ponudba mora vsebovati vse stroske popuste rabate in davek na dodano vrednost. narocnik se zavezuje naroceno ter dobavljeno blago placati v roku 60 dni od datuma uradnega prejema racuna oziroma v roku skladno z veljavno zakonodajo. merilo za izbor najnizja vrednost ponudbe v eur z ddv ob izpolnjevanju tehnicnih zahtev narocnika. kontaktni osebi s strani narocnika ; splosna bolnisnica celje mag.matej sinko elektro delavnica in medicinski plini e matej.sinko sb celje.si 041/245 823", "ner": [{"TenderOrg": "splosna bolnisnica celje"}, {"TenderTel": "(03) 42 33 000"}, {"TenderFax": "(03) 42 33 757"}, {"TenderNumber": "209"}, {"TenderYear": "2023"}, {"TenderCode": "sm/ms"}, {"TenderType": "x"}, {"TenderPerson": "matej sinko"}, {"TenderTel": "041/245 823"}], "ner_refine": []}
{"id": "2023_EN_X_209_TENDER", "chunk_id": "1", "input_tokens": 1853, "refiner_input_tokens": 0, "total_output_tokens": 161, "text": "mulej stane sluzba za nabavo nemedicinskega materiala e stane.mulej sb celje.si 041/765 324 ponudbe posljite na naslov elektronske poste nabava2 sb celje.si z oznako n 209 2023 nabava in montaza nadomestne potopne crpalke za fekalije do najkasneje 07.08. 2023 do 12 ure. vodja sluzbe za nabavo nemedicinske materiala opreme in storitev matjaz stinek univ.dipl.ekon postopek ms/ms narocnik splosna bolnisnica celje 3 obr 1 obrazec predracuna ponudnik v postopku oddaje obrazec predracuna dobava in montaza potopne crpalke v obsegu kot izhaja v nadaljevanju demontaza ter odklop obstojece crpalke v crpaliscu (glazija) dobava ustrezne nove crpalke (skladne z tehnicnimi zahtevami) montaza in priklop nove crpalke v crpaliscu (glazija) funkcionalni zagon crpalke izvedba meritev. testiranje funkcioniranja celotnega sistema avtomatskega preklopa delovanja po priklopu nove crpalke v sistem. izdaja potrdila o pravilnosti delovanja sistema. oo rona skupaj vrednost ponudbe v eur z ddv ponudbena vrednost je pripravljena po sistemu na kljuc. koncna ponudbena cena mora vkljucevati vse elemente iz katerih je sestavljena in mora vkljucevati vse stroske (zavarovanje dostave..) davke in morebitne popuste tako da narocnika ne bremenijo kakrsnikoli dodatni stroski. pri izracunu ponudbene vrednosti morajo ponudniki upostevati vse elemente ki vplivajo na izracun cene dobavo dostavo demontazo in montazo opreme opravljanje storitev vse potne stroske. obvezne priloge k ponudbi 1. izjava ponudnika storitve da je pooblascen serviser za crpalko ki je predmet ponudbe 2. tehnicna dokumentacija ki je predmet ponudbe 3. garancijska izjava. datum zig in podpis ponudnika postopek ms/ms", "ner": [{"TenderPerson": "mulej stane"}, {"TenderOrg": "sluzba za nabavo nemedicinskega materiala"}, {"TenderNumber": "209"}, {"TenderYear": "2023"}, {"TenderDeadline": "07.08.2023"}, {"TenderPerson": "matjaz stinek"}], "ner_refine": []}
{"id": "2023_EN_X_119_TENDER", "chunk_id": "0", "input_tokens": 1840, "refiner_input_tokens": 0, "total_output_tokens": 255, "text": "splosna bolnisnica celje oblakova ulica 5 3000 celje tel (03) 42 33 000 fax (03) 42 33 757 postopek n 119 2023 kt/ms povabilo k oddaji ponudbe vabimo vas k oddaji ponudbe za storitev odprava ugotovljenih pomanjkljivosti v transformatorskih postajah proizvajalec obstojece opreme je schneider electric k ponudbi je potrebno priloziti dokumentacijo s katero se dokazuje ustreznost izvajalca za izvedbo del. izvajalec mora biti certificiran schneider electric partner. vec podatkov je v popisu materialov in del v prilogi 1. osnova za realizacijo storitve je prejem pisnega narocila strani narocnika. ponudbe zbiramo informativno za predlozitev v presojo odobritve. v kolikor bomo prejeli odobritev s strani pristojnih bomo realizacijo izvedli pri najugodnejsemu ponudniku. cena mora vsebovati vse stroske popuste rabate in davek na dodano vrednost. kolicine v povprasevanju so okvirne. narocnik bo storitve narocal na osnovi dejanskih potreb. narocnik se zavezuje naroceno ter dobavljeno blago placati v roku 60 dni od datuma uradnega prejema racuna oziroma v roku skladno z veljavno zakonodajo. merilo za izbora najnizja vrednost ponudbe v eur z ddv ob izpolnjevanju tehnicnih zahtev narocnika. kontaktna oseba s strani narocnika mag. matej sinko telefon 041 245 823 elektronska posta matej.sinko(0 sb celje.si ponudbe posljite na naslov elektronske poste nabava2 sb celje.si z oznako n 119 odprava ugotovljenih pomanjkljivosti v transformatorskih postajah 2023 do najkasneje 31.3.2023 do 12 ure. pripravila klavdija trunkl vodja nabavne sluzbe matjaz stinek univ. dipl. ekon.", "ner": [{"TenderOrg": "splosna bolnisnica celje"}, {"TenderTel": "(03) 42 33 000"}, {"TenderFax": "(03) 42 33 757"}, {"TenderType": "x"}, {"TenderNumber": "119"}, {"TenderYear": "2023"}, {"TenderCode": "kt/ms"}, {"TenderDeadline": "31.03.2023"}, {"TenderPerson": "matej sinko"}, {"TenderPerson": "klavdija trunkl"}, {"TenderPerson": "matjaz stinek"}, {"TenderTel": "041 245 823"}], "ner_refine": []}
{"id": "2023_EN_X_122_TENDER", "chunk_id": "0", "input_tokens": 1986, "refiner_input_tokens": 0, "total_output_tokens": 235, "text": "splosna bolnisnica celje oblakova ulica 5 3000 celje tel (03) 42 33.000 fax (08) 42 33.757 postopek n 122 2023 ms povabilo k oddajt ponudbe vabimo vas k oddaji ponudbe za predmet izvedba delavnic vescina vodenja. ponudbena cena naj vkljucuje e izvedbo delavnic na katerem bodo udelezenci pridobili potrebne kompetence za vodenje in sicer psihologija vodenja vloga vodje in stili vodenja komunikacija vodje konstruktivno resevanje konfliktov ter prepoznava razlicnosti sodelavcev dajanje in prejemanje ucinkovitih povratnih informacij ter motiviranje e predavatelj ki ima reference z izkusnjami na podrocju mehkih vescin e prilozi naj reference svojega delovanja zadnjih petih let izvedba delavnic na temo vodenja e izvajanje usposabljanja na narocnikovi lokaciji za 3 skupine (10 udelezencev) po 4 module (6 pedagoskih ur) e termin izvedbe pomlad in jesen 2023 za tocen datum se narocnik in ponudnik dogovorita po oddaji narocila e izvedbo priprav za delavnice vse materialne stroske izvajalca ter posredovanje gradiva in potrdil v elektronski obliki e izdajo potrdil o uspesno opravljenem usposabljanju. narocnik bo zagotovil e ustrezno opremljeno predavalnico za izvedbo usposabljanja v prostorih narocnika e malico in napitke za vse udelezence usposabljanja in predavatelja e notranjo organizacijo usposabljanja z obvescanjem udelezencev. cena mora vsebovati vse stroske popuste rabate in davek na dodano vrednost. narocnik se zavezuje naroceno ter dobavljeno blago placati v roku 60 dni od datuma uradnega prejema racuna oziroma v roku skladno z veljavno zakonodajo. merilo za izbor najnizja vrednost ponudbe v eur brez ddv ob izpolnjevanju tehnicnih zahtev narocnika. kontaktna oseba s strani narocnika jasna erzen tel. 03 423 30 55 e mail jasna.erzen sb celje.si ponudbe posljite na naslov elektronske poste nabava2 sb celje.si z oznako n 122 2023 izvedba delavnic vescina vodenja . do najkasneje 31.08.2023 do 12 ure. vodja nabavne sluzbe matjaz stinek univ.dipl.ekon", "ner": [{"TenderOrg": "splosna bolnisnica celje"}, {"TenderTel": "(03) 42 33.000"}, {"TenderFax": "(08) 42 33.757"}, {"TenderType": "x"}, {"TenderNumber": "122"}, {"TenderYear": "2023"}, {"TenderCode": "ms"}, {"TenderPerson": "jasna erzen"}, {"TenderTel": "03 423 30 55"}, {"TenderDeadline": "31.08.2023"}, {"TenderPerson": "matjaz stinek"}], "ner_refine": []}
{"id": "2023_EN_X_179_TENDER", "chunk_id": "0", "input_tokens": 2160, "refiner_input_tokens": 0, "total_output_tokens": 182, "text": "2 oblakova ulica 5 3000 celje tel (03) 42 33 000 postopek 2023 sm/ms n 179 povabilo k oddaji ponudbe predmet evidencnega narocila ciscenje kuhinjskega prezracevalnega sistema v predvidenem obsegu kot izhaja v nadaljevanju splosne zahteve predmeta osnova za realizacijo dobave je prejem pisnega narocila strani narocnika. ponudbe zbiramo informativno za predlozitev v presojo odobritve. v kolikor bomo prejeli odobritev s strani pristojnih bomo realizacijo izvedli pri najugodnejsemu ponudniku ki bo izpolnjeval tehnicne zahteve. ponudnik mora imeti za izvajanje del veljavni certifikat haccap. v kolikor je za pripravo ponudbe potrebno lahko narocnik po predhodnem dogovoru doloci termin in izvede ogled prezracevalnega sistema. narocnik omogoca ponudniku ogled prezracevalnega sistema ki je predmet vzdrzevanja. ogled se omogoci dne 06.06. 2023 ob 8 uri. zbirno mesto za odhod na lokacijo objekta je sluzba za nabavo nemedicinske opreme. kontaktna oseba narocnika za ogled je mulej stane izvajalec mora pred izvedbo zacetka del podati narocniku okvirni nacrt popisa del z casovnim obsegom. termin izvedbe del se uskladil z narocnikom in uposteval zahteve glede njegovega procesa dela. dela se lahko izvajajo med 20 00 in 05 00 vse dni v tednu. terminski nacrt se posreduje kontaktni osebi narocnika. delovno okolje mora po izvedbi del ostati cisto. izvajalec je dolzan odstraniti vso odpadno embalazo na lastne stroske in izvesti prvo grobo ciscenje. narocnik nima nobenih stroskov odvoza unicenja ali drugih stroskov. ciscenje ter odstranitev je potrebno izvesti po vsakokratnem zakljucku del. izvajalec mora predloziti terminski nacrt za izvedbo del v roku najkasneje 7 dni od prejema pisnega narocila s strani narocnika. pri pripravi terminskega nacrta naj se uposteva da je maksimalni dopustni rok za izvedbo del 5 delovnih dni. po zakljucku izvedenih del je potrebno predloziti potrdilo o opravljenem ciscenju in dezinfekciji prezracevalnega sistema. varnostne liste za uporabljena cistila in dezinfekcijska sredstva. predlozitev slikovnega materiala. (zap. st.15 obr. predracuna) ponudba mora veljati tri mesece od poteka roka za oddajo ponudbe. narocnik se zavezuje naroceno ter dobavljeno blago placati v roku kot ga doloca veljavna zakonodaja. pogoj za placilo racuna je uspesna primopredaja izvedenih del ki vkljucuje predlozitev dokumentacije iz tocke 7 s strani narocnika podpisano porocilo izvajalca o izvedenem obsegu del v obliki delovnega naloga z natancnim opisom izvedenih storitev in zamenjavi materiala. pristojna oseba narocnika za podpis je franc bracko. merilo za izbor najnizja ponudbena vrednost v eur z ddv ob izpolnjevanju tehnicnih zahtev narocnika.", "ner": [{"TenderOrg": "oblakova ulica 5 3000 celje", "TenderTel": "(03) 42 33 000"}, {"TenderYear": "2023"}, {"TenderCode": "sm/ms"}, {"TenderType": "x"}, {"TenderNumber": "179"}, {"TenderDeadline": "06.06.2023"}, {"TenderPerson": "mulej stane"}, {"TenderPerson": "franc bracko"}], "ner_refine": []}
{"id": "2023_EN_X_179_TENDER", "chunk_id": "1", "input_tokens": 2011, "refiner_input_tokens": 0, "total_output_tokens": 133, "text": "kontaktni osebi s strani narocnika ; splosna bolnisnica celje g franc bracko vzdrzevanje kotovskih in klimatskih naprav e franc.bracko1 guest.arnes.si 041/765 327 mulej stane sluzba za nabavo nemedicinskega materiala e stane.mulej sb celje.si 041/765 324 ponudbe posljite na naslov elektronske poste nabava2 sb celje.si z oznako n 179 ciscenje kuhinjskega prezracevalnega sistema do najkasneje 08.06. 2023 do 12 ure. vodja sluzbe za nabavo nemedicinske materiala opreme in storitev matjaz stinek univ.dipl.ekon priloge nacrt odvodne ventilacije nacrt klimatske naprave tlorisa prezracevalnega sistema br 1 obrazec predracun ponudnik v postopki oddaje obrazec predracuna ciscenje kuhinjskega prezracevalnega sistema v obsegu kot izhaja v nadaljevanju 1 mokro kemicno ciscenje klimatske naprave (klet) 2 mokro kemicno ciscenje odvodnega ventilatoja (podstresje) 3 mokro kemicno ciscenje kuhinjskih nap 4 ciscenje odvodnih ventilatorjev 5 mokro kemicno ciscenje mascobnih filtrov 6 mokro ciscenje resetk in difuzorjev 7 suho strojno ciscenje dovodnih kanalov dim 750200mm 8 suho strojno ciscenje dovodnih kanalov dim 500300mm 9 suho strojno ciscenje dovodnih kanalov dim fi 400mm 10 mokro strojno ciscenje odvodnih kanalov dim 750200mm 11 mokro strojno ciscenje odvodnih kanalov dim 900600mm 12 mokro strojno ciscenje odvodnih kanalov dim 1800650mm 13 mokro strojno ciscenje odvodnih kanalov dim fi 400mm 14 dezinfekcija prezracevalnega sistema 15 slikanje sistemov pred med in po ciscenju skupaj vrednost ponudbe v eur z ddv ponudbena vrednost je pripravljena po sistemu na kljuc. koncna ponudbena cena mora vkljucevati vse elemente iz katerih je sestavljena in mora vkljucevati vse stroske (zavarovanje dostave..) davke in morebitne popuste tako da narocnika ne bremenijo kakrsnikoli dodatni stroski. pri izracunu ponudbene vrednosti morajo ponudniki upostevati vse elemente ki vplivajo na izracun cene dobavo dostavo in montazo opreme opravljanje storitev vse potne stroske. obvezna priloga ponudbe je certifikat haccap. datum zig in podpis ponudnika", "ner": [{"TenderOrg": "splosna bolnisnica celje", "TenderPerson": "franc bracko"}, {"TenderPerson": "mulej stane"}, {"TenderNumber": "179"}, {"TenderDeadline": "08.06.2023"}, {"TenderPerson": "matjaz stinek"}], "ner_refine": []}
{"id": "2023_EN_X_225_TENDER", "chunk_id": "0", "input_tokens": 2148, "refiner_input_tokens": 0, "total_output_tokens": 185, "text": "3 oblakova ulica 5 3000 celje tel (03) 42 33 000 postopek n 225 2023 sm/ms povabilo k oddaji ponudbe predmet evidencnega narocila redni letni servis treh kompresorjev kaeser bs 51 popis kompresorjev st. serijska stevilka delovne ure na dan 07.09. 2023 stroskovno mesto lokacija naprave 1 410851 2577 2963 poliklinika klet 2 410852 2385 2963 poliklinika klet 3 7.2490.2 66724 3150 pralnica splosne zahteve predmeta osnova za realizacijo dobave je prejem pisnega narocila strani narocnika. ponudbe zbiramo informativno za predlozitev v presojo odobritve. v kolikor bomo prejeli odobritev s strani pristojnih bomo realizacijo izvedli pri najugodnejsemu ponudniku ki bo izpolnjeval tehnicne ponudnik mora biti pooblascen zastopnik na kompresorskih napravah kaeser. ponudnik mora zagotavljati originalne rezervne dele. ponudnik mora ponudbi predvideti vse stroske servisa na posamezni napravi. delovno okolje mora po izvedbi del ostati cisto. izvajalec je dolzan odstraniti vso odpadno embalazo na lastne stroske. narocnik nima nobenih stroskov odvoza unicenja ali drugih stroskov.. izvajalec mora predloziti nacrtovan termin za izvedbo servisa v roku najkasneje 10 dni od prejema pisnega narocila s strani narocnika. po zakljucku izvedenih del je potrebno predloziti porocilo o opravljenem servisu za vsako napravo posebej z seznamom opravljenih del na posameznem kompresorju in rezultati meritev. ponudba mora veljati tri mesece od poteka roka za oddajo ponudbe. narocnik se zavezuje naroceno ter dobavljeno blago placati v roku kot ga doloca veljavna zakonodaja. pogoj za placilo racuna je uspesna primopredaja izvedenih del ki vkljucuje predlozitev dokumentacije iz tocke 7 s strani narocnika podpisana porocila izvajalca o izvedenem obsegu del v obliki delovnega naloga z natancnim opisom izvedenih storitev in zamenjavi materiala. pristojna oseba narocnika za podpis je g. blaz dezelak. merilo za izbor najnizja ponudbena vrednost v eur z ddv ob izpolnjevanju tehnicnih zahtev narocnika. kontaktni osebi s strani narocnika ; splosna bolnisnica celje g blaz dezelak referat medicinska elektronika e blaz.dezelak sb celje.si 070/428 328 mulej stane sluzba za nabavo nemedicinskega materiala e stane.mulej sb celje.si 041/765 324 ponudbe posljite na naslov elektronske poste nabava2 sb celje.si z oznako n 225 redni letni servis treh kompresorjev kaeser bs 51 do 14.09. 2023 do 12 ure.", "ner": [{"TenderOrg": "splosna bolnisnica celje"}, {"TenderTel": "(03) 42 33 000"}, {"TenderNumber": "225"}, {"TenderYear": "2023"}, {"TenderCode": "sm/ms"}, {"TenderDeadline": "14.09.2023"}, {"TenderPerson": "blaz dezelak"}, {"TenderPerson": "mulej stane"}, {"TenderType": "x"}], "ner_refine": []}
{"id": "2023_EN_X_225_TENDER", "chunk_id": "1", "input_tokens": 1693, "refiner_input_tokens": 0, "total_output_tokens": 41, "text": "vodja sluzbe za nabavo nemedicinske materiala opreme in storitev matjaz stinek univ.dipl.ekon ponudbeni predracun na podlagi evidencnega javnega narocila i redni letni servis treh kompresorjev kaeser bs 51 v splosni bolnisnici celje oddajamo ponudbo ponudnik zap.st naziv storitve kolicina cena/ kpl v eur brez ddv ddv% ddv ponudbena vrednost v eur z ddv 1 letni servis kompresorja bs 51 ser.st 410851 1 kpl 2 letni servis kompresorja bs 51 ser.st 410852 1 kpl 3 letni servis kompresorja bs 51 ser.st 7.2490.2 1 kpl vrednost skupaj brez ddv znesek ddv skupaj z ddv ponudbena vrednost je pripravljena po sistemu na kljuc. koncna ponudbena cena mora vkljucevati vse elemente iz katerih je sestavljena in mora vkljucevati vse stroske (zavarovanje dostave..) davke in morebitne popuste tako da narocnika ne bremenijo kakrsnikoli dodatni stroski. pri izracunu ponudbene vrednosti morajo ponudniki upostevati vse elemente ki vplivajo na izracun cene dobavo dostavo in montazo opreme opravljanje storitev vse potne stroske. obvezna priloga k ponudbi dokazilo o pooblascenem zastopstvu katerega izdajatelj je proizvajalec kompresorjev. datum zig in podpis ponudnika", "ner": [{"TenderPerson": "matjaz stinek"}], "ner_refine": []}
{"id": "2023_EN_X_198_TENDER", "chunk_id": "0", "input_tokens": 2149, "refiner_input_tokens": 0, "total_output_tokens": 259, "text": "be) splosna bolnisnica celje oblakova ulica 5 3000 celje tel (03) 42 33 000 fax (03) 42 33 757 postopek n 198 2023 ms povabilo k oddaji ponudbe vabimo vas k oddaji ponudbe za predmet zamenjava snemalnika na polikliniki opis in konfiguracija 1x s 7316hqhi k4 analogna turbo hd real time 16 kanalna snemalna naprava h.265+ h.265 h.264+ h.264 kompresija vhodi pal hdtv ahd hdcvi cvbs moznost priklopa do sestnajst 3 megapixel ali pal kamer in 2 ip megapixel kamera ( do 4 megapixel ) mozno je povecati stevilo ip kamer s tem da se sorazmerno zmanjsuje stevilo analognih kamer 16 x bnc vhod hdmi(do 3840x2160)/vga izhod do 1920 x 1080 resolucija 4 x sata interface( do 8 tb disk) pametno iskanje posnetkov 2 x usb port lan prikljucek rs 485 prenos hd analognega signala po koaksialnem kablu na veliko razdaljo naprava je kompatibilna z vsemi hikvision softweri podpira tudi android ipad2 iphone 1x trdi disk hdd 8.0 tb purple drobno potrosni material montaza naprav priklop kamer in testiranje delovanja ponudnik lahko izdela predracun na svojem obrazcu ob upostevanju da je vsebina enaka pripravljenemu obrazcu predracuna! osnova za realizacijo dobave je prejem pisnega narocila s strani narocnika. ponudbe zbiramo informativno za predlozitev v presojo odobritve. v kolikor bomo prejeli odobritev s strani pristojnih bomo realizacijo izvedli pri najugodnejsemu ponudniku ko bo izpolnjeval tehnicne zahteve. narocnik bo ponudnike ki so oddali ponudbo skladno z dolocilom drugega odstavka 21. clena z) n 3 pisno obvestil najkasneje v roku 30 dni od oddaje evidencnega narocila. cena mora vsebovati vse stroske popuste rabate in davek na dodano vrednost. narocnik se zavezuje naroceno ter dobavljeno blago placati v roku 60 dni od datuma uradnega prejema racuna oziroma v roku skladno z veljavno zakonodajo. merilo izbora najnizja vrednost ponudbe v eur z ddv ob izpolnjevanju tehnicnih zahtev narocnika. kontaktna oseba s strani narocnika gregor kovac 031 365 005 elektronska posta gregor.kovac() sb celje.si matjaz stinek univ. dipl. ekon. tel.st. 03 423 30 76 elektronska posta matjaz.stinek() sb celje.si ponudbe posljite na naslov elektronske poste nabava2 sb celje.si z oznako n 198 2023 zamenjava snemalnika na polikliniki do najkasneje 13.07.2023 do 12 ure. v odja sluzbe za nabavo nemedicinske opreme materiala in storitev matjaz stinek univ. dipl. ekon.", "ner": [{"TenderOrg": "splosna bolnisnica celje"}, {"TenderTel": "(03) 42 33 000"}, {"TenderFax": "(03) 42 33 757"}, {"TenderType": "x"}, {"TenderNumber": "198"}, {"TenderYear": "2023"}, {"TenderCode": "ms"}, {"TenderPerson": "gregor kovac"}, {"TenderTel": "031 365 005"}, {"TenderPerson": "matjaz stinek"}, {"TenderTel": "03 423 30 76"}, {"TenderDeadline": "13.07.2023"}], "ner_refine": []}
{"id": "2023_EN_X_223_TENDER", "chunk_id": "0", "input_tokens": 2160, "refiner_input_tokens": 0, "total_output_tokens": 200, "text": "cd splosna bolnisnica celje oblakova ulica 5 3000 celje tel (03) 42 33 000 postopek n 223 2023 sm povabilo k oddaji ponudbe predmet evidencnega narocila dobava in zamenjava komponent v it sistemih bender. splosne zahteve predmeta 1. osnova za realizacijo dobave je prejem pisnega narocila strani narocnika. ponudbe zbiramo informativno za predlozitev v presojo odobritve. v kolikor bomo prejeli odobritev s strani pristojnih bomo realizacijo izvedli pri najugodnejsemu ponudniku ki bo izpolnjeval tehnicne ponudnik mora biti pooblascen zastopnik podjetja bender. ponudnik mora zagotavljati originalne rezervne dele. dela se opravijo na lokaciji v obrazcu predracuna navedenih it sistemov po predhodnem dogovoru. 5. delovno okolje mora po izvedbi del ostati cisto. izvajalec je dolzan odstraniti vso odpadno embalazo na lastne stroske. narocnik nima nobenih stroskov odvoza unicenja ali drugih stroskov.. 6. izvajalec mora navesti predviden datum dobave komponent. datum montaze uskladi narocnik upostevajoc medicinsko stroko glede vstopa v ciste prostore. 7. po zakljucku izvedenih del je potrebno predloziti e porocilo za vsak naveden it sistem posebej z navedenimi serijskimi stevilkami pregledanega sistema v katerem so bile izvedene zamenjave komponent. v porocilu morajo biti navedeni rezultati pregleda ter podan zakljucek ce je pregledan sistem ustrezno delujoc. rsb 8. ponudba mora veljati tri mesece od poteka roka za oddajo ponudbe. narocnik se zavezuje naroceno storitev placati v roku kot ga doloca veljavna zakonodaja. pogoj za placilo racuna je uspesna primopredaja izvedenih del ki vkljucuje e predlozitev dokumentacije iz tocke 7 e s strani narocnika podpisano porocilo izvajalca o izvedenem obsegu del v obliki delovnega naloga z natancnim opisom izvedenih storitev. pristojna oseba narocnika za podpis je matej sinko. merilo za izbor najnizja ponudbena vrednost v eur z ddv ob izpolnjevanju tehnicnih zahtev narocnika. kontaktni osebi s strani narocnika ; splosna bolnisnica celje mag.matej sinko elektro delavnica in medicinski plini e matej.sinko sb celje.si 041/245 823 mulej stane sluzba za nabavo nemedicinskega materiala e stane.mulej sb celje.si 041/765 324 ponudbe posljite na naslov elektronske poste nabava2 sb celje.si z oznako n 223 2023 dobava in zamenjava komponent v it sistemih bender do najkasneje 06 .09. 2023 do 12 ure. vodja sluzbe za nabavo nemedicinske materiala opreme in storitev matjaz stinek univ.dipl.ekon br 1 obrazec predracun ponudnik o.o... v postopku oddaje obrazec predracuna oznaka it sistema kolicina | cena na skupaj brez . .", "ner": [{"TenderOrg": "splosna bolnisnica celje"}, {"TenderTel": "(03) 42 33 000"}, {"TenderNumber": "223"}, {"TenderYear": "2023"}, {"TenderCode": "sm"}, {"TenderType": "x"}, {"TenderPerson": "matej sinko"}, {"TenderPerson": "stane mulej"}, {"TenderDeadline": "06.09.2023"}, {"TenderPerson": "matjaz stinek"}], "ner_refine": []}
{"id": "2023_EN_X_223_TENDER", "chunk_id": "1", "input_tokens": 1633, "refiner_input_tokens": 0, "total_output_tokens": 23, "text": "enoto brez ddv naziv artikla ddv 1 dobava in montaza rlm pa/2 1/1 it 1 komponente atics 2 80a iso 4 zagon sistema 2 dobava in montaza rlm pa/2 1/2 it 1 komponente atics 2 80a iso 4 zagon sistema 3 dobava in montaza rlm pa/2 1/3 it 1 komponente atics 2 80a iso 4 zagon sistema 4 dobava in montaza rp 8t 2 komponente eds151 4 zagon sistema skupaj brez ddv skupaj z ddv ponudbena vrednost je pripravljena po sistemu na kljuc. koncna ponudbena cena mora vkljucevati vse elemente iz katerih je sestavljena in mora vkljucevati vse stroske (zavarovanje dostave..) davke in morebitne popuste tako da narocnika ne bremenijo kakrsnikoli dodatni stroski. pri izracunu ponudbene vrednosti morajo ponudniki upostevati vse elemente ki vplivajo na izracun cene dobavo dostavo in montazo opreme opravljanje storitev vse potne stroske. obvezna priloga k ponudbi e dokazilo o pooblascenem zastopstvu katerega izdajatelj je proizvajalec sistemov bender. datum zig in podpis ponudnika", "ner": [], "ner_refine": []}
{"id": "2023_EN_X_180_TENDER", "chunk_id": "0", "input_tokens": 2229, "refiner_input_tokens": 0, "total_output_tokens": 186, "text": "cl) splosna bolnisnica celje oblakova ulica 5 3000 celje tel (03) 42 33 000 postopek n 180 2023 kt/ms povabilo k oddaji ponudbe predmet evidencnega narocila popravilo cokla fasade in odstranitev grafita natancneje gre za sanacijo poskodovanega dela fasade (fasadni podzidek cokel) in odstranitev grafita na procelju upravne stavbe sbc. grafit se mora odstraniti brez agresivnih sredstev (kemikalij). na poskodovanem delu fasade v izmeri 16 m2 je potrebno odstraniti stari (dotrajani) kulirplast opraviti impregnacijo opraviti kitanje s fasadnim lepilom nanesti emulzijo in na novo nanesti kulirplast. v ponujeni ceni mora biti upostevan ves material (tudi demit malta) skupaj z vsemi stroski dela. mad. max vibe splosne zahteve predmeta 1. osnova za realizacijo dobave je prejem pisnega narocila strani narocnika. ponudbe zbiramo informativno za predlozitev v presojo odobritve. v kolikor bomo prejeli odobritev s strani pristojnih bomo realizacijo izvedli pri najugodnejsemu ponudniku ki bo izpolnjeval tehnicne zahteve. v kolikor je za pripravo ponudbe potrebno lahko narocnik po predhodnem dogovoru doloci termin in izvede ogled. narocnik omogoca ponudniku ogled fasade ki je predmet vzdrzevanja. ogled se omogoci dne 12.06. 2023 ob 8 uri. zbirno mesto za odhod na lokacijo objekta je sluzba za nabavo nemedicinske opreme. kontaktna oseba narocnika za ogled je gregor kovac. 3. izvajalec mora pred izvedbo zacetka del podati narocniku okvirni nacrt popisa del z casovnim obsegom. termin izvedbe del se uskladil z narocnikom in uposteval zahteve glede njegovega procesa dela. terminski nacrt se posreduje kontaktni osebi narocnika. 4. delovno okolje mora po izvedbi del ostati cisto. izvajalec je dolzan odstraniti vso odpadno embalazo na lastne stroske in izvesti prvo grobo ciscenje. narocnik nima nobenih stroskov odvoza unicenja ali drugih stroskov. ciscenje ter odstranitev je potrebno izvesti po vsakokratnem zakljucku del. 5. izvajalec mora predloziti terminski nacrt za izvedbo del v roku najkasneje 7 dni od prejema pisnega narocila s strani narocnika. pri pripravi terminskega nacrta naj se uposteva da je maksimalni dopustni rok za izvedbo del 5 delovnih dni. 6. ponudba mora veljati tri mesece od poteka roka za oddajo ponudbe. narocnik se zavezuje naroceno ter dobavljeno blago placati v roku kot ga doloca veljavna zakonodaja. pogoj za placilo racuna je uspesna primopredaja izvedenih del ki vkljucuje s strani narocnika podpisano porocilo izvajalca o izvedenem obsegu del v obliki delovnega naloga z natancnim opisom izvedenih storitev in uporabljenega materiala. pristojna oseba narocnika za podpis je gregor kovac. merilo za izbor najnizja ponudbena vrednost v eur z ddv ob izpolnjevanju tehnicnih zahtev narocnika. kontaktni osebi s strani narocnika ; klavdija trunkl uni. dipl.ekon. tel.st. 03 423 35 35 faks", "ner": [{"TenderOrg": "splosna bolnisnica celje"}, {"TenderTel": "(03) 42 33 000"}, {"TenderNumber": "180"}, {"TenderYear": "2023"}, {"TenderCode": "kt/ms"}, {"TenderPerson": "gregor kovac"}, {"TenderPerson": "klavdija trunkl"}, {"TenderTel": "03 423 35 35"}, {"TenderType": "x"}], "ner_refine": []}
{"id": "2023_EN_X_180_TENDER", "chunk_id": "1", "input_tokens": 1740, "refiner_input_tokens": 0, "total_output_tokens": 126, "text": "st. 03 423 37 56 elektronska posta klavdija.trunkl sb celje.si gregor kovac tel. 031 365 005 elektronska posta gregor.kovac sb celje.si ponudbe posljite na naslov elektronske poste nabava2 0sb celje.si z oznako n 180 popravilo cokla fasade in odstranitev grafita 2023 do najkasneje 14.06. 2023 do 12 ure. vodja sluzbe za nabavo nemedicinske materiala opreme in storitev matjaz stinek univ.dipl.ekon br obrazec predracun ponudbeni predracun na podlagi evidencnega javnega narocila popravilo cokla fasade in odstranitev grafita oddajamo ponudbo ponudnik zap.s navedba storitev (postavke kolicina | cena/ kom vrednost v eur ddv | ddv ponudbena vrednost t podrobneje opredeljene v v eur brez brez ddv % v eur z ddv razpisni dokumentaciji) ddv popravilo podzidka | 1 00 kpl 1 fasade in odstranitev grafita vrednost skupaj ponudbena vrednost je pripravljena po sistemu na kljuc. koncna ponudbena cena mora vkljucevati vse elemente iz katerih je sestavljena in mora vkljucevati vse stroske (zavarovanje dostave..) davke in morebitne popuste tako da narocnika ne bremenijo kakrsnikoli dodatni stroski. pri izracunu ponudbene vrednosti morajo ponudniki upostevati vse elemente ki vplivajo na izracun cene dobavo dostavo in montazo opreme opravljanje storitev vse potne stroske. datum zig in podpis ponudnika", "ner": [{"TenderTel": "03 423 37 56"}, {"TenderNumber": "180"}, {"TenderYear": "2023"}, {"TenderDeadline": "14.06.2023"}, {"TenderPerson": "matjaz stinek"}], "ner_refine": []}
{"id": "2023_EN_X_096_TENDER", "chunk_id": "0", "input_tokens": 2242, "refiner_input_tokens": 0, "total_output_tokens": 150, "text": "be) splosna bolnisnica celje oblakova ulica 5 3000 celje tel (03) 42 33.000 fax (08) 42 33.757 postopek n 96 2023 kt/ms povabilo k oddaj i ponudbe vabimo vas k oddaji ponudbe za storitev usposabljanje odgovornih oseb za gasenje zacetnih pozarov in izvajanje evakuacije zahteve narocnika 1. izvajanje usposabljanja odgovornih oseb za gasenje zacetnih pozarov in izvajanje evakuacije skladno s pozarnim redom splosne bolnisnice celje in programom usposabljanja (priloga) bo narocnik usposobil vecino zaposlenih za odgovorne osebe za zacetno gasenje pozarov in izvajanje evakuacije. izvajalec bo pripravljal in izvajal obdobna teoreticna in prakticna usposabljanja zaposlenih in izvajal preizkuse usposobljenosti zaposlenih za odgovorne osebe za zacetno gasenje pozarov in izvajanje evakuacije. pred pricetkom usposabljanja bosta narocnik in izvajalec po potrebi izvedla revizijo programa usposabljanja. narocnik bo izvajalcu zagotovil tehnicne in prostorske pogoje za izvedbo teoreticnega usposabljanja. narocnik bo izvajalcu zagotovil prostorske pogoje za izvedbo prakticnega usposabljanja (poligon za usposabljanje in izvedbo prakticnega preizkusa znanja na prostem). tehnicne pogoje za izvedbo prakticnega usposabljanja in preizkusa znanja (gasilniki euro hidrant voda) mora zagotoviti izvajalec. strosek tehnicnih pogojev za izvedbo prakticnega usposabljanja in preizkusa znanja mora biti vkljucen v ceno usposabljanja. narocnik bo izdelal nacrt usposabljanja in oblikoval skupine. skupine bodo oblikovane po organizacijskih enotah/oddelkih. narocnik bo zagotovil da bo v vsaki skupini 20 40 slusateljev. za termine usposabljanja bo izvajalec usklajeval s strokovnim delavcem za varno delo narocnika. predvidoma bo v obdobju 12 mesecev izvedeno 10 usposabljanj. po koncanem usposabljanju posamezne skupine delavcev bo izvajalec izdelal zapisnik in potrdila o teoreticnem in prakticnem preizkusu usposobljenosti za varstvo pred pozarom v pisni in elektronski pdf. obliki. ponudnik naj v predracunu poda ceno storitev ki zajema izvedbo usposabljanja tehnicna sredstva za prakticno usposabljanje in preizkus znanja ter vso potrebno dokumentacijo. ponudnik naj v ponudbi poda ceno za usposabljanje na skupino. 2. izvajanje prakticnega usposabljanja za izvajanje evakuacije iz objekta (vaja) izvajalec bo skladno s 7. odstavkom 35. clena zakona o varstvu pred pozarom ((uradni list rs st. 3/07 uradno precisceno besedilo 9/11 83/12 in 61/17 gz) in 11. clenom pravilnika o pozarnem redu (uradni list rs st. 52/07 34/11 in 101/11) enkrat letno organiziral in izvedel prakticno usposabljanje za izvajanje evakuacije iz objekta sbc ob pozaru (v nadaljevanju vaja). namen vaje je preverjanje zmogljivosti ukrepanja ob pozaru v sbc.", "ner": [{"TenderOrg": "splosna bolnisnica celje"}, {"TenderTel": "(03) 42 33.000"}, {"TenderFax": "(08) 42 33.757"}, {"TenderNumber": "96"}, {"TenderYear": "2023"}, {"TenderCode": "kt/ms"}, {"TenderType": "x"}], "ner_refine": []}
{"id": "2023_EN_X_096_TENDER", "chunk_id": "1", "input_tokens": 2181, "refiner_input_tokens": 0, "total_output_tokens": 109, "text": "hkrati sluzi vaja kot najvisja stopnja usposabljanja vseh sodelujocih subjektov v organizacijsko in kompleksno cim bolj realnih razmerah. skladno s pozarnim redom sbc mora vsaka vaja potekati v sodelovanju s poklicno gasilsko enoto celje. za namen usposabljanja (vaje) bo izvajalec skupaj s poklicno gasilsko enoto celje predhodno pripravil nacrt za izvedbo 2 vaj ter v sodelovanju z narocnikom izvedel 2 vaji v dogovorjenem terminu. izvajalec bo med vajo vodil evidenco o casu sodelujocih in nacinu izvedbe vaj. po izvedeni vsaki vaji bo izvajalec izdelal porocilo po izvedbi prakticnega usposabljanja za izvajanje evakuacije iz objekta. ponudnik naj v ponudbi poda ceno za usposabljanje na vajo. v ceni morajo biti zajeti tudi morebitni stroski poklicne gasilske enote celje. cene za posamezne sklope podajte v naslednji tabeli okvirna cena na vrednost brez z.s. | vrsta usposabljanja em ays em brez | ddv(%) kolicina ddv ddv usposabljanje odgovornih oseb za gasenje zacetnih pozarov in . 1 k 10 izvajanje evakuacije (skupina 20 40 skupina udelezencev) izvajanje prakticnega usposabljanja 2 | za izvajanje evakuacije iz objekta in | vaja 1 izvedba vaje (vaja) 3 izvedba vaje v primeru pozara vaja 1 zrakoplova na heliportu sbc (vaja) ponudbena cena dov ee koncna ponudbena cena znasa (z besedo) ostale zahteve narocnika ponudbe zbiramo informativno za predlozitev v presojo odobritve. v kolikor bomo prejeli odobritev s strani pristojnih bomo realizacijo izvedli pri najugodnejsemu ponudniku. izvajalec se obvezuje da bo storitve opravljal po predhodnem dogovoru (telefon ali elektronska posta) z odgovorno osebo narocnika. izvajalec se obvezuje da bo pogodbena dela opravil strokovno in kvalitetno ter v skladu z veljavnimi predpisi standardi normativi in da bo poravnal morebitno nastalo skodo oziroma stroske nastale po njegovi krivdi kakor tudi posledicno skodo nastalo zaradi nestrokovne in nekvalitetne izvedbe. narocnik bo izvajalcu omogocil vpogled in preucitev vso potrebno dokumentacijo potrebno za izvedbo usposabljanja. po opravljeni storitvi bo odgovorna oseba narocnika opravila kakovostni prevzem. rok za placilo je 60 dni od prejema racuna. merilo za izbora najnizja vrednost ponudbe v eur z ddv kontaktna oseba s strani narocnika ; robert vodusek tel.st. 03 423 36 91 elektronska posta robert.vodusek sb celje.si ponudbe posljite na naslov elektronske poste nabava2 0sb celje.si z oznako n 96 usposabljanje odgovornih oseb za gasenje zacetnih pozarov in izvajanje evakuacije rok oddaje ponudb 31. 3. 2023 do 12.00 ure. vodja nabavne sluzbe nemedicinske opreme in storitev matjaz stinek univ.dipl.ekon.", "ner": [{"TenderPerson": "robert vodusek"}, {"TenderTel": "03 423 36 91"}, {"TenderDeadline": "31.03.2023"}, {"TenderPerson": "matjaz stinek"}], "ner_refine": []}
{"id": "2023_EN_X_226_TENDER", "chunk_id": "0", "input_tokens": 2205, "refiner_input_tokens": 0, "total_output_tokens": 100, "text": "6 oblakova ulica 5 3000 celje tel (03) 42 33 000 postopek n 226 2023 ms povabilo k oddaji ponudbe predmet evidencnega narocila vzdrzevanje povrsin heliporta zahteve narocnika namen javnega narocila je izbira izvajalca ki bo opravljal vzdrzevanje povrsin heliporta in sicer so predmet evidencnega narocila za obdobje 12 mesecev naslednje storitve crpanje pozarne vode na heliportu vkljucno z rezervoarjem odpadne vode v kleti priprava pozarne vode na heliportu vkljucno z rezervoarjem odpadne vode v kleti (na zahtevek skrbnika heliporta oziroma organizacijskega vodje heliporta ciscenje odtokov na heliportu (najmanj enkrat mesecno in na zahtevek skrbnika heliporta oziroma organizacijskega vodje heliporta). ciscenje sidrisc z odtoki na heliportu (najmanj dvakrat mesecno in na zahtevek skrbnika heliporta oziroma organizacijskega vodje heliporta). ciscenje streh z betumenskimi povrsinami z visokotlacnim cistilnikom (vsak tretji mesec). vzdrzevanje in menjava repalentov proti golobom na heliportu (menjava glede na garancijsko dobo). vzdrzevanje topov za gasenje samo podmazovanje z mastjo (enkrat mesecno in na zahtevek skrbnika heliporta oziroma organizacijskega vodje heliporta). tehnicna usposobljenost ponudnika podjetje mora imeti na ajpes u vpisano dejavnost ciscenje in vzdrzevanje objektov. podjetje mora imeti sklenjeno pogodbo s podizvajalcem za crpanje pozarne vode. izvajalec mora zagotavljati delo v skladu z varnostnimi normami zaposleni morajo imeti opravljen zdravniski pregled za delo na visini in opravljeno usposabljanje za varno delo na visini. narocnik teh dokazil ne bo preverjal. odzivni cas za morebitna vzdrzevanja je dolocen na do 8 ur. izvajalec se bo na servisni poziv odzval v roku 8 ur od prejema sporocila s strani odgovorne osebe narocnika. v tem casu se mora vzdrzevalec izvajalca javiti odgovorni osebi narocnika in se dogovoriti o vsebini dela in prihodu na lokacijo z namenom izvedbe del. cas za izvedbo storitve je najvec 2 delovna dneva od poteka odzivnega casa. vsa popravila se bodo vrsila v delavnikih (od ponedeljka do petka) med 7.00 in 17.00 uro. v kolikor bi dela motila delovni proces narocnika se bo delo izvajalo v skladu z dogovorom med narocnikom in izvajalcem. v urgentnih primerih bo izvajalec opravil servisno vzdrzevanje tudi izven delovnega casa ter med prazniki in vikendi (v casu dela prostih dni). ostale zahteve narocnika osnova za realizacijo storitve je prejem pisnega narocila s strani narocnika. ponudbe zbiramo informativno za predlozitev v presojo odobritve. v kolikor bomo prejeli odobritev s strani pristojnih bomo realizacijo izvedli pri najugodnejsemu ponudniku. rok izvedbe del je 12 mesecev nacin narocanja storitev vzdrzevanje se izvaja na lokaciji narocnika. storitve pri izvajalcu naroca samo pooblascena oseba narocnika.", "ner": [{"TenderTel": "(03) 42 33 000"}, {"TenderNumber": "226"}, {"TenderYear": "2023"}, {"TenderCode": "ms"}, {"TenderType": "x"}], "ner_refine": []}
{"id": "2023_EN_X_226_TENDER", "chunk_id": "1", "input_tokens": 2145, "refiner_input_tokens": 0, "total_output_tokens": 186, "text": "v primeru da izvajalec izvaja servis brez vednosti in potrditve s strani pooblascenih oseb narocnika mu le ta ni dolzan placati popravila in porabljenega blaga. narocnik si pridrzuje pravico da nadzoruje izvedbo del. po opravljenem vzdrzevanju je izvajalec dolzan podati odgovorni osebi narocnika porocilo v obliki delovnega naloga z natancnim opisom izvedenih storitev in o eventualni zamenjavi delov/materiala in sicer stevilo opravljenih ur vrsto opravljene storitve v enotni ceni storitev je potrebno zajeti vse stroske vkljucno potrosni material ali drug material potreben za storitev kakor tudi stroski dela potni stroski stroski bivanja vzdrzevalcev dnevnice kilometrine transport dajatve davscine in drugi morebitni stroski potrebni za izvedbo vzdrzevanja. izvajalec se obvezuje da bo storitve opravljal po predhodnem dogovoru (telefon ali elektronska posta) z odgovorno osebo narocnika. izvajalec se obvezuje da bo pogodbena dela opravil strokovno in kvalitetno ter v skladu z veljavnimi predpisi standardi normativi in da bo poravnal morebitno nastalo skodo oziroma stroske nastale po njegovi krivdi kakor tudi posledicno skodo nastalo zaradi nestrokovne in nekvalitetne izvedbe. osnova za realizacijo storitve je prejem pisnega narocila strani narocnika. ponudbe zbiramo informativno za predlozitev v presojo odobritve. v kolikor bomo prejeli odobritev s strani pristojnih bomo realizacijo izvedli pri najugodnejsemu ponudniku. cena mora vsebovati vse stroske popuste rabate in davek na dodano vrednost. v ceni mora biti zajeta kompletna dobava in montaza ter vsi zakljucki. izvajalec mora zagotoviti dostavo blaga ter montazo in namestitev v prostor pri narocniku v delovnem casu za dostavo oz. prevzem blaga (od ponedeljka do petka od 6 00 do 14 ure). narocnik se zavezuje naroceno ter dobavljeno blago placati v roku 60 dni od datuma uradnega prejema racuna oziroma v roku skladno z veljavno zakonodajo. narocnik bo ponudnike ki so oddali ponudbo skladno z dolocilom drugega odstavka 21. clena zjn 3 pisno obvestil najkasneje v roku 30 dni od oddaje evidencnega narocila. merilo za izbora najnizja vrednost ponudbe v eur z ddv ob izpolnjevanju tehnicnih zahtev narocnika. kontaktni osebi s strani narocnika ; gregor kovac sluzba za korporativno varnost gsm +386 031 365 005 e mail gregor.kovac sb celje.si matjaz stinek sluzba za nabavo nemedicinskega materiala tel +38634233076 e mail matjaz.stinek sb celje.si ponudbe posljite na naslov elektronske poste nabava2 sb celje.si z oznako n 226 2023 vzdrzevanje povrsin heliporta rok oddaje do 12.09. 2023 do 12 ure.", "ner": [{"TenderPerson": "gregor kovac"}, {"TenderTel": "+386 031 365 005"}, {"TenderPerson": "matjaz stinek"}, {"TenderTel": "+38634233076"}, {"TenderNumber": "226"}, {"TenderYear": "2023"}, {"TenderCode": "en"}, {"TenderDeadline": "12.09.2023"}], "ner_refine": []}
{"id": "2023_EN_X_269_TENDER", "chunk_id": "0", "input_tokens": 2280, "refiner_input_tokens": 0, "total_output_tokens": 232, "text": "6 oblakova ulica 5 3000 celje tel (03) 42 33 000 14.12.2023 postopek n 269 2023 ms povabilo k oddaji ponudbe predmet evidencnega narocila dobava in zamenjava parnega registra na susilnem stroju jensen dt60 hd splosne zahteve povprasevanja predmet evidencnega povprasevanja je dobava in zamenjava parnega registra na susilnem stroju jensen dt60 hd. ponudba naj zajema dobavo ustreznega parnega registra demontazo obstojecega okvarjenega registra in montazo novega parnega registra. v ponudbi naj bo zajeto tudi odklop in ponoven priklop parne napeljave (parni vod in odvod kondenzata). datum izvajanja del doloci narocnik naknadno in sicer tako da proces dela v pralnici ne bo moten. tehnicne podatki susilnika tip jensen dt 60 hd serijska dewr006003005322010 leto proizvodnje 2020 nacin gretja para max. 14bar max. pretok pare 478 kg/h max. moc 284 8 kw tehnicne parnega registra tip jensen 9050224101 serijska 19061252b leto proizvodnje 2019 delovni tlak < 1 2 mpa temp. pare 0 2000c max. moc 284 8 kw osnova za realizacijo dobave je prejem pisnega narocila strani narocnika. ponudbe zbiramo informativno za predlozitev v presojo odobritve. v kolikor bomo prejeli odobritev s strani pristojnih bomo realizacijo izvedli pri najugodnejsemu ponudniku ki bo izpolnjeval tehnicne zahteve. cena mora vsebovati vse stroske popuste rabate in davek na dodano vrednost. v ceni mora biti zajeta kompletna dobava in montaza ter vsi zakljucki. izvajalec mora zagotoviti dostavo blaga ter montazo in namestitev v prostor pri narocniku v delovnem casu za dostavo oz. prevzem blaga (od ponedeljka do petka od 6 00 do 14 ure). pogoj za placilo racuna je uspesna primopredaja izvedenih del ki vkljucuje s strani narocnika podpisano porocilo izvajalca o izvedenem obsegu del v obliki delovnega naloga z natancnim opisom izvedenih storitev in zamenjavi materiala. pristojna oseba narocnika za podpis je blaz dezelak. narocnik se zavezuje naroceno ter dobavljeno blago placati v roku 60 dni od datuma uradnega prejema racuna oziroma v roku skladno z veljavno zakonodajo. narocnik bo ponudnike ki so oddali ponudbo skladno z dolocilom drugega odstavka 21. clena zjn 3 pisno obvestil najkasneje v roku 30 dni od oddaje evidencnega narocila. merilo za izbora najnizja vrednost ponudbe v eur z ddv ob izpolnjevanju tehnicnih zahtev narocnika. kontaktni osebi s strani narocnika ; splosna bolnisnica celje blaz dezelak referat medicinska elektronika e blaz.dezelak sb celje.si 070 428 328 matjaz stinek sluzba za nabavo nemedicinskega materiala e matjaz.stinek sb celje.si tel +38634233076 ponudbe posljite na naslov elektronske poste nabava2 sb celje.si z oznako n 269 dobava in zamenjava parnega registra na susilnem stroju jensen dt60 hd do 19.12.2023 do 12 ure.", "ner": [{"TenderOrg": "splosna bolnisnica celje"}, {"TenderTel": "(03) 42 33 000"}, {"TenderDeadline": "14.12.2023"}, {"TenderType": "x"}, {"TenderNumber": "269"}, {"TenderYear": "2023"}, {"TenderCode": "ms"}, {"TenderPerson": "blaz dezelak"}, {"TenderTel": "+38634233076"}, {"TenderPerson": "matjaz stinek"}, {"TenderDeadline": "19.12.2023"}], "ner_refine": []}
{"id": "2023_EN_X_269_TENDER", "chunk_id": "1", "input_tokens": 1706, "refiner_input_tokens": 0, "total_output_tokens": 41, "text": "vodja sluzbe za nabavo nemedicinske materiala opreme in storitev matjaz stinek univ.dipl.ekon ponudbeni predracun na podlagi evidencnega javnega narocila dobava in zamenjava parnega registra na susilnem stroju jensen dt60 hd oddajamo ponudbo ponudnik zap.st navedba storitev (postavke podrobneje opredeljene v razpisni dokumentaciji) kolicina cena/ kom v eur brez ddv vrednost/ kom v eur brez ddv ddv% ddv ponudbena vrednost v eur z ddv 1 dobava in zamenjava parnega registra na susilnem stroju jensen dt60 hd tehnicni podatki parnega registra tip jensen 9050224101 serijska 19061252b leto proizvodnje 2019 delovni tlak < 1 2 mpa temp. pare 0 2000c max. moc 284 8 kw 1 00 kpl vrednost skupaj brez ddv znesek ddv skupaj z ddv ponudbena vrednost je pripravljena po sistemu na kljuc. koncna ponudbena cena mora vkljucevati vse elemente iz katerih je sestavljena in mora vkljucevati vse stroske (zavarovanje dostave..) davke in morebitne popuste tako da narocnika ne bremenijo kakrsnikoli dodatni stroski. pri izracunu ponudbene vrednosti morajo ponudniki upostevati vse elemente ki vplivajo na izracun cene dobavo dostavo in montazo opreme opravljanje storitev vse potne stroske. datum zig in podpis ponudnika", "ner": [{"TenderPerson": "matjaz stinek"}], "ner_refine": []}
{"id": "2023_EN_X_265_TENDER", "chunk_id": "0", "input_tokens": 2243, "refiner_input_tokens": 0, "total_output_tokens": 178, "text": "2 2 oblakova ulica 5 3000 celje tel (03) 42 33 000 fax (03) 42 33 757 postopek n 265 2023 ms 06.12.2023 povabilo k oddaji ponudbe vabimo vas k oddaji ponudbe za predmet/storitev nadgradnja obstojecega av sistema proizvajalca sophos na xdr funkcionalnosti za obdobje od datuma potrditve narocila do 27.03.2024. tehnicne zahteve za nadgradnjo/razsiritev funkcionalnosti sistema splosna tehnicna zahteva nov sistem mora podpirati povezavo oz. sinhronizacijo z obstojeco pozarno pregrado proizvajalca sophos nov sistem mora omogocati upravljanje iz sophos cloud konzole (enako kot obstojeci intercept x advanced sistem) funkcionalnosti zaznavanja (angl. detect functionalities) live discover (cross estate sql querying for threat hunting & it security operations hygiene) sql query library (pre written fully customizable queries) suspicious events detection and prioritization suspicious events detection and prioritization fast access on disk data storage (up to 90 days) cross product data sources e.g. firewall email (sophos xdr) cross product querying (sophos xdr) sophos data lake cloud storage 30 days scheduled queries funkcionalnosti analiziranja (angl. investigate functionalities) deep learning malware analysis advanced on demand sophos x ops threat intelligence forensic data export funkcionalnost saniranja (angl. remediate functionalities) live response (remotely investigate and take action) on demand endpoint isolation ti. single click clean and block obseg ponudbe ponudba naj vsebuje storitve aktivacije licenc in tehnicno podporo v naslednjem obsegu namestitev in nadgradnja sistema na koncnih napravah v obsegu 3 clovek/dan. vkljucena podpora za programsko opremo za obdobje od aktivacije storitev pri proizvajalcu do 27.3.2024. razpolozljivost storitev tehnicne podpore izvajalca v rednem delovnem casu od ponedeljka do petka od 8 00 do 16 00. storitev vkljucuje tehnicno in programsko podporo proizvajalca za ponujeno programsko opremo. splosni pogoji za sodelovanje usposobljenost podjetja ponudnik mora razpolagati s certifikatom iso 9001 sistem vodenja kakovosti certifikatom iso 27001 sistem vodenja varovanja informacij dokazilo lastna podpisana izjava ponudnika. ponudnik mora biti v casu oddaje ponudbe neposredno poslovno povezan s principalom ali s proizvajalcem ponujene tehnologije katerih dobava in namestitev je predmet tega javnega narocila. dobava podpora in vzdrzevanje zajemata celotno podporo proizvajalca ali principala ponujenih tehnologij vkljucno z dostopom do principalove tehnicne podpore in baze znanj in pravico da lahko razpolaga z vsemi licencami in pravicami intelektualne lastnine potrebnimi za izvedbo predmetnega narocila. ponudnik je dolzan zagotavljati veljavnost pogodbe s principalom ali proizvajalcem ves cas trajanja pogodbe o izvajanju tega javnega narocila. ponudnik mora izkazovati pri principalu ali proizvajalcu vsaj partnerski status sophos gold dokazilo izjava principala ali proizvajalca (lahko v tujem jezilu) ponudnik mora imeti v zadnjih 3 (treh) letih pred oddajo ponudbe za predmetno opremo po tem razpisu vsaj 1 (eno) primerljivo referencno postavitev znotraj slovenije ali eu z ekvivalentnimi resitvami kot zahteva predmetni projekt. dokazilo lastna podpisana izjava ponudnika.", "ner": [{"TenderOrg": "oblakova ulica 5 3000 celje"}, {"TenderTel": "(03) 42 33 000"}, {"TenderFax": "(03) 42 33 757"}, {"TenderNumber": "265"}, {"TenderYear": "2023"}, {"TenderCode": "ms"}, {"TenderDeadline": "06.12.2023"}, {"TenderType": "x"}], "ner_refine": []}
{"id": "2023_EN_X_265_TENDER", "chunk_id": "1", "input_tokens": 2118, "refiner_input_tokens": 0, "total_output_tokens": 96, "text": "strokovna usposobljenost ponudnik mora razpolagati s certifikati o strokovni usposobljenosti za postavitev in integracijo ponujene resitve izdan s strani proizvajalcev opreme in sicer vsaj 1 (eno) osebo s certifikatom proizvajalca programske opreme. za veljavno potrdilo se steje ce je certifikat pridobljen do dne objave predmetne razpisne dokumentacije. vsi kadri morajo delati na podrocju slovenije in aktivno obvladovati slovenski jezik. v nasprotnem primeru mora ponudnik na svoje stroske zagotoviti ustrezno osebo ki bo tekom izvajanja storitev montaze konfiguracij in vzdrzevanja skrbela za ustrezen prevod v slovenski jezik. osebe ki jih ponudnik navede kot nosilce certifikatov morajo biti v rednem delovnem razmerju pri ponudniku ali kateremu od partnerjev s katerim ponudnik skupaj nastopa na razpisu. dokazilo lastna podpisana izjava ponudnika in kopije veljavnih dovoljenj in certifikatov. narocnik si pridruzuje pravico preveritve vseh izjav in prilog ponudnika. nacin placila narocnik javnega narocila je javni zavod splosna bolnisnica celje oblakova ulica 5 3000 celje. izvajalec bo e racun za opravljeno delo po tej pogodbi izstavil narocniku skladno s pogodbenimi dolocili. racun se mora sklicevati na pogodbo na podlagi katere se izstavlja. narocnik bo izbranemu izvajalcu racun placal 60. (sestdeseti) dan po uradnem prejemu pravilno izstavljenega e racuna. pogodba o sodelovanju narocnik bo z izbranim izvajalcem naknadno sklenil pogodbi o izvajanju storitev in vzdrzevanju sistema nerazkrivanju poslovnih informacij (angl. nda) merilo za izbor najnizja vrednost ponudbe v eur z ddv ob izpolnjevanju tehnicnih zahtev narocnika. priloge priloga 1 izjava o udelezbi fizicnih in pravnih oseb v lastnistvu ponudnika ponudbeni predracun ponudnik lahko poslje ponudbo na svojem obrazcu. osnova za realizacijo storitve je prejem pisnega narocila strani narocnika. ponudbe zbiramo informativno za predlozitev v presojo odobritve. v kolikor bomo prejeli odobritev s strani pristojnih bomo realizacijo izvedli pri najugodnejsemu ponudniku. narocnik se zavezuje naroceno ter dobavljeno blago oz storitev placati v roku 60 dni od datuma uradnega prejema racuna oziroma v roku skladno z veljavno zakonodajo. narocnik bo ponudnike ki so oddali ponudbo skladno z dolocilom drugega odstavka 21. clena zjn 3 pisno obvestil najkasneje v roku 30 dni od oddaje evidencnega narocila. merilo za izbora najnizja vrednost ponudbe v eur z ddv ob izpolnjevanju tehnicnih zahtev narocnika. kontaktna oseba s strani narocnika ; matjaz stinek uni. dipl.ekon. tel.st. 03 423 3076 faks", "ner": [{"TenderOrg": "splosna bolnisnica celje"}, {"TenderPerson": "matjaz stinek"}, {"TenderTel": "03 423 3076"}], "ner_refine": []}
{"id": "2023_EN_X_258_TENDER", "chunk_id": "0", "input_tokens": 2173, "refiner_input_tokens": 0, "total_output_tokens": 124, "text": "6 oblakova ulica 5 3000 celje tel (03) 42 33 000 21.11.2023 postopek n 258 2023 ms povabilo k oddaji ponudbe predmet evidencnega narocila zamenjava videonadzornih kamer in servis videonadzornega sistema 4 x servis videonadzornega sistema znamke hikvision (radioloski oddelek kirurska prva pomoc in internisticna prva pomoc urgentnega centra upravna stavba) 2 x analogna turbo hd real time 16 kanalna snemalna naprava h.265+ h.265 h.264+ h.264 kompresija vhodi pal hdtvi ahd hdcvi cvbs moznost priklopa do sestnajst 3 megapixel ali pal kamer in 2 ip megapixel kamera ( do 4 megapixel ) mozno je povecati stevilo ip kamer s tem da se sorazmerno zmasuje stevilo analognih kamer 16 x bnc vhod hdmi(do 3840x2160)/vga izhod do 1920 x 1080 resolucija 4 x sata interface( do 8 tb disk ) pametno iskanje posnetkov 2 x usb port lan prikljucek rs 485 prenos hd analognega signala po koaksialnem kablu na veliko razdaljo naprava je kompatibilna z vsemi hikvision softweri 10 x nabava videonadzorne kamere. posamezna kamera mora biti kompatibilna z obstojecim snemalnikom hikvision ds 7316hqhik4 in imeti naslednjokonfiguracijo oz. oznako ds 2ce78h8tit3f (2.8mm) 5 megapixel analogna kamera v kupoli ultra low light hd analogni izhod do 5mp resolucije ( 2560x1944) 5mp cmos senzor 2 8 mm objektiv day/night ir cut 0.003 lux f1.2 0 lux ir dnr exir do 60m wdr 130 v kompletu s kamerami potrebujemo tudi drobni inventar in storitev 10x ds 1280zj s podnozje kamere (junction box) 10 x napajalnik za kamer montaza naprav na pripravljene instalacije nastavitev parametrov kamere ter testiranje spuscanje sistema v pogon ter uskladitev kriticnih tock snemanja z narocnikom priloga povprasevanja obrazec predracuna izjava o udelezbi fizicnih in pravnih oseb v lastnistvu ponudnika ki ju mora ponudnik izpolniti podpisati in poslati narocniku. obrazec predracuna opis (1) em (2) kolicina (3) cena/em brez ddv (4) vrednost brez ddv (5)=(3)*(4) servis videonadzornega sistema kos 4 analogna turbo hd real time 16 kanalna snemalna naprava kos 2 videonadzorna kamera kos 10 skupaj brez ddv ddv skupaj z ddv v ceni so zajeti vsi stroski dajatve popusti rabati prevozni stroski zavarovanja carine davki manipulativni stroski ter drugi morebitni oz. pricakovani stroski ki jih ima izvajalec v zvezi z izvajanjem del. v ceni delovne ure so zajeti tudi vsi stroski prihodov in kilometrina v primeru prihodov na popravila in intervencije. datum ................................ zig podpis odgovorne osebe kraj .................................... .......................................", "ner": [{"TenderTel": "(03) 42 33 000"}, {"TenderDeadline": "21.11.2023"}, {"TenderNumber": "258"}, {"TenderYear": "2023"}, {"TenderCode": "ms"}, {"TenderType": "x"}], "ner_refine": []}
{"id": "2023_EN_X_258_TENDER", "chunk_id": "1", "input_tokens": 2210, "refiner_input_tokens": 0, "total_output_tokens": 134, "text": "izjava o udelezbi fizicnih in pravnih oseb v lastnistvu ponudnika v skladu s 6. odstavkom 14. clena zakona o integriteti in preprecevanju korupcije (zintpk 1 upb2) podatki o ponudniku/podizvajalcu (v nadaljevanju ponudniku) naziv naslov maticna stevilka zakoniti zastopnik ponudnika v postopku sklenitve pogodbe za javno narocilo zamenjava videonadzornih kamer in servis videonadzornega sistema narocniku splosna bolnisnica celje zaradi zagotovitve transparentnosti posla in preprecitve korupcijskih tveganj pri sklepanju pravnih poslov posredujemo izjavo oziroma podatke o udelezbi fizicnih in pravnih oseb z vec kot 5 odstotnim delezem v lastnistvu ponudnika vkljucno z udelezbo tihih druzbenikov ter o gospodarskih subjektih za katere se glede na dolocbe zakona ki ureja gospodarske druzbe steje da so povezane druzbe s ponudnikom. izjavljam da je lastniska struktura ponudnika naslednja (podatke lahko podate tudi v prilogi) podatki o udelezbi fizicnih in pravnih oseb v lastnistvu ponudnika ime in priimek/ firma pravne osebe naslov prebivalisca/ sedez pravne osebe delez lastnistva ponudnika podatki o udelezbi tihih druzbenikov v lastnistvu druzbe ime in priimek/ firma pravne osebe naslov prebivalisca/ sedez pravne osebe delez lastnistva ponudnika podatki o povezanih druzbah s ponudnikom (v skladu s 527. clenom zgd 1 upb3) firma pravne osebe sedez pravne osebe s podpisom jamcim za tocnost in resnicnost podatkov ter se zavedam da je sporazum v primeru lazne izjave ali neresnicnih podatkov o dejstvih v izjavi nicna. seznanjeni smo da je narocnik dolzan to izjavo oziroma podatke na njeno zahtevo predloziti komisiji za preprecevanje korupcije. datum ................................ zig podpis odgovorne osebe kraj .................................... ....................................... ponudnik lahko poslje ponudbo na svojem obrazcu. osnova za realizacijo storitve je prejem pisnega narocila strani narocnika. ponudbe zbiramo informativno za predlozitev v presojo odobritve. v kolikor bomo prejeli odobritev s strani pristojnih bomo realizacijo izvedli pri najugodnejsemu ponudniku. narocnik se zavezuje naroceno ter dobavljeno blago oz storitev placati v roku 60 dni od datuma uradnega prejema racuna oziroma v roku skladno z veljavno zakonodajo. narocnik bo ponudnike ki so oddali ponudbo skladno z dolocilom drugega odstavka 21. clena zjn 3 pisno obvestil najkasneje v roku 30 dni od oddaje evidencnega narocila. merilo za izbora najnizja vrednost ponudbe v eur z ddv ob izpolnjevanju tehnicnih zahtev narocnika. kontaktni osebi s strani narocnika ; gregor kovac sluzba za korporativno varnost gsm +386 031 365 005 e mail gregor.kovac sb celje.si matjaz stinek sluzba za nabavo nemedicinskega materiala tel +38634233076 e mail matjaz.stinek sb celje.si ponudbe posljite na naslov elektronske poste nabava2 sb celje.si z oznako n", "ner": [{"TenderOrg": "splosna bolnisnica celje"}, {"TenderPerson": "gregor kovac"}, {"TenderTel": "+386 031 365 005"}, {"TenderPerson": "matjaz stinek"}, {"TenderTel": "+38634233076"}], "ner_refine": []}
{"id": "2023_EN_X_244_TENDER", "chunk_id": "0", "input_tokens": 1997, "refiner_input_tokens": 0, "total_output_tokens": 256, "text": "1 oblakova ulica 5 3000 celje tel (03) 42 33 000 fax (03) 42 33 757 postopek n 244 2023 ms povabilo k oddaji ponudbe vabimo vas k oddaji ponudbe za predmet obnovitev ibm qradar licenc za 2 leti st. opis storitve kolicina cena brez ddv/leto/licenco vrednost brez ddv/leto 1 obnovitev ibm qradar licenc 17 skupaj brez ddv za 2 leti ddv skupaj z ddv prilozena je izjava o udelezbi fizicnih oseb v lastnistvu ponudnika katero mora ponudnik izpolnjeno priloziti ponudbi. ponudnik lahko izdela predracun na svojem obrazcu ob upostevanju da je vsebina enaka pripravljenemu obrazcu predracuna! osnova za realizacijo dobave je prejem pisnega narocila s strani narocnika. ponudbe zbiramo informativno za predlozitev v presojo odobritve. v kolikor bomo prejeli odobritev s strani pristojnih bomo realizacijo izvedli pri najugodnejsemu ponudniku ko bo izpolnjeval tehnicne zahteve. narocnik bo ponudnike ki so oddali ponudbo skladno z dolocilom drugega odstavka 21. clena zjn 3 pisno obvestil najkasneje v roku 30 dni od oddaje evidencnega narocila. cena mora vsebovati vse stroske popuste rabate in davek na dodano vrednost. narocnik bo narocil blago z eno narocilnico za 2 leti placal pa v dveh obrokih vsako leto posebej. narocnik se zavezuje naroceno ter dobavljeno blago placati v roku 60 dni od datuma uradnega prejema racuna oziroma v roku skladno z veljavno zakonodajo. merilo izbora najnizja vrednost ponudbe v eur z ddv ob izpolnjevanju tehnicnih zahtev narocnika. kontaktna oseba s strani narocnika rok sitar 030 708 737 elektronska posta rok.sitar sb celje.si matjaz stinek univ. dipl. ekon. tel.st. 03 423 30 76 elektronska posta matjaz.stinek sb celje.si ponudbe posljite na naslov elektronske poste nabava2 sb celje.si z oznako n 244 2023 obnovitev ibm qradar licenc za 2 leti do najkasneje 23.10.2023 do 12 ure. vodja sluzbe za nabavo nemedicinske opreme materiala in storitev matjaz stinek univ. dipl. ekon. 10", "ner": [{"TenderOrg": "sb celje.si"}, {"TenderTel": "(03) 42 33 000"}, {"TenderFax": "(03) 42 33 757"}, {"TenderNumber": "244"}, {"TenderYear": "2023"}, {"TenderCode": "ms"}, {"TenderType": "x"}, {"TenderPerson": "rok sitar"}, {"TenderTel": "030 708 737"}, {"TenderPerson": "matjaz stinek"}, {"TenderTel": "03 423 30 76"}, {"TenderDeadline": "23.10.2023"}], "ner_refine": []}
{"id": "2023_EN_X_473_TENDER", "chunk_id": "0", "input_tokens": 2238, "refiner_input_tokens": 0, "total_output_tokens": 129, "text": "oblakova ulica 5 3000 celje tel (03) 42 33 000 postopek 473 2023 sj/vh povabilo k oddaji ponudbe vabimo vas k oddaji ponudbe za storitev energetski menedzment z energetskim knjigovodstvom za spremljanje stroskov in porabe energentov v smislu ucinkovite in racionalne rabe energije na lokaciji novi del kardio (1.nadst) in novi del orl (2.nadst). za potrebe zagotavljanja pravih mikroklimatskih pogojev in hkrati doseganja energetske ucinkovitosti bomo izvedli pilotni projekt spremljanja / monitoringa / krmiljenja prostorskih pogojev. na ta nacin zelimo nadzorovati kljucne mikroklimatske parametre po razlicnih bolniskih sobah zdravniskih in sestrskih sobah za vsak posamezni oddelek ter spremljati rabo energije ki bo omogocalo optimizacijo stroskov ter razdeljevanje stroska po stroskovnih mestih. projekt se izvede v fazah 1. faza zajem podatkov in monitoring za zajem podatkov se vgradi brezzicne wi fi iot senzorje temperature vlage in co2 ki jih je potrebno najprej usmeriti na referencno vrednost (in upostevati odstopanja). senzorji se prikljucijo na 230 v napajanje (bolniski kanal vticnice) in se povezejo na obstojece wi fi omrezje narocnika. podatki se bodo prenasali v 30s ciklusu (lahko tudi hitreje) in povprecju na 5 minut. predvideno je da se bodo senzorji namestili na novi del kardiolskega oddelka senzorji odprtosti oken in za nadzor klimatskih naprav ter temperature in co2 v bolniske sobe senzorji odprtosti oken in za nadzor klimatskih naprav ter temperature na hodniku in sobah osebja ter wc pametni merilnik za elektricno energijo senzor temperature zunaj aktuatorji za odpiranje oken kalorimeter za ogrevanje. novi del orl pametni merilnik za elektricno energijo kalorimeter za ogrevanje. stevilo senzorjev je navedeno v zahtevah za strojno opremo. kalorimetri za ogrevanje se namestijo ce bo to dopuscala zasnova ogrevalnega sistema. brezzicna wi fi povezljivost se v fazi pilotnega projekta izvede preko obstojece brezzicne infrastrukture narocnika. vzpostavljeno bo namensko ssid omrezje z wpa2 zascito in omejenim dostopom v internet z ustreznimi varnostnimi politikami (v skladu s pogoji obratovanja narocnika in bodo z izbranim ponudnikom usklajeni pred izvedbo). v fazi pilotnega projekta bo narocnik zagotovil ustrezno pokritost z wi fi signalom. podatki se zajemajo na dobaviteljevem centralnem nadzornem sistemu za energetski monitoring kjer se podatki tudi arhivirajo. podatki sluzijo analizi in kasneje za pripravo predlogov ukrepov zmanjsanja porabe toplotne in hladilne energije objekta poliklinika. sitem mora prikazovati 3d obliko trenutnega stanja meritev ter zagotovitvijo diagramskega prikaza po casu. omogocati mora alarmne vrednosti za obvescanje o prekoracenju nastavljene temperature za vsak prostor posebej. za izracun kpi (kljucnega kazalnika uspesnosti) se bosta primerjala kardioloski oddelek in orl oddelek. najprej se primerjata brez ukrepov z eno mesecnim merjenjem ter se izracuna njun index.", "ner": [{"TenderOrg": "oblakova ulica 5 3000 celje"}, {"TenderTel": "(03) 42 33 000"}, {"TenderNumber": "473"}, {"TenderYear": "2023"}, {"TenderCode": "sj/vh"}, {"TenderType": "x"}], "ner_refine": []}
{"id": "2023_EN_X_473_TENDER", "chunk_id": "1", "input_tokens": 2212, "refiner_input_tokens": 0, "total_output_tokens": 23, "text": "po izvedbi ukrepov se primerjata kardioloski oddelek z ukrepi in orl brez ukrepov pomnozeno z njunim indexom. zaradi zagotovitve realnih podatkov se meri temperatura v prostoru in zunaj ter se za osnovo vzame njuna razlika (t). aplikacija mora stalno meriti in izracunavati temperaturno razliko ter to primerjati z vzorcem porabe energije. po dolocenem casu ko se zbere dovolj podatkov mora naprava omogocati moznost nastavitve na tak nacin da imajo najmanjso oz. optimalno porabo glede na t. 2. faza porocilo izvedenega monitoriga faza 2 se zakljuci z izdelavo delovnega porocilo izvedenega monitoriga. delovno porocilo mora vkljucevati naslednje tocke. energetska primerjava oddelka kardio in orl primerjava oddelka kardio pred ukrep in po izvedenih ukrepih in sicer v kwh eur in co2 odtisu izracun roi investicija v druge oddelke prihranek casovno obdobje predloge ukrepov za zmanjsanje porabe energije (organizacijski ukrepi investicijski ali vzdrzevalni ukrepi) v drugi fazi se izvaja obvescanje uporabnikov (zdravstvenega osebja bolnikov in obiskovalcev) preko info tocke na vsakem oddelku. info tocko predstavlja smart tv ki se namesti na vidnem mestu in prikazuje trenutne mikroklimatske pogoje v merjenih prostorih ter kazalnike predvidena vrednost temperature / vlaznosti / co2 v prostoru mejne vrednosti merjenih velicin in vecnivojsko alarmiranje pri odstopanjih energetske podatke za celoten oddelek (poraba toplotne hladilne in ostale energije) ukrepi so torej usmerjeni tudi v navade zaposlenih (npr. puscena odprta okna odprti radiatorji v praznih pisarnah ipd.). ponudnik zagotovi smarttv (z nosilcem in wi fi vmesnikom). mikrolokacija in nacin montaze se definira ob ogledu lokacije in v dogovoru z narocnikom. prav tako se dogovori od nastavitev na tv (anroid) do pogojev za dostop do spletne strani in nacina za prikazovanje podatkov na zaslonu. smart tv zagotovi izvajalec. namestitev lokacije se uskladi z narocnikom. povezljivost smart tv je preko wi fi. potrebne zahteve za vzpostavitev energetskega managementa zahteve za programsko opremo zaradi razvejenosti stavb in opreme ki so vkljucene v zajem podatkov mora imeti aplikacija 3d graficni vmesnik ki omogoca enostavno orientacijo in identifikacijo sredstev ter moznost opisa podatkov posameznih sredstev ali delov stavbe (kot asset management) 3d model obeh oddelkov ter vnos bistvenih sredstev in instalacij v 3d model 3d vmesnik mora omogocati vnos in prikaz podometnih in podtalnih instalacij (elektrika lan povezave vodovod kanalizacija) ter prikaz samo teh brez zidovja podatki naj se zbirajo v sql okolju. aplikacija mora imeti moznost delovanja v oblaku in/ali lokalno. v pilotski fazi naj aplikacija deluje v oblaku. podatki morajo imeti moznost izvoza in uvoza v lokalno podatkovno bazo v kolikor bo narocnik izvedel prehod na lokalno streznisko infrastrukturo prijava v aplikativno okolje mora omogocati dvofaktorsko avtentikacijo dostop do podatkovne baze sql mora biti zascitena in omejena.", "ner": [], "ner_refine": []}
{"id": "2023_EN_X_207_TENDER", "chunk_id": "0", "input_tokens": 2256, "refiner_input_tokens": 0, "total_output_tokens": 256, "text": "1 oblakova ulica 5 3000 celje tel (03) 42 33 000 fax (03) 42 33 757 postopek n 207 2023 kt ms povabilo k oddaji ponudbe vabimo vas k oddaji ponudbe za predmet sanacija tlakovane ceste med vhodom 13a in 6 poliklinika skrajni rok izvedbe del 30.8.2023 ponudnik lahko izdela predracun na svojem obrazcu ob upostevanju da je vsebina enaka pripravljenemu obrazcu predracuna! osnova za realizacijo dobave je prejem pisnega narocila s strani narocnika. ponudbe zbiramo informativno za predlozitev v presojo odobritve. v kolikor bomo prejeli odobritev s strani pristojnih bomo realizacijo izvedli pri najugodnejsemu ponudniku ko bo izpolnjeval tehnicne zahteve. narocnik bo ponudnike ki so oddali ponudbo skladno z dolocilom drugega odstavka 21. clena zjn 3 pisno obvestil najkasneje v roku 30 dni od oddaje evidencnega narocila. cena mora vsebovati vse stroske popuste rabate in davek na dodano vrednost. narocnik se zavezuje naroceno ter dobavljeno blago placati v roku 60 dni od datuma uradnega prejema racuna oziroma v roku skladno z veljavno zakonodajo. merilo izbora najnizja vrednost ponudbe v eur z ddv ob izpolnjevanju tehnicnih zahtev narocnika. kontaktna oseba s strani narocnika robert blazinsek 041 794 681 elektronska posta robert.blazinsek sb celje.si matjaz stinek univ. dipl. ekon. tel.st. 03 423 30 76 elektronska posta klavdija.trunkl sb celje.si ponudbe posljite na naslov elektronske poste nabava2 sb celje.si z oznako n 207 2023 sanacija tlakovane ceste med vhodom 13a in 6 poliklinika do najkasneje 2.08.2023 do 12 ure. vodja sluzbe za nabavo nemedicinske opreme materiala in storitev matjaz stinek univ. dipl. ekon. ponudbeni predracun na podlagi evidencnega javnega narocila sanacija tlakovane ceste med vhodom 13a in 6 poliklinika oddajamo ponudbo ponudnik zap.st navedba storitev (postavke podrobneje opredeljene v razpisni dokumentaciji) enota kolicina cena/ enoto v eur brez ddv vrednost/ enoto v eur brez ddv ddv% ddv ponudbena vrednost v eur z ddv 1 zavarovanje cestisca z zascitno ograjo ter prometno signalizacijo kom 1 00 2 odstranitev obstojecih tlakovcev ter ciscenje le teh (umazanija). m2 84 00 3 odstranitev in dolbenje granitnih kock ciscenje starega betona ter ( umazanije). m2 12 00 4 popravilo litozeleznih jaskov dvig na visino z podloznim betonom ter ponovna namestitev jaskov kom 3 00 5 nasutje tampona in utrditev terena z vibro plosco pesek granulat 0 16. m2 84 00 6 ponovna vgradnja starih ociscenih granitnih kock z nanosom podloznega betona in izravnavo na visino. m2 12 00 7 ponovna vgradnja starih ociscenih tlakovcev z podloznim peskom 0 4 granulat.", "ner": [{"TenderOrg": "sb celje.si"}, {"TenderTel": "(03) 42 33 000"}, {"TenderFax": "(03) 42 33 757"}, {"TenderNumber": "207"}, {"TenderYear": "2023"}, {"TenderCode": "kt ms"}, {"TenderDeadline": "30.08.2023"}, {"TenderPerson": "robert blazinsek"}, {"TenderPerson": "matjaz stinek"}, {"TenderTel": "03 423 30 76"}, {"TenderDeadline": "2.08.2023"}, {"TenderType": "x"}], "ner_refine": []}
{"id": "2023_EN_X_024_TENDER", "chunk_id": "0", "input_tokens": 2082, "refiner_input_tokens": 0, "total_output_tokens": 155, "text": "oblakova ulica 5 3000 celje tel (03) 42 33 000 fax (03) 42 33 757 postopek 24 2023 bg/vh povabilo k oddaji ponudbe narocnik vabi ponudnike da v skladu z navodili ponudnikom izdelajo ponudbo za popravilo monitorja comen c50 oddelek infekcija inv. st. 00543488 sn k5191220005 leto proiz. 2019.12.20 popravilo gumba za vzig monitorja. 1. v letu 2023 veljavna pisna pooblastila proizvajalcev s katerim pooblascajo zgoraj navedeni servis za servisiranje opreme in dobavo rezervnih delov. 2. izjava dana pod kazensko in materialno odgovornostjo z navedbo imen in priimkov serviserjev (pooblasceni servis mora imeti na razpolago vsaj enega serviserja) ki je usposobljen za vzdrzevanje ponujene opreme. serviserji morajo ze v casu oddaje ponudbe imeti s pooblascenim servisom sklenjeno pogodbo o zaposlitvi ali civilnopravno pogodbo o delu ali kaksno drugo civilnopravno pogodbo o sodelovanju v izjavi je potrebno navesti obliko sklenjene pogodbe in cas trajanja te pogodbe. v primeru da gre za redno zaposlenega serviserja pri pooblascenem servisu je potrebno priloziti obrazce m 1/m 2 (prijava odjava iz pokojninskega in invalidskega zavarovanja) ki dokazuje sklenjeno pogodbo o zaposlitvi. 3. certifikati o usposobljenosti za brezhibno vzdrzevanje referencne opreme izdane s strani ucnega servisnega centra proizvajalca ki so jih pridobili navedeni serviserji v izjavi iz druge tocke. pojem referencna oprema si bo narocnik tolmacil iz vidika potrebnega pridobljenega strokovnega znanja usposobljenih oseb za vzdrzevanje opreme ki je primerljiva ponujeni opremi. certifikat ne sme biti starejsi od 24 mesecev (leto izdaje najkasneje 2020). splosne zahteve osnova za realizacijo dobave je prejem pisnega narocila strani narocnika. ponudbe zbiramo informativno za predlozitev v presojo odobritve. v kolikor bomo prejeli odobritev s strani pristojnih bomo realizacijo izvedli pri najugodnejsemu ponudniku ki bo izpolnjeval tehnicne zahteve. cena mora vsebovati vse stroske popuste rabate dostavo montazo in davek na dodano vrednost. ponudbi predlozite prospekte ter drugo dokumentacijo iz katere je razvidno izpolnjevanje zahtev narocnika. narocnik se zavezuje naroceno ter dobavljeno blago placati v roku kot ga doloca veljavna zakonodaja. merilo izbora najnizja vrednost ponudbe v eur z ddv ob izpolnjevanju tehnicnih zahtev narocnika.", "ner": [{"TenderTel": "(03) 42 33 000"}, {"TenderFax": "(03) 42 33 757"}, {"TenderNumber": "24"}, {"TenderYear": "2023"}, {"TenderCode": "bg/vh"}, {"TenderOrg": "oblakova ulica 5 3000 celje"}, {"TenderType": "x"}], "ner_refine": []}
{"id": "2023_EN_X_024_TENDER", "chunk_id": "1", "input_tokens": 1782, "refiner_input_tokens": 0, "total_output_tokens": 201, "text": "4. izvajalec je narocniku po preventivnem in kurativnem vzdrzevalnem posegu na opremi dolzan podati porocilo v obliki delovnega naloga z natancnim opisom izvedenih storitev in o eventualni zamenjavi delov/materiala in sicer stevilo opravljenih ur (redne izredne) naziv aparata inventarna stevilka opreme oziroma aparata serijska stevilka aparata oddelek narocnika (nahajalisce aparata) kolicina in vrsta vgrajenega materiala oz. rezervnih delov cena vgrajenega materiala oz. rezervnih delov velja za popravila ki niso vkljucena v all inclusive vzdrzevanje dolzino garancijskega obdobja za vgrajene rezervne/nadomestne dele/materiala da je aparat brezhiben in varen za uporabo. 5. racun za opravljeno storitev mora vsebovati naziv opreme serijska stevilka inventarna stevilka stevilko narocilnice ter kot prilogo porocilo v obliki delovnega naloga z natancnim opisom izvedenih del. racuni ki ne bodo imeli izkazanega protokola narocila in potrjevanja po tem clenu bodo zavrnjena. kontaktna oseba s strani narocnika; bostjan gajsek tel. st. 030 203 011 elektronska posta bostjan.gajsek sb celje.si matej vidmar tel. st. 030 464 787 elektronska posta matej.vidmar sb celje.si ponudbe posljite na naslov elektronske poste nabava1 sb celje.si z oznako 24 2023 popravilo aparata za mesanje preparata do 13.01.2023. do 12 ure. vanja herman gril dipl. ekon. vodja sluzbe za nabavo medicinske opreme potrosnega materiala in storitev", "ner": [{"TenderPerson": "bostjan gajsek"}, {"TenderTel": "030 203 011"}, {"TenderPerson": "matej vidmar"}, {"TenderTel": "030 464 787"}, {"TenderNumber": "24"}, {"TenderYear": "2023"}, {"TenderDeadline": "13.01.2023"}, {"TenderPerson": "vanja herman gril"}], "ner_refine": []}
{"id": "2023_EN_X_158_TENDER", "chunk_id": "0", "input_tokens": 2210, "refiner_input_tokens": 0, "total_output_tokens": 151, "text": "splosna bolnisnica celje oblakova ulica 5 3000 celje tel (03) 42 33 000 fax (03) 42 33 757 postopek n 158 2023 kt/ms povabilo k oddaji ponudbe v abimo vas k oddaji ponudbe za predmet redna letna sledljiva kalibracija analizatorjev ki jih uporabljamo v referatu medicinske elektronike. podatki o aparatih kolicina 1. 1 kom fluke index 2 spo2 simulator sn 9908025 inv. st 00524211 2. 1 kom fluke ida 5 s/n 3668023 inventarna stevilka 00538443 3. 1 kom fluke esa609 s/n 4073007 inventarna stevilka 00540280 4. 1 kom esa620 electrical safety analyzer s/n 3148552 inv. st 00534978 rok za izvedbo 30 dni od oddaje narocila obvezne priloge 1. v letu 2022 veljavna pisna pooblastila proizvajalcev s katerim pooblascajo zgoraj navedeni servis za servisiranje opreme in dobavo rezervnih delov. 2. izjava dana pod kazensko in materialno odgovornostjo z navedbo imen in priimkov serviserjev (pooblasceni servis mora imeti na razpolago vsaj enega serviserja) ki je usposobljen za vzdrzevanje ponujene opreme. serviserji morajo ze v casu oddaje ponudbe imeti s pooblascenim servisom sklenjeno pogodbo o zaposlitvi ali civilnopravno pogodbo o delu ali kaksno drugo civilnopravno pogodbo o sodelovanju v izjavi je potrebno navesti obliko sklenjene pogodbe in cas trajanja te pogodbe. v narocnik splosna bolnisnica celje 2 primeru da gre za redno zaposlenega serviserja pri pooblascenem servisu je potrebno priloziti obrazce m 1/m 2 (prijava odjava iz pokojninskega in invalidskega zavarovanja) ki dokazuje sklenjeno pogodbo o zaposlitvi. 3. certifikati o usposobljenosti za brezhibno vzdrzevanje referencne opreme izdane s strani ucnega servisnega centra proizvajalca ki so jih pridobili navedeni serviserji v izjavi iz druge tocke. pojem referencna oprema si bo narocnik tolmacil iz vidika potrebnega pridobljenega strokovnega znanja usposobljenih oseb za vzdrzevanje opreme ki je primerljiva ponujeni opremi. certifikat ne sme biti starejsi od 24 mesecev (leto izdaje najkasneje 2020). splosne zahteve osnova za realizacijo dobave je prejem pisnega narocila strani narocnika. ponudbe zbiramo informativno za predlozitev v presojo odobritve. v kolikor bomo prejeli odobritev s strani pristojnih bomo realizacijo izvedli pri najugodnejsemu ponudniku ki bo izpolnjeval tehnicne zahteve. cena mora vsebovati vse stroske popuste rabate dostavo montazo in davek na dodano vrednost. ponudbi predlozite prospekte ter drugo dokumentacijo iz katere je razvidno izpolnjevanje zahtev narocnika. rok za placilo je 60 dni od prejema racuna. merilo izbora najnizja vrednost ponudbe v eur z ddv ob izpolnjevanju tehnicnih zahtev narocnika.", "ner": [{"TenderOrg": "splosna bolnisnica celje"}, {"TenderTel": "(03) 42 33 000"}, {"TenderFax": "(03) 42 33 757"}, {"TenderNumber": "158"}, {"TenderYear": "2023"}, {"TenderCode": "kt/ms"}, {"TenderType": "x"}], "ner_refine": []}
{"id": "2023_EN_X_158_TENDER", "chunk_id": "1", "input_tokens": 2180, "refiner_input_tokens": 0, "total_output_tokens": 242, "text": "4. izvajalec je narocniku po preventivnem in kurativnem vzdrzevalnem posegu na opremi dolzan podati porocilo v obliki delovnega naloga z natancnim opisom izvedenih storitev in o eventualni zamenjavi delov/materiala in sicer stevilo opravljenih ur (redne izredne) naziv aparata inventarna stevilka opreme oziroma aparata serijska stevilka aparata oddelek narocnika (nahajalisce aparata) koliina in vrsta vgrajenega materiala oz. rezervnih delov cena vgrajenega materiala oz. rezervnih delov velja za popravila ki niso vkljucena v all inclusiv e vzdrzevanje dolzino garancijskega obdobja za vgrajene rezervne/nadomestne dele/materiala daje aparat brezhiben in varen za uporabo. 5. racun za opravljeno storitev mora vsebovati naziv opreme serijska stevilka inventarna stevilka stevilko narocilnice ter kot prilogo postopek kt/ms narocnik splosna bolnisnica celje 3 porocilo v obliki delovnega naloga z natancnim opisom izvedenih del. racuni ki ne bodo imeli izkazanega protokola narocila in potrjevanja po tem clenu bodo zavrnjena. kontaktna oseba s strani narocnika; bostjan gajsek tel. st. 030 203 011 elektronska posta bostjan.gajsek() sb celje.si matej vidmar tel. 8t. 030 464 787 elektronska posta matej.vidmar sb celje.si ponudbe posljite na naslov elektronske poste nabava2 sb celje.si z oznako n 158 sledljiva kalibracija analizatorjev 2023 do najkasneje 22.5.2023 do 12 ure. v odja nabave nemedicinske opreme in storitev matjaz stinek univ.dipl.ekon. postopek kt/ms ponudbeni predracun na podlagi javnega narocila redna letna sledljiva kalibracija analizatorjev oddajamo ponudbo ponudnik zap.st navedba storitev (postavke podrobneje opredeljene v razpisni dokumentaciji) ponudbena cena (v eur brez ddv) ponudbena vrednost (v eur z ddv) kalibracija analizatorja fluke index 2 spo2 simulator sn 9908025 inv. st 00524211 1kom kalibracija analizatorja fluke ida 5 s/n 3668023 inventarna stevilka 00538443 1kom kalibracija analizatorja fluke esa609 s/n 4073007 inventarna stevilka 00540280 1kom kalibracija analizatorja esa620 electrical safety analyzer s/n 3148552 inv. st 00534978 1kom vrednost skupaj narocnik splosna bolnisnica celje ddv je za posamezne storitve upostevan v visini % in znasa eur. vsi stroski za izvedbo narocila ki niso posebej specificirani v ponudbenem predracunu so zajeti v enotnih cenah ponudbenega predracuna. uposteva se da je gospodarski subjekt pred oddajo svoje ponudbe natancno pregledal dokumentacijo narocila ter vse ostale okoliscine ki lahko vplivajo na izvedbo storitve.", "ner": [{"TenderCode": "kt/ms"}, {"TenderOrg": "splosna bolnisnica celje"}, {"TenderPerson": "bostjan gajsek"}, {"TenderTel": "030 203 011"}, {"TenderPerson": "matej vidmar"}, {"TenderTel": "030 464 787"}, {"TenderNumber": "158"}, {"TenderYear": "2023"}, {"TenderDeadline": "22.05.2023"}, {"TenderPerson": "matjaz stinek"}], "ner_refine": []}
{"id": "2023_EN_X_240_TENDER", "chunk_id": "0", "input_tokens": 2198, "refiner_input_tokens": 0, "total_output_tokens": 256, "text": "1 oblakova ulica 5 3000 celje tel (03) 42 33 000 fax (03) 42 33 757 postopek n 240 2023 ms povabilo k oddaji ponudbe vabimo vas k oddaji ponudbe za predmet popravilo sistema zapornic vhod oblakova st. opis storitve kolicina cena brez ddv vrednost brez ddv 1 odstranitev obstojece opreme in ureditev temelja in vgradnja ustrezne siderne plosce 1 komplet 2 zamenjava mehanizma vgrajen zmogljiv motor 24v in kovinski zobniki hitrost dviga/spusta roke 3 6 sek. delovna temperatura 20 50 st.c napetost napajanja 230v ac svetlobna funkcija delovanja funkcija rocnega odpiranja fotocelica za zunanjo vgradnjo vgradnja na pripravljen temelj priklop in zagon opreme dobava in vgradnja lte komunikacijskega modula z integracijo lokacije v obstojec cns sistem sbc vzpostavitev funkcije krmiljenja po programskem casovnem urniku nastavljivo preko oddaljene ip povezave vzpostavitev funkcije oddaljenega lte odpiranja z urgence in receptorskega mesta 1 komplet 3 zamenjava poskodovanega droga dolzine 5 6m s pvc zascito in horizontalno led osvetlitvijo droga (odprto zeleno zaprto rdece) 1 komplet 4 dobava in vgradnja induktivne zanke v cestisce (izrez in zalitje asfalta) ter povezava s sistemom 1 komplet skupaj brez ddv ddv skupaj z ddv ponudnik lahko izdela predracun na svojem obrazcu ob upostevanju da je vsebina enaka pripravljenemu obrazcu predracuna! osnova za realizacijo dobave je prejem pisnega narocila s strani narocnika. ponudbe zbiramo informativno za predlozitev v presojo odobritve. v kolikor bomo prejeli odobritev s strani pristojnih bomo realizacijo izvedli pri najugodnejsemu ponudniku ko bo izpolnjeval tehnicne zahteve. narocnik bo ponudnike ki so oddali ponudbo skladno z dolocilom drugega odstavka 21. clena zjn 3 pisno obvestil najkasneje v roku 30 dni od oddaje evidencnega narocila. cena mora vsebovati vse stroske popuste rabate in davek na dodano vrednost. narocnik se zavezuje naroceno ter dobavljeno blago placati v roku 60 dni od datuma uradnega prejema racuna oziroma v roku skladno z veljavno zakonodajo. merilo izbora najnizja vrednost ponudbe v eur z ddv ob izpolnjevanju tehnicnih zahtev narocnika. kontaktna oseba s strani narocnika gregor kovac 031 365 005 elektronska posta gregor.kovac sb celje.si matjaz stinek univ. dipl. ekon. tel.st. 03 423 30 76 elektronska posta matjaz.stinek sb celje.si ponudbe posljite na naslov elektronske poste nabava2 sb celje.si z oznako n 240 2023 popravilo sistema zapornic vhod oblakova do najkasneje 16.10.2023 do 12 ure. vodja sluzbe za nabavo nemedicinske opreme materiala in storitev matjaz stinek univ. dipl. ekon. 10", "ner": [{"TenderOrg": "sb celje.si"}, {"TenderNumber": "240"}, {"TenderYear": "2023"}, {"TenderCode": "ms"}, {"TenderTel": "(03) 42 33 000"}, {"TenderFax": "(03) 42 33 757"}, {"TenderPerson": "gregor kovac"}, {"TenderTel": "031 365 005"}, {"TenderPerson": "matjaz stinek"}, {"TenderTel": "03 423 30 76"}, {"TenderDeadline": "16.10.2023"}, {"TenderType": "x"}], "ner_refine": []}
{"id": "2023_EN_M_164_TENDER", "chunk_id": "0", "input_tokens": 1783, "refiner_input_tokens": 0, "total_output_tokens": 231, "text": "oblakova ulica 5 3000 celje tel (03) 42 33 000 fax (03) 42 33 757 postopek 164 2023 sdk/vh povabilo k oddaji ponudbe vabimo vas k oddaji ponudbe za predmet atrialni kateter za ventrikulo atrialni shunt kateter mora biti skladen s codman certas valvulo ter prepreciti retro flow krvi iz desnega atria letna kolicina 1 kom osnova za realizacijo dobave je prejem pisnega narocila strani narocnika. ponudbe zbiramo informativno za predlozitev v presojo odobritve. v kolikor bomo prejeli odobritev s strani pristojnih bomo realizacijo izvedli pri najugodnejsemu ponudniku. cena mora vsebovati vse stroske popuste rabate in davek na dodano vrednost. izvajalec mora zagotoviti dostavo blaga v skladisce lekarne v delovnem casu za dostavo oz. prevzem blaga (od ponedeljka do petka od 6 00 do 14 ure). narocnik se zavezuje naroceno placati v roku kot ga doloca veljavna zakonodaja. merilo izbora najnizja vrednost ponudbe v eur z ddv ob izpolnjevanju tehnicnih zahtev narocnika. kontaktna oseba s strani narocnika ; sandra drljic kopranovic tel. st. 03 423 31 25 elektronska posta sandra.drljic kopranovic sb celje.si ponudbe posljite na naslov elektronske poste nabava1 sb celje.si z oznako 164 2023 atrialni kateter za ventrikulo do najkasneje 28.03.2023 do 10. ure. vodja sluzbe za nabavo medicinske opreme potrosnega materiala in storitev vanja herman gril mag.manag.", "ner": [{"TenderOrg": "sb celje.si", "TenderTel": "(03) 42 33 000"}, {"TenderFax": "(03) 42 33 757"}, {"TenderNumber": "164"}, {"TenderYear": "2023"}, {"TenderCode": "sdk/vh"}, {"TenderDeadline": "28.03.2023"}, {"TenderPerson": "sandra drljic kopranovic"}, {"TenderTel": "03 423 31 25"}, {"TenderPerson": "vanja herman gril"}, {"TenderType": "m"}], "ner_refine": []}
{"id": "2023_EN_M_659_TENDER", "chunk_id": "0", "input_tokens": 2090, "refiner_input_tokens": 0, "total_output_tokens": 243, "text": "oblakova ulica 5 3000 celje tel (03) 42 33 000 fax (03) 42 33 757 postopek 659 2021 sp/vh povabilo k oddaji ponudbe narocnik vabi ponudnike da v skladu z navodili ponudnikom za izdelavo ponudbe za stenski ir grelec nad previjalnim pultom 2 kom dobava iz zaloge splosne zahteve osnova za realizacijo dobave je prejem pisnega narocila strani narocnika.. v kolikor bomo prejeli odobritev s strani pristojnih bomo realizacijo izvedli pri najugodnejsemu ponudniku ki bo izpolnjeval tehnicne zahteve. cena mora vsebovati vse stroske popuste rabate dostavo montazo in davek na dodano vrednost. ponudbi predlozite prospekte ter drugo dokumentacijo iz katere je razvidno izpolnjevanje zahtev narocnika. narocnik je v specifikacijah zahtev oz. koda artikla navedel tip opreme izkljucno z namenom da se doloci zahtevana raven kakovosti. v ponudbi lahko ponudite tudi artikel drugih proizvajalcev vendar mora biti le ta enakovredna. narocnik se zavezuje naroceno ter dobavljeno blago placati v roku kot ga doloca veljavna zakonodaja. narocnik bo po analizi ponudb pozval najugodnejsega ponudnika da v roku 10 dni posreduje artikel iz ponudbe da se preveri ustreznost ponujenega. merilo izbora najnizja vrednost ponudbe v eur z ddv ob izpolnjevanju tehnicnih zahtev narocnika. narocnik bo ponudnike ki so oddali ponudbo skladno z dolocilom drugega odstavka 21. clena zjn 3 pisno obvestil najkasneje v roku 30 dni od oddaje evidencnega narocila kontaktna oseba s strani narocnika ; stanislava pahole dipl.ekon. tel.st. 03 423 33 84 faks st. 03 423 37 56 elektronska posta stanislava.pahole sb celje.si ponudbe posljite na naslov elektronske poste nabava1 sb celje.si z oznako 659 2023 stenski ir grelec nad previjalnim pultom do najkasneje 14.11.2023 do 12 ure. priloga obrazec predracuna (obr 2) izjavna o izpolnjevanju tehnicne specifikacije opreme (obr 3) izjava o zastopstvu (obr 4) obveznost izbranega ponudnika obrazec predracuna obr 2 ponudnik predmet stenski ir grelec nad previjalnim pultom predracun (oprema vzdrzevanje preventivni pregledi opreme za obdobje 7 let ) opis proizvajalec (1) model oz. kataloska stevilka (2) v kolikor proizvajalec na opremi dopusca uporabo aparata drugega proizvajalca vnesite artikel stevilko opis material ter naziv proizvajalca oz oznacite da dopusca kolicina (3)", "ner": [{"TenderOrg": "sb celje.si"}, {"TenderTel": "(03) 42 33 000"}, {"TenderFax": "(03) 42 33 757"}, {"TenderNumber": "659"}, {"TenderYear": "2021"}, {"TenderCode": "sp/vh"}, {"TenderPerson": "stanislava pahole"}, {"TenderTel": "03 423 33 84"}, {"TenderFax": "03 423 37 56"}, {"TenderDeadline": "14.11.2023"}, {"TenderType": "m"}], "ner_refine": []}
{"id": "2023_EN_M_659_TENDER", "chunk_id": "1", "input_tokens": 2187, "refiner_input_tokens": 0, "total_output_tokens": 23, "text": "vrednost brez ddv (4) stenski ir grelec nad previjalnim pultom 2 kom 2.vrednost preventivnega vzdrzevanje ter redni letni pregled opreme za obdobje 7 let vrednost opreme v eur brez ddv(1) znesek ddv za opremo vrednost preventivnega vzdrzevanja redni letni pregledi opreme v eur brez ddv (3) znesek ddv v eur za preventivno vzdrzevanje redni letni pregled opreme skupaj vrednost v eur za 1+2 v eur z ddv datum zig in podpis ponudnik obr 4 izjava o izpolnjevanju tehnicne specifikacije opreme ponudnik pod kazensko in materialno odgovornostjo izjavljamo da izpolnjujemo tehnicne zahteve navedene v tem dokumentu da bomo ponudbi predlozili originalne prospekte proizvajalca ter ostalo originalno dokumentacijo proizvajalca iz katere je razvidna oprema ki je predmet ponudbe da bo izpolnjevanje vseh zahtev iz opisa predmeta narocila mora biti razvidno iz originalnih prospektov proizvajalca ter ostale originalne dokumentacije proizvajalca slednje bomo ustrezno oznacili podcrtali in navedli ustrezno zap.st. ki izhaja iz opisa predmeta narocila stenski ir grelec nad previjalnim pultom v skladu z naslednjimi tehnicnimi zahtevami ir grelec s stensko montazo nastavitev temperature ogrevanja nadzor temperature ogrevanja preko lcd zaslona zagotavljanje nastavljene temperature stevilcni prikaz nastavljene temperature moznost rocnega ali avtomatskega upravljanja gretja s pomocjo senzorja za belezenje temperature koze obmocje delovanja v okolju s temperaturo od 18c do vsaj 30c relativno vlaznostjo zraka od vsaj 15 % do 95% in atmosferskega tlaka od 700 do vsaj 1100 hpa alarmi v primeru nepravilnega delovanja oz. previsokih temperatur termicno stikalo za izklop za dodatno varnost vgrajeno led svetilo za osvetlitev ogrevanega polja z moznostjo nastavljanja osvetlitve ohisje grelca omogoca varnost uporabnika in otroka brez moznosti nastanka opeklin in drugih poskodb oci in koze moznost ciscena z dezinfekcijskimi sredstvi ce certifikat v ponudbi obvezno vpisati dobavni rok kraj in datum zig in podpis ponudnika obr 4 izjava o zastopstvu ponudnik obvezne priloge v letu 2021 veljavno izjava o zastopstvu lastne blagovne znamke oz. izjava proizvajalca o pooblastilu zastopanja za prodajo tovrstnih aparatov. izjava mora biti potrjena z zigom ter podpisom proizvajalca. v letu 2021 veljavno izjava o zastopstvu lastne blagovne znamke oz. izjava proizvajalca o pooblastilu zastopanja za prodajo originalnega potrosnega materiala potrebnega za delovanje aparatov. izjava mora biti potrjena z zigom ter podpisom proizvajalca. v letu 2021 veljavna pisna pooblastila proizvajalcev ki so proizvedli ponujeno opremo s katerim pooblascajo zgoraj navedeni servis za servisiranje opreme in dobavo rezervnih delov. certifikate o usposobljenosti za brezhibno vzdrzevanje referencne opreme izdane s strani ucnega servisnega centra proizvajalca ki so jih pridobili navedeni serviserji v izjavi iz druge tocke.", "ner": [], "ner_refine": []}
{"id": "2023_EN_M_668_TENDER", "chunk_id": "0", "input_tokens": 1919, "refiner_input_tokens": 0, "total_output_tokens": 246, "text": "6 narocnik splosna bolnisnica celje oblakova ulica 5 3000 celje tel (03) 42 33 000 fax (03) 42 33 757 postopek 668 2023 sp/vh povabilo k oddaji ponudbe narocnik vabi ponudnike da v skladu z navodili ponudnikom za izdelavo ponudbe za aparat za transkranialni doppler 1 kom splosne zahteve osnova za realizacijo dobave je prejem pisnega narocila strani narocnika.. v kolikor bomo prejeli odobritev s strani pristojnih bomo realizacijo izvedli pri najugodnejsemu ponudniku ki bo izpolnjeval tehnicne zahteve. cena mora vsebovati vse stroske popuste rabate dostavo montazo in davek na dodano vrednost. ponudbi predlozite prospekte ter drugo dokumentacijo iz katere je razvidno izpolnjevanje zahtev narocnika. narocnik se zavezuje naroceno ter dobavljeno blago placati v roku kot ga doloca veljavna zakonodaja. merilo izbora najnizja vrednost ponudbe v eur z ddv ob izpolnjevanju tehnicnih zahtev narocnika. narocnik bo ponudnike ki so oddali ponudbo skladno z dolocilom drugega odstavka 21. clena zjn 3 pisno obvestil najkasneje v roku 30 dni od oddaje evidencnega narocila dodatne zahteve na medicinski opremi mora biti obvezno prilepljena proizvajalceva nalepka ki mora izkazovati vsaj naslednje podatke ime in tip naprave oznake ce serijska stevilka naprave datum proizvodnje (leto mesec dan) ime proizvajalca drzava proizvajalca na aparatu mora biti obvezno tudi nalepka ki oznacuje termin naslednjega potrebnega preventivnega servisa. letnik proizvodnje obvezno tekoce leto. kontaktna oseba s strani narocnika ; stanislava pahole dipl.ekon. tel.st. 03 423 36 84 faks st. 03 423 36 56 elektronska posta stanislava.pahole sb celje.si. ponudbe posljite na naslov elektronske poste nabava1 sb celje.si z oznako 668 2023 aparat za transkranialni doppler do najkasneje 16.11.2023 do 12 ure.", "ner": [{"TenderOrg": "splosna bolnisnica celje"}, {"TenderTel": "(03) 42 33 000"}, {"TenderFax": "(03) 42 33 757"}, {"TenderNumber": "668"}, {"TenderYear": "2023"}, {"TenderCode": "sp/vh"}, {"TenderPerson": "stanislava pahole"}, {"TenderTel": "03 423 36 84"}, {"TenderFax": "03 423 36 56"}, {"TenderDeadline": "16.11.2023"}, {"TenderType": "m"}], "ner_refine": []}
{"id": "2023_EN_M_668_TENDER", "chunk_id": "1", "input_tokens": 2212, "refiner_input_tokens": 0, "total_output_tokens": 23, "text": "priloga obrazec predracuna (obr 2) izjavna o izpolnjevanju tehnicne specifikacije opreme (obr 3) obveznost izbranega ponudnika obrazec predracuna obr 2 ponudnik predmet aparat za transkranialni doppler predracun (oprema ) proizvajalec (1) model oz. kataloska stevilka (2) kolicina (3) vrednost brez ddv (4) 1. aparat za transkranialni doppler 1 2. kompletno vzdrzevanje opreme za obdobje 7 let cena za 1 kom v eur brez ddv znesek ddv za 1 kom vzdrzevanje v eur brez ddv za obdobje 7 let znesek ddv v eur za vzdrzevanje skupaj vrednost 1+2 v eur z ddv datum zig in podpis ponudnika obr 3 izjava o izpolnjevanju tehnicne specifikacije opreme ponudnik pod kazensko in materialno odgovornostjo izjavljamo da izpolnjujemo tehnicne zahteve navedene v tem dokumentu da bomo ponudbi predlozili originalne prospekte proizvajalca ter ostalo originalno dokumentacijo proizvajalca iz katere je razvidna oprema ki je predmet ponudbe da bo izpolnjevanje vseh zahtev iz opisa predmeta narocila mora biti razvidno iz originalnih prospektov proizvajalca ter ostale originalne dokumentacije proizvajalca slednje bomo ustrezno oznacili podcrtali in navedli ustrezno zap. st. ki izhaja iz opisa predmeta narocila tehnicne zahteve narocnika za aparat za transkranialni doppler naziv oz. vrsta dokumenta iz katerega je razvidno izpolnjevanje tehnicnih karakteristik stevilka strani dokumenta iz katerega je razvidno izpolnjevanje tehnicne zahteve v celoti digitaliziran aparat 2 mhz pulzni dopplerski sondi (slepi) za spektralno analizo in s software za power m mode smerno obcutljiv doppler za merjenje pretoka monitor na dotik (touch screen) za prikaz dopplerskega dvosmernega signala in intenzitete signala robotski bilateralni set za avtomatsko detekcijo in spremljanje dopplerskih signalov vkljucena aplikacija za ugotavljanje embolusov hits vkljucena aplikacija za pfo vkljucen protokol za vazospazme kognitivni odziv moznost postprocesiranja parametrov (globina jakost zvok volumen vzorca skale) povezljivost (dicom) avtomatiziran standardiziran izpis rezultatov preiskave z vkljucenimi krivuljami kraj in datum zig in podpis ponudnika i. obvezna dokumentacija ob dobavi opreme informacija ponudniku.dokumente ne prilagate ponudbi. seznam spremne dokumentacije skrbnik spremne dokumentacije medicinskega aparata obkrozi ustrezno. 1. prevod navodil v slovenskem jeziku za uporabo ter o nacinu preizkusanja in vzdrzevanja sipv oddelek 2. originalno navodilo za uporabo v angleskem jeziku (user book) sipv oddelek 3. kompletno tehnicno dokumentacijo oz. tehnicni opis v angleskem jeziku (service manual) sipv oddelek 4. izjavo dobavitelja da je oprema izdelana v skladu s predpisanimi varstvenimi ukrepi normativi standardi in tehnicnimi predpisi sipv oddelek 5. ostalo dokumentacijo ki sodi k medicinski opremi reference manuel certifikati izjavo o skladnosti s tehnicnimi zahtevami. med certifikati pricakujemo certifikat harmonizirane smernice mdd93/42/eec za medicinske naprave in ce oznacbo o skladnosti na omenjeno direktivo.", "ner": [], "ner_refine": []}
{"id": "2023_EN_M_018_TENDER", "chunk_id": "0", "input_tokens": 2196, "refiner_input_tokens": 0, "total_output_tokens": 266, "text": "oblakova ulica 5 3000 celje tel (03) 42 33 000 fax (03) 42 33 757 postopek 18 2023 sp/vh povabilo k oddaji ponudbe narocnik vabi ponudnike da v skladu z navodili ponudnikom za izdelavo ponudbe za pregradna stena zlozljiva 2 kom rok dobave najkasneje 31.01.2023 splosne zahteve osnova za realizacijo dobave je prejem pisnega narocila strani narocnika. ponudbe zbiramo informativno za predlozitev v presojo odobritve. v kolikor bomo prejeli odobritev s strani pristojnih bomo realizacijo izvedli pri najugodnejsemu ponudniku ki bo izpolnjeval tehnicne zahteve. cena mora vsebovati vse stroske popuste rabate dostavo montazo in davek na dodano vrednost. narocnik se zavezuje naroceno ter dobavljeno blago placati v roku kot ga doloca veljavna zakonodaja. izvajalec mora zagotoviti dostavo blaga ponudbi predlozite prospekte ter drugo dokumentacijo iz katere je razvidno izpolnjevanje tehnicnih zahtev. kontaktna oseba s strani narocnika ; stanislava pahole dipl.ekon. tel.st. 03 423 36 84 faks st. 03 423 37 56 elektronska posta stanislava.pahole sb celje.si. ponudbe posljite na naslov elektronske poste nabava1 sb celje.si z oznako 18 2023 pregradna stena zlozljiva do najkasneje 13.01.2023 do 12 ure. priloga obrazec predracuna (obr 2) izjavna o izpolnjevanju tehnicne specifikacije opreme (obr 3) obrazec predracuna obr 2 ponudnik predmet zlozljiva pregradna stena predracun opis proizvajalec (1) model oz. kataloska stevilka (2) kolicina (3) vrednost brez ddv (4) 1. zlozljiva pregradna stena 2 kom cena za kom v eur brez ddv skupaj vrednost v eur z ddv datum zig in podpis ponudnik obr 3 izjava o izpolnjevanju tehnicne specifikacije opreme ponudnik pod kazensko in materialno odgovornostjo izjavljamo da izpolnjujemo tehnicne zahteve navedene v tem dokumentu da bomo ponudbi predlozili originalne prospekte proizvajalca ter ostalo originalno dokumentacijo proizvajalca iz katere je razvidna oprema ki je predmet ponudbe da bo izpolnjevanje vseh zahtev iz opisa predmeta narocila mora biti razvidno iz originalnih prospektov proizvajalca ter ostale originalne dokumentacije proizvajalca slednje bomo ustrezno oznacili podcrtali in navedli ustrezno zap. st. ki izhaja iz opisa predmeta narocila pregradna stena zlozljiva v skladu z naslednjimi tehnicnimi zahtevami opomba mobilna na kolesih na zavoro zlozljiva (na tri razdelke) dolzina 200cm do max. 220 visina 150cm (vkljucno s kolesi max 170cm) laminat ali drug obstojni material ne platno ali drug vpojni material povrsina primerna za dezinfekcijo razkuzevanje ali vlazno ciscenje barvo bo uporabnik izbral naknadno kraj in datum zig in podpis ponudnika", "ner": [{"TenderOrg": "sb celje.si"}, {"TenderTel": "(03) 42 33 000"}, {"TenderFax": "(03) 42 33 757"}, {"TenderNumber": "18"}, {"TenderYear": "2023"}, {"TenderCode": "sp/vh"}, {"TenderDeadline": "31.01.2023"}, {"TenderPerson": "stanislava pahole"}, {"TenderTel": "03 423 36 84"}, {"TenderFax": "03 423 37 56"}, {"TenderDeadline": "13.01.2023"}, {"TenderType": "m"}], "ner_refine": []}
{"id": "2023_EN_M_745_TENDER", "chunk_id": "0", "input_tokens": 2158, "refiner_input_tokens": 0, "total_output_tokens": 223, "text": "4 narocnik splosna bolnisnica celje oblakova ulica 5 3000 celje tel (03) 42 33 000 fax (03) 42 33 757 postopek 745 2023 sph/vh povabilo k oddaji ponudbe narocnik vabi ponudnike da v skladu z navodili ponudnikom za izdelavo ponudbe za pregledna terapevtska miza 3 kom splosne zahteve osnova za realizacijo dobave je prejem pisnega narocila strani narocnika.. v kolikor bomo prejeli odobritev s strani pristojnih bomo realizacijo izvedli pri najugodnejsemu ponudniku ki bo izpolnjeval tehnicne zahteve. cena mora vsebovati vse stroske popuste rabate dostavo montazo in davek na dodano vrednost. ponudbi predlozite prospekte ter drugo dokumentacijo iz katere je razvidno izpolnjevanje zahtev narocnika. narocnik se zavezuje naroceno ter dobavljeno blago placati v roku kot ga doloca veljavna zakonodaja. narocnik bo po analizi ponudb pozval najugodnejsega ponudnika da v roku 10 dni posreduje artikel iz ponudbe da se preveri ustreznost ponujenega. merilo izbora najnizja vrednost ponudbe v eur z ddv ob izpolnjevanju tehnicnih zahtev narocnika. narocnik bo ponudnike ki so oddali ponudbo skladno z dolocilom drugega odstavka 21. clena zjn 3 pisno obvestil najkasneje v roku 30 dni od oddaje evidencnega narocila kontaktna oseba s strani narocnika ; stanislava pahole hocevar dipl.ekon. tel.st. 03 423 36 84 elektronska posta stanislava.pahole sb celje.si. ponudbe posljite na naslov elektronske poste nabava1 sb celje.si z oznako 745 2023 pregledna terapevtska miza do najkasneje 08.01.2024 do 12 ure. priloga obrazec predracuna (obr 2) izjava o izpolnjevanju tehnicne specifikacije opreme (obr 3) obrazec predracuna obr 2 ponudnik predmet pregledna terapevtska miza predracun (oprema) opis proizvajalec (1) model oz. kataloska stevilka (2) kolicina (3) vrednost brez ddv (4) 1. pregledna terapevtska miza 3 kom vrednost opreme v eur brez ddv za 1 kom (1) znesek davka za opremo za 1 kom skupaj vrednost v eur z ddv 3kom datum zig in podpis ponudnika obr 3 izjava o izpolnjevanju tehnicne specifikacije opreme ponudnik pod kazensko in materialno odgovornostjo izjavljamo da izpolnjujemo tehnicne zahteve navedene v tem dokumentu da bomo ponudbi predlozili originalne prospekte proizvajalca ter ostalo originalno dokumentacijo proizvajalca iz katere je razvidna oprema ki je predmet ponudbe da bo izpolnjevanje vseh zahtev iz opisa predmeta narocila mora biti razvidno iz originalnih prospektov proizvajalca ter ostale originalne dokumentacije proizvajalca slednje bomo ustrezno oznacili podcrtali in navedli ustrezno zap.st.", "ner": [{"TenderOrg": "splosna bolnisnica celje"}, {"TenderTel": "(03) 42 33 000"}, {"TenderFax": "(03) 42 33 757"}, {"TenderNumber": "745"}, {"TenderYear": "2023"}, {"TenderCode": "sph/vh"}, {"TenderDeadline": "08.01.2024"}, {"TenderPerson": "stanislava pahole hocevar"}, {"TenderTel": "03 423 36 84"}, {"TenderType": "m"}], "ner_refine": []}
{"id": "2023_EN_M_745_TENDER", "chunk_id": "1", "input_tokens": 1581, "refiner_input_tokens": 0, "total_output_tokens": 40, "text": "ki izhaja iz opisa predmeta narocila tehnicne zahteve opreme pregledna miza v skladu z naslednjimi zahtevami opomba hidravlicna od 20 do + 70 stopinjski naklon vzglavja nastavljiv s plinsko vzmetjo miza je nastavljiva po visini s pomocjo hidravlicnega cilindra dvodelna vzglavna plosca lezalna plosca sirina lezisca 70 cm (+/ 5%) dolzina lezisca od 200 cm do 210cm antistaticna kolesa vsaj 120 mm centralni zavorni sistem nosilec za rolo papir ob vzglavju nastavitev visine od vsaj 46 cm (najnizja pozicija mize) do vsaj 90 cm rocica za dvig in spust mize dostop iz leve in desne strani (obeh strani) blazina debeline vsaj 9 cm obstojno blazinjenje nosilnost vsaj 200 kg omogocati suho ter mokro ciscenje s sredstvi za higienizacijo in dezinfekcijo. kraj in datum 10 postopek sph/vh", "ner": [{"TenderCode": "sph/vh"}], "ner_refine": []}
{"id": "2023_EN_M_272_TENDER", "chunk_id": "0", "input_tokens": 2260, "refiner_input_tokens": 0, "total_output_tokens": 102, "text": "oblakova ulica 5 3000 celje tel (03) 42 33 000 postopek 272 2023 sdk/vh povabilo k oddaji ponudbe vabimo vas k oddaji ponudbe za predmet inhalator aerogen solo v skladu z opisom kot sledi iz obr 1 nebulizer razprsilec zdravil s tehnologijo vibrirajoce mrezice t.i. mesh. aerogen solo kit inhalator s t clenom kot na primer kataloska st. ag as3350 letna kolicina 10 kos sukcesivna dobava pripomocek za inhalacijsko dovajanje zdravil aerogen ultra v skladu z opisom kot sledi iz obr 1 posodica razprsilca zdravil s tehnologijo vibrirajoce mrezice za spontano dihajoce bolnike pri cemer naj doza zdravila potrjeno presega 30%. bolnikov izdih naj bo mozno zascititi s standardnim 22mm baterijsko viralnim filtrom z nepovratnim ventilom in cevko za dodajane kisika. uporablja se v kombinaciji z inhalatorjem aerogen solo. kot na primer kataloska st. ag as7000. letna kolicina 50 kos sukcesivna dobava splosne zahteve osnova za realizacijo dobave je prejem pisnega narocila strani narocnika. ponudbe zbiramo informativno za predlozitev v presojo odobritve. v kolikor bomo prejeli odobritev s strani pristojnih bomo realizacijo izvedli pri najugodnejsemu ponudniku. ponudbene vrednosti vkljucujejo vse stroske davke in morebitne popuste stroske dela rezijske stroske morebitne nadure amortizacijo opreme stroske dostave odvoza menjave blaga rokovanja in del povezanih z embalazo in morebitne druge stroske ki vplivajo na izracun cene. narocnik bo narocal blago s pisno z narocilnico. narocnik bo v narocilnici opredeliti vrste in kolicine blaga. dobavitelj je dolzan najkasneje v roku dveh ur od prejema narocila potrditi prejem narocila in obvestiti narocnika o morebitno zamudi pri dobavi ali zamenjavi istovrstnega blaga. kolicine in vrste blaga po predracunu so okvirne in za narocnika niso obvezujoce. dobavitelj zagotavlja dostavo blaga ddp splosna bolnisnica celje razlozeno lekarna narocnika (v delovnem casu narocnika od ponedeljka do petka). ponudnik mora zagotavljati dobavo celotne narocene kolicine v roku najkasneje 2. delovnih dni oziroma v nujnih primerih manj po predhodnem dogovoru z narocnikom (v delovnem casu od ponedeljka do petka v delovnem casu od 7 00 do 14 00 ). narocnik se obvezuje blago prevzeti v celoti na podlagi pravilno izpolnjene dobavnice. steje se da je dobavnica pravilno izpolnjena ce vsebuje najmanj naslednje naziv artikla cena na enoto mere kolicina morebitni popust kataloska stevilka artikla crtna koda dobaviteljeva sifra serijsko stevilko artikla rok uporabnosti stopnjo ddv ja stevilka narocilnice. kolicinski prevzem blaga oz. pregled se opravi takoj ob prevzemu blaga. kolicinska odstopanja ki jih ni bilo moc ugotoviti ob prevzemu mora posamezni narocnik pisno reklamirati najkasneje v treh (8) delovnih dneh od prevzema. dobavljeno blago mora ustrezati dogovorjeni kakovosti ter biti v skladu s tem sporazumom in njegovimi prilogami za vsak artikel posebej.", "ner": [{"TenderTel": "(03) 42 33 000"}, {"TenderNumber": "272"}, {"TenderYear": "2023"}, {"TenderCode": "sdk/vh"}, {"TenderType": "m"}], "ner_refine": []}
{"id": "2023_EN_M_272_TENDER", "chunk_id": "1", "input_tokens": 2199, "refiner_input_tokens": 0, "total_output_tokens": 23, "text": "kakovostna odstopanja lahko posamezni narocnik pisno reklamira najkasneje v 30. (tridesetih) dneh od prevzema blaga. ce dobava ne ustreza naroceni kolicini in/ali kakovosti je dobavitelj dolzan pomanjkljivosti nemudoma brezplacno odpraviti. v kolikor dobavitelj napak ne odpravi v roku dveh delovnih dni od prejema reklamacije to lahko stori posamezni narocnik na stroske dobavitelja in zahteva od dobavitelja povrnitev nastale skode. kakovost blaga mora ustrezati obstojecim standardom in deklarirani kakovosti na embalazi oziroma spremljajocih dokumentih. blago mora ustrezati tudi pogojem in zahtevam opredeljenimi v razpisni dokumentaciji narocnika in strokovnim kriterijem oz. znacilnostim. blago mora biti obvezno pakirano v originalni embalazi (kot izhaja iz proizvajalcevega kataloga). blago mora imeti oznako ce in izpolnjevati vse tehnicne zahteve dolocena v navodilih ponudnikov. dobavljeno blago mora imeti rok uporabe se najmanj dve tretjini deklariranega roka uporabe ki ga navaja proizvajalec ponujenega blaga. v primeru krajsega roka uporabe mora ponudnik pred dostavo pridobiti pisno soglasje narocnika. vsak izstavljen racun mora vsebovati podatke o narocnikovi stevilki okvirnega sporazuma narocilnice oz. odjave porabljenega blaga in dobavnice ter vse elemente kot dobavnica. izstavljen racun mora imeti prilogo narocilnice oz. odjave porabljenega blaga dobavnice dobavitelj mora vse racune narocniku posiljati izkljucno v elektronski obliki (e racun) skladno z veljavnim zakonom o opravljanju placilnih storitev za proracunske uporabnike. dobavitelj mora izdati locen racun izkljucno vezan na predmetni sporazum zbirni racun ni dopusten in ga bo narocnik zavrnil. ponudnik mora biti vpisan v enega od registrov ki ga vodi jazmp (po skupini registrov) registrov poslovnih subjektov s sedezem v republiki sloveniji ki opravljajo dejavnost na podrocju medicinskih pripomockov registriranih po zacetku uporabe uredbe o medicinskih pripomockih (eu) st. 2017/745 registrov poslovnih subjektov z dejavnostjo na podrocju medicinskih pripomockov pred zacetkom uporabe uredbe o medicinskih pripomockih (eu) st. 2017/745 registrov medicinskih pripomockov skladnih z mdr katerih proizvajalci oz. predstavniki proizvajalcev imajo sedez v rs registrov medicinskih pripomockov skladnih z direktivo 90/385/es o aktivnih medicinskih pripomockih za vsaditev direktivo 93/42/egs o medicinskih pripomockih direktivo 98/79/es o in vitro diagnosticnih medicinskih pripomockih registrov medicinskih pripomockov katerih proizvajalci oz. predstavniki proizvajalcev imajo sedez v rs ponudniku medicinskih pripomockov s sedezem v drugi drzavi clanici evropske unije se ni potrebno priglasiti v register veletrgovcev ali proizvajalcev medicinskih pripomockov v sloveniji predloziti pa mora ustrezno potrdilo drzave clanice iz katere izhaja.", "ner": [], "ner_refine": []}
{"id": "2023_EN_M_279_TENDER", "chunk_id": "0", "input_tokens": 2206, "refiner_input_tokens": 0, "total_output_tokens": 223, "text": "3 narocnik splosna bolnisnica celje oblakova ulica 5 3000 celje tel (03) 42 33 000 fax (03) 42 33 757 postopek 279 2023 sp/vh povabilo k oddaji ponudbe narocnik vabi ponudnike da v skladu z navodili ponudnikom za izdelavo ponudbe za tehtnica za pacienta talna z visinomerom 1 kom splosne zahteve osnova za realizacijo dobave je prejem pisnega narocila strani narocnika. ponudbe zbiramo informativno za predlozitev v presojo odobritve. v kolikor bomo prejeli odobritev s strani pristojnih bomo realizacijo izvedli pri najugodnejsemu ponudniku ki bo izpolnjeval tehnicne zahteve. narocnik se zavezuje naroceno ter dobavljeno blago placati v roku kot ga doloca veljavna zakonodaja. cena mora vsebovati vse stroske popuste rabate dostavo montazo in davek na dodano vrednost. ponudbi predlozite prospekte ter drugo dokumentacijo iz katere je razvidno izpolnjevanje zahtev. kontaktna oseba s strani narocnika ; stanislava pahole hocevar dipl. ekon. tel. st. 03 423 36 84 elektronska posta stanislava.pahole sb celje.si ponudbe posljite na naslov elektronske poste nabava1 sb celje.si z oznako 279 2023 tehtnica za pacienta do najkasneje 09.06.2023 do 12 ure. priloga obrazec predracuna (obr 2) izjavna o izpolnjevanju tehnicne specifikacije opreme (obr 4) obveznost izbranega ponudnika obrazec predracuna obr 2 ponudnik predmet tehtnica za pacienta talna z visinomerom predracun (oprema ) opis proizvajalec (1) model oz. kataloska stevilka (2) kolicina (3) vrednost brez ddv (4) 1. tehtnica za pacienta talna z visinomerom 1 kom vrednost opreme v eur brez ddv (1) znesek davka za opremo skupaj vrednost v eur z ddv datum zig in podpis ponudnika sestavni del in priloga ponudbe . obr 4 izjava o izpolnjevanju tehnicne specifikacije opreme ponudnik pod kazensko in materialno odgovornostjo izjavljamo da izpolnjujemo tehnicne zahteve navedene v tem dokumentu da bomo ponudbi predlozili originalne prospekte proizvajalca ter ostalo originalno dokumentacijo proizvajalca iz katere je razvidna oprema ki je predmet ponudbe da bo izpolnjevanje vseh zahtev iz opisa predmeta narocila mora biti razvidno iz originalnih prospektov proizvajalca ter ostale originalne dokumentacije proizvajalca slednje bomo ustrezno oznacili podcrtali in navedli ustrezno zap.st. ki izhaja iz opisa predmeta narocila tehtnica za pacienta talna z merilno letvijo v skladu z naslednjimi tehnicnimi zahtevami opomba natancnost 100g 150g<200g. baterijsko in omrezno napajanje 220v funkcija hold in tara overljiva tocnostni razred iii tehtnica odobrena za medicinske namene (m) imeti mora merilno letev visina merjenja vsaj 200 cm teza merjenja cca 200kg kraj in datum zig in podpis ponudnika 10 postopek sp/vh", "ner": [{"TenderOrg": "splosna bolnisnica celje"}, {"TenderTel": "(03) 42 33 000"}, {"TenderFax": "(03) 42 33 757"}, {"TenderNumber": "279"}, {"TenderYear": "2023"}, {"TenderCode": "sp/vh"}, {"TenderDeadline": "09.06.2023"}, {"TenderPerson": "stanislava pahole hocevar"}, {"TenderTel": "03 423 36 84"}, {"TenderType": "m"}], "ner_refine": []}
{"id": "2023_EN_M_486_TENDER", "chunk_id": "0", "input_tokens": 2256, "refiner_input_tokens": 0, "total_output_tokens": 124, "text": "oblakova ulica 5 3000 celje tel (03) 42 33 000 postopek 486 2023 sdk/vh povabilo k oddaji ponudbe vabimo vas k oddaji ponudbe za predmet dolgo zilno uvajalo 25cm 7f kateter dolgo zilno uvajalo za femoralni pristop 25 cm 7f kateter notranji in zunanji lumen morata biti prevlecena s prevleko za manjse trenje med katetrom in zilnim uvajalom. letna kolicina 120 kos sukcesivna dobava splosne zahteve osnova za realizacijo dobave je prejem pisnega narocila strani narocnika.. v kolikor bomo prejeli odobritev s strani pristojnih bomo realizacijo izvedli pri najugodnejsemu ponudniku ki bo izpolnjeval tehnicne zahteve. narocnik bo ponudnike ki so oddali ponudbo skladno z dolocilom drugega odstavka 21. clena zjn 3 pisno obvestil najkasneje v roku 30 dni od oddaje evidencnega narocila. narocnik je v specifikacijah zahtev oz. koda artikla navedel tip opreme izkljucno z namenom da se doloci zahtevana raven kakovosti. v ponudbi lahko ponudite tudi artikel drugih proizvajalcev vendar mora biti le ta enakovredna. ponudbene vrednosti vkljucujejo vse stroske davke in morebitne popuste stroske dela rezijske stroske morebitne nadure amortizacijo opreme stroske dostave odvoza menjave blaga rokovanja in del povezanih z embalazo in morebitne druge stroske ki vplivajo na izracun cene. narocnik bo narocal blago s pisno z narocilnico. narocnik bo v narocilnici opredeliti vrste in kolicine blaga. dobavitelj je dolzan najkasneje v roku dveh ur od prejema narocila potrditi prejem narocila in obvestiti narocnika o morebitno zamudi pri dobavi ali zamenjavi istovrstnega blaga. kolicine in vrste blaga po predracunu so okvirne in za narocnika niso obvezujoce. dobavitelj zagotavlja dostavo blaga ddp splosna bolnisnica celje razlozeno lekarna narocnika (v delovnem casu narocnika od ponedeljka do petka). ponudnik mora zagotavljati dobavo celotne narocene kolicine v roku najkasneje 2. delovnih dni oziroma v nujnih primerih manj po predhodnem dogovoru z narocnikom (v delovnem casu od ponedeljka do petka v delovnem casu od 7 00 do 14 00 ). narocnik se obvezuje blago prevzeti v celoti na podlagi pravilno izpolnjene dobavnice. steje se da je dobavnica pravilno izpolnjena ce vsebuje najmanj naslednje naziv artikla cena na enoto mere kolicina morebitni popust kataloska stevilka artikla crtna koda dobaviteljeva sifra serijsko stevilko artikla rok uporabnosti stopnjo ddv ja stevilka narocilnice. kolicinski prevzem blaga oz. pregled se opravi takoj ob prevzemu blaga. kolicinska odstopanja ki jih ni bilo moc ugotoviti ob prevzemu mora posamezni narocnik pisno reklamirati najkasneje v treh (8) delovnih dneh od prevzema. dobavljeno blago mora ustrezati dogovorjeni kakovosti ter biti v skladu s tem sporazumom in njegovimi prilogami za vsak artikel posebej. kakovostna odstopanja lahko posamezni narocnik pisno reklamira najkasneje v 30. (tridesetih) dneh od prevzema blaga.", "ner": [{"TenderOrg": "splosna bolnisnica celje"}, {"TenderTel": "(03) 42 33 000"}, {"TenderNumber": "486"}, {"TenderYear": "2023"}, {"TenderCode": "sdk/vh"}, {"TenderType": "m"}], "ner_refine": []}
{"id": "2023_EN_M_486_TENDER", "chunk_id": "1", "input_tokens": 2220, "refiner_input_tokens": 0, "total_output_tokens": 23, "text": "ce dobava ne ustreza naroceni kolicini in/ali kakovosti je dobavitelj dolzan pomanjkljivosti nemudoma brezplacno odpraviti. v kolikor dobavitelj napak ne odpravi v roku dveh delovnih dni od prejema reklamacije to lahko stori posamezni narocnik na stroske dobavitelja in zahteva od dobavitelja povrnitev nastale skode. kakovost blaga mora ustrezati obstojecim standardom in deklarirani kakovosti na embalazi oziroma spremljajocih dokumentih. blago mora ustrezati tudi pogojem in zahtevam opredeljenimi v razpisni dokumentaciji narocnika in strokovnim kriterijem oz. znacilnostim. blago mora biti obvezno pakirano v originalni embalazi (kot izhaja iz proizvajalcevega kataloga). blago mora imeti oznako ce in izpolnjevati vse tehnicne zahteve dolocena v navodilih ponudnikov. dobavljeno blago mora imeti rok uporabe se najmanj dve tretjini deklariranega roka uporabe ki ga navaja proizvajalec ponujenega blaga. v primeru krajsega roka uporabe mora ponudnik pred dostavo pridobiti pisno soglasje narocnika. vsak izstavljen racun mora vsebovati podatke o narocnikovi stevilki okvirnega sporazuma narocilnice oz. odjave porabljenega blaga in dobavnice ter vse elemente kot dobavnica. izstavljen racun mora imeti prilogo narocilnice oz. odjave porabljenega blaga dobavnice dobavitelj mora vse racune narocniku posiljati izkljucno v elektronski obliki (e racun) skladno z veljavnim zakonom o opravljanju placilnih storitev za proracunske uporabnike. dobavitelj mora izdati locen racun izkljucno vezan na predmetni sporazum zbirni racun ni dopusten in ga bo narocnik zavrnil. ponudnik mora biti vpisan v enega od registrov ki ga vodi jazmp (po skupini registrov) registrov poslovnih subjektov s sedezem v republiki sloveniji ki opravljajo dejavnost na podrocju medicinskih pripomockov registriranih po zacetku uporabe uredbe o medicinskih pripomockih (eu) st. 2017/745 registrov poslovnih subjektov z dejavnostjo na podrocju medicinskih pripomockov pred zacetkom uporabe uredbe o medicinskih pripomockih (eu) st. 2017/745 registrov medicinskih pripomockov skladnih z mdr katerih proizvajalci oz. predstavniki proizvajalcev imajo sedez v rs registrov medicinskih pripomockov skladnih z direktivo 90/385/es o aktivnih medicinskih pripomockih za vsaditev direktivo 93/42/egs o medicinskih pripomockih direktivo 98/79/es o in vitro diagnosticnih medicinskih pripomockih registrov medicinskih pripomockov katerih proizvajalci oz. predstavniki proizvajalcev imajo sedez v rs ponudniku medicinskih pripomockov s sedezem v drugi drzavi clanici evropske unije se ni potrebno priglasiti v register veletrgovcev ali proizvajalcev medicinskih pripomockov v sloveniji predloziti pa mora ustrezno potrdilo drzave clanice iz katere izhaja. ce je ponudnik iz druge drzave clanice eu ne glede na to ali je hkrati proizvajalec razpisanega blaga v ponudbi prilozi dokazilo v skladu s predpisi drzave v kateri ima ponudnik svoj sedez.", "ner": [], "ner_refine": []}
{"id": "2023_EN_M_423_TENDER", "chunk_id": "0", "input_tokens": 2269, "refiner_input_tokens": 0, "total_output_tokens": 124, "text": "oblakova ulica 5 3000 celje tel (03) 42 33 000 postopek 423 2023 sdk/vh povabilo k oddaji ponudbe vabimo vas k oddaji ponudbe za predmet kiwi omnicup vakum.ekstraktor v skladu z opisom kot sledi iz obr 1 kot npr. kataloska stevilka vac 6000me letna kolicina 30 kos sukcesivna dobava splosne zahteve osnova za realizacijo dobave je prejem pisnega narocila strani narocnika.. v kolikor bomo prejeli odobritev s strani pristojnih bomo realizacijo izvedli pri najugodnejsemu ponudniku ki bo izpolnjeval tehnicne zahteve. narocnik bo ponudnike ki so oddali ponudbo skladno z dolocilom drugega odstavka 21. clena zjn 3 pisno obvestil najkasneje v roku 30 dni od oddaje evidencnega narocila. narocnik je v specifikacijah zahtev oz. koda artikla navedel tip opreme izkljucno z namenom da se doloci zahtevana raven kakovosti. v ponudbi lahko ponudite tudi artikel drugih proizvajalcev vendar mora biti le ta enakovredna. ponudbene vrednosti vkljucujejo vse stroske davke in morebitne popuste stroske dela rezijske stroske morebitne nadure amortizacijo opreme stroske dostave odvoza menjave blaga rokovanja in del povezanih z embalazo in morebitne druge stroske ki vplivajo na izracun cene. narocnik bo narocal blago s pisno z narocilnico. narocnik bo v narocilnici opredeliti vrste in kolicine blaga. dobavitelj je dolzan najkasneje v roku dveh ur od prejema narocila potrditi prejem narocila in obvestiti narocnika o morebitno zamudi pri dobavi ali zamenjavi istovrstnega blaga. kolicine in vrste blaga po predracunu so okvirne in za narocnika niso obvezujoce. dobavitelj zagotavlja dostavo blaga ddp splosna bolnisnica celje razlozeno lekarna narocnika (v delovnem casu narocnika od ponedeljka do petka). ponudnik mora zagotavljati dobavo celotne narocene kolicine v roku najkasneje 2. delovnih dni oziroma v nujnih primerih manj po predhodnem dogovoru z narocnikom (v delovnem casu od ponedeljka do petka v delovnem casu od 7 00 do 14 00 ). narocnik se obvezuje blago prevzeti v celoti na podlagi pravilno izpolnjene dobavnice. steje se da je dobavnica pravilno izpolnjena ce vsebuje najmanj naslednje naziv artikla cena na enoto mere kolicina morebitni popust kataloska stevilka artikla crtna koda dobaviteljeva sifra serijsko stevilko artikla rok uporabnosti stopnjo ddv ja stevilka narocilnice. kolicinski prevzem blaga oz. pregled se opravi takoj ob prevzemu blaga. kolicinska odstopanja ki jih ni bilo moc ugotoviti ob prevzemu mora posamezni narocnik pisno reklamirati najkasneje v treh (8) delovnih dneh od prevzema. dobavljeno blago mora ustrezati dogovorjeni kakovosti ter biti v skladu s tem sporazumom in njegovimi prilogami za vsak artikel posebej. kakovostna odstopanja lahko posamezni narocnik pisno reklamira najkasneje v 30. (tridesetih) dneh od prevzema blaga. ce dobava ne ustreza naroceni kolicini in/ali kakovosti je dobavitelj dolzan pomanjkljivosti nemudoma brezplacno odpraviti.", "ner": [{"TenderOrg": "splosna bolnisnica celje"}, {"TenderTel": "(03) 42 33 000"}, {"TenderNumber": "423"}, {"TenderYear": "2023"}, {"TenderCode": "sdk/vh"}, {"TenderType": "m"}], "ner_refine": []}
{"id": "2023_EN_M_423_TENDER", "chunk_id": "1", "input_tokens": 2177, "refiner_input_tokens": 0, "total_output_tokens": 23, "text": "v kolikor dobavitelj napak ne odpravi v roku dveh delovnih dni od prejema reklamacije to lahko stori posamezni narocnik na stroske dobavitelja in zahteva od dobavitelja povrnitev nastale skode. kakovost blaga mora ustrezati obstojecim standardom in deklarirani kakovosti na embalazi oziroma spremljajocih dokumentih. blago mora ustrezati tudi pogojem in zahtevam opredeljenimi v razpisni dokumentaciji narocnika in strokovnim kriterijem oz. znacilnostim. blago mora biti obvezno pakirano v originalni embalazi (kot izhaja iz proizvajalcevega kataloga). blago mora imeti oznako ce in izpolnjevati vse tehnicne zahteve dolocena v navodilih ponudnikov. dobavljeno blago mora imeti rok uporabe se najmanj dve tretjini deklariranega roka uporabe ki ga navaja proizvajalec ponujenega blaga. v primeru krajsega roka uporabe mora ponudnik pred dostavo pridobiti pisno soglasje narocnika. vsak izstavljen racun mora vsebovati podatke o narocnikovi stevilki okvirnega sporazuma narocilnice oz. odjave porabljenega blaga in dobavnice ter vse elemente kot dobavnica. izstavljen racun mora imeti prilogo narocilnice oz. odjave porabljenega blaga dobavnice dobavitelj mora vse racune narocniku posiljati izkljucno v elektronski obliki (e racun) skladno z veljavnim zakonom o opravljanju placilnih storitev za proracunske uporabnike. dobavitelj mora izdati locen racun izkljucno vezan na predmetni sporazum zbirni racun ni dopusten in ga bo narocnik zavrnil. ponudnik mora biti vpisan v enega od registrov ki ga vodi jazmp (po skupini registrov) registrov poslovnih subjektov s sedezem v republiki sloveniji ki opravljajo dejavnost na podrocju medicinskih pripomockov registriranih po zacetku uporabe uredbe o medicinskih pripomockih (eu) st. 2017/745 registrov poslovnih subjektov z dejavnostjo na podrocju medicinskih pripomockov pred zacetkom uporabe uredbe o medicinskih pripomockih (eu) st. 2017/745 registrov medicinskih pripomockov skladnih z mdr katerih proizvajalci oz. predstavniki proizvajalcev imajo sedez v rs registrov medicinskih pripomockov skladnih z direktivo 90/385/es o aktivnih medicinskih pripomockih za vsaditev direktivo 93/42/egs o medicinskih pripomockih direktivo 98/79/es o in vitro diagnosticnih medicinskih pripomockih registrov medicinskih pripomockov katerih proizvajalci oz. predstavniki proizvajalcev imajo sedez v rs ponudniku medicinskih pripomockov s sedezem v drugi drzavi clanici evropske unije se ni potrebno priglasiti v register veletrgovcev ali proizvajalcev medicinskih pripomockov v sloveniji predloziti pa mora ustrezno potrdilo drzave clanice iz katere izhaja. ce je ponudnik iz druge drzave clanice eu ne glede na to ali je hkrati proizvajalec razpisanega blaga v ponudbi prilozi dokazilo v skladu s predpisi drzave v kateri ima ponudnik svoj sedez.", "ner": [], "ner_refine": []}
{"id": "2023_EN_M_421_TENDER", "chunk_id": "0", "input_tokens": 2267, "refiner_input_tokens": 0, "total_output_tokens": 124, "text": "oblakova ulica 5 3000 celje tel (03) 42 33 000 postopek 421 2023 sdk/vh povabilo k oddaji ponudbe vabimo vas k oddaji ponudbe za predmet kit za zapiranje hepar.kapilar v skladu z opisom kot sledi iz obr 1 kot npr. kataloska stevilka 749510 letna kolicina 2 sc sukcesivna dobava splosne zahteve osnova za realizacijo dobave je prejem pisnega narocila strani narocnika.. v kolikor bomo prejeli odobritev s strani pristojnih bomo realizacijo izvedli pri najugodnejsemu ponudniku ki bo izpolnjeval tehnicne zahteve. narocnik bo ponudnike ki so oddali ponudbo skladno z dolocilom drugega odstavka 21. clena zjn 3 pisno obvestil najkasneje v roku 30 dni od oddaje evidencnega narocila. narocnik je v specifikacijah zahtev oz. koda artikla navedel tip opreme izkljucno z namenom da se doloci zahtevana raven kakovosti. v ponudbi lahko ponudite tudi artikel drugih proizvajalcev vendar mora biti le ta enakovredna. ponudbene vrednosti vkljucujejo vse stroske davke in morebitne popuste stroske dela rezijske stroske morebitne nadure amortizacijo opreme stroske dostave odvoza menjave blaga rokovanja in del povezanih z embalazo in morebitne druge stroske ki vplivajo na izracun cene. narocnik bo narocal blago s pisno z narocilnico. narocnik bo v narocilnici opredeliti vrste in kolicine blaga. dobavitelj je dolzan najkasneje v roku dveh ur od prejema narocila potrditi prejem narocila in obvestiti narocnika o morebitno zamudi pri dobavi ali zamenjavi istovrstnega blaga. kolicine in vrste blaga po predracunu so okvirne in za narocnika niso obvezujoce. dobavitelj zagotavlja dostavo blaga ddp splosna bolnisnica celje razlozeno lekarna narocnika (v delovnem casu narocnika od ponedeljka do petka). ponudnik mora zagotavljati dobavo celotne narocene kolicine v roku najkasneje 2. delovnih dni oziroma v nujnih primerih manj po predhodnem dogovoru z narocnikom (v delovnem casu od ponedeljka do petka v delovnem casu od 7 00 do 14 00 ). narocnik se obvezuje blago prevzeti v celoti na podlagi pravilno izpolnjene dobavnice. steje se da je dobavnica pravilno izpolnjena ce vsebuje najmanj naslednje naziv artikla cena na enoto mere kolicina morebitni popust kataloska stevilka artikla crtna koda dobaviteljeva sifra serijsko stevilko artikla rok uporabnosti stopnjo ddv ja stevilka narocilnice. kolicinski prevzem blaga oz. pregled se opravi takoj ob prevzemu blaga. kolicinska odstopanja ki jih ni bilo moc ugotoviti ob prevzemu mora posamezni narocnik pisno reklamirati najkasneje v treh (8) delovnih dneh od prevzema. dobavljeno blago mora ustrezati dogovorjeni kakovosti ter biti v skladu s tem sporazumom in njegovimi prilogami za vsak artikel posebej. kakovostna odstopanja lahko posamezni narocnik pisno reklamira najkasneje v 30. (tridesetih) dneh od prevzema blaga. ce dobava ne ustreza naroceni kolicini in/ali kakovosti je dobavitelj dolzan pomanjkljivosti nemudoma brezplacno odpraviti.", "ner": [{"TenderOrg": "splosna bolnisnica celje"}, {"TenderTel": "(03) 42 33 000"}, {"TenderNumber": "421"}, {"TenderYear": "2023"}, {"TenderCode": "sdk/vh"}, {"TenderType": "m"}], "ner_refine": []}
{"id": "2023_EN_M_421_TENDER", "chunk_id": "1", "input_tokens": 2177, "refiner_input_tokens": 0, "total_output_tokens": 23, "text": "v kolikor dobavitelj napak ne odpravi v roku dveh delovnih dni od prejema reklamacije to lahko stori posamezni narocnik na stroske dobavitelja in zahteva od dobavitelja povrnitev nastale skode. kakovost blaga mora ustrezati obstojecim standardom in deklarirani kakovosti na embalazi oziroma spremljajocih dokumentih. blago mora ustrezati tudi pogojem in zahtevam opredeljenimi v razpisni dokumentaciji narocnika in strokovnim kriterijem oz. znacilnostim. blago mora biti obvezno pakirano v originalni embalazi (kot izhaja iz proizvajalcevega kataloga). blago mora imeti oznako ce in izpolnjevati vse tehnicne zahteve dolocena v navodilih ponudnikov. dobavljeno blago mora imeti rok uporabe se najmanj dve tretjini deklariranega roka uporabe ki ga navaja proizvajalec ponujenega blaga. v primeru krajsega roka uporabe mora ponudnik pred dostavo pridobiti pisno soglasje narocnika. vsak izstavljen racun mora vsebovati podatke o narocnikovi stevilki okvirnega sporazuma narocilnice oz. odjave porabljenega blaga in dobavnice ter vse elemente kot dobavnica. izstavljen racun mora imeti prilogo narocilnice oz. odjave porabljenega blaga dobavnice dobavitelj mora vse racune narocniku posiljati izkljucno v elektronski obliki (e racun) skladno z veljavnim zakonom o opravljanju placilnih storitev za proracunske uporabnike. dobavitelj mora izdati locen racun izkljucno vezan na predmetni sporazum zbirni racun ni dopusten in ga bo narocnik zavrnil. ponudnik mora biti vpisan v enega od registrov ki ga vodi jazmp (po skupini registrov) registrov poslovnih subjektov s sedezem v republiki sloveniji ki opravljajo dejavnost na podrocju medicinskih pripomockov registriranih po zacetku uporabe uredbe o medicinskih pripomockih (eu) st. 2017/745 registrov poslovnih subjektov z dejavnostjo na podrocju medicinskih pripomockov pred zacetkom uporabe uredbe o medicinskih pripomockih (eu) st. 2017/745 registrov medicinskih pripomockov skladnih z mdr katerih proizvajalci oz. predstavniki proizvajalcev imajo sedez v rs registrov medicinskih pripomockov skladnih z direktivo 90/385/es o aktivnih medicinskih pripomockih za vsaditev direktivo 93/42/egs o medicinskih pripomockih direktivo 98/79/es o in vitro diagnosticnih medicinskih pripomockih registrov medicinskih pripomockov katerih proizvajalci oz. predstavniki proizvajalcev imajo sedez v rs ponudniku medicinskih pripomockov s sedezem v drugi drzavi clanici evropske unije se ni potrebno priglasiti v register veletrgovcev ali proizvajalcev medicinskih pripomockov v sloveniji predloziti pa mora ustrezno potrdilo drzave clanice iz katere izhaja. ce je ponudnik iz druge drzave clanice eu ne glede na to ali je hkrati proizvajalec razpisanega blaga v ponudbi prilozi dokazilo v skladu s predpisi drzave v kateri ima ponudnik svoj sedez.", "ner": [], "ner_refine": []}
{"id": "2023_EN_M_444_TENDER", "chunk_id": "0", "input_tokens": 2247, "refiner_input_tokens": 0, "total_output_tokens": 102, "text": "oblakova ulica 5 3000 celje tel (03) 42 33 000 postopek 444 2023 sdk/vh povabilo k oddaji ponudbe vabimo vas k oddaji ponudbe za predmet posodica za urin z navojem 120 ml letna kolicina 13.000 kos sukcesivna dobava splosne zahteve osnova za realizacijo dobave je prejem pisnega narocila strani narocnika.. v kolikor bomo prejeli odobritev s strani pristojnih bomo realizacijo izvedli pri najugodnejsemu ponudniku ki bo izpolnjeval tehnicne zahteve. narocnik bo ponudnike ki so oddali ponudbo skladno z dolocilom drugega odstavka 21. clena zjn 3 pisno obvestil najkasneje v roku 30 dni od oddaje evidencnega narocila. narocnik je v specifikacijah zahtev oz. koda artikla navedel tip opreme izkljucno z namenom da se doloci zahtevana raven kakovosti. v ponudbi lahko ponudite tudi artikel drugih proizvajalcev vendar mora biti le ta enakovredna. ponudbene vrednosti vkljucujejo vse stroske davke in morebitne popuste stroske dela rezijske stroske morebitne nadure amortizacijo opreme stroske dostave odvoza menjave blaga rokovanja in del povezanih z embalazo in morebitne druge stroske ki vplivajo na izracun cene. narocnik bo narocal blago s pisno z narocilnico. narocnik bo v narocilnici opredeliti vrste in kolicine blaga. dobavitelj je dolzan najkasneje v roku dveh ur od prejema narocila potrditi prejem narocila in obvestiti narocnika o morebitno zamudi pri dobavi ali zamenjavi istovrstnega blaga. kolicine in vrste blaga po predracunu so okvirne in za narocnika niso obvezujoce. dobavitelj zagotavlja dostavo blaga ddp splosna bolnisnica celje razlozeno lekarna narocnika (v delovnem casu narocnika od ponedeljka do petka). ponudnik mora zagotavljati dobavo celotne narocene kolicine v roku najkasneje 2. delovnih dni oziroma v nujnih primerih manj po predhodnem dogovoru z narocnikom (v delovnem casu od ponedeljka do petka v delovnem casu od 7 00 do 14 00 ). narocnik se obvezuje blago prevzeti v celoti na podlagi pravilno izpolnjene dobavnice. steje se da je dobavnica pravilno izpolnjena ce vsebuje najmanj naslednje naziv artikla cena na enoto mere kolicina morebitni popust kataloska stevilka artikla crtna koda dobaviteljeva sifra serijsko stevilko artikla rok uporabnosti stopnjo ddv ja stevilka narocilnice. kolicinski prevzem blaga oz. pregled se opravi takoj ob prevzemu blaga. kolicinska odstopanja ki jih ni bilo moc ugotoviti ob prevzemu mora posamezni narocnik pisno reklamirati najkasneje v treh (8) delovnih dneh od prevzema. dobavljeno blago mora ustrezati dogovorjeni kakovosti ter biti v skladu s tem sporazumom in njegovimi prilogami za vsak artikel posebej. kakovostna odstopanja lahko posamezni narocnik pisno reklamira najkasneje v 30. (tridesetih) dneh od prevzema blaga. ce dobava ne ustreza naroceni kolicini in/ali kakovosti je dobavitelj dolzan pomanjkljivosti nemudoma brezplacno odpraviti.", "ner": [{"TenderTel": "(03) 42 33 000"}, {"TenderNumber": "444"}, {"TenderYear": "2023"}, {"TenderCode": "sdk/vh"}, {"TenderType": "m"}], "ner_refine": []}
{"id": "2023_EN_M_444_TENDER", "chunk_id": "1", "input_tokens": 2177, "refiner_input_tokens": 0, "total_output_tokens": 23, "text": "v kolikor dobavitelj napak ne odpravi v roku dveh delovnih dni od prejema reklamacije to lahko stori posamezni narocnik na stroske dobavitelja in zahteva od dobavitelja povrnitev nastale skode. kakovost blaga mora ustrezati obstojecim standardom in deklarirani kakovosti na embalazi oziroma spremljajocih dokumentih. blago mora ustrezati tudi pogojem in zahtevam opredeljenimi v razpisni dokumentaciji narocnika in strokovnim kriterijem oz. znacilnostim. blago mora biti obvezno pakirano v originalni embalazi (kot izhaja iz proizvajalcevega kataloga). blago mora imeti oznako ce in izpolnjevati vse tehnicne zahteve dolocena v navodilih ponudnikov. dobavljeno blago mora imeti rok uporabe se najmanj dve tretjini deklariranega roka uporabe ki ga navaja proizvajalec ponujenega blaga. v primeru krajsega roka uporabe mora ponudnik pred dostavo pridobiti pisno soglasje narocnika. vsak izstavljen racun mora vsebovati podatke o narocnikovi stevilki okvirnega sporazuma narocilnice oz. odjave porabljenega blaga in dobavnice ter vse elemente kot dobavnica. izstavljen racun mora imeti prilogo narocilnice oz. odjave porabljenega blaga dobavnice dobavitelj mora vse racune narocniku posiljati izkljucno v elektronski obliki (e racun) skladno z veljavnim zakonom o opravljanju placilnih storitev za proracunske uporabnike. dobavitelj mora izdati locen racun izkljucno vezan na predmetni sporazum zbirni racun ni dopusten in ga bo narocnik zavrnil. ponudnik mora biti vpisan v enega od registrov ki ga vodi jazmp (po skupini registrov) registrov poslovnih subjektov s sedezem v republiki sloveniji ki opravljajo dejavnost na podrocju medicinskih pripomockov registriranih po zacetku uporabe uredbe o medicinskih pripomockih (eu) st. 2017/745 registrov poslovnih subjektov z dejavnostjo na podrocju medicinskih pripomockov pred zacetkom uporabe uredbe o medicinskih pripomockih (eu) st. 2017/745 registrov medicinskih pripomockov skladnih z mdr katerih proizvajalci oz. predstavniki proizvajalcev imajo sedez v rs registrov medicinskih pripomockov skladnih z direktivo 90/385/es o aktivnih medicinskih pripomockih za vsaditev direktivo 93/42/egs o medicinskih pripomockih direktivo 98/79/es o in vitro diagnosticnih medicinskih pripomockih registrov medicinskih pripomockov katerih proizvajalci oz. predstavniki proizvajalcev imajo sedez v rs ponudniku medicinskih pripomockov s sedezem v drugi drzavi clanici evropske unije se ni potrebno priglasiti v register veletrgovcev ali proizvajalcev medicinskih pripomockov v sloveniji predloziti pa mora ustrezno potrdilo drzave clanice iz katere izhaja. ce je ponudnik iz druge drzave clanice eu ne glede na to ali je hkrati proizvajalec razpisanega blaga v ponudbi prilozi dokazilo v skladu s predpisi drzave v kateri ima ponudnik svoj sedez.", "ner": [], "ner_refine": []}
{"id": "2023_EN_M_218_TENDER", "chunk_id": "0", "input_tokens": 2198, "refiner_input_tokens": 0, "total_output_tokens": 223, "text": "2 narocnik splosna bolnisnica celje oblakova ulica 5 3000 celje tel (03) 42 33 000 fax (03) 42 33 757 postopek 218 2023 sp/vh povabilo k oddaji ponudbe narocnik vabi ponudnike da v skladu z navodili ponudnikom za izdelavo ponudbe za vozicek za nego 1kom splosne zahteve osnova za realizacijo dobave je prejem pisnega narocila strani narocnika. ponudbe zbiramo informativno za predlozitev v presojo odobritve. v kolikor bomo prejeli odobritev s strani pristojnih bomo realizacijo izvedli pri najugodnejsemu ponudniku ki bo izpolnjeval tehnicne zahteve. cena mora vsebovati vse stroske popuste rabate dostavo montazo in davek na dodano vrednost. narocnik se zavezuje naroceno ter dobavljeno blago placati v roku kot ga doloca veljavna zakonodaja. izvajalec mora zagotoviti dostavo blaga ter montazo in namestitev v prostor pri narocniku. ponudbi predlozite prospekte ter drugo dokumentacijo iz katere je razvidno izpolnjevanje tehnicnih zahtev. kontaktna oseba s strani narocnika ; stanislava pahole hocevar dipl.ekon. tel.st. 03 423 36 84 stanislava.pahole sb celje.si ponudbe posljite na naslov elektronske poste nabava1 sb celje.si z oznako 218 2023 vozicek za nego do najkasneje 04.05.2023 do 12ure. priloga obrazec predracuna (obr 1) obveznost izbranega ponudnika (obr 2) obrazec predracuna obr 1 ponudnik predmet servirni vozicek opis proizvajalec (1) model oz. kataloska stevilka (2) kolicina (3) vrednost brez ddv (4) 1. vozicek za nego 1 kom vrednost opreme v eur brez ddv (1) znesek davka za opremo skupaj vrednost v eur z ddv datum zig in podpis ponudnika obr 2 izjava o izpolnjevanju tehnicne specifikacije opreme ponudnik pod kazensko in materialno odgovornostjo izjavljamo da izpolnjujemo tehnicne zahteve navedene v tem dokumenta ter obr 3 da bomo ponudbi predlozili originalne prospekte proizvajalca ter ostalo originalno dokumentacijo proizvajalca iz katere je razvidna oprema ki je predmet ponudbe da bo izpolnjevanje vseh zahtev iz opisa predmeta narocila mora biti razvidno iz originalnih prospektov proizvajalca ter ostale originalne dokumentacije proizvajalca slednje bomo ustrezno oznacili podcrtali in navedli ustrezno zap. st. ki izhaja iz opisa predmeta narocila vozicek za nego opomba inox nerjaveci material dimenzije cca. 130 x 55 x 105 hcm razdeljen na dva dela vecji del opremljen s tremi policami iz nerjavecega jekla manjsi del z eno polico minimalna velikost 50x 35 cm (polica spodaj) celni stanici zaprti z mrezo kolesa fi 125mm od tega imata dve kolesi tockovno zaporo omogoceno je suho ter mokro ciscenje s sredstvi za higienizacijo in dezinfekcijo kraj in datum zig in podpis ponudnika 10 postopek sp/vh", "ner": [{"TenderOrg": "splosna bolnisnica celje"}, {"TenderTel": "(03) 42 33 000"}, {"TenderFax": "(03) 42 33 757"}, {"TenderNumber": "218"}, {"TenderYear": "2023"}, {"TenderCode": "sp/vh"}, {"TenderPerson": "stanislava pahole hocevar"}, {"TenderTel": "03 423 36 84"}, {"TenderDeadline": "04.05.2023"}, {"TenderType": "m"}], "ner_refine": []}
{"id": "2023_EN_M_496_TENDER", "chunk_id": "0", "input_tokens": 2255, "refiner_input_tokens": 0, "total_output_tokens": 124, "text": "oblakova ulica 5 3000 celje tel (03) 42 33 000 postopek 496 2023 sdk/vh povabilo k oddaji ponudbe vabimo vas k oddaji ponudbe za predmet liquiband lepilo z aplikatorjem za fiksiranje mrezice pri laparoskopski operaciji kil. letna kolicina 60 kos sukcesivna dobava splosne zahteve osnova za realizacijo dobave je prejem pisnega narocila strani narocnika.. v kolikor bomo prejeli odobritev s strani pristojnih bomo realizacijo izvedli pri najugodnejsemu ponudniku ki bo izpolnjeval tehnicne zahteve. narocnik bo ponudnike ki so oddali ponudbo skladno z dolocilom drugega odstavka 21. clena zjn 3 pisno obvestil najkasneje v roku 30 dni od oddaje evidencnega narocila. narocnik je v specifikacijah zahtev oz. koda artikla navedel tip opreme izkljucno z namenom da se doloci zahtevana raven kakovosti. v ponudbi lahko ponudite tudi artikel drugih proizvajalcev vendar mora biti le ta enakovredna. ponudbene vrednosti vkljucujejo vse stroske davke in morebitne popuste stroske dela rezijske stroske morebitne nadure amortizacijo opreme stroske dostave odvoza menjave blaga rokovanja in del povezanih z embalazo in morebitne druge stroske ki vplivajo na izracun cene. narocnik bo narocal blago s pisno z narocilnico. narocnik bo v narocilnici opredeliti vrste in kolicine blaga. dobavitelj je dolzan najkasneje v roku dveh ur od prejema narocila potrditi prejem narocila in obvestiti narocnika o morebitno zamudi pri dobavi ali zamenjavi istovrstnega blaga. kolicine in vrste blaga po predracunu so okvirne in za narocnika niso obvezujoce. dobavitelj zagotavlja dostavo blaga ddp splosna bolnisnica celje razlozeno lekarna narocnika (v delovnem casu narocnika od ponedeljka do petka). ponudnik mora zagotavljati dobavo celotne narocene kolicine v roku najkasneje 2. delovnih dni oziroma v nujnih primerih manj po predhodnem dogovoru z narocnikom (v delovnem casu od ponedeljka do petka v delovnem casu od 7 00 do 14 00 ). narocnik se obvezuje blago prevzeti v celoti na podlagi pravilno izpolnjene dobavnice. steje se da je dobavnica pravilno izpolnjena ce vsebuje najmanj naslednje naziv artikla cena na enoto mere kolicina morebitni popust kataloska stevilka artikla crtna koda dobaviteljeva sifra serijsko stevilko artikla rok uporabnosti stopnjo ddv ja stevilka narocilnice. kolicinski prevzem blaga oz. pregled se opravi takoj ob prevzemu blaga. kolicinska odstopanja ki jih ni bilo moc ugotoviti ob prevzemu mora posamezni narocnik pisno reklamirati najkasneje v treh (8) delovnih dneh od prevzema. dobavljeno blago mora ustrezati dogovorjeni kakovosti ter biti v skladu s tem sporazumom in njegovimi prilogami za vsak artikel posebej. kakovostna odstopanja lahko posamezni narocnik pisno reklamira najkasneje v 30. (tridesetih) dneh od prevzema blaga. ce dobava ne ustreza naroceni kolicini in/ali kakovosti je dobavitelj dolzan pomanjkljivosti nemudoma brezplacno odpraviti.", "ner": [{"TenderOrg": "splosna bolnisnica celje"}, {"TenderTel": "(03) 42 33 000"}, {"TenderNumber": "496"}, {"TenderYear": "2023"}, {"TenderCode": "sdk/vh"}, {"TenderType": "m"}], "ner_refine": []}
{"id": "2023_EN_M_496_TENDER", "chunk_id": "1", "input_tokens": 2177, "refiner_input_tokens": 0, "total_output_tokens": 23, "text": "v kolikor dobavitelj napak ne odpravi v roku dveh delovnih dni od prejema reklamacije to lahko stori posamezni narocnik na stroske dobavitelja in zahteva od dobavitelja povrnitev nastale skode. kakovost blaga mora ustrezati obstojecim standardom in deklarirani kakovosti na embalazi oziroma spremljajocih dokumentih. blago mora ustrezati tudi pogojem in zahtevam opredeljenimi v razpisni dokumentaciji narocnika in strokovnim kriterijem oz. znacilnostim. blago mora biti obvezno pakirano v originalni embalazi (kot izhaja iz proizvajalcevega kataloga). blago mora imeti oznako ce in izpolnjevati vse tehnicne zahteve dolocena v navodilih ponudnikov. dobavljeno blago mora imeti rok uporabe se najmanj dve tretjini deklariranega roka uporabe ki ga navaja proizvajalec ponujenega blaga. v primeru krajsega roka uporabe mora ponudnik pred dostavo pridobiti pisno soglasje narocnika. vsak izstavljen racun mora vsebovati podatke o narocnikovi stevilki okvirnega sporazuma narocilnice oz. odjave porabljenega blaga in dobavnice ter vse elemente kot dobavnica. izstavljen racun mora imeti prilogo narocilnice oz. odjave porabljenega blaga dobavnice dobavitelj mora vse racune narocniku posiljati izkljucno v elektronski obliki (e racun) skladno z veljavnim zakonom o opravljanju placilnih storitev za proracunske uporabnike. dobavitelj mora izdati locen racun izkljucno vezan na predmetni sporazum zbirni racun ni dopusten in ga bo narocnik zavrnil. ponudnik mora biti vpisan v enega od registrov ki ga vodi jazmp (po skupini registrov) registrov poslovnih subjektov s sedezem v republiki sloveniji ki opravljajo dejavnost na podrocju medicinskih pripomockov registriranih po zacetku uporabe uredbe o medicinskih pripomockih (eu) st. 2017/745 registrov poslovnih subjektov z dejavnostjo na podrocju medicinskih pripomockov pred zacetkom uporabe uredbe o medicinskih pripomockih (eu) st. 2017/745 registrov medicinskih pripomockov skladnih z mdr katerih proizvajalci oz. predstavniki proizvajalcev imajo sedez v rs registrov medicinskih pripomockov skladnih z direktivo 90/385/es o aktivnih medicinskih pripomockih za vsaditev direktivo 93/42/egs o medicinskih pripomockih direktivo 98/79/es o in vitro diagnosticnih medicinskih pripomockih registrov medicinskih pripomockov katerih proizvajalci oz. predstavniki proizvajalcev imajo sedez v rs ponudniku medicinskih pripomockov s sedezem v drugi drzavi clanici evropske unije se ni potrebno priglasiti v register veletrgovcev ali proizvajalcev medicinskih pripomockov v sloveniji predloziti pa mora ustrezno potrdilo drzave clanice iz katere izhaja. ce je ponudnik iz druge drzave clanice eu ne glede na to ali je hkrati proizvajalec razpisanega blaga v ponudbi prilozi dokazilo v skladu s predpisi drzave v kateri ima ponudnik svoj sedez.", "ner": [], "ner_refine": []}
{"id": "2023_EN_M_170_TENDER", "chunk_id": "0", "input_tokens": 1773, "refiner_input_tokens": 0, "total_output_tokens": 218, "text": "oblakova ulica 5 3000 celje tel (03) 42 33 000 fax (03) 42 33 757 postopek 170 2023 sdk/vh povabilo k oddaji ponudbe vabimo vas k oddaji ponudbe za predmet stilete izvijaci in kljucki potrebni so za revizijo elektrod pm in/ali menjavo elektrod 5 kos sukcesivna dobava osnova za realizacijo dobave je prejem pisnega narocila strani narocnika. ponudbe zbiramo informativno za predlozitev v presojo odobritve. v kolikor bomo prejeli odobritev s strani pristojnih bomo realizacijo izvedli pri najugodnejsemu ponudniku. cena mora vsebovati vse stroske popuste rabate in davek na dodano vrednost. izvajalec mora zagotoviti dostavo blaga v skladisce lekarne v delovnem casu za dostavo oz. prevzem blaga (od ponedeljka do petka od 6 00 do 14 ure). narocnik se zavezuje naroceno placati v roku kot ga doloca veljavna zakonodaja. merilo izbora najnizja vrednost ponudbe v eur z ddv ob izpolnjevanju tehnicnih zahtev narocnika. kontaktna oseba s strani narocnika ; sandra drljic kopranovic tel. st. 03 423 31 25 elektronska posta sandra.drljic kopranovic sb celje.si ponudbe posljite na naslov elektronske poste nabava1 sb celje.si z oznako 170 2023 stilete izvijaci in kljucki do najkasneje 30.03.2023 do 9. ure. vodja sluzbe za nabavo medicinske opreme potrosnega materiala in storitev vanja herman gril mag.manag.", "ner": [{"TenderTel": "(03) 42 33 000"}, {"TenderFax": "(03) 42 33 757"}, {"TenderNumber": "170"}, {"TenderYear": "2023"}, {"TenderCode": "sdk/vh"}, {"TenderDeadline": "30.03.2023"}, {"TenderPerson": "sandra drljic kopranovic"}, {"TenderTel": "03 423 31 25"}, {"TenderPerson": "vanja herman gril"}, {"TenderType": "m"}], "ner_refine": []}
{"id": "2023_EN_M_242_TENDER", "chunk_id": "0", "input_tokens": 2254, "refiner_input_tokens": 0, "total_output_tokens": 102, "text": "oblakova ulica 5 3000 celje tel (03) 42 33 000 postopek 242 2023 ss/vh povabilo k oddaji ponudbe vabimo vas k oddaji ponudbe za predmet hitri presejalni test na rota adenovirus v skladu z opisom kot sledi iz obr 1 splosne zahteve osnova za realizacijo dobave je prejem pisnega narocila strani narocnika. ponudbe zbiramo informativno za predlozitev v presojo odobritve. v kolikor bomo prejeli odobritev s strani pristojnih bomo realizacijo izvedli pri najugodnejsemu ponudniku. ponudbene vrednosti vkljucujejo vse stroske davke in morebitne popuste stroske dela rezijske stroske morebitne nadure amortizacijo opreme stroske dostave odvoza menjave blaga rokovanja in del povezanih z embalazo in morebitne druge stroske ki vplivajo na izracun cene. narocnik bo narocal blago s pisno z narocilnico. narocnik bo v narocilnici opredeliti vrste in kolicine blaga. dobavitelj je dolzan najkasneje v roku dveh ur od prejema narocila potrditi prejem narocila in obvestiti narocnika o morebitno zamudi pri dobavi ali zamenjavi istovrstnega blaga. kolicine in vrste blaga po predracunu so okvirne in za narocnika niso obvezujoce. dobavitelj zagotavlja dostavo blaga ddp splosna bolnisnica celje razlozeno lekarna narocnika (v delovnem casu narocnika od ponedeljka do petka). ponudnik mora zagotavljati dobavo celotne narocene kolicine v roku najkasneje 2. delovnih dni oziroma v nujnih primerih manj po predhodnem dogovoru z narocnikom (v delovnem casu od ponedeljka do petka v delovnem casu od 7 00 do 14 00 ). narocnik se obvezuje blago prevzeti v celoti na podlagi pravilno izpolnjene dobavnice. steje se da je dobavnica pravilno izpolnjena ce vsebuje najmanj naslednje naziv artikla cena na enoto mere kolicina morebitni popust kataloska stevilka artikla dobaviteljeva sifra serijsko stevilko artikla rok uporabnosti stopnjo ddv ja stevilka narocilnice kolicinski prevzem blaga oz. pregled se opravi takoj ob prevzemu blaga. kolicinska odstopanja ki jih ni bilo moc ugotoviti ob prevzemu mora posamezni narocnik pisno reklamirati najkasneje v treh (8) delovnih dneh od prevzema. dobavljeno blago mora ustrezati dogovorjeni kakovosti ter biti v skladu s tem sporazumom in njegovimi prilogami za vsak artikel posebej. kakovostna odstopanja lahko posamezni narocnik pisno reklamira najkasneje v 30. (tridesetih) dneh od prevzema blaga. ce dobava ne ustreza naroceni kolicini in/ali kakovosti je dobavitelj dolzan pomanjkljivosti nemudoma brezplacno odpraviti. v kolikor dobavitelj napak ne odpravi v roku dveh delovnih dni od prejema reklamacije to lahko stori posamezni narocnik na stroske dobavitelja in zahteva od dobavitelja povrnitev nastale skode. kakovost blaga mora ustrezati obstojecim standardom in deklarirani kakovosti na embalazi oziroma spremljajocih dokumentih. blago mora ustrezati tudi pogojem in zahtevam opredeljenimi v razpisni dokumentaciji narocnika in strokovnim kriterijem oz. znacilnostim.", "ner": [{"TenderTel": "(03) 42 33 000"}, {"TenderNumber": "242"}, {"TenderYear": "2023"}, {"TenderCode": "ss/vh"}, {"TenderType": "m"}], "ner_refine": []}
{"id": "2023_EN_M_242_TENDER", "chunk_id": "1", "input_tokens": 2237, "refiner_input_tokens": 0, "total_output_tokens": 23, "text": "blago mora biti obvezno pakirano v originalni embalazi (kot izhaja iz proizvajalcevega kataloga). blago mora imeti oznako ce in izpolnjevati vse tehnicne zahteve dolocena v navodilih ponudnikov. dobavljeno blago mora imeti rok uporabe se najmanj dve tretjini deklariranega roka uporabe ki ga navaja proizvajalec ponujenega blaga. v primeru krajsega roka uporabe mora ponudnik pred dostavo pridobiti pisno soglasje narocnika. vsak izstavljen racun mora vsebovati podatke o narocnikovi stevilki okvirnega sporazuma narocilnice oz. odjave porabljenega blaga in dobavnice ter vse elemente kot dobavnica. izstavljen racun mora imeti prilogo narocilnice oz. odjave porabljenega blaga dobavnice dobavitelj mora vse racune narocniku posiljati izkljucno v elektronski obliki (e racun) skladno z veljavnim zakonom o opravljanju placilnih storitev za proracunske uporabnike. dobavitelj mora izdati locen racun izkljucno vezan na predmetni sporazum zbirni racun ni dopusten in ga bo narocnik zavrnil. ponudnik mora biti vpisan v enega od registrov ki ga vodi jazmp (po skupini registrov) registrov poslovnih subjektov s sedezem v republiki sloveniji ki opravljajo dejavnost na podrocju medicinskih pripomockov registriranih po zacetku uporabe uredbe o medicinskih pripomockih (eu) st. 2017/745 registrov poslovnih subjektov z dejavnostjo na podrocju medicinskih pripomockov pred zacetkom uporabe uredbe o medicinskih pripomockih (eu) st. 2017/745 registrov medicinskih pripomockov skladnih z mdr katerih proizvajalci oz. predstavniki proizvajalcev imajo sedez v rs registrov medicinskih pripomockov skladnih z direktivo 90/385/es o aktivnih medicinskih pripomockih za vsaditev direktivo 93/42/egs o medicinskih pripomockih direktivo 98/79/es o in vitro diagnosticnih medicinskih pripomockih registrov medicinskih pripomockov katerih proizvajalci oz. predstavniki proizvajalcev imajo sedez v rs ponudniku medicinskih pripomockov s sedezem v drugi drzavi clanici evropske unije se ni potrebno priglasiti v register veletrgovcev ali proizvajalcev medicinskih pripomockov v sloveniji predloziti pa mora ustrezno potrdilo drzave clanice iz katere izhaja. ce je ponudnik iz druge drzave clanice eu ne glede na to ali je hkrati proizvajalec razpisanega blaga v ponudbi prilozi dokazilo v skladu s predpisi drzave v kateri ima ponudnik svoj sedez. ce drzava clanica ne izdaja taksnih dokumentov in potrdil ali ce ti ne zajemajo vseh zgoraj navedenih primerov narocnik lahko namesto pisnega dokazila sprejme zaprisezeno izjavo ce ta v drzavi clanici ali tretji drzavi ni predvidena pa izjavo dolocene osebe dano pred pravosodnim ali upravnim organom notarjem ali pred pristojno poklicno ali trgovinsko organizacijo v maticni drzavi te osebe ali v drzavi v kateri ima sedez gospodarski subjekt. v kolikor je predlozeno dokazilo iz uradnih evidenc oz. izjava sestavljeno/sestavljena v tujem jeziku mora biti v ponudbi prilozen tudi njun originalen prevod s strani sodnega tolmaca za slovenski jezik.", "ner": [], "ner_refine": []}
{"id": "2023_EN_M_091_TENDER", "chunk_id": "0", "input_tokens": 2107, "refiner_input_tokens": 0, "total_output_tokens": 196, "text": "2 narocnik splosna bolnisnica celje oblakova ulica 5 3000 celje tel (03) 42 33 000 fax (03) 42 33 757 postopek 91 2023 sp/vh povabilo k oddaji ponudbe narocnik vabi ponudnike da v skladu z navodili ponudnikom za izdelavo ponudbe za dokomolcne opornice (bergle) 100 kom splosne zahteve osnova za realizacijo dobave je prejem pisnega narocila strani narocnika. ponudbe zbiramo informativno za predlozitev v presojo odobritve. v kolikor bomo prejeli odobritev s strani pristojnih bomo realizacijo izvedli pri najugodnejsemu ponudniku ki bo izpolnjeval tehnicne zahteve. cena mora vsebovati vse stroske popuste rabate dostavo montazo in davek na dodano vrednost. ponudbi predlozite prospekte ter drugo dokumentacijo iz katere je razvidno izpolnjevanje tehnicnih zahtev. narocnik se zavezuje naroceno ter dobavljeno blago placati v roku kot ga doloca veljavna zakonodaja. merilo za izbora najnizja vrednost ponudbe v eur z ddv ob izpolnjevanju tehnicnih zahtev narocnika. kontaktna oseba s strani narocnika ; stanislava pahole hocevar dipl.ekon. tel.st. 03 423 30 78 faks st. 03 423 37 56 elektronska posta stanislava.pahole sb celje.si. ponudbe posljite na naslov elektronske poste nabava1 sb celje.si z oznako 91 2023 dokomolcne opornice do najkasneje 15.02.2023 do 12 ure. priloga obrazec predracuna (obr 2) izjavna o izpolnjevanju tehnicne specifikacije opreme (obr 4) obrazec predracuna obr 2 ponudnik predmet dokomolcme opornice (bergle) predracun opis proizvajalec (1) model oz. kataloska stevilka (2) kolicina (3) vrednost brez ddv (4) 1. dokomolcne opornice (bergle za obicajno tezke uporabnike) 100 kom cena brez ddv za 1 kom znesek ddv za 1 kom skupaj vrednost 100 kom v eur z ddv datum zig in podpis ponudnika sestavni del in priloga ponudbe . obr 4 izjava o izpolnjevanju tehnicne specifikacije opreme ponudnik pod kazensko in materialno odgovornostjo izjavljamo da izpolnjujemo tehnicne zahteve navedene v tem dokumenta ter obr 4 da bomo ponudbi predlozili originalne prospekte proizvajalca ter ostalo originalno dokumentacijo proizvajalca iz katere je razvidna oprema ki je predmet ponudbe da bo izpolnjevanje vseh zahtev iz opisa predmeta narocila mora biti razvidno iz originalnih prospektov proizvajalca ter ostale originalne dokumentacije proizvajalca slednje bomo ustrezno oznacili podcrtali in navedli ustrezno zap.st.", "ner": [{"TenderOrg": "splosna bolnisnica celje"}, {"TenderTel": "(03) 42 33 000"}, {"TenderFax": "(03) 42 33 757"}, {"TenderNumber": "91"}, {"TenderYear": "2023"}, {"TenderCode": "sp/vh"}, {"TenderDeadline": "15.02.2023"}, {"TenderPerson": "stanislava pahole hocevar"}, {"TenderType": "m"}], "ner_refine": []}
{"id": "2023_EN_M_015_TENDER", "chunk_id": "0", "input_tokens": 1952, "refiner_input_tokens": 0, "total_output_tokens": 272, "text": "2 2 narocnik splosna bolnisnica celje oblakova ulica 5 3000 celje tel (03) 42 33 000 fax (03) 42 33 757 postopek 15 2023 sp/vh povabilo k oddaji ponudbe narocnik vabi ponudnike da v skladu z navodili ponudnikom za izdelavo ponudbe za monitorji za spremljanje osnovnih zivljenskih funkcij z nadzorno postajo rok dobave in namestitve najkasneje 31.01.2023. splosne zahteve osnova za realizacijo dobave je prejem pisnega narocila strani narocnika. ponudbe zbiramo informativno za predlozitev v presojo odobritve. v kolikor bomo prejeli odobritev s strani pristojnih bomo realizacijo izvedli pri najugodnejsemu ponudniku ki bo izpolnjeval tehnicne zahteve. cena mora vsebovati vse stroske popuste rabate dostavo montazo in davek na dodano vrednost. narocnik se zavezuje naroceno ter dobavljeno blago placati v roku kot ga doloca veljavna zakonodaja. izvajalec mora zagotoviti dostavo blaga ter montazo in namestitev v prostor pri narocniku termin montaze/primopredaje je potrebno uskladiti z narocnikom (kontaktna oseba narocnika stanislava pahole hocevar) obveznost dobavitelja je da bo zagotovil brezplacno oz. na lastne stroske potrebno izvedbo edukacije uporabnikov (normalni uporabniski nivo) s strani narocnika za pravilno ter varno uporabo opreme ter njeno nego. ce je za ustrezno pridobitev znanja potrebno opraviti vec locenih edukacij je dobavitelj dolzan vsa ta solanja organizirati v smislu te tocke. ponudbi predlozite prospekte ter drugo dokumentacijo iz katere je razvidno izpolnjevanje tehnicnih zahtev. kontaktna oseba s strani narocnika ; stanislava pahole hocevar dipl.ekon. tel.st. 03 423 36 84 faks st. 03 423 37 56 elektronska posta stanislava.pahole sb celje.si. ponudbe posljite na naslov elektronske poste nabava1 sb celje.si z oznako 15 2023 monitorji za spremljanje zivljenjskih funkcij z nadzorno postajo do najkasneje 12.01.2023 do 12ure.", "ner": [{"TenderOrg": "splosna bolnisnica celje"}, {"TenderTel": "(03) 42 33 000"}, {"TenderFax": "(03) 42 33 757"}, {"TenderNumber": "15"}, {"TenderYear": "2023"}, {"TenderCode": "sp/vh"}, {"TenderDeadline": "31.01.2023"}, {"TenderPerson": "stanislava pahole hocevar"}, {"TenderTel": "03 423 36 84"}, {"TenderFax": "03 423 37 56"}, {"TenderType": "m"}, {"TenderDeadline": "12.01.2023"}], "ner_refine": []}
{"id": "2023_EN_M_015_TENDER", "chunk_id": "1", "input_tokens": 2275, "refiner_input_tokens": 0, "total_output_tokens": 23, "text": "priloga obrazec predracuna (obr 2 obr 2/1) izjava o zastopstvu (obr 3) izjavna o izpolnjevanju tehnicne specifikacije opreme (obr 4) obveznost izbranega ponudnika obrazec predracuna obr 2 ponudnik predmet monitorji za spremljanje osnovnih zivljenskih funkcij s centralno nadzorno postajo predracun (oprema vzdrzevanje preventivni pregledi opreme za obdobje 7 let ) opis proizvajalec (1) model oz. kataloska stevilka (2) kolicina (3) vrednost brez ddv (4) 1. monitorji za spremljanje osnovnih zivljenjskih funkcij s centralno nadzorno postajo v skladu z zahtevami iz obr 4 6 kom 3. kompletno vzdrzevanje opreme za obdobje 7 let vrednost opreme v eur brez ddv(1) znesek ddv za opremo vrednost preventivnega vzdrzevanja redni letni pregledi opreme v eur brez ddv (3) znesek ddv v eur za preventivno vzdrzevanje redni letni pregled opreme skupaj vrednost v eur za 1+2 v eur z ddv i. specifikacija vzdrzevanja kompletno vzdrzevanje v celotnem obdobju vzdrzevanja zajema naslednje vrste del ki so vkljucene v ceno vzdrzevalnine preventivno kurativno in programirano vzdrzevanje (vkljucno potrosni material ali drug material potreben za storitev kakor tudi stroski dela potni stroski stroski bivanja vzdrzevalcev dnevnice kilometrine transport dajatve davscine in drugi morebitni stroski potrebni za izvedbo vzdrzevanja opreme) z namenom ohranjanja stopnje funkcionalnosti sistemov in naprav ob nakupu oz. pravilnega in brezhibnega delovanja opreme; zamenjava vseh okvarjenih in izrabljenih originalnih rezervnih/nadomestnih delov ter potrosnega in drugega materiala ki so se izrabili oz. okvarili pri normalni in pravilni uporabi velja tako za kurativno vzdrzevanje kot tudi za preventivno vzdrzevanje po casovni dinamiki in obsegu ki je predpisan z navodili proizvajalca za vzdrzevanje opreme; redne preventivne kontrole nastavitve meritve po casovni dinamiki in obsegu ki je predpisan z navodili proizvajalca za vzdrzevanje opreme (vkljucno z delom in materialom po navodilih proizvajalca); nastavitve sistema po potrebi; pripravljenost ter stroske dela za popravila okvar ki nastanejo izven rednega delovnega casa; letne kalibracije meritve nastavitve overitve ves potrosni material ter drug potreben material za izvedbo vzdrzevanja po navodilih proizvajalca; nujne nadgradnje in zamenjave (programske in strojne opreme) za ohranitev funkcionalnosti sistema ob zagonu (kot npr. update i ipd.) (v skladu z zahtevo proizvajalca); nujne nadgradnje in zamenjave (programske in strojne) za povecanje funkcionalnosti sistema od nakupa (v skladu z zahtevo proizvajalca); odpravo nepravilnega delovanja ali okvare sistema ki niso posledica nepravilne uporabe na strani narocnika; daljinski nadzor in servis; kontrole inspekcije certificiranje in zagotovitev kakovosti opremljanje z oznacbami (nalepkami na opremi) o izvedenem vzdrzevanju; optimiranje funkcijskih parametrov delovanja; zagotovitev pravice k produktivni nadgradnji ki predstavlja zamenjavo/posodobitev/nadgradnjo obstojecih verzij programske opreme ki v celoti nadomestijo licencirano verzijo programskih licenc; druge stroske ki niso posebej specificirani so pa potrebni za funkcionalno zagotovitev delovanja aparata.", "ner": [], "ner_refine": []}
{"id": "2023_EN_M_206_TENDER", "chunk_id": "0", "input_tokens": 1829, "refiner_input_tokens": 0, "total_output_tokens": 218, "text": "oblakova ulica 5 3000 celje tel (03) 42 33 000 fax (03) 42 33 757 postopek 206 2023 sdk/vh povabilo k oddaji ponudbe vabimo vas k oddaji ponudbe za predmet ecmo fix 1 set za pritrjevanje ecmo kanile na glavo bolnika med vensko vensko izven telesno membransko oksigenacijo skozi vratno veno. ecmo fix 2 set sistem fiksacije za kanilo pri ecmo na nogi za odrasle in najstnike pri veno venski in veno arterijski izven telesni oksigenaciji preko femoralne vene. osnova za realizacijo dobave je prejem pisnega narocila strani narocnika. ponudbe zbiramo informativno za predlozitev v presojo odobritve. v kolikor bomo prejeli odobritev s strani pristojnih bomo realizacijo izvedli pri najugodnejsemu ponudniku. cena mora vsebovati vse stroske popuste rabate in davek na dodano vrednost. izvajalec mora zagotoviti dostavo blaga v skladisce lekarne v delovnem casu za dostavo oz. prevzem blaga (od ponedeljka do petka od 6 00 do 14 ure). narocnik se zavezuje naroceno placati v roku kot ga doloca veljavna zakonodaja. merilo izbora najnizja vrednost ponudbe v eur z ddv ob izpolnjevanju tehnicnih zahtev narocnika. kontaktna oseba s strani narocnika ; sandra drljic kopranovic tel. st. 03 423 31 25 elektronska posta sandra.drljic kopranovic sb celje.si ponudbe posljite na naslov elektronske poste nabava1 sb celje.si z oznako 206 2023 sistem za ecmo kanile do najkasneje 20.04.2023 do 10. ure. vodja sluzbe za nabavo medicinske opreme potrosnega materiala in storitev vanja herman gril mag.manag.", "ner": [{"TenderTel": "(03) 42 33 000"}, {"TenderFax": "(03) 42 33 757"}, {"TenderNumber": "206"}, {"TenderYear": "2023"}, {"TenderCode": "sdk/vh"}, {"TenderDeadline": "20.04.2023"}, {"TenderPerson": "sandra drljic kopranovic"}, {"TenderTel": "03 423 31 25"}, {"TenderPerson": "vanja herman gril"}, {"TenderType": "m"}], "ner_refine": []}
{"id": "2023_EN_M_472_TENDER", "chunk_id": "0", "input_tokens": 2247, "refiner_input_tokens": 0, "total_output_tokens": 102, "text": "oblakova ulica 5 3000 celje tel (03) 42 33 000 postopek 472 2023 sdk/vh povabilo k oddaji ponudbe vabimo vas k oddaji ponudbe za predmet palcka za jod jodiranje 20cm in 30cm letna kolicina 6500 kos sukcesivna dobava splosne zahteve osnova za realizacijo dobave je prejem pisnega narocila strani narocnika.. v kolikor bomo prejeli odobritev s strani pristojnih bomo realizacijo izvedli pri najugodnejsemu ponudniku ki bo izpolnjeval tehnicne zahteve. narocnik bo ponudnike ki so oddali ponudbo skladno z dolocilom drugega odstavka 21. clena zjn 3 pisno obvestil najkasneje v roku 30 dni od oddaje evidencnega narocila. narocnik je v specifikacijah zahtev oz. koda artikla navedel tip opreme izkljucno z namenom da se doloci zahtevana raven kakovosti. v ponudbi lahko ponudite tudi artikel drugih proizvajalcev vendar mora biti le ta enakovredna. ponudbene vrednosti vkljucujejo vse stroske davke in morebitne popuste stroske dela rezijske stroske morebitne nadure amortizacijo opreme stroske dostave odvoza menjave blaga rokovanja in del povezanih z embalazo in morebitne druge stroske ki vplivajo na izracun cene. narocnik bo narocal blago s pisno z narocilnico. narocnik bo v narocilnici opredeliti vrste in kolicine blaga. dobavitelj je dolzan najkasneje v roku dveh ur od prejema narocila potrditi prejem narocila in obvestiti narocnika o morebitno zamudi pri dobavi ali zamenjavi istovrstnega blaga. kolicine in vrste blaga po predracunu so okvirne in za narocnika niso obvezujoce. dobavitelj zagotavlja dostavo blaga ddp splosna bolnisnica celje razlozeno lekarna narocnika (v delovnem casu narocnika od ponedeljka do petka). ponudnik mora zagotavljati dobavo celotne narocene kolicine v roku najkasneje 2. delovnih dni oziroma v nujnih primerih manj po predhodnem dogovoru z narocnikom (v delovnem casu od ponedeljka do petka v delovnem casu od 7 00 do 14 00 ). narocnik se obvezuje blago prevzeti v celoti na podlagi pravilno izpolnjene dobavnice. steje se da je dobavnica pravilno izpolnjena ce vsebuje najmanj naslednje naziv artikla cena na enoto mere kolicina morebitni popust kataloska stevilka artikla crtna koda dobaviteljeva sifra serijsko stevilko artikla rok uporabnosti stopnjo ddv ja stevilka narocilnice. kolicinski prevzem blaga oz. pregled se opravi takoj ob prevzemu blaga. kolicinska odstopanja ki jih ni bilo moc ugotoviti ob prevzemu mora posamezni narocnik pisno reklamirati najkasneje v treh (8) delovnih dneh od prevzema. dobavljeno blago mora ustrezati dogovorjeni kakovosti ter biti v skladu s tem sporazumom in njegovimi prilogami za vsak artikel posebej. kakovostna odstopanja lahko posamezni narocnik pisno reklamira najkasneje v 30. (tridesetih) dneh od prevzema blaga. ce dobava ne ustreza naroceni kolicini in/ali kakovosti je dobavitelj dolzan pomanjkljivosti nemudoma brezplacno odpraviti.", "ner": [{"TenderTel": "(03) 42 33 000"}, {"TenderNumber": "472"}, {"TenderYear": "2023"}, {"TenderCode": "sdk/vh"}, {"TenderType": "m"}], "ner_refine": []}
{"id": "2023_EN_M_472_TENDER", "chunk_id": "1", "input_tokens": 2177, "refiner_input_tokens": 0, "total_output_tokens": 23, "text": "v kolikor dobavitelj napak ne odpravi v roku dveh delovnih dni od prejema reklamacije to lahko stori posamezni narocnik na stroske dobavitelja in zahteva od dobavitelja povrnitev nastale skode. kakovost blaga mora ustrezati obstojecim standardom in deklarirani kakovosti na embalazi oziroma spremljajocih dokumentih. blago mora ustrezati tudi pogojem in zahtevam opredeljenimi v razpisni dokumentaciji narocnika in strokovnim kriterijem oz. znacilnostim. blago mora biti obvezno pakirano v originalni embalazi (kot izhaja iz proizvajalcevega kataloga). blago mora imeti oznako ce in izpolnjevati vse tehnicne zahteve dolocena v navodilih ponudnikov. dobavljeno blago mora imeti rok uporabe se najmanj dve tretjini deklariranega roka uporabe ki ga navaja proizvajalec ponujenega blaga. v primeru krajsega roka uporabe mora ponudnik pred dostavo pridobiti pisno soglasje narocnika. vsak izstavljen racun mora vsebovati podatke o narocnikovi stevilki okvirnega sporazuma narocilnice oz. odjave porabljenega blaga in dobavnice ter vse elemente kot dobavnica. izstavljen racun mora imeti prilogo narocilnice oz. odjave porabljenega blaga dobavnice dobavitelj mora vse racune narocniku posiljati izkljucno v elektronski obliki (e racun) skladno z veljavnim zakonom o opravljanju placilnih storitev za proracunske uporabnike. dobavitelj mora izdati locen racun izkljucno vezan na predmetni sporazum zbirni racun ni dopusten in ga bo narocnik zavrnil. ponudnik mora biti vpisan v enega od registrov ki ga vodi jazmp (po skupini registrov) registrov poslovnih subjektov s sedezem v republiki sloveniji ki opravljajo dejavnost na podrocju medicinskih pripomockov registriranih po zacetku uporabe uredbe o medicinskih pripomockih (eu) st. 2017/745 registrov poslovnih subjektov z dejavnostjo na podrocju medicinskih pripomockov pred zacetkom uporabe uredbe o medicinskih pripomockih (eu) st. 2017/745 registrov medicinskih pripomockov skladnih z mdr katerih proizvajalci oz. predstavniki proizvajalcev imajo sedez v rs registrov medicinskih pripomockov skladnih z direktivo 90/385/es o aktivnih medicinskih pripomockih za vsaditev direktivo 93/42/egs o medicinskih pripomockih direktivo 98/79/es o in vitro diagnosticnih medicinskih pripomockih registrov medicinskih pripomockov katerih proizvajalci oz. predstavniki proizvajalcev imajo sedez v rs ponudniku medicinskih pripomockov s sedezem v drugi drzavi clanici evropske unije se ni potrebno priglasiti v register veletrgovcev ali proizvajalcev medicinskih pripomockov v sloveniji predloziti pa mora ustrezno potrdilo drzave clanice iz katere izhaja. ce je ponudnik iz druge drzave clanice eu ne glede na to ali je hkrati proizvajalec razpisanega blaga v ponudbi prilozi dokazilo v skladu s predpisi drzave v kateri ima ponudnik svoj sedez.", "ner": [], "ner_refine": []}
{"id": "2023_EN_N_162_TENDER", "chunk_id": "0", "input_tokens": 1965, "refiner_input_tokens": 0, "total_output_tokens": 229, "text": "ci splosna bolnisnica celje oblakova ulica 5 3000 celje tel (03) 42 33 000 fax (03) 42 33 757 postopek n 162 2023 sm/ms povabilo k oddaji ponudbe predmet evidencnega narocila e nabava regalov za nevarne snovi in vnetljive materiale tke (simbolica slika) 1.zahteve opis skupna visina 2000mm skupna sirina 1000 1100mm skupna globina 600 650mm konstrukcija kovinska pocinkana police v izvedbi mrezastih resetk. st. polic resetk 3 kom (kot nivo za shranjevanje) zbiralnik tekocin. nosilnost najmanj 130 kg/polica regal mora biti stabilen. wo c}n dd ob u| nih primernost shrambe vnetljivih snovi g hs kategorij ter vseh razredov nevarnosti za vodo. hb o regalni nivoji prestavljivi po visini. narocnik splosna bolnisnica celje 2 2. obrazec predracuna naziv artikla kolicina | cena na enoto | vrednost brez brez ddv ddv 1 regal za nevarne snovi 3 (3x nivo za shranjevanje zbiralnik tekocin) skupaj z ddv obvezne priloge . atest izjava o skladnosti izdelka. opombe e ponudba mora vsebovati vse stroske popuste rabate in davek na dodano vrednost. narocnik se zavezuje naroceno ter dobavljeno blago placati v roku 60 dni od datuma uradnega prejema racuna oziroma v roku skladno z veljavno zakonodajo. merilo za izbor najnizja vrednost ponudbe v eur z ddv ob izpolnjevanju tehnicnih zahtev narocnika. kontaktna oseba s strani narocnika ; splosna bolnisnica celje g. robert vodusek e robert.vodusek sb celje.si 070/393 070 mulej stane sluzba za nabavo nemedicinskega materiala e stane.mulej sb celje.si 041/765 324 ponudbe posljite na naslov elektronske poste nabava2 sb celje.si z oznako n 162 2023 nabava regalov za nevarne snovi in vnetljive materiale najkasneje do 25. 05.2023 do 12 ure. vodja sluzbe za nabavo nemedicinske materiala opreme in storitev matjaz stinek univ.dipl.ekon postopek ms/ms", "ner": [{"TenderOrg": "splosna bolnisnica celje"}, {"TenderTel": "(03) 42 33 000"}, {"TenderFax": "(03) 42 33 757"}, {"TenderNumber": "162"}, {"TenderYear": "2023"}, {"TenderCode": "sm/ms"}, {"TenderType": "n"}, {"TenderPerson": "robert vodusek"}, {"TenderPerson": "stane mulej"}, {"TenderDeadline": "25.05.2023"}, {"TenderPerson": "matjaz stinek"}], "ner_refine": []}
{"id": "2023_EN_N_135_TENDER", "chunk_id": "0", "input_tokens": 1756, "refiner_input_tokens": 0, "total_output_tokens": 238, "text": "splosna bolnisnica celje oblakova ulica 5 3000 celje tel (03) 42 33.000 fax (08) 42 33.757 postopek n 135 2023 ki/ms povabilo k oddaj i ponudbe vabimo vas k oddaji ponudbe za dobavo blaga 6 kosov philips lfh320000 speechmike iii pro vkljuceni stroski dostave garancija 24 mesecev osnova za realizacijo storitve je prejem pisnega narocila strani narocnika. ponudbe zbiramo informativno za predlozitev v presojo odobritve. v kolikor bomo prejeli odobritev s strani pristojnih bomo realizacijo izvedli pri najugodnejsemu ponudniku. cena mora vsebovati vse stroske popuste rabate in davek na dodano vrednost. narocnik se zavezuje naroceno ter dobavljeno blago placati v roku 60 dni od datuma uradnega prejema racuna oziroma v roku skladno z veljavno zakonodajo. merilo za izbor najnizja vrednost ponudbe v eur brez ddv ob izpolnjevanju tehnicnih zahtev narocnika. kontaktna oseba s strani narocnika rok sitar tel. +386 3 423 38 16 gsm +386 30 708 737 e posta rok.sitar(osb celje.si ponudbe posljite na naslov elektronske poste nabava2 sb celje.si z oznako n 135 2023 philips lfh20000 speechmike iti pro do najkasneje 25.4.2023 do 12 ure. vodja nabavne sluzbe matjaz stinek univ.dipl.ekon", "ner": [{"TenderOrg": "splosna bolnisnica celje"}, {"TenderTel": "(03) 42 33.000"}, {"TenderFax": "(08) 42 33.757"}, {"TenderType": "n"}, {"TenderNumber": "135"}, {"TenderYear": "2023"}, {"TenderCode": "ki/ms"}, {"TenderPerson": "rok sitar"}, {"TenderTel": "+386 3 423 38 16"}, {"TenderDeadline": "25.4.2023"}, {"TenderPerson": "matjaz stinek"}], "ner_refine": []}
{"id": "2023_EN_N_167_TENDER", "chunk_id": "0", "input_tokens": 2058, "refiner_input_tokens": 0, "total_output_tokens": 262, "text": "splosna bolnisnica celje oblakova ulica 5 3000 celje tel (03) 42 33000 fax (03) 42 33 757 postopek n 167 2023 kt/ms povabilo k oddaj i ponudbe vabimo vas k oddaji ponudbe za predmet rezalne plosce za sesekljalnik zelenjave robot coupe cl50 ultra kot sledi rezalna plosca rezine 0 6mm 28166 1 00 kos rezalna plosca rezine 2mm 28063 rc 1 00 kos rezalna plosca za rezanje na rezine 6mm 27786 1 00 kos rezalna plosca julienne 3x3mm 28101 1 00 kos rezalna plosca za ribanje 6mm 27046 1 00 kos rezalna plosca za rezine 6mm 27786 1 00 kos rezalna plosca julienn 6x6 28053 1 00 kos rezalna plosca za rezine 9mm 27046 1 kos dodatne zahteve ponudnik naj ponudi originalne rezalne plosce ponudnik naj ponudi vse artikle iz seznama. osnova za realizacijo dobave je prejem pisnega narocila strani narocnika. ponudbe zbiramo informativno za predlozitev v presojo odobritve. v kolikor bomo prejeli odobritev s strani pristojnih bomo realizacijo izvedli pri najugodnejsemu ponudniku. cena mora vsebovati vse stroske popuste rabate in davek na dodano vrednost. v ceni mora biti zajeta kompletna dobava in montaza ter vsi zakljucki. izvajalec mora zagotoviti dostavo blaga casu za dostavo oz. prevzem blaga (od ponedeljka do petka od 6 00 do 14 ure). narocnik se zavezuje naroceno ter dobavljeno blago placati v roku 60 dni od datuma uradnega prejema racuna oziroma v roku skladno z veljavno zakonodajo. merilo za izbora najnizja vrednost ponudbe v eur z ddv ob izpolnjevanju tehnicnih zahtev narocnika. kontaktna oseba s strani narocnika ; klavdija trunkl uni. dipl.ekon. tel.st. 03 423 35 35 faks st. 03 423 37 56 elektronska posta klavdija.trunkl sb celje.si narocnik splosna bolnisnica celje 2 ponudbe posljite na naslov elektronske poste nabava2 sb celje.si z oznako n 167 rezalne plosce za sesekljalnik zelenjave 2023 do najkasneje 25.5.2023 do 12 ure. vodja nabave nemedicinske opreme in storitev matjaz stinek univ.dipl.ekon.", "ner": [{"TenderOrg": "splosna bolnisnica celje"}, {"TenderTel": "(03) 42 33000"}, {"TenderFax": "(03) 42 33 757"}, {"TenderNumber": "167"}, {"TenderYear": "2023"}, {"TenderCode": "kt/ms"}, {"TenderType": "n"}, {"TenderTel": "03 423 35 35"}, {"TenderFax": "03 423 37 56"}, {"TenderPerson": "klavdija trunkl"}, {"TenderDeadline": "25.5.2023"}, {"TenderPerson": "matjaz stinek"}], "ner_refine": []}
{"id": "2023_EN_N_167_TENDER", "chunk_id": "1", "input_tokens": 2115, "refiner_input_tokens": 0, "total_output_tokens": 62, "text": "postopek kt/ms ponudbeni predracun na podlagi evidencnega javnega narocila rezalne plosce za sesekljalnik zelenjave robot coupe cl55 oddajamo ponudbo ponudnik zap.st navedba storitev (postavke podrobneje ponudbena cena ponudbena vrednost opredeljene v razpisni dokumentaciji) (v eur brez ddv) (v eur z ddv) 1 rezalna plosca rezine 0 6mm 28166 | 00 kos 2 rezalna plosca rezine 2mm 28063 rc | 90 kos rezalna plosca za rezanje na 1 00 kos 3 rezine 6mm 27786 rezalna plosca julienne 3x3mm 1 00 kos 4 28101 rezalna plosca za ribanje 6mm 1 00 kos 5 27046 rezalna plosca za rezine 6mm 1 00 kos 6 27786 narocnik splosna bolnisnica celje 7 rezalna plosca julienn 6x6 28053 | 1 00 kos 8 rezalna plosca za rezine 9mm 1kos 27046 vrednost skupaj ddv je za posamezne storitve upostevan v visini % in znasa eur. vsi stroski za izvedbo narocila ki niso posebej specificirani v ponudbenem predracunu so zajeti v enotnih cenah ponudbenega predracuna. uposteva se da je gospodarski subjekt pred oddajo svoje ponudbe natancno pregledal dokumentacijo narocila ter vse ostale okoliscine ki lahko vplivajo na izvedbo storitve. uposteva se da je gospodarski subjekt pred oddajo svoje ponudbe seznanjen z vsemi predpisi in zakoni glede placila taks davkov in ostalih dajatev v rs da je v celoti preucil razpisno dokumentacijo da je prisel do vseh potrebnih podatkov ki vplivajo na izvedbo del ter na podlagi vsega tega tudi pripravil svojo ponudbo. s podpisom ponudnik sprejema zahteve narocnika navedene v predmetni razpisni dokumentaciji. rok veljavnosti ponudbe je 15 dni od roka za oddajo ponudbe. narocniku izjavljamo da smo pri izracunu ponudbenih cen upostevali vse zahteve narocnika iz razpisne dokumentacije in vse veljavne predpise ki urejajo podrocje predmeta javnega narocila; smo pri izracunu ponudbenih cen upostevali vse stroske vezane na izvedbo javnega narocila kot so stroski dela materialni stroski stroski dobave in ostale stroske ki vplivajo na izracun ponudbene vrednosti vkljucno z vsemi popusti; so ponujene cene na katerih temelji ponudbena cena fiksne in se v casu do izpolnitve pogodbenih obveznosti ne bodo spremenile. podpisnik v imenu gospodarskega subjekta postopek kt/ms narocnik splosna bolnisnica celje postopek kt/ms ime in priimek podpis datum in zig narocnik splosna bolnisnica celje postopek kt/ms", "ner": [{"TenderCode": "kt/ms"}, {"TenderOrg": "splosna bolnisnica celje"}], "ner_refine": []}
{"id": "2023_EN_N_089_TENDER", "chunk_id": "0", "input_tokens": 2111, "refiner_input_tokens": 0, "total_output_tokens": 262, "text": "splosna bolnisnica celje oblakova ulica 5 3000 celje tel (03) 42 33000 fax (03) 42 33 757 postopek n 89 2023 kt/ms povabilo k oddaj i ponudbe vabimo vas k oddaji ponudbe za predmet hladilna omara (nemedicinska) 1 kom v sestavu in opisu kot sledi v nadaljevanju dimenzije cca 142 x 80 x 203 5 / 210 5 cm (sxgxv) prostornina cca. 1400 litrov temperaturno obmocje 2'/ 8' c dvojna vrata po visini nastavljive nogice elektronsko upravljanje avtomatsko odtajanje iz nerjavece plocevine kompresor in izmenjevalec toplote namescen na zgornji strani hladilnika wondhrpwne splosne zahteve 1. ponudbi predlozite prospekte ter drugo dokumentacijo iz katere je razvidno izpolnjevanje tehnicnih zahtev. 2. obvezna spremna dokumentacija ob dobavi opreme je prevod navodil v slovenskem jeziku originalno navodilo za uporabo (user book) ce oznacba po moznosti pritrjena tudi na opremo. kontakt pooblascenega serviserja garancija najmanj 12 mesecev osnova za realizacijo dobave je prejem pisnega narocila strani narocnika. ponudbe zbiramo informativno za predlozitev v presojo odobritve. v kolikor bomo prejeli odobritev s strani pristojnih bomo realizacijo izvedli pri najugodnejsemu ponudniku. narocnik je v specifikacijah zahtev navedel tip opreme izkljucno z namenom da se doloci zahtevana raven kakovosti. v ponudbi lahko ponudite tudi opremo drugih proizvajalcev vendar mora biti le ta tehnicno najmanj enakovredna opremi navedeni v specifikaciji zahtev narocnika. narocnik splosna bolnisnica celje 2 cena mora vsebovati vse stroske popuste rabate in davek na dodano vrednost. izvajalec mora zagotoviti dostavo blaga skladisce nabavne sluzbe v delovnem casu za dostavo oz. prevzem blaga (od ponedeljka do petka od 6 00 do 14 ure). rok za placilo je 60 dni od prejema racuna. merilo za izbora najnizja vrednost ponudbe v eur z ddv ob izpolnjevanju tehnicnih zahtev narocnika. kontaktna oseba s strani narocnika ; klavdija trunkl uni. dipl.ekon. tel.st. 03 423 35 35 faks st. 03 423 37 56 elektronska posta klavdija.trunkl sb celje.si ponudbe posljite na naslov elektronske poste nabava2 sb celje.si z oznako n 89 hladilna omara 2(23 do najkasneje 09.03.2022 do 12 ure. vodja nabavne sluzbe matjaz stinek univ.dipl.ekon postopek kt/ms narocnik splosna bolnisnica celje postopek kt/ms", "ner": [{"TenderOrg": "splosna bolnisnica celje"}, {"TenderTel": "(03) 42 33000"}, {"TenderFax": "(03) 42 33 757"}, {"TenderType": "n"}, {"TenderNumber": "89"}, {"TenderYear": "2023"}, {"TenderCode": "kt/ms"}, {"TenderDeadline": "09.03.2022"}, {"TenderPerson": "matjaz stinek"}, {"TenderPerson": "klavdija trunkl"}, {"TenderTel": "03 423 35 35"}, {"TenderFax": "03 423 37 56"}], "ner_refine": []}
{"id": "2023_EN_N_109_TENDER", "chunk_id": "0", "input_tokens": 1871, "refiner_input_tokens": 0, "total_output_tokens": 207, "text": "oblakova ulica 5 3000 celje tel (03) 42 33 000 fax (03) 42 33 757 postopek n 109 2023 ms povabilo k oddaji ponudbe vabimo vas k oddaji ponudbe za predmet medicinski racunalniski vozicek z racunalnikom in monitorjem specifikacija blaga/predracun opis kolicina cena na kos (brez ddv) znesek (brez ddv) proizvajalec in tip ponujenega aparata vozicek 1 racunalnik + monitor ali aio racunalnik 1 citalec crtnih kod 1 skupaj brez ddv ddv skupaj z ddv ponudnik lahko prilozi predracun na svojem obrazcu ki je identicen zgornjemu. splosni pogoji za sodelovanje ponudnik mora ponudbi priloziti prospektni in ostali material iz katerega je razvidno izpolnjevanje zahtevanih tehnicnih specifikacij opreme. ponudnik lahko ponudi rabljeno opremo ki pa ne sme biti starejsa kot 3 leta. ponudnik v ponudbi navede ali ponuja novo ali rabljeno opremo in kateri letnik proizvodnje je oprema. ponudnik nudi ne glede ali ponuja novo ali rabljeno opremo garancijski rok 12 mesecev. cena mora vsebovati vse stroske popuste rabate in davek na dodano vrednost. narocnik se zavezuje naroceno ter dobavljeno blago placati v roku 60 dni od datuma uradnega prejema racuna oziroma v roku skladno z veljavno zakonodajo. merilo za izbor najnizja vrednost ponudbe v eur z ddv ob izpolnjevanju tehnicnih zahtev narocnika. kontaktna oseba s strani narocnika dusan knezevic gsm +386 41 393 083 e mail dusan.knezevic sb celje.si . ponudbe posljite na naslov elektronske poste nabava2 sb celje.si z oznako n 109 medicinski racunalniski vozicek z racunalnikom in monitorjem do najkasneje 27.03.2023 do 12 ure. vodja nabavne sluzbe matjaz stinek univ.dipl.ekon", "ner": [{"TenderTel": "(03) 42 33 000"}, {"TenderFax": "(03) 42 33 757"}, {"TenderType": "n"}, {"TenderNumber": "109"}, {"TenderYear": "2023"}, {"TenderCode": "ms"}, {"TenderPerson": "dusan knezevic"}, {"TenderDeadline": "27.03.2023"}, {"TenderPerson": "matjaz stinek"}, {"TenderOrg": "sb celje.si"}], "ner_refine": []}
{"id": "2023_EN_N_190_TENDER", "chunk_id": "0", "input_tokens": 2015, "refiner_input_tokens": 0, "total_output_tokens": 258, "text": "co splosna bolnisnica celje oblakova ulica 5 3000 celje tel (03) 42 33000 fax (03) 42 33 757 postopek n 190 2023 ms povabilo k oddaj i ponudbe vabimo vas k oddaji ponudbe za predmet wew deset brezzicnih panik tipk opis in konfiguracija tihi alarm plegium (nosljiv) 10 00 kos plegium platforma 1 00 10 licenc naroenina za 12 mesecev. navedba zeljenega rezima panik tipk mora omogocati panik tipka mora biti brezzicna nosljiva z izdelano platformo aplikacijo. z uporabo mobilne ali web aplikacije mora biti omogoceno da se sistem ter povezane naprave (panik tipke) upravljajo na daljavo obsprozitvi alarma mora aplikacija poslati sms s tocno lokacijo aplikacija mora omogocati vnos kontaktov za nujne primere sistem mora omogocati namestite brezplacne aplikacije za android in apple telefone sistem mora omogocati vnos 5 kontaktov za nujne primere sistem mora omogocati da se v primeru groznje sprozi alarm z 2 sekundnim pritiskom na tipke naprave ponudnik lahko izdela predracun na svojem obrazcu ob upostevanju da je vsebina enaka pripravljenemu obrazcu predracuna! osnova za realizacijo dobave je prejem pisnega narocila s strani narocnika. ponudbe zbiramo informativno za predlozitev v presojo odobritve. v kolikor bomo prejeli odobritev s strani pristojnih bomo realizacijo izvedli pri najugodnejsemu ponudniku. cena mora vsebovati vse stroske popuste rabate in davek na dodano vrednost. narocnik se zavezuje naroceno ter dobavljeno blago placati v roku 60 dni od datuma uradnega prejema racuna oziroma v roku skladno z veljavno zakonodajo. merilo izbora najnizja vrednost ponudbe v eur z ddv ob izpolnjevanju tehnicnih zahtev narocnika. kontaktna oseba s strani narocnika gregor kovac 031 365 005 elektronska posta gregor.kovac() sb celje.si matjaz stinek univ. dipl. ekon. tel.st. 03 423 30 76 elektronska posta matjaz.stinek() sb celje.si ponudbe posljite na naslov elektronske poste nabava2 sb celje.si z oznako n 190 2023 deset brezzienih panik tipk do najkasneje 30.06.2023 do 12 ure. v odja sluzbe za nabavo nemedicinske opreme materiala in storitev matjaz stinek univ. dipl. ekon.", "ner": [{"TenderOrg": "splosna bolnisnica celje"}, {"TenderTel": "(03) 42 33000"}, {"TenderFax": "(03) 42 33 757"}, {"TenderNumber": "190"}, {"TenderYear": "2023"}, {"TenderCode": "ms"}, {"TenderTel": "031 365 005"}, {"TenderPerson": "gregor kovac"}, {"TenderTel": "03 423 30 76"}, {"TenderPerson": "matjaz stinek"}, {"TenderDeadline": "30.06.2023"}, {"TenderType": "n"}], "ner_refine": []}
{"id": "2023_EN_N_232_TENDER", "chunk_id": "0", "input_tokens": 2073, "refiner_input_tokens": 0, "total_output_tokens": 260, "text": "2 narocnik splosna bolnisnica celje oblakova ulica 5 3000 celje tel (03) 42 33 000 fax (03) 42 33 757 postopek n 232 2023 ms povabilo k oddaji ponudbe vabimo vas k oddaji ponudbe za predmet 10 kosov digitalni diktafon po naslednjih specifikacijah vrsta diktafona digitalni zaslon 2.4\" 6 1 cm tft lcd 320 x 240 locljivosti premer zvocnika 28 mm izhodna moc zvocnika 200 mw moznost razsiritve da podprti formati dss/dss pro (digital speech standard) mp3 pcm cas snemanja 700 ur (sp) 350 ur (qp) 50 ur (mp3) 27 ur (pcm voice) 13 ur (pcm stereo) vgrajen mikrofon enosmerni 360 frekvencni odziv 300 7500 hz vrsta baterije polnilna baterija li ion acc8100 1000 mah vhodi 3 5 mm mikrofon usb 2.0 vgrajen citalec crtne kode izhodi 3 5 mm slusalke dodatni pogoji garancija 24 mesecev (material in delo) ponudnik mora za ponujeno napravo predloziti potrdilo proizvajalca da je pooblascen za prodajo ter ima zagotovljeno celotno podporo (dostop do baze znanj zagotavljanje rezervnih delov zagotovljen certificiran servis) osnova za realizacijo dobave je prejem pisnega narocila strani narocnika. ponudbe zbiramo informativno za predlozitev v presojo odobritve. v kolikor bomo prejeli odobritev s strani pristojnih bomo realizacijo izvedli pri najugodnejsemu ponudniku. cena mora vsebovati vse stroske popuste rabate in davek na dodano vrednost. izvajalec mora zagotoviti dostavo blaga skladisce sb celje. narocnik se zavezuje naroceno ter dobavljeno blago placati v roku 60 dni od datuma uradnega prejema racuna oziroma v roku skladno z veljavno zakonodajo. merilo za izbora najnizja vrednost ponudbe v eur z ddv ob izpolnjevanju tehnicnih zahtev narocnika. kontaktna oseba s strani narocnika ; matjaz stinek uni.dipl.ekon. tel.st. 03 423 30 76 faks st. 03 423 37 56 elektronska posta matjaz.stinek sb celje.si ponudbe posljite na naslov elektronske poste nabava2 sb celje.si z oznako n 232 2023 10 kos digitalni diktafon oddaja ponudb do najkasneje 25.9.2023 do 12 ure. vodja nabavne sluzbe matjaz stinek univ.dipl.eko 10 postopek kt/ms", "ner": [{"TenderOrg": "splosna bolnisnica celje"}, {"TenderTel": "(03) 42 33 000"}, {"TenderFax": "(03) 42 33 757"}, {"TenderType": "n"}, {"TenderNumber": "232"}, {"TenderYear": "2023"}, {"TenderCode": "ms"}, {"TenderPerson": "matjaz stinek"}, {"TenderTel": "03 423 30 76"}, {"TenderFax": "03 423 37 56"}, {"TenderDeadline": "25.09.2023"}, {"TenderCode": "kt/ms"}], "ner_refine": []}
{"id": "2023_EN_N_193_TENDER", "chunk_id": "0", "input_tokens": 1897, "refiner_input_tokens": 0, "total_output_tokens": 259, "text": "be) splosna bolnisnica celje oblakova ulica 5 3000 celje tel (03) 42 33 000 fax (03) 42 33 757 postopek n 193 2023 ms povabilo k oddaji ponudbe vabimo vas k oddaji ponudbe za predmet snemalnik videonadzor ucc opis in konfiguracija izvedba naslednjih del diagnostika sistema odklop in demontaza obstojece opreme vgradnja in priklop nove opreme paramertriranje sistema zagon sistema in testiranje delovanja predaja sistema narocniku prevozni stroski 1x snemalnik video 16ch bnc/4m 16ch ip/6m 1x disk trdi 4 tb potrosni instalacijski material ponudnik lahko izdela predracun na svojem obrazcu ob upostevanju da je vsebina enaka pripravljenemu obrazcu predracuna! osnova za realizacijo dobave je prejem pisnega narocila s strani narocnika. ponudbe zbiramo informativno za predlozitev v presojo odobritve. v kolikor bomo prejeli odobritev s strani pristojnih bomo realizacijo izvedli pri najugodnejsemu ponudniku. cena mora vsebovati vse stroske popuste rabate in davek na dodano vrednost. narocnik se zavezuje naroceno ter dobavljeno blago placati v roku 60 dni od datuma uradnega prejema racuna oziroma v roku skladno z veljavno zakonodajo. merilo izbora najnizja vrednost ponudbe v eur z ddv ob izpolnjevanju tehnicnih zahtev narocnika. kontaktna oseba s strani narocnika gregor kovac 031 365 005 elektronska posta gregor.kovac() sb celje.si matjaz stinek univ. dipl. ekon. tel.st. 03 423 30 76 elektronska posta matjaz.stinek(0 sb celje.si ponudbe posljite na naslov elektronske poste nabava2 sb celje.si z oznako n 193 2023 snemalnik videonadzor ucc do najkasneje 03.07.2023 do 12 ure. v odja sluzbe za nabavo nemedicinske opreme materiala in storitev matjaz stinek univ. dipl. ekon.", "ner": [{"TenderOrg": "splosna bolnisnica celje"}, {"TenderTel": "(03) 42 33 000"}, {"TenderFax": "(03) 42 33 757"}, {"TenderType": "n"}, {"TenderNumber": "193"}, {"TenderYear": "2023"}, {"TenderCode": "ms"}, {"TenderPerson": "gregor kovac"}, {"TenderTel": "031 365 005"}, {"TenderPerson": "matjaz stinek"}, {"TenderTel": "03 423 30 76"}, {"TenderDeadline": "03.07.2023"}], "ner_refine": []}
{"id": "2023_EN_N_092_TENDER", "chunk_id": "0", "input_tokens": 2285, "refiner_input_tokens": 0, "total_output_tokens": 149, "text": "splosna bolnisnica celje oblakova ulica 5 3000 celje tel (03) 42 33000 fax (03) 42 33 757 postopek n 92 2023 kt/ms povabilo k oddaj i ponudbe vabimo vas k oddaji ponudbe za predmet pohistvena oprema v sestavu kot na opisu in dodatnih prilogah. \"splosni opis korpusi pohistvenih elementov in police so iz iverala d<18 mm cela korpusa in polic zascitena z abs trakom deb. 2 9 mm. stene korpusa perforirane na 32 mm za nastavitev polic. lesena vrata in licnice predalov so iz iverala d 18 mm vsi zakljucki iz abs d 2 9 mm. steklena vrata iz kaljenega stekla d 6 mm kvalitetno okovje odpiranje 952. vse omare (razen visecih omaric) montirane na lesene podstavke izvedene v sklopu omare v barvi vratnih kril. visina podstavkov 10 cm na stiku s tlakom vgrajeno tipsko silikonsko tesnilo v prozorni barvi. vsi predali tipske kovinske izvedbe z teleskopskimi vodili in mehkim zapiranjem. vso okovje kvalitetne izdelave z mehkim zapiranjem. rocaji inox cca f 8 mm elipsasti. delovni pulti so iz iverke debeline min. 38 mm obojestransko lepljen laminat min. 0 9 mm zakljucki iz abs a deb. 2.9 mm. ( laminat primeren za bolnisnicne prostore odporen na vsakodnevno razkuzevanje dezinficiranje ciscenje..). iveral in laminat v kvaliteti egger oz. fundermax. barva plosc oz. lesnega dekorja rocajev in delovnega pulta po izbiri uporabnika dopustne barve so bela umirjeni toni pastelnih barv ali lesni dekor svetlih tonov. abs zakljucki v barvi plosc oz. po izbiri uporabnika v ceni mora biti zajeta kompletna dobava in montaza ter vsi zakljucki oz. zapiranje rege med steno in opremo v sirini do 10 cm. police so izdelane iz iverke d 24 mm obojestransko lepljen laminat min. 0 9 mm vsi zakljucki iz abs a d=2 9 mm. tipske konzole inox izvedbe. ne glede na opis v posameznih pozicijah morajo biti vsa vrata in predali na zaklepanje s kljucavnico. delovne povrsine pisalnih miz so iz iverke d 28 mm obojestransko lepljen laminat min. 0 9 mm max abet ali egger kvalitete z zakljucki iz abs a deb. 2.9 mm. vogali nekaterih miz so zakljuceni v radiju 15 cm. noge pri mizah tipske kromirane z moznostjo regulacije visin. pisalne mize imajo tipske \"\"t\"\" noge z precnimi veznimi elementi. pisalne mize imajo tudi po eno izvlecno polico na delovno mesto za tipkovnico in izreze (s roseto 3x) za prehod kablov oboje izvesti na mestu samem po navodilih uporabnika. barvo pohistva bo narocnik izbral naknadno. narocnik splosna bolnisnica celje 2 osnova za realizacijo dobave je prejem pisnega narocila strani narocnika. ponudbe zbiramo informativno za predlozitev v presojo odobritve. v kolikor bomo prejeli odobritev s strani pristojnih bomo realizacijo izvedli pri najugodnejsemu ponudniku. cena mora vsebovati vse stroske popuste rabate in davek na dodano vrednost. v ceni mora biti zajeta kompletna dobava in montaza ter vsi zakljucki.", "ner": [{"TenderOrg": "splosna bolnisnica celje"}, {"TenderTel": "(03) 42 33000"}, {"TenderFax": "(03) 42 33 757"}, {"TenderNumber": "92"}, {"TenderYear": "2023"}, {"TenderCode": "kt/ms"}, {"TenderType": "n"}], "ner_refine": []}
{"id": "2023_EN_N_092_TENDER", "chunk_id": "1", "input_tokens": 1626, "refiner_input_tokens": 0, "total_output_tokens": 187, "text": "izvajalec mora zagotoviti dostavo blaga ter montazo in namestitev v prostor pri narocniku v delovnem casu za dostavo oz. prevzem blaga (od ponedeljka do petka od 6 00 do 14 ure). termin montaze je potrebno dogovoriti z narocnikom (kontaktna oseba narocnika klavdija trunkl) narocnik se zavezuje naroceno ter dobavljeno blago placati v roku 60 dni od datuma uradnega prejema racuna oziroma v roku skladno z veljavno zakonodajo. merilo za izbora najnizja vrednost ponudbe v eur z ddv ob izpolnjevanju tehnicnih zahtev narocnika. kontaktna oseba s strani narocnika ; klavdija trunkl uni. dipl.ekon. tel.st. 03 423 35 35 faks st. 03 423 37 56 elektronska posta klavdija.trunkl sb celje.si ponudbe posljite na naslov elektronske poste nabava2 sb celje.si z oznako n 92 pohistvena oprema 2023 do najkasneje 10.3.2023 do 12 ure. vodja nabavne sluzbe matjaz stinek univ.dipl.ekon. postopek kt/ms", "ner": [{"TenderPerson": "klavdija trunkl"}, {"TenderTel": "03 423 35 35"}, {"TenderFax": "03 423 37 56"}, {"TenderDeadline": "10.03.2023"}, {"TenderPerson": "matjaz stinek"}, {"TenderCode": "kt/ms"}], "ner_refine": []}
{"id": "2023_EN_N_161_TENDER", "chunk_id": "0", "input_tokens": 2239, "refiner_input_tokens": 0, "total_output_tokens": 222, "text": "splosna bolnisnica celje oblakova ulica 5 3000 celje tel (03) 42 33 000 fax (03) 42 33 757 postopek n 161 2023 kt/ms povabilo k oddaji ponudbe v abimo vas k oddaji ponudbe za predmet delovna oblacila receptorji 1. zimskajakna 11 kom zahtevana tehnicna tehnicni list izdelka dokumentacija zahtevana sestava 100% poliester podloga 100% poliester tpu membrana gramatura materiala 245 g/m (+/ 5%) dodatne zahteve dihajoea nepremoeljiva zascita proti vetru varjeni sivi dva stranska zepa s poklopcem in zadrgo dva prsna zepa s poklopcem in zadrgo notranji zep zapiranje z zadrgo in poklopcem snemljiva kapuca ki se lahko tudi zlozi v ovratnik ovratnik podlozen s flisom nastavljiva v predelu bokov nastavitev v zapestju z sprimnim trakom barva materiala crna velikost xs 4xl 2. jakna softshell 11 kom zahtevana tehnicna tehnicni list izdelka dokumentacija zahtevana sestava 100% poliester podloga 100% poliester tpu membrana 400 g/m (+/ materiala 5%) dodatne zahteve nepremocljiva zascita proti vetru dva stranska zepa z zadrgo zapiranje z zadrgo dodatna ojacitev v predelu ramen in komolcev elasticna manseta v zapestju elastika v predelu bokov barva materiala crna velikost xs 4xl narocnik splosna bolnisnica celje 2 3. hlace 11kom zahtevana tehnicna tehnicni list izdelka dokumentacija zahtevana sestava 96% poliester 4% elastan 220 g/m (4 / 5%) materiala dodatne zahteve elasticne dva stranska zepa stegenski zep s poklopcem drzalom za pisalo stegenski zep za mobilni telefon z zadrgo elastika v pasu dva zepa z zadrgo na predelu zadnjice zanke za nosenje pasa barva materiala crna velikost 42 64 dodatne zahteve ponudnik naj ponudi vse povprasevanje artikle. k ponudbi prilozite dokumentacijo iz katere je razviden ponujen model (skico fotografijo) osnova za realizacijo dobave je prejem pisnega narocila strani narocnika. ponudbe zbiramo informativno za predlozitev v presojo odobritve. v kolikor bomo prejeli odobritev s strani pristojnih bomo realizacijo izvedli pri najugodnejsemu ponudniku. cena mora vsebovati vse stroske popuste rabate in davek na dodano vrednost. v ceni mora biti zajeta kompletna dobava in montaza ter vsi zakljucki. izvajalec mora zagotoviti dostavo blaga casu za dostavo oz. prevzem blaga (od ponedeljka do petka od 6 00 do 14 ure). narocnik se zavezuje naroceno ter dobavljeno blago placati v roku 60 dni od datuma uradnega prejema racuna oziroma v roku skladno z veljavno zakonodajo. merilo za izbora najnizja vrednost ponudbe v eur z ddv ob izpolnjevanju tehnicnih zahtev narocnika. kontaktna oseba s strani narocnika ; klavdija trunkl uni. dipl.ekon. tel.st. 03 423 35 35 faks st. 03 423 37 56 elektronska posta klavdija.trunkl sb celje.si ponudbe posljite na naslov elektronske poste nabava2 sb celje.si", "ner": [{"TenderOrg": "splosna bolnisnica celje"}, {"TenderTel": "(03) 42 33 000"}, {"TenderFax": "(03) 42 33 757"}, {"TenderNumber": "161"}, {"TenderYear": "2023"}, {"TenderCode": "kt/ms"}, {"TenderType": "n"}, {"TenderPerson": "klavdija trunkl"}, {"TenderTel": "03 423 35 35"}, {"TenderFax": "03 423 37 56"}], "ner_refine": []}
{"id": "2023_EN_N_161_TENDER", "chunk_id": "1", "input_tokens": 1980, "refiner_input_tokens": 0, "total_output_tokens": 139, "text": "z oznako n 161 delovna oblacila receptorji 2023 do najkasneje 23.5.2023 do 12 ure. v odja nabave nemedicinske opreme in storitev matjaz stinek univ.dipl.ekon. postopek kt/ms ponudbeni predracun na podlagi evidencnega javnega narocila delovna oblacila receptorji oddajamo ponudbo ponudnik zap.st navedba storitev (postavke podrobneje ponudbena cena ponudbena vrednost opredeljene v razpisni dokumentaciji) (v eur brez ddv) (v eur z ddv) 1 zimska jakna 11 kom jakna softshell 11 kom 2 hlace 11 kom 3 vrednost skupaj ddv je za posamezne storitve upostevan v visini % in znasa eur. vsi stroski za izvedbo narocila ki niso posebej specificirani v ponudbenem predracunu so zajeti v enotnih cenah ponudbenega predracuna. uposteva se da je gospodarski subjekt pred oddajo svoje ponudbe natancno pregledal dokumentacijo narocila ter vse ostale okoliscine ki lahko vplivajo na izvedbo storitve. uposteva se da je gospodarski subjekt pred oddajo svoje ponudbe seznanjen z vsemi predpisi in zakoni glede placila taks davkov in ostalih dajatev v rs da je v celoti preucil razpisno dokumentacijo da je prisel do vseh potrebnih podatkov ki vplivajo na izvedbo del ter na podlagi vsega tega tudi pripravil svojo ponudbo. narocnik splosna bolnisnica celje s podpisom ponudnik sprejema zahteve narocnika navedene v predmetni razpisni dokumentaciji. rok veljavnosti ponudbe je 15 dni od roka za oddajo ponudbe. narocniku izjavljamo da smo pri izracunu ponudbenih cen upostevali vse zahteve narocnika iz razpisne dokumentacije in vse veljavne predpise ki urejajo podrocje predmeta javnega narocila; smo pri izracunu ponudbenih cen upostevali vse stroske vezane na izvedbo javnega narocila kot so stroski dela materialni stroski stroski dobave in ostale stroske ki vplivajo na izracun ponudbene vrednosti vkljucno z vsemi popusti; so ponujene cene na katerih temelji ponudbena cena fiksne in se v casu do izpolnitve pogodbenih obveznosti ne bodo spremenile. podpisnik v imenu gospodarskega subjekta ime in priimek podpis datum in zig postopek kt/ms narocnik splosna bolnisnica celje postopek kt/ms", "ner": [{"TenderType": "n"}, {"TenderNumber": "161"}, {"TenderYear": "2023"}, {"TenderDeadline": "23.05.2023"}, {"TenderPerson": "matjaz stinek"}, {"TenderCode": "kt/ms"}, {"TenderOrg": "splosna bolnisnica celje"}], "ner_refine": []}
{"id": "2023_EN_N_139_TENDER", "chunk_id": "0", "input_tokens": 2098, "refiner_input_tokens": 0, "total_output_tokens": 257, "text": "splosna bolnisnica celje oblakova ulica 5 3000 celje tel (08) 42 33000 fax (08) 42 33.757 postopek n 139 2023 ms povabilo k oddajt ponudbe vabimo vas k oddaji ponudbe za predmet pametne kljuke za oddelene lekarne opis stanja v splosni bolnisnici celje imamo na posameznih oddelkih urejena skladisca zdravil (v nadaljevanju oddelcne lekarne) katerih prostori morajo biti zaradi narave dela in svojih sestavin locena od ostalih prostorov. trenutno so tovrstni prostori brez t.i. kontrole dostopa splosna bolnisnica celje pa je v fazi nadgraditve ostojecenega sistema prenosa in knjizenja zdravil iz glavne lekarne na posamezne oddelcne lekarne. ker je kontrola dostopa eden od segmentov zagotovitve minimalnega standarda s podrocja varovanja premozenja v tej zvezi potrebujemo resitev digitalnega dostopa s pametno kartico oziroma z mfire za vec oddelcnih lekarn. v splosni bolnisnici celje trenutno uporabljamo dva sistema t. i. kontrole dostopa (cetrta pot in assa abloy). v tej zvezi potrebujemo resitev ki bo kompatibilna z obstojecim sistemom ter z ze postavljeno infrasturukturo. resitev mora vsebovati uporabnika opis em | kolicina | cena brez | vrednost brez ddv ddv wireless kljuka kos | 13 brezzicni usmerjevalnik hub kos | 11 sprejemnik c controler kos |1 kartica mfire kos | 100 stenski citalec rds sps kos | 2 modul vratnega citalnika kos | 2 vratno samozapiralo kos | 7 montaza posameznih elementov kos | 1 integracija in programiranje ter solanje | kos | 1 skupaj brez ddv ddv 22% skupaj z ddv utp kablaza napajanje uredi splosna bolnisnica celje. cena mora vsebovati vse stroske popuste rabate in davek na dodano vrednost. narocnik se zavezuje naroceno ter dobavljeno blago placati v roku 60 dni od datuma uradnega prejema racuna oziroma v roku skladno z veljavno zakonodajo. merilo za izbor najnizja vrednost ponudbe v eur brez ddv ob izpolnjevanju tehnicnih zahtev narocnika. kontaktna oseba s strani narocnika matjaz stinek tel. 041 675 561 e mail matjaz.stinek sb celje.si gregor kovac tel. 031 365 005 e mail gregor.kovac sb celje.si ponudbe posljite na naslov elektronske poste nabava2 sb celje.si z oznako n 139 2023 pametne kljuke za oddelcne lekarne do najkasneje 28.04.2023 do 12 ure . vodja nabavne sluzbe matjaz stinek univ.dipl.ekon", "ner": [{"TenderOrg": "splosna bolnisnica celje"}, {"TenderTel": "(08) 42 33000"}, {"TenderFax": "(08) 42 33.757"}, {"TenderType": "n"}, {"TenderNumber": "139"}, {"TenderYear": "2023"}, {"TenderCode": "ms"}, {"TenderDeadline": "28.04.2023"}, {"TenderPerson": "matjaz stinek"}, {"TenderTel": "041 675 561"}, {"TenderPerson": "gregor kovac"}, {"TenderTel": "031 365 005"}], "ner_refine": []}
{"id": "2022_EN_X_309_TENDER", "chunk_id": "0", "input_tokens": 2166, "refiner_input_tokens": 0, "total_output_tokens": 151, "text": "co splosna bolnisnica celje oblakova ulica 5 3000 celje tel (03) 42 33 000 fax (03) 42 33 757 postopek 309 2022 da/vh povabilo k oddaji ponudbe narocnik vabi ponudnike da v skladu z navodili ponudnikom izdelajo ponudbo za popravilo centrifuge heraeus cryofuge 6000 naziv aparata centrifuga proizvajalec heraeus tip cryofuge 6000 inv.st. 00502023 serijska stevilka 210039 oddelek transfuzijski center stroskovno mesto 2815 razlog narocila popravilo zaradi napake. na displeyu izpise alarm system check. centrifuga se ne zazene. prav tako pada pokrov centrifuge zaradi oslabljenih vzmeti. ponudnik mora v ponudbi zajet popravilo same centrifuge in zamenjavo plinskih vzmeti. obvezne priloge 1. v letu 2022 veljavna pisna pooblastila proizvajalcev s katerim pooblascajo zgoraj navedeni servis za servisiranje opreme in dobavo rezervnih delov. 2. izjava dana pod kazensko in materialno odgovornostjo z navedbo imen in priimkov serviserjev (pooblasceni servis mora imeti na razpolago vsaj enega serviserja) ki je usposobljen za vzdrzevanje ponujene opreme. serviserji morajo ze v casu oddaje ponudbe imeti s pooblascenim servisom sklenjeno pogodbo o zaposlitvi ali civilnopravno pogodbo o delu ali kaksno drugo civilnopravno pogodbo o sodelovanju v izjavi je potrebno navesti obliko sklenjene pogodbe in cas trajanja te pogodbe. v primeru da gre za redno zaposlenega serviserja pri pooblascenem servisu je potrebno priloziti obrazce m 1/m 2 (prijava odjava iz pokojninskega in invalidskega zavarovanja) ki dokazuje sklenjeno pogodbo o zaposlitvi. 3. certifikati o usposobljenosti za brezhibno vzdrzevanje referencne opreme izdane s strani ucnega servisnega centra proizvajalca ki so jih pridobili navedeni serviserji v izjavi iz druge tocke. pojem referencna oprema si bo narocnik tolmacil iz vidika potrebnega pridobljenega strokovnega znanja usposobljenih oseb za vzdrzevanje opreme ki je primerljiva ponujeni opremi. certifikat ne sme biti starejsi od 24 mesecev (leto izdaje najkasneje 2020). splosne zahteve osnova za realizacijo dobave je prejem pisnega narocila strani narocnika. ponudbe zbiramo informativno za predlozitev v presojo odobritve. v kolikor bomo prejeli odobritev s strani pristojnih bomo realizacijo izvedli pri najugodnejsemu ponudniku ki bo izpolnjeval tehnicne zahteve. cena mora vsebovati vse stroske popuste rabate dostavo montazo in davek na dodano vrednost. ponudbi predlozite prospekte ter drugo dokumentacijo iz katere je razvidno izpolnjevanje zahtev narocnika. rok za plaeilo je 60 dni od prejema racuna. merilo izbora najnizja vrednost ponudbe v eur z ddv ob izpolnjevanju tehnicnih zahtev narocnika.", "ner": [{"TenderOrg": "splosna bolnisnica celje"}, {"TenderTel": "(03) 42 33 000"}, {"TenderFax": "(03) 42 33 757"}, {"TenderNumber": "309"}, {"TenderYear": "2022"}, {"TenderCode": "da/vh"}, {"TenderType": "x"}], "ner_refine": []}
{"id": "2022_EN_X_309_TENDER", "chunk_id": "1", "input_tokens": 1757, "refiner_input_tokens": 0, "total_output_tokens": 142, "text": "4. izvajalec je narocniku po preventivnem in kurativnem vzdrzevalnem posegu na opremi dolzan podati porocilo v obliki delovnega naloga z natancnim opisom izvedenih storitev in o eventualni zamenjavi delov/materiala in sicer stevilo opravljenih ur (redne izredne) naziv aparata inventarna stevilka opreme oziroma aparata serijska stevilka aparata oddelek narocnika (nahajalisce aparata) kolicina in vrsta vgrajenega materiala oz. rezervnih delov cena vgrajenega materiala oz. rezervnih delov velja za popravila ki niso vkljucena v all inclusive vzdrzevanje dolzino garancijskega obdobja za vgrajene rezervne/nadomestne dele/materiala da je aparat brezhiben in varen za uporabo. 3. racun za opravljeno storitev mora vsebovati naziv opreme serijska stevilka inventarna stevilka stevilko narocilnice ter kot prilogo porocilo v obliki delovnega naloga z natancnim opisom izvedenih del. racuni ki ne bodo imeli izkazanega protokola narocila in potrjevanja po tem clenu bodo zavrnjena. kontaktna oseba s strani narocnika; matej vidmar tel. st. 030 464 787 elektronska posta matej.vidmar(4sb celje.si ponudbe posljite na naslov elektronske poste | nabaval sb celje.si z oznako 309 2022 popravilo centrifuge heraeus cryofuge 6000 | (m02) 19.05.2022 do 12 ure. | vanja herman gril dipl. ekon. vodja sluzbe za nabavo medicinske opreme potrosnega materiala in storitev", "ner": [{"TenderNumber": "309"}, {"TenderYear": "2022"}, {"TenderDeadline": "19.05.2022"}, {"TenderPerson": "matej vidmar"}, {"TenderTel": "030 464 787"}, {"TenderPerson": "vanja herman gril"}], "ner_refine": []}
{"id": "2022_EN_X_353_TENDER", "chunk_id": "0", "input_tokens": 2145, "refiner_input_tokens": 0, "total_output_tokens": 151, "text": "splosna bolnisnica celje oblakova ulica 5 3000 celje tel (03) 42 33 000 fax (03) 42 33 757 postopek 353 2022 bg/vh povabilo k oddaji ponudbe narocnik vabi ponudnike da v skladu z navodili ponudnikom izdelajo ponudbo za letni pregled dveh stresalnikov za trombocite (mo1) 1. proizvajalec lmb tip 96 inventarna stevilka 00521846 serijska stevilka 080502 leto nabave 2008 2. proizvajalec forma tip 4721 inventarna stevilka 00515800 serijska stevilka 502078 56 leto nabave 2004 transfuzijskem centru (sm 2815) obvezne priloge 1. v letu 2022 veljavna pisna pooblastila proizvajalcev s katerim pooblascajo zgoraj navedeni servis za servisiranje opreme in dobavo rezervnih delov. 2. izjava dana pod kazensko in materialno odgovornostjo z navedbo imen in priimkov serviserjev (pooblasceni servis mora imeti na razpolago vsaj enega serviserja) ki je usposobljen za vzdrzevanje ponujene opreme. serviserji morajo ze v casu oddaje ponudbe imeti s pooblascenim servisom sklenjeno pogodbo o zaposlitvi ali civilnopravno pogodbo o delu ali kaksno drugo civilnopravno pogodbo o sodelovanju v izjavi je potrebno navesti obliko sklenjene pogodbe in cas trajanja te pogodbe. v primeru da gre za redno zaposlenega serviserja pri pooblascenem servisu je potrebno priloziti obrazce m 1/m 2 (prijava odjava iz pokojninskega in invalidskega zavarovanja) ki dokazuje sklenjeno pogodbo o zaposlitvi. 3. certifikati o usposobljenosti za brezhibno vzdrzevanje referencne opreme izdane s strani ucnega servisnega centra proizvajalca ki so jih pridobili navedeni serviserji v izjavi iz druge tocke. pojem referencna oprema si bo narocnik tolmacil iz vidika potrebnega pridobljenega strokovnega znanja usposobljenih oseb za vzdrzevanje opreme ki je primerljiva ponujeni opremi. certifikat ne sme biti starejsi od 24 mesecev (leto izdaje najkasneje 2020). splosne zahteve osnova za realizacijo dobave je prejem pisnega narocila strani narocnika. ponudbe zbiramo informativno za predlozitev v presojo odobritve. v kolikor bomo prejeli odobritev s strani pristojnih bomo realizacijo izvedli pri najugodnejsemu ponudniku ki bo izpolnjeval tehnicne zahteve. cena mora vsebovati vse stroske popuste rabate dostavo montazo in davek na dodano vrednost. ponudbi predlozite prospekte ter drugo dokumentacijo iz katere je razvidno izpolnjevanje zahtev narocnika. rok za placilo je 60 dni od prejema racuna. merilo izbora najnizja vrednost ponudbe v eur z ddv ob izpolnjevanju tehnicnih zahtev narocnika.", "ner": [{"TenderOrg": "splosna bolnisnica celje"}, {"TenderTel": "(03) 42 33 000"}, {"TenderFax": "(03) 42 33 757"}, {"TenderNumber": "353"}, {"TenderYear": "2022"}, {"TenderCode": "bg/vh"}, {"TenderType": "x"}], "ner_refine": []}
{"id": "2022_EN_X_353_TENDER", "chunk_id": "1", "input_tokens": 1776, "refiner_input_tokens": 0, "total_output_tokens": 182, "text": "4. izvajalec je narocniku po preventivnem in kurativnem vzdrzevalnem posegu na opremi dolzan podati porocilo v obliki delovnega naloga z natancnim opisom izvedenih storitev in o eventualni zamenjavi delov/materiala in sicer stevilo opravljenih ur (redne izredne) naziv aparata inventarna stevilka opreme oziroma aparata serijska stevilka aparata oddelek narocnika (nahajalisce aparata) kolicina in vrsta vgrajenega materiala oz. rezervnih delov cena vgrajenega materiala oz. rezervnih delov velja za popravila ki niso vkljucena v all inclusiv e vzdrzevanje dolzino garancijskega obdobja za vgrajene rezervne/nadomestne dele/materiala da je aparat brezhiben in varen za uporabo. 5. racun za opravljeno storitev mora vsebovati naziv opreme serijska stevilka inventarna stevilka stevilko narocilnice ter kot prilogo porocilo v obliki delovnega naloga z natancnim opisom izvedenih del. racuni ki ne bodo imeli izkazanega protokola narocila in potrjevanja po tem clenu bodo zavrnjena. kon taktna oseba s strani narocnika; bostjan gajsek tel. st. 031 203 011 elektronska posta bostjan.gajsek(4sb celje.si matej vidmar tel. st. 030 464 787 elektronska posta matej.vidmar(4sb celje.si ponudbe posljite na naslov elektronske poste nab aval ( sb celje.si z oznako 353 2022 letni pregled dveh stresalnikov za trombocite (m01) 07.06.2022 do 12 ure. vanja herman gril dipl. ekon.", "ner": [{"TenderNumber": "353"}, {"TenderYear": "2022"}, {"TenderDeadline": "07.06.2022"}, {"TenderPerson": "vanja herman gril"}, {"TenderPerson": "bostjan gajsek"}, {"TenderTel": "031 203 011"}, {"TenderPerson": "matej vidmar"}, {"TenderTel": "030 464 787"}], "ner_refine": []}
{"id": "2022-EN_X_256_TENDER", "chunk_id": "0", "input_tokens": 2241, "refiner_input_tokens": 0, "total_output_tokens": 151, "text": "cd splosna bolnisnica celje oblakova ulica 5 3000 celje tel (03) 42 33 000 fax (03) 42 33 757 postopek 256 2022 id/vh povabilo k oddaji ponudbe narocnik vabi ponudnike da v skladu z navodili ponudnikom izdelajo ponudbo za popravilo rocnika (m03) obvezne priloge 1. v letu 2022 veljavna pisna pooblastila proizvajalcev s katerim pooblascajo zgoraj navedeni servis za servisiranje opreme in dobavo rezervnih delov. 2. izjava dana pod kazensko in materialno odgovornostjo z navedbo imen in priimkov serviserjev (pooblasceni servis mora imeti na razpolago vsaj enega serviserja) ki je usposobljen za vzdrzevanje ponujene opreme. serviserji morajo ze v casu oddaje ponudbe imeti s pooblascenim servisom sklenjeno pogodbo o zaposlitvi ali civilnopravno pogodbo o delu ali kaksno drugo civilnopravno pogodbo o sodelovanju v izjavi je potrebno navesti obliko sklenjene pogodbe in cas trajanja te pogodbe. v primeru da gre za redno zaposlenega serviserja pri pooblascenem servisu je potrebno priloziti obrazce m 1/m 2 (prijava odjava iz pokojninskega in invalidskega zavarovanja) ki dokazuje sklenjeno pogodbo o zaposlitvi. 3. certifikati o usposobljenosti za brezhibno vzdrzevanje referencne opreme izdane s strani ucnega servisnega centra proizvajalca ki so jih pridobili navedeni serviserji v izjavi iz druge tocke. pojem referencna oprema si bo narocnik tolmacil iz vidika potrebnega pridobljenega strokovnega znanja usposobljenih oseb za vzdrzevanje opreme ki je primerljiva ponujeni opremi. certifikat ne sme biti starejsi od 24 mesecev (leto izdaje najkasneje 2020). splosne zahteve osnova za realizacijo dobave je prejem pisnega narocila strani narocnika. ponudbe zbiramo informativno za predlozitev v presojo odobritve. v kolikor bomo prejeli odobritev s strani pristojnih bomo realizacijo izvedli pri najugodnejsemu ponudniku ki bo izpolnjeval tehnicne zahteve. cena mora vsebovati vse stroske popuste rabate dostavo montazo in davek na dodano vrednost. ponudbi predlozite prospekte ter drugo dokumentacijo iz katere je razvidno izpolnjevanje zahtev narocnika. rok za placilo je 60 dni od prejema racuna. merilo izbora najnizja vrednost ponudbe v eur z ddv ob izpolnjevanju tehnicnih zahtev narocnika. 4. izvajalec je narocniku po preventivnem in kurativnem vzdrzevalnem posegu na opremi dolzan podati porocilo v obliki delovnega naloga z natancnim opisom izvedenih storitev in o eventualni zamenjavi delov/materiala in sicer stevilo opravljenih ur (redne izredne) naziv aparata inventarna stevilka opreme oziroma aparata serijska stevilka aparata oddelek narocnika (nahajalisce aparata) kolicina in vrsta vgrajenega materiala oz. rezervnih delov cena vgrajenega materiala oz. rezervnih delov velja za popravila ki niso vkljucena v all inclusive vzdrzevanje dolzino garancijskega obdobja za vgrajene rezervne/nadomestne dele/materiala da je aparat brezhiben in varen za uporabo.", "ner": [{"TenderOrg": "splosna bolnisnica celje"}, {"TenderTel": "(03) 42 33 000"}, {"TenderFax": "(03) 42 33 757"}, {"TenderNumber": "256"}, {"TenderYear": "2022"}, {"TenderCode": "id/vh"}, {"TenderType": "x"}], "ner_refine": []}
{"id": "2022-EN_X_256_TENDER", "chunk_id": "1", "input_tokens": 1547, "refiner_input_tokens": 0, "total_output_tokens": 168, "text": "5. racun za opravljeno storitev mora vsebovati naziv opreme serijska stevilka inventarna stevilka stevilko narocilnice ter kot prilogo porocilo v obliki delovnega naloga z natancnim opisom izvedenih. racuni ki ne bodo imeli izkazanega protokola narocila in potrjevanja po tem clenu bodo zavrnjena. kontaktna oseba s strani narocnika ; ivan drobez. tel.st. 03 423 32 04 faks st. 03 423 37 56 elektronska posta ivan.drobez sb celje.si ponudbe posljite na naslov elektronske poste nabaval(4)sb celje.si h z oznako 256 2022 servis rocnika do najkasneje 28.04.2022 do 12 ure. vanja herman gril dipl. ekon. vodja sluzbe za nabavo medicinske opreme potrosnega materiala in storitev", "ner": [{"TenderNumber": "256"}, {"TenderYear": "2022"}, {"TenderDeadline": "28.04.2022"}, {"TenderPerson": "ivan drobez"}, {"TenderTel": "03 423 32 04"}, {"TenderFax": "03 423 37 56"}, {"TenderPerson": "vanja herman gril"}], "ner_refine": []}
{"id": "2022_EN_X_278_TENDER", "chunk_id": "0", "input_tokens": 2076, "refiner_input_tokens": 0, "total_output_tokens": 151, "text": "c( splosna bolnisnica celje oblakova ulica 5 3000 celje tel (03) 42 33 000 fax (03) 42 33 757 postopek 278 2022 id/vh povabilo k oddaji ponudbe narocnik vabi ponudnike da v skladu z navodili ponudnikom izdelajo ponudbo za redni servis injektor kontrasta acist cvi (m0) naziv injektor kontrasta model acist cvi sn ep0021470 inventarna stevilka 00535051 leto dobave 2015 obvezne priloge 1. v letu 2022 veljavna pisna pooblastila proizvajalcev s katerim pooblascajo zgoraj navedeni servis za servisiranje opreme in dobavo rezervnih delov. 2. izjava dana pod kazensko in materialno odgovornostjo z navedbo imen in priimkov serviserjev (pooblasceni servis mora imeti na razpolago vsaj enega serviserja) ki je usposobljen za vzdrzevanje ponujene opreme. serviserji morajo ze v casu oddaje ponudbe imeti s pooblascenim servisom sklenjeno pogodbo o zaposlitvi ali civilnopravno pogodbo o delu ali kaksno drugo civilnopravno pogodbo o sodelovanju v izjavi je potrebno navesti obliko sklenjene pogodbe in cas trajanja te pogodbe. v primeru da gre za redno zaposlenega serviserja pri pooblascenem servisu je potrebno priloziti obrazce m 1/m 2 (prijava odjava iz pokojninskega in invalidskega zavarovanja) ki dokazuje sklenjeno pogodbo o zaposlitvi. 3. certifikati o usposobljenosti za brezhibno vzdrzevanje referencne opreme izdane s strani ucnega servisnega centra proizvajalca ki so jih pridobili navedeni serviserji v izjavi iz druge tocke. pojem referencna oprema si bo narocnik tolmacil iz vidika potrebnega pridobljenega strokovnega znanja usposobljenih oseb za vzdrzevanje opreme ki je primerljiva ponujeni opremi. certifikat ne sme biti starejsi od 24 mesecev (leto izdaje najkasneje 2020). splosne zahteve osnova za realizacijo dobave je prejem pisnega narocila strani narocnika. ponudbe zbiramo informativno za predlozitev v presojo odobritve. v kolikor bomo prejeli odobritev s strani pristojnih bomo realizacijo izvedli pri najugodnejsemu ponudniku ki bo izpolnjeval tehnicne zahteve. cena mora vsebovati vse stroske popuste rabate dostavo montazo in davek na dodano vrednost. ponudbi predlozite prospekte ter drugo dokumentacijo iz katere je razvidno izpolnjevanje zahtev narocnika. rok za placilo je 60 dni od prejema racuna. merilo izbora najnizja vrednost ponudbe v eur z ddv ob izpolnjevanju tehnicnih zahtev narocnika.", "ner": [{"TenderOrg": "splosna bolnisnica celje"}, {"TenderTel": "(03) 42 33 000"}, {"TenderFax": "(03) 42 33 757"}, {"TenderNumber": "278"}, {"TenderYear": "2022"}, {"TenderCode": "id/vh"}, {"TenderType": "x"}], "ner_refine": []}
{"id": "2022_EN_X_278_TENDER", "chunk_id": "1", "input_tokens": 1770, "refiner_input_tokens": 0, "total_output_tokens": 168, "text": "4. izvajalec je narocniku po preventivnem in kurativnem vzdrzevalnem posegu na opremi dolzan podati porocilo v obliki delovnega naloga z natancnim opisom izvedenih storitev in o eventualni zamenjavi delov/materiala in sicer stevilo opravljenih ur (redne izredne) naziv aparata inventarna stevilka opreme oziroma aparata serijska stevilka aparata oddelek narocnika (nahajalisce aparata) kolicina in vrsta vgrajenega materiala oz. rezervnih delov cena vgrajenega materiala oz. rezervnih delov velja za popravila ki niso vkljucena v all inclusive vzdrzevanje dolzino garancijskega obdobja za vgrajene rezervne/nadomestne dele/materiala da je aparat brezhiben in varen za uporabo. 5. racun za opravljeno storitev mora vsebovati naziv opreme serijska stevilka inventarna stevilka stevilko narocilnice ter kot prilogo porocilo v obliki delovnega naloga z natancnim opisom izvedenih del. racuni ki ne bodo imeli izkazanega protokola narocila in potrjevanja po tem clenu bodo zavrnjena. kontaktna oseba s strani narocnika ; ivan drobez. tel.st. 03 423 32 04 faks st. 03 423 37 56 elektronska posta ivan.drobez(4)sb celje.si ponudbe posljite na naslov elektronske poste | nabaval sb celje.si | z oznako 278 2022 redni servis injektor kontrasta acist cvi (m01) 09.05.2022 do 12 ure. vanja herman gril dipl. ekon. vodja sluzbe za nabavo medicinske opreme potrosnega materiala in storitev", "ner": [{"TenderTel": "03 423 32 04"}, {"TenderFax": "03 423 37 56"}, {"TenderPerson": "ivan drobez"}, {"TenderNumber": "278"}, {"TenderYear": "2022"}, {"TenderDeadline": "09.05.2022"}, {"TenderPerson": "vanja herman gril"}], "ner_refine": []}
{"id": "2022_EN_X_367_TENDER", "chunk_id": "0", "input_tokens": 2095, "refiner_input_tokens": 0, "total_output_tokens": 151, "text": "splosna bolnisnica celje oblakova ulica 5 3000 celje tel (03) 42 33 000 fax (03) 42 33 757 postopek 367 2022 bg/vh povabilo k oddaji ponudbe narocnik vabi ponudnike da v skladu z navodili ponudnikom izdelajo ponudbo za popravilo 2 aparatov bw3 kanmed (m02) kanmed sn. 4655/17 inv. 00540564 kanmed sn. 4672/17 inv. 00540565 menjava celne folije s tipkami za dva aparata bw 3 obvezne priloge 1. v letu 2022 veljavna pisna pooblastila proizvajalcev s katerim pooblascajo zgoraj navedeni servis za servisiranje opreme in dobavo rezervnih delov. 2. izjava dana pod kazensko in materialno odgovornostjo z navedbo imen in priimkov serviserjev (pooblasceni servis mora imeti na razpolago vsaj enega serviserja) ki je usposobljen za vzdrzevanje ponujene opreme. serviserji morajo ze v casu oddaje ponudbe imeti s pooblascenim servisom sklenjeno pogodbo o zaposlitvi ali civilnopravno pogodbo o delu ali kaksno drugo civilnopravno pogodbo o sodelovanju v izjavi je potrebno navesti obliko sklenjene pogodbe in cas trajanja te pogodbe. v primeru da gre za redno zaposlenega serviserja pri pooblascenem servisu je potrebno priloziti obrazce m 1/m 2 (prijava odjava iz pokojninskega in invalidskega zavarovanja) ki dokazuje sklenjeno pogodbo o zaposlitvi. 3. certifikati o usposobljenosti za brezhibno vzdrzevanje referencne opreme izdane s strani ucnega servisnega centra proizvajalca ki so jih pridobili navedeni serviserji v izjavi iz druge tocke. pojem referencna oprema si bo narocnik tolmacil iz vidika potrebnega pridobljenega strokovnega znanja usposobljenih oseb za vzdrzevanje opreme ki je primerljiva ponujeni opremi. certifikat ne sme biti starejsi od 24 mesecev (leto izdaje najkasneje 2020). splosne zahteve osnova za realizacijo dobave je prejem pisnega narocila strani narocnika. ponudbe zbiramo informativno za predlozitev v presojo odobritve. v kolikor bomo prejeli odobritev s strani pristojnih bomo realizacijo izvedli pri najugodnejsemu ponudniku ki bo izpolnjeval tehnicne zahteve. cena mora vsebovati vse stroske popuste rabate dostavo montazo in davek na dodano vrednost. ponudbi predlozite prospekte ter drugo dokumentacijo iz katere je razvidno izpolnjevanje zahtev narocnika. rok za placilo je 60 dni od prejema racuna. merilo izbora najnizja vrednost ponudbe v eur z ddv ob izpolnjevanju tehnicnih zahtev narocnika.", "ner": [{"TenderOrg": "splosna bolnisnica celje"}, {"TenderTel": "(03) 42 33 000"}, {"TenderFax": "(03) 42 33 757"}, {"TenderNumber": "367"}, {"TenderYear": "2022"}, {"TenderCode": "bg/vh"}, {"TenderType": "x"}], "ner_refine": []}
{"id": "2022_EN_X_367_TENDER", "chunk_id": "1", "input_tokens": 1792, "refiner_input_tokens": 0, "total_output_tokens": 187, "text": "4. izvajalec je narocniku po preventivnem in kurativnem vzdrzevalnem posegu na opremi dolzan podati porocilo v obliki delovnega naloga z natancnim opisom izvedenih storitev in o eventualni zamenjavi delov/materiala in sicer stevilo opravljenih ur (redne izredne) naziv aparata inventarna stevilka opreme oziroma aparata serijska stevilka aparata oddelek narocnika (nahajalisce aparata) kolicina in vrsta vgrajenega materiala oz. rezervnih delov cena vgrajenega materiala oz. rezervnih delov velja za popravila ki niso vkljucena v all inclusive vzdrzevanje dolzino garancijskega obdobja za vgrajene rezervne/nadomestne dele/materiala da je aparat brezhiben in varen za uporabo. 5. racun za opravljeno storitev mora vsebovati naziv opreme serijska stevilka inventarna stevilka stevilko narocilnice ter kot prilogo porocilo v obliki delovnega naloga z natancnim opisom izvedenih del. racuni ki ne bodo imeli izkazanega protokola narocila in potrjevanja po tem clenu bodo zavrnjena. kontaktna oseba s strani narocnika; bostjan gajsek tel. st. 031 203 011 elektronska posta bostjan.gajsek(4)sb celje.si matej vidmar tel. st. 030 464 787 elektronska posta matej. vidmar(4 sb celje.si ponudbe posljite na naslov elektronske poste nabaval (4 sb celje.si zoznako 367 2022 popravilo2 aparatov bw3 kanmed (m02) 10.06.2022 do 12 ure. vanja herman gril dipl. ekon. vodja sluzbe za nabavo medicinske opreme potrosnega materiala in storitev", "ner": [{"TenderNumber": "367"}, {"TenderYear": "2022"}, {"TenderDeadline": "10.06.2022"}, {"TenderPerson": "bostjan gajsek"}, {"TenderTel": "031 203 011"}, {"TenderPerson": "matej vidmar"}, {"TenderTel": "030 464 787"}, {"TenderPerson": "vanja herman gril"}], "ner_refine": []}
{"id": "2022_EN_X_605_TENDER", "chunk_id": "0", "input_tokens": 2138, "refiner_input_tokens": 0, "total_output_tokens": 151, "text": "narocnik splosna bolnisnica celje 1 splosna bolnisnica celje oblakova ulica 5 3000 celje tel (03) 42 33 000 fax (03) 42 33 757 postopek 605 2022 bg/vh povabilo k oddaji ponudbe narocnik vabi ponudnike da v skladu z navodili ponudnikom izdelajo ponudbo za popravilo resevalne postelje proizvajalec stryker rugged tip m1 inv.st. 00538913 serijska stevilka 171239149 leto nabave 2017 enota za splosno nujno medicinsko pomoc; (sm 2620). potrebno zamenjati vzmetenje vzglavja. obvezne priloge 1. v letu 2022 veljavna pisna pooblastila proizvajalcev s katerim pooblascajo zgoraj navedeni servis za servisiranje opreme in dobavo rezervnih delov. 2. izjava dana pod kazensko in materialno odgovornostjo z navedbo imen in priimkov serviserjev (pooblasceni servis mora imeti na razpolago vsaj enega serviserja) ki je usposobljen za vzdrzevanje ponujene opreme. serviserji morajo ze v casu oddaje ponudbe imeti s pooblascenim servisom sklenjeno pogodbo o zaposlitvi ali civilnopravno pogodbo o delu ali kaksno drugo civilnopravno pogodbo o sodelovanju v izjavi je potrebno navesti obliko sklenjene pogodbe in cas trajanja te pogodbe. v primeru da gre za redno zaposlenega serviserja pri pooblascenem servisu je potrebno priloziti obrazce m 1/m 2 (prijava odjava iz pokojninskega in invalidskega zavarovanja) ki dokazuje sklenjeno pogodbo o zaposlitvi. 3. certifikati o usposobljenosti za brezhibno vzdrzevanje referencne opreme izdane s strani ucnega servisnega centra proizvajalca ki so jih pridobili navedeni serviserji v izjavi iz druge tocke. pojem referencna oprema si bo narocnik tolmacil iz vidika potrebnega pridobljenega strokovnega znanja postopek sp/vh narocnik splosna bolnisnica celje 2 usposobljenih oseb za vzdrzevanje opreme ki je primerljiva ponujeni opremi. certifikat ne sme biti starejsi od 24 mesecev (leto izdaje najkasneje 2020). splosne zahteve osnova za realizacijo dobave je prejem pisnega narocila strani narocnika. ponudbe zbiramo informativno za predlozitev v presojo odobritve. v kolikor bomo prejeli odobritev s strani pristojnih bomo realizacijo izvedli pri najugodnejsemu ponudniku ki bo izpolnjeval tehnicne zahteve. cena mora vsebovati vse stroske popuste rabate dostavo montazo in davek na dodano vrednost. ponudbi predlozite prospekte ter drugo dokumentacijo iz katere je razvidno izpolnjevanje zahtev narocnika. rok za placilo je 30 dni od prejema racuna. merilo izbora najnizja vrednost ponudbe v eur z ddv ob izpolnjevanju tehnicnih zahtev narocnika.", "ner": [{"TenderOrg": "splosna bolnisnica celje"}, {"TenderTel": "(03) 42 33 000"}, {"TenderFax": "(03) 42 33 757"}, {"TenderNumber": "605"}, {"TenderYear": "2022"}, {"TenderCode": "bg/vh"}, {"TenderType": "x"}], "ner_refine": []}
{"id": "2022_EN_X_605_TENDER", "chunk_id": "1", "input_tokens": 1805, "refiner_input_tokens": 0, "total_output_tokens": 226, "text": "4. izvajalec je narocniku po preventivnem in kurativnem vzdrzevalnem posegu na opremi dolzan podati porocilo v obliki delovnega naloga z natancnim opisom izvedenih storitev in o eventualni zamenjavi delov/materiala in sicer stevilo opravljenih ur (redne izredne) naziv aparata inventarna stevilka opreme oziroma aparata serijska stevilka aparata oddelek narocnika (nahajalisce aparata) kolicina in vrsta vgrajenega materiala oz. rezervnih delov cena vgrajenega materiala oz. rezervnih delov velja za popravila ki niso vkljucena v all inclusive vzdrzevanje dolzino garancijskega obdobja za vgrajene rezervne/nadomestne dele/materiala da je aparat brezhiben in varen za uporabo. 3. racun za opravljeno storitev mora vsebovati naziv opreme serijska stevilka inventarna stevilka stevilko narocilnice ter kot prilogo porocilo v obliki delovnega naloga z natancnim opisom izvedenih del. racuni ki ne bodo imeli izkazanega protokola narocila in potrjevanja po tem clenu bodo zavrnjena. kontaktna oseba s strani narocnika; bostjan gajsek tel. st. 030 203 011 elektronska posta bostjan.gajsek(a sb celje.si matej vidmar tel. st. 030 464 787 elektronska posta matej.vidmaric sb celje.si postopek sp/vh narocnik splosna bolnisnica celje 3 ponudbe posljite na naslov elektronske poste nabaval sb celjesi z oznako 605 2022 popravilo resevalne postelje do 14.10.2022 do 12 ure. vanja herman gril dipl. ekon. vodja sluzbe za nabavo medicinske opreme potrosnega materiala in storitev postopek sp/vh", "ner": [{"TenderPerson": "bostjan gajsek"}, {"TenderTel": "030 203 011"}, {"TenderPerson": "matej vidmar"}, {"TenderTel": "030 464 787"}, {"TenderCode": "sp/vh"}, {"TenderOrg": "splosna bolnisnica celje"}, {"TenderNumber": "605"}, {"TenderYear": "2022"}, {"TenderDeadline": "14.10.2022"}, {"TenderPerson": "vanja herman gril"}], "ner_refine": []}
{"id": "2022_EN_X_494_TENDER", "chunk_id": "0", "input_tokens": 2105, "refiner_input_tokens": 0, "total_output_tokens": 151, "text": "rs be) splosna bolnisnica celje oblakova ulica 5 3000 celje tel (03) 42 33 000 fax (03) 42 33 757 postopek 494 2022 bg/vh povabilo k oddaji ponudbe narocnik vabi ponudnike da v skladu z navodili ponudnikom izdelajo ponudbo za popravilo termodezinfektorja (m02) nahaja se v pritlicju (oddelek za bolezni prebavil) proizvajalec olympus tip mini etd jinv.st. 00530837 serijska stevilka 12842606 leto nabave 2012 okvara f26. obvezne priloge 1. v letu 2022 veljavna pisna pooblastila proizvajalcev s katerim pooblascajo zgoraj navedeni servis za servisiranje opreme in dobavo rezervnih delov. 2. izjava dana pod kazensko in materialno odgovornostjo z navedbo imen in priimkov serviserjev (pooblasceni servis mora imeti na razpolago vsaj enega serviserja) ki je usposobljen za vzdrzevanje ponujene opreme. serviserji morajo ze v casu oddaje ponudbe imeti s pooblascenim servisom sklenjeno pogodbo o zaposlitvi ali civilnopravno pogodbo o delu ali kaksno drugo civilnopravno pogodbo o sodelovanju v izjavi je potrebno navesti obliko sklenjene pogodbe in cas trajanja te pogodbe. v primeru da gre za redno zaposlenega serviserja pri pooblascenem servisu je potrebno priloziti obrazce m 1/m 2 (prijava odjava iz pokojninskega in invalidskega zavarovanja) ki dokazuje sklenjeno pogodbo o zaposlitvi. 3. certifikati o usposobljenosti za brezhibno vzdrzevanje referencne opreme izdane s strani ucnega servisnega centra proizvajalca ki so jih pridobili navedeni serviserji v izjavi iz druge tocke. pojem referencna oprema si bo narocnik tolmacil iz vidika potrebnega pridobljenega strokovnega znanja usposobljenih oseb za vzdrzevanje opreme ki je primerljiva ponujeni opremi. certifikat ne sme biti starejsi od 24 mesecev (leto izdaje najkasneje 2020). splosne zahteve osnova za realizacijo dobave je prejem pisnega narocila strani narocnika. ponudbe zbiramo informativno za predlozitev v presojo odobritve. v kolikor bomo prejeli odobritev s strani pristojnih bomo realizacijo izvedli pri najugodnejsemu ponudniku ki bo izpolnjeval tehnicne zahteve. cena mora vsebovati vse stroske popuste rabate dostavo montazo in davek na dodano vrednost. ponudbi predlozite prospekte ter drugo dokumentacijo iz katere je razvidno izpolnjevanje zahtev narocnika. rok za placilo je 60 dni od prejema racuna. merilo izbora najnizja vrednost ponudbe v eur z ddv ob izpolnjevanju tehnicnih zahtev narocnika.", "ner": [{"TenderOrg": "splosna bolnisnica celje"}, {"TenderTel": "(03) 42 33 000"}, {"TenderFax": "(03) 42 33 757"}, {"TenderNumber": "494"}, {"TenderYear": "2022"}, {"TenderCode": "bg/vh"}, {"TenderType": "x"}], "ner_refine": []}
{"id": "2022_EN_X_494_TENDER", "chunk_id": "1", "input_tokens": 1790, "refiner_input_tokens": 0, "total_output_tokens": 204, "text": "4. izvajalec je narocniku po preventivnem in kurativnem vzdrzevalnem posegu na opremi dolzan podati porocilo v obliki delovnega naloga z natancnim opisom izvedenih storitev in o eventualni zamenjavi delov/materiala in sicer stevilo opravljenih ur (redne izredne) naziv aparata inventarna stevilka opreme oziroma aparata serijska stevilka aparata oddelek narocnika (nahajalisce aparata) kolicina in vrsta vgrajenega materiala oz. rezervnih delov cena vgrajenega materiala oz. rezervnih delov velja za popravila ki niso vkljucena v all inclusive vzdrzevanje dolzino garancijskega obdobja za vgrajene rezervne/nadomestne dele/materiala da je aparat brezhiben in varen za uporabo. 3. racun za opravljeno storitev mora vsebovati naziv opreme serijska stevilka inventarna stevilka stevilko narocilnice ter kot prilogo porocilo v obliki delovnega naloga z natancnim opisom izvedenih del. racuni ki ne bodo imeli izkazanega protokola narocila in potrjevanja po tem clenu bodo zavrnjena. kontaktna oseba s strani narocnika; bostjan gajsek tel. st. 030 203 011 elektronska posta bostjan.gajsek(4 sb celje.si matej vidmar tel. st. 030 464 787 elektronska posta matej. vidmar(4 sb eelje.si | ponudbe posljite na naslov elektronske poste nabaval sb celje.si z oznako 494 2022 | popravilo termodezinfektorja (m02) 12.08.2022 do 12 ure. vanja herman gril dipl. ekon. vodja sluzbe za nabavo medicinske opreme potrosnega materiala in storitev", "ner": [{"TenderNumber": "494"}, {"TenderYear": "2022"}, {"TenderDeadline": "12.08.2022"}, {"TenderPerson": "bostjan gajsek"}, {"TenderTel": "030 203 011"}, {"TenderPerson": "matej vidmar"}, {"TenderTel": "030 464 787"}, {"TenderPerson": "vanja herman gril"}, {"TenderOrg": "sb celje"}], "ner_refine": []}
{"id": "2022_EN_X_227_TENDER", "chunk_id": "0", "input_tokens": 2151, "refiner_input_tokens": 0, "total_output_tokens": 151, "text": "c splosna bolnisnica celje oblakova ulica 5 3000 celje tel (03) 42 33 000 fax (03) 42 33 757 postopek 227 2022 id/vh povabilo k oddaji ponudbe narocnik vabi ponudnike da v skladu z navodili ponudnikom izdelajo ponudbo za popravilo ali za zamenjavo staro za novo optiko (m03) popravilo motne optike l.popravilo optike proizvajalca karl storz s stevilko artikla 27005aa hopkins ii telescope 0 4mm 1 kpl 2.popravilo optike proizvajalca olympus wa53000a | kpl 3.popravilo optike proizvajalca tecno 1x 700 074 in 1x 700 079 (kotna) 2 kpl obvezne priloge 1. v letu 2022 veljavna pisna pooblastila proizvajalcev s katerim pooblascajo zgoraj navedeni servis za servisiranje opreme in dobavo rezervnih delov. 2. izjava dana pod kazensko in materialno odgovornostjo z navedbo imen in priimkov serviserjev (pooblasceni servis mora imeti na razpolago vsaj enega serviserja) ki je usposobljen za vzdrzevanje ponujene opreme. serviserji morajo ze v casu oddaje ponudbe imeti s pooblascenim servisom sklenjeno pogodbo o zaposlitvi ali civilnopravno pogodbo o delu ali kaksno drugo civilnopravno pogodbo o sodelovanju v izjavi je potrebno navesti obliko sklenjene pogodbe in cas trajanja te pogodbe. v primeru da gre za redno zaposlenega serviserja pri pooblascenem servisu je potrebno priloziti obrazce m 1/m 2 (prijava odjava iz pokojninskega in invalidskega zavarovanja) ki dokazuje sklenjeno pogodbo o zaposlitvi. 3. certifikati o usposobljenosti za brezhibno vzdrzevanje referencne opreme izdane s strani ucnega servisnega centra proizvajalca ki so jih pridobili navedeni serviserji v izjavi iz druge tocke. pojem referencna oprema si bo narocnik tolmacil iz vidika potrebnega pridobljenega strokovnega znanja usposobljenih oseb za vzdrzevanje opreme ki je primerljiva ponujeni opremi. certifikat ne sme biti starejsi od 24 mesecev (leto izdaje najkasneje 2020). splosne zahteve osnova za realizacijo dobave je prejem pisnega narocila strani narocnika. ponudbe zbiramo informativno za predlozitev v presojo odobritve. v kolikor bomo prejeli odobritev s strani pristojnih bomo realizacijo izvedli pri najugodnejsemu ponudniku ki bo izpolnjeval tehnicne zahteve. cena mora vsebovati vse stroske popuste rabate dostavo montazo in davek na dodano vrednost. ponudbi predlozite prospekte ter drugo dokumentacijo iz katere je razvidno izpolnjevanje zahtev narocnika. rok za placilo je 60 dni od prejema racuna. merilo izbora najnizja vrednost ponudbe v eur z ddv ob izpolnjevanju tehnicnih zahtev narocnika.", "ner": [{"TenderOrg": "splosna bolnisnica celje"}, {"TenderTel": "(03) 42 33 000"}, {"TenderFax": "(03) 42 33 757"}, {"TenderNumber": "227"}, {"TenderYear": "2022"}, {"TenderCode": "id/vh"}, {"TenderType": "x"}], "ner_refine": []}
{"id": "2022_EN_X_227_TENDER", "chunk_id": "1", "input_tokens": 1771, "refiner_input_tokens": 0, "total_output_tokens": 168, "text": "4. izvajalec je narocniku po preventivnem in kurativnem vzdrzevalnem posegu na opremi dolzan podati porocilo v obliki delovnega naloga z natancnim opisom izvedenih storitev in o eventualni zamenjavi delov/materiala in sicer stevilo opravljenih ur (redne izredne) naziv aparata inventarna stevilka opreme oziroma aparata serijska stevilka aparata oddelek narocnika (nahajalisce aparata) kolicina in vrsta vgrajenega materiala oz. rezervnih delov cena vgrajenega materiala oz. rezervnih delov velja za popravila ki niso vkljucena v all inclusive vzdrzevanje dolzino garancijskega obdobja za vgrajene rezervne/nadomestne dele/materiala da je aparat brezhiben in varen za uporabo. 5. racun za opravljeno storitev mora vsebovati naziv opreme serijska stevilka inventarna stevilka stevilko narocilnice ter kot prilogo porocilo v obliki delovnega naloga z natancnim opisom izvedenih. racuni ki ne bodo imeli izkazanega protokola narocila in potrjevanja po tem clenu bodo zavrnjena. kontaktna oseba s strani narocnika ; ivan drobez. tel.st. 03 423 32 04 faks st. 03 423 37 56 elektronska posta ivan.drobez(dsb celje.si ponudbe posljite na naslov elektronske poste nabaval( sb celje.si z oznako 227 2022 popravilo ali zamenjava staro za novo | optiko do najkasneje 15.04.2022 do 12 ure. | vanja herman gril dipl. ekon. vodja sluzbe za nabavo medicinske opreme potrosnega materiala in storitev", "ner": [{"TenderPerson": "ivan drobez"}, {"TenderTel": "03 423 32 04"}, {"TenderFax": "03 423 37 56"}, {"TenderNumber": "227"}, {"TenderYear": "2022"}, {"TenderDeadline": "15.04.2022"}, {"TenderPerson": "vanja herman gril"}], "ner_refine": []}
{"id": "2022_EN_X_408_TENDER", "chunk_id": "0", "input_tokens": 2102, "refiner_input_tokens": 0, "total_output_tokens": 151, "text": "cl splosna bolnisnica celje oblakova ulica 5 3000 celje tel (03) 42 33 000 fax (03) 42 33 757 postopek 408 2022 bg/vh povabilo k oddaji ponudbe narocnik vabi ponudnike da v skladu z navodili ponudnikom izdelajo ponudbo za popravilo prenosnega ventilatorja za dihanje drager oxylog (m02) proizvajalec drager tip oxylog 3000 + inventarna stevilka 00536149 serijska stevilka ashj 0105 leto nabave 2013 urgentni center (sm 2600) obvezne priloge 1. v letu 2022 veljavna pisna pooblastila proizvajalcev s katerim pooblascajo zgoraj navedeni servis za servisiranje opreme in dobavo rezervnih delov. 2. izjava dana pod kazensko in materialno odgovornostjo z navedbo imen in priimkov serviserjev (pooblasceni servis mora imeti na razpolago vsaj enega serviserja). ki je usposobljen za vzdrzevanje ponujene opreme. serviserji morajo ze v casu oddaje ponudbe imeti s pooblascenim servisom sklenjeno pogodbo o zaposlitvi ali civilnopravno pogodbo o delu ali kaksno drugo civilnopravno pogodbo o sodelovanju v izjavi je potrebno navesti obliko sklenjene pogodbe in cas trajanja te pogodbe. v primeru da gre za redno zaposlenega serviserja pri pooblascenem servisu je potrebno priloziti obrazce m 1/m 2 (prijava odjava iz pokojninskega in invalidskega zavarovanja) ki dokazuje sklenjeno pogodbo o zaposlitvi. 3. certifikati o usposobljenosti za brezhibno vzdrzevanje referencne opreme izdane s strani ucnega servisnega centra proizvajalca ki so jih pridobili navedeni serviserji v izjavi iz druge tocke. pojem referencna oprema si bo narocnik tolmacil iz vidika potrebnega pridobljenega strokovnega znanja usposobljenih oseb za vzdrzevanje opreme. ki je primerljiva ponujeni opremi. certifikat ne sme biti starejsi od 24 mesecev (leto izdaje najkasneje 2020). splosne zahteve osnova za realizacijo dobave je prejem pisnega narocila strani narocnika. ponudbe zbiramo informativno za predlozitev v presojo odobritve. v kolikor bomo prejeli odobritev s strani pristojnih bomo realizacijo izvedli pri najugodnejsemu ponudniku ki bo izpolnjeval tehnicne zahteve. cena mora vsebovati vse stroske popuste. rabate. dostavo montazo in davek na dodano vrednost. ponudbi predlozite prospekte ter drugo dokumentacijo iz katere je razvidno izpolnjevanje zahtev narocnika. rok za placilo je 60 dni od prejema racuna. merilo izbora najnizja vrednost ponudbe v eur z ddv ob izpolnjevanju tehnicnih zahtev narocnika.", "ner": [{"TenderOrg": "splosna bolnisnica celje"}, {"TenderTel": "(03) 42 33 000"}, {"TenderFax": "(03) 42 33 757"}, {"TenderNumber": "408"}, {"TenderYear": "2022"}, {"TenderCode": "bg/vh"}, {"TenderType": "x"}], "ner_refine": []}
{"id": "2022_EN_X_408_TENDER", "chunk_id": "1", "input_tokens": 1797, "refiner_input_tokens": 0, "total_output_tokens": 183, "text": "4. izvajalec je narocniku po preventivnem in kurativnem vzdrzevalnem posegu na opremi dolzan podati porocilo v obliki delovnega naloga z natancnim opisom izvedenih storitev in o eventualni zamenjavi delov/materiala in sicer stevilo opravljenih ur (redne izredne) naziv aparata inventarna stevilka opreme oziroma aparata serijska stevilka aparata oddelek narocnika (nahajalisce aparata) kolicina in vrsta vgrajenega materiala oz. rezervnih delov cena vgrajenega materiala oz. rezervnih delov velja za popravila ki niso vkljucena v all inclusive vzdrzevanje dolzino garancijskega obdobja za vgrajene rezervne/nadomestne dele/materiala da je aparat brezhiben in varen za uporabo. 5. racun za opravljeno storitev mora vsebovati naziv opreme serijska stevilka inventarna stevilka stevilko narocilnice ter kot prilogo porocilo v obliki delovnega naloga z natancnim opisom izvedenih del. racuni ki ne bodo imeli izkazanega protokola narocila in potrjevanja po tem clenu bodo zavrnjena. kontaktna oseba s strani narocnika; bostjan gajsek tel. st. 031 203 oli elektronska posta bostjan.gajsek(2sb celje.si matej vidmar tel. st. 030 464 787 elektronska posta matej.vidmar)sb celje.si ponudbe posljite na naslov elektronske poste nabaval( sb celje.si z oznako 408 2022 popravilo prenosnega ventilatorja za dihanje drager oxylog 3000 (m02) 24.06.2022 do 12 ure. vanja herman gril dipl. ekon. vodja sluzbe za nabavo medicinske opreme potrosnega materiala in storitev", "ner": [{"TenderPerson": "bostjan gajsek"}, {"TenderTel": "031 203"}, {"TenderPerson": "matej vidmar"}, {"TenderTel": "030 464 787"}, {"TenderNumber": "408"}, {"TenderYear": "2022"}, {"TenderDeadline": "24.06.2022"}, {"TenderPerson": "vanja herman gril"}], "ner_refine": []}
{"id": "2022_EN_X_220_TENDER", "chunk_id": "0", "input_tokens": 2164, "refiner_input_tokens": 0, "total_output_tokens": 210, "text": "splosna bolnisnica celje oblakova ulica 5 3000 celje tel (03) 42 33 000 fax (03) 42 33 757 postopek 220 2022 da/vh povabilo k oddaji ponudbe narocnik vabi ponudnike da v skladu z navodili ponudnikom izdelajo ponudbo za vzdrzevanje ups sistemov v sb celje za obdobje enega leta splosne zahteve osnova za realizacijo dobave je prejem pisnega narocila strani narocnika. ponudbe zbiramo informativno za predlozitev v presojo odobritve. v kolikor bomo prejeli odobritev s strani pristojnih bomo realizacijo izvedli pri najugodnejsemu ponudniku ki bo izpolnjeval tehnicne zahteve. cena mora vsebovati vse stroske popuste rabate dostavo montazo in davek na dodano vrednost. ponudbi predlozite prospekte ter drugo dokumentacijo iz katere je razvidno izpolnjevanje zahtev narocnika. rok za placilo je 60 dni od prejema racuna. merilo izbora najnizja vrednost ponudbe v eur z ddv ob izpolnjevanju tehnicnih zahtev narocnika. kontaktna oseba s strani narocnika ; dusan antlej. tel.st.041 605 675 elektronska posta dusan.antlej(4 sb celje.si ponudbe posljite na naslov elektronske poste nabaval(4sb celje.si z oznako 220 2022 vzdrzevanje ups sistemov v sb celje za obdobje enega leta do najkasneje 19.04.2022 do 12 ure. vanja herman gril dipl. ekon. vodja sluzbe za nabavo medicinske opreme potrosnega materiala in storitev splosna bolnisnica celje oblakova ulica 5 ci... splosna bolnisnica celje 3000 celje re id za ddv si42119022 celje 8.4.2021 zadeva povabilo za oddajo ponudbe za redno vzdrzevanje brezprekinitvenega napajanja ups in sicer 1. sklop redno vzdrzevanje ups naprav za obdobje (1) enega leta zajema ciscenje modulov ups sistema mehanicni pregled vseh komponent in povezav med posameznimi moduli znotraj ups a in pripadajocimi napravami analiza alarmnih zapisov in parametrov (autonomy charging current flt voltage ...) preko servisnega programa analiza in meritve referencnih signalov (t2 signal oscilator load sharing ...) preko servisnega programa preverjanje in nastavitev enosmerne napetosti preverjanje in nastavitev izhodne napetosti razsmernika preverjanje in nastavitev frekvence oscilatorja kontrola delovanje zascite proti povratnemu toku (back feed protection) preverjanje in nastavitev elektronske regulacije kontrolnih in alarmnih sklopov usmernika in razsmernika kontrola delovanja usmernika testiranje zmogljivosti baterijskih setov (bremenski test vseh baterij) kontrola stanja baterij v rezimu praznjenja in polnjenja kompleten funkcionalni test vkljucno s simulacijo izpada omrezne napetosti z bremeni prikljucenimi na ups sistem izdelava porocil o delovanju ups sistema seznam ups naprav 1. psc 33 30 kva", "ner": [{"TenderOrg": "splosna bolnisnica celje"}, {"TenderTel": "(03) 42 33 000"}, {"TenderFax": "(03) 42 33 757"}, {"TenderNumber": "220"}, {"TenderYear": "2022"}, {"TenderCode": "da/vh"}, {"TenderPerson": "dusan antlej"}, {"TenderDeadline": "19.04.2022"}, {"TenderPerson": "vanja herman gril"}, {"TenderType": "x"}], "ner_refine": []}
{"id": "2022_EN_X_220_TENDER", "chunk_id": "1", "input_tokens": 2138, "refiner_input_tokens": 0, "total_output_tokens": 41, "text": "st.3 eit.int 5 samurai patologija 6. 7. pv 31 pv 31 bobri leonardo masterys 20p 10 kva 6kva op 4/laboratorij gama kamera ct mr kronograf poliklinika/informatika masterys 20p poliklinika/informatika 12. green pover 2.0 40kkva poliklinika/informatika 13. galaxy pw 40 40kva travmatoloski oddelek 14. extreme iikva operacijska uroloska 15. samurai 20kva ucc nova urgenca (komunikacija) 16. delphys 160kva ucc nova urgenca (it sistem) 17. masterys iskkva stara plastika (sistem prostor) upsi 18. masterys iskva stara plastika (sistem prostor) ups2 19. green pover 2.0 | 1okva mr novi 20. e.t.n. 93 ps 15 iskva angiograf |.nadstropje samurai 1okva angiograf stari eaton 15kva rtg aparat novi 3.) sklop dobava in zamenjava baterij akumulatorjev za ups sisteme baterija 12v 9ah svincena (kot je ultracell ul9 12) 180 kosov baterija 12 v 40ah svincena (kot je ultracell ul40 12) 40 kosov baterija 12 v 26ah svincena (kot je ultracell ul26 12) 50 kosov baterija 12v 75ah svincena (kot je ultracell ul75 12) 50 kosov sklop dobava in montaza novih ups sistemov z vgrajenimi ustrezni baterijskimi seti (avtonomija baterij |5min pri polni obremenitvi) dobava montaza in zagon ups sistema 20kva (po tehnicnih specifikacijah) | kos tehnicne specifikacije ups nazivna napetost 380/400/415 v ac (3 ph +n + pe) igbt tehnologija dsp tehnologija epo izklop v sili on line dvojna konverzija vhodni faktor moci <0.99 izhodni faktor moci 1.0 korekcija faktorja moci avtonomija baterij pri 100% obremenitve vsaj 15min cas preklopa omrezje baterija 0 ms; omrezje bypass 0 ms zascita prenapetost kratek stik globoko praznjenje toplotna zascita izhod je lahko fazno nesimetricno obremenjen komunikacijska vrata usb/rs485/parallel port/dry contact moznost nadzora spremljanja ups naprave preko obstojecega sistema cns (modbus tcp in ustrezna dokumentacija) sklop intervencijsko vzdrzevanje intervencijsko vzdrzevanje naj zajema 48 intervencijskih ur prevozni stroski intervencija (10 krat prevoz). ponudbena cena redno vzdrzevanje cena brez ddv cena z ddv cena brez ddv cena z ddv intervencijsko vzdrzevanje (48 ur) prevoz (10 krat) cena brez ddv cena z ddv skupna ponujena cena redno vzdrzevanje baterije ups i intervencijsko vzdrzevanje cena brez ddv cena z ddv narocnik bo z izvajalcem sklenil pogodbo za obdobje enega (|) leta. lep pozdrav antlej d usan", "ner": [{"TenderPerson": "antlej d usan"}], "ner_refine": []}
{"id": "2022_EN_X_106_TENDER", "chunk_id": "0", "input_tokens": 2094, "refiner_input_tokens": 0, "total_output_tokens": 151, "text": "splosna bolnisnica celje oblakova ulica 5 3000 celje tel (03) 42 33 000 fax (03) 42 33 757 postopek 106 2022 id/vh povabilo k oddaji ponudbe narocnik vabi ponudnike da v skladu z navodili ponudnikom izdelajo ponudbo za izredni servis termodezinfektor za cokle miel (m02) naziv termodezinfektor za cokle miel model sn cd47882 inventarna stevilka 00534067 leto dobave 2015 na termodezinfektorju je odlomljen gumb za nastavitev programa. obvezne priloge 1. v letu 2022 veljavna pisna pooblastila proizvajalcev s katerim pooblascajo zgoraj navedeni servis za servisiranje opreme in dobavo rezervnih delov. 2. izjava dana pod kazensko in materialno odgovornostjo z navedbo imen in priimkov serviserjev (pooblasceni servis mora imeti na razpolago vsaj enega serviserja) ki je usposobljen za vzdrzevanje ponujene opreme. serviserji morajo ze v casu oddaje ponudbe imeti s pooblascenim servisom sklenjeno pogodbo o zaposlitvi ali civilnopravno pogodbo o delu ali kaksno drugo civilnopravno pogodbo o sodelovanju v izjavi je potrebno navesti obliko sklenjene pogodbe in cas trajanja te pogodbe. v primeru da gre za redno zaposlenega serviserja pri pooblascenem servisu je potrebno priloziti obrazce m 1/m 2 (prijava odjava iz pokojninskega in invalidskega zavarovanja) ki dokazuje sklenjeno pogodbo o zaposlitvi. 3. certifikati o usposobljenosti za brezhibno vzdrzevanje referencne opreme izdane s strani ucnega servisnega centra proizvajalca ki so jih pridobili navedeni serviserji v izjavi iz druge tocke. pojem referencna oprema si bo narocnik tolmacil iz vidika potrebnega pridobljenega strokovnega znanja usposobljenih oseb za vzdrzevanje opreme ki je primerljiva ponujeni opremi. certifikat ne sme biti starejsi od 24 mesecev (leto izdaje najkasneje 2020). splosne zahteve osnova za realizacijo dobave je prejem pisnega narocila strani narocnika. ponudbe zbiramo informativno za predlozitev v presojo odobritve. v kolikor bomo prejeli odobritev s strani pristojnih bomo realizacijo izvedli pri najugodnejsemu ponudniku ki bo izpolnjeval tehnicne zahteve. cena mora vsebovati vse stroske popuste rabate dostavo montazo in davek na dodano vrednost. ponudbi predlozite prospekte ter drugo dokumentacijo iz katere je razvidno izpolnjevanje zahtev narocnika. rok za placilo je 60 dni od prejema racuna. merilo izbora najnizja vrednost ponudbe v eur z ddv ob izpolnjevanju tehnicnih zahtev narocnika.", "ner": [{"TenderOrg": "splosna bolnisnica celje"}, {"TenderTel": "(03) 42 33 000"}, {"TenderFax": "(03) 42 33 757"}, {"TenderNumber": "106"}, {"TenderYear": "2022"}, {"TenderCode": "id/vh"}, {"TenderType": "x"}], "ner_refine": []}
{"id": "2022_EN_X_106_TENDER", "chunk_id": "1", "input_tokens": 1772, "refiner_input_tokens": 0, "total_output_tokens": 168, "text": "4. izvajalec je narocniku po preventivnem in kurativnem vzdrzevalnem posegu na opremi dolzan podati porocilo v obliki delovnega naloga z natancnim opisom izvedenih storitev in o eventualni zamenjavi delov/materiala in sicer stevilo opravljenih ur (redne izredne) naziv aparata inventarna stevilka opreme oziroma aparata serijska stevilka aparata oddelek narocnika (nahajalisce aparata) kolicina in vrsta vgrajenega materiala oz. rezervnih delov cena vgrajenega materiala oz. rezervnih delov velja za popravila ki niso vkljucena v all inclusive vzdrzevanje dolzino garancijskega obdobja za vgrajene rezervne/nadomestne dele/materiala da je aparat brezhiben in varen za uporabo. 5. racun za opravljeno storitev mora vsebovati naziv opreme serijska stevilka inventarna stevilka stevilko narocilnice ter kot prilogo porocilo v obliki delovnega naloga z natancnim opisom izvedenih. racuni ki ne bodo imeli izkazanega protokola narocila in potrjevanja po tem clenu bodo zavrnjena. kontaktna oseba s strani narocnika ; ivan drobez. tel.st. 03 423 32 04 faks st. 03 423 37 56 elektronska posta ivan.drobez sb celje.si ponudbe posljite na naslov elektronske poste | nabava1 sb celje.si | z oznako 106 2022 izredni servis termodezinfektorja za sokle | | miel do najkasneje 24.02.2022 do 12 ure. vanja herman gril dipl. ekon. vodja sluzbe za nabavo medicinske opreme potrosnega materiala in storitev", "ner": [{"TenderTel": "03 423 32 04"}, {"TenderFax": "03 423 37 56"}, {"TenderPerson": "ivan drobez"}, {"TenderNumber": "106"}, {"TenderYear": "2022"}, {"TenderDeadline": "24.02.2022"}, {"TenderPerson": "vanja herman gril"}], "ner_refine": []}
{"id": "2022_EN_X_435_TENDER", "chunk_id": "0", "input_tokens": 2089, "refiner_input_tokens": 0, "total_output_tokens": 151, "text": "c( splosna bolnisnica celje oblakova ulica 5 3000 celje tel (03) 42 33 000 fax (03) 42 33 757 postopek 435 2022 bg/vh povabilo k oddaji ponudbe narocnik vabi ponudnike da v skladu z navodili ponudnikom izdelajo ponudbo za kalibracija data logerjev (m03) 661999 661994 733551 733578 633856 577573 transfuzijskem centru (2815) primer data logerja obvezne priloge 1. v letu 2022 veljavna pisna pooblastila proizvajalcev s katerim pooblascajo zgoraj navedeni servis za servisiranje opreme in dobavo rezervnih delov. 2. izjava dana pod kazensko in materialno odgovornostjo z navedbo imen in priimkov serviserjev (pooblasceni servis mora imeti na razpolago vsaj enega serviserja) ki je usposobljen za vzdrzevanje ponujene opreme. serviserji morajo ze v casu oddaje ponudbe imeti s pooblascenim servisom sklenjeno pogodbo o zaposlitvi ali civilnopravno pogodbo o delu ali kaksno drugo civilnopravno pogodbo o sodelovanju v izjavi je potrebno navesti obliko sklenjene pogodbe in cas trajanja te pogodbe. v primeru da gre za redno zaposlenega serviserja pri pooblascenem servisu je potrebno priloziti obrazce m 1/m 2 (prijava odjava iz pokojninskega in invalidskega zavarovanja) ki dokazuje sklenjeno pogodbo o zaposlitvi. 3. certifikati o usposobljenosti za brezhibno vzdrzevanje referencne opreme izdane s strani ucnega servisnega centra proizvajalca ki so jih pridobili navedeni serviserji v izjavi iz druge tocke. pojem referencna oprema si bo narocnik tolmacil iz vidika potrebnega pridobljenega strokovnega znanja usposobljenih oseb za vzdrzevanje opreme ki je primerljiva ponujeni opremi. certifikat ne sme biti starejsi od 24 mesecev (leto izdaje najkasneje 2020). splosne zahteve osnova za realizacijo dobave je prejem pisnega narocila strani narocnika. ponudbe zbiramo informativno za predlozitev v presojo odobritve. v kolikor bomo prejeli odobritev s strani pristojnih bomo realizacijo izvedli pri najugodnejsemu ponudniku ki bo izpolnjeval tehnicne zahteve. cena mora vsebovati vse stroske popuste rabate dostavo montazo in davek na dodano vrednost. ponudbi predlozite prospekte ter drugo dokumentacijo iz katere je razvidno izpolnjevanje zahtev narocnika. rok za placilo je 60 dni od prejema racuna. merilo izbora najnizja vrednost ponudbe v eur z ddv ob izpolnjevanju tehnicnih zahtev narocnika.", "ner": [{"TenderOrg": "splosna bolnisnica celje"}, {"TenderTel": "(03) 42 33 000"}, {"TenderFax": "(03) 42 33 757"}, {"TenderNumber": "435"}, {"TenderYear": "2022"}, {"TenderCode": "bg/vh"}, {"TenderType": "x"}], "ner_refine": []}
{"id": "2022_EN_X_658_TENDER", "chunk_id": "1", "input_tokens": 1749, "refiner_input_tokens": 0, "total_output_tokens": 143, "text": "4. izvajalec je narocniku po preventivnem in kurativnem vzdrzevalnem posegu na opremi dolz ino an podati porocilo v obliki delovnega naloga z natancnim opisom izvedenih storitev eventualni zamenjavi delov/materiala in sicer stevilo opravljenih ur (redne izredne) naziv aparata inventarna stevilka opreme oziroma aparata serijska stevilka aparata oddelek narocnika (nahajalisce aparata) kolicina in vrsta vgrajenega materiala oz. rezervnih delov cena vgrajenega materiala oz. rezervnih delov velja za popravila ki niso vkljucena v all inclusive vzdrzevanje dolzino garancijskega obdobja za vgrajene rezervne/nadomestne dele/materiala da je aparat brezhiben in varen za uporabo. 5. racun za opravljeno storitev mora vsebovati ter rac naziv opreme serijska stevilka inventarna stevilka stevilko narocilnice kot prilogo porocilo v obliki delovnega naloga z natancnim opisom izvedenih del. uni ki ne bodo imeli izkazanega protokola narocila in potrjevanja po tem clenu bodo zavrnjena. kontaktna oseba s strani narocnika; matej sinko tel. st. 041 245 823 elektronska posta matej.sinko csb celje.si ponudbe posljite na naslov elektronske poste nabaval(csb celje.si z oznako 658 2022 popravilo termodezinfektorja (m02) 10.11.2022. do 12 ure. van ja herman gril mag. manag. vodja sluzbe za nabavo medicinske opreme potrosnega materiala in storitev", "ner": [{"TenderPerson": "matej sinko"}, {"TenderTel": "041 245 823"}, {"TenderNumber": "658"}, {"TenderYear": "2022"}, {"TenderDeadline": "10.11.2022"}, {"TenderPerson": "van ja herman gril"}], "ner_refine": []}
{"id": "2022_EN_M_459_TENDER", "chunk_id": "0", "input_tokens": 2080, "refiner_input_tokens": 0, "total_output_tokens": 246, "text": "3 narocnik splosna bolnisnica celje oblakova ulica 5 3000 celje tel (03) 42 33 000 fax (03) 42 33 757 postopek 459 2022 sp/vh povabilo k oddaji ponudbe narocnik vabi ponudnike da v skladu z navodili ponudnikom za izdelavo ponudbe za pulzni oksimeter za novorojence 1 kom splosne zahteve osnova za realizacijo dobave je prejem pisnega narocila strani narocnika. ponudbe zbiramo informativno za predlozitev v presojo odobritve. v kolikor bomo prejeli odobritev s strani pristojnih bomo realizacijo izvedli pri najugodnejsemu ponudniku ki bo izpolnjeval tehnicne zahteve. cena mora vsebovati vse stroske popuste rabate dostavo montazo in davek na dodano vrednost. ponudbi predlozite prospekte ter drugo dokumentacijo iz katere je razvidno izpolnjevanje tehnicnih zahtev. rok za placilo je 60 dni od prejema racuna. merilo za izbora najnizja vrednost ponudbe v eur z ddv ob izpolnjevanju tehnicnih zahtev narocnika. dodatne zahteve na medicinski opremi mora biti obvezno prilepljena proizvajalceva nalepka ki mora izkazovati vsaj naslednje podatke ime in tip naprave oznake ce serijska stevilka naprave datum proizvodnje (leto mesec dan) ime proizvajalca drzava proizvajalca na aparatu mora biti obvezno tudi nalepka ki oznacuje termin naslednjega potrebnega preventivnega servisa. letnik proizvodnje obvezno tekoce leto. kontaktna oseba s strani narocnika ; stanislava pahole dipl.ekon. tel.st. 03 423 36 84 faks st. 03 423 37 56 elektronska posta stanislava.pahole sb celje.si. ponudbe posljite na naslov elektronske poste nabava1 sb celje.si z oznako pulzni oksimeter 459 2022 do najkasneje 18.07.2022 do 12 ure. priloga obrazec predracuna (obr 2) izjavna o izpolnjevanju tehnicne specifikacije opreme (obr 3) izjava o zastopstvu (obr 4) obveznost izbranega ponudnika obrazec predracuna obr 2 ponudnik predmet pulzni oksimeter predracun opis proizvajalec (1) model oz. kataloska stevilka (2) kolicina (3) vrednost brez ddv (4) 1 pulzni oksimeter 1 kom cena za kom v eur brez ddv skupaj vrednost v eur z ddv datum zig in podpis ponudnik priloga predracuna obr 2 preglednica originalnih rezervnih delov ki se najveckrat uporabljajo v casu vzdrzevanja in originalnega potrosnega materiala potrebnega pri delovanju medicinskih aparatov in tehnoloske opreme (npr.senzorji kabli...) zap.st. (1)", "ner": [{"TenderOrg": "splosna bolnisnica celje"}, {"TenderTel": "(03) 42 33 000"}, {"TenderFax": "(03) 42 33 757"}, {"TenderNumber": "459"}, {"TenderYear": "2022"}, {"TenderCode": "sp/vh"}, {"TenderTel": "03 423 36 84"}, {"TenderFax": "03 423 37 56"}, {"TenderPerson": "stanislava pahole"}, {"TenderDeadline": "18.07.2022"}, {"TenderType": "m"}], "ner_refine": []}
{"id": "2022_EN_M_459_TENDER", "chunk_id": "1", "input_tokens": 2220, "refiner_input_tokens": 0, "total_output_tokens": 41, "text": "kot proizvajalec (2) artikel (3) opis (4) em (5) cena v eur brez ddv (7) stopnja ddv v % (8) naziv aparata model veza (9) vnesite ustrezno material za veckratno uporabo material za enkratno oporabo (10) v kolikor proizvajalec na opremi dopusca uporabo materiala drugega proizvajalca vnesite artikel stevilko opis materiala ter naziv proizvajalca (11) pogodbeni partner (12) 1. ponudbi je potrebno predloziti originalne prospekte proizvajalca ter ostalo originalno dokumentacijo proizvajalca iz katere je razviden ponujen potrosni material ki je predmet ponudbe. izpolnjevanje vseh zahtev iz opisa predmeta narocila mora biti razvidno iz originalnih prospektov proizvajalca ter ostale originalne dokumentacije proizvajalca ponudnik je slednje dolzan ustrezno oznaciti podcrtati in navesti ustrezno zap.st. ki izhaja iz obr 5/2a. 2. navodilo za izpolnjevanje v vrstice stolpca (1) vpisete artikel (2) vpisete opis naziv artikla (3) cena/enoto brez ddv (4) vrednost v eur brez ddv (5) vnesete stopnjo (v %) ddv (6) vnesite vrednost v eur z ddv 3. v obr vnesite potrebno stevilo dodatnih vrstic za vnos vseh artiklov potrebnih za delovanje aparata iz obr 2 datum zig in podpis ponudnika obr 3 izjava o izpolnjevanju tehnicne specifikacije opreme ponudnik pod kazensko in materialno odgovornostjo izjavljamo da izpolnjujemo tehnicne zahteve navedene v tem dokumentu da bomo ponudbi predlozili originalne prospekte proizvajalca ter ostalo originalno dokumentacijo proizvajalca iz katere je razvidna oprema ki je predmet ponudbe da bo izpolnjevanje vseh zahtev iz opisa predmeta narocila mora biti razvidno iz originalnih prospektov proizvajalca ter ostale originalne dokumentacije proizvajalca slednje bomo ustrezno oznacili podcrtali in navedli ustrezno zap.st. ki izhaja iz opisa predmeta narocila pulzni oksimeter v skladu z naslednjimi tehnicnimi zahtevami opomba 1. barvni tft zaslon 2. prikaz vrednosti spo2 srcne frekvence pi(perfuzijski index) prikaz pletizmograma 3. zvocni in vizualni alarmi 4. indikator stanja baterije 5. delovanje aa baterije (najvec tri) za vsaj 36 ur delovanja (prilozne) 6. vsaj 72 ur shranjevanja podatkov 7. primeren za novorojencke (ponujeni naprstni senzor za novorojencke) 8. omogoca uporabo senzorjev za veckratno uporabo ter enkratno uporabo za novorojencke 9. natancnost spo2 2% pri 70 100% 10. ustreza standardu iec 60601 1 1 4th kraj in datum zig in podpis ponudnika obr 4 izjava o zastopstvu ponudnik obvezne priloge v letu 2022 veljavno izjava o zastopstvu lastne blagovne znamke oz. izjava proizvajalca o pooblastilu zastopanja za prodajo tovrstnih aparatov. izjava mora biti potrjena z zigom ter podpisom proizvajalca. v letu 2022 veljavno izjava o zastopstvu lastne blagovne znamke oz. izjava proizvajalca o pooblastilu zastopanja za prodajo originalnega potrosnega materiala potrebnega za delovanje aparatov.", "ner": [], "ner_refine": []}
{"id": "2022_EN_M_303_TENDER", "chunk_id": "0", "input_tokens": 2232, "refiner_input_tokens": 0, "total_output_tokens": 246, "text": "3 narocnik splosna bolnisnica celje oblakova ulica 5 3000 celje tel (03) 42 33 000 fax (03) 42 33 757 postopek 303 2022 sp/vh povabilo k oddaji ponudbe narocnik vabi ponudnike da v skladu z navodili ponudnikom za izdelavo ponudbe za tehtnica za dojencke 1 kom splosne zahteve osnova za realizacijo dobave je prejem pisnega narocila strani narocnika. ponudbe zbiramo informativno za predlozitev v presojo odobritve. v kolikor bomo prejeli odobritev s strani pristojnih bomo realizacijo izvedli pri najugodnejsemu ponudniku ki bo izpolnjeval tehnicne zahteve. cena mora vsebovati vse stroske popuste rabate dostavo montazo in davek na dodano vrednost. ponudbi predlozite prospekte ter drugo dokumentacijo iz katere je razvidno izpolnjevanje tehnicnih zahtev. rok za placilo je 60 dni od prejema racuna. merilo za izbora najnizja vrednost ponudbe v eur z ddv ob izpolnjevanju tehnicnih zahtev narocnika. kontaktna oseba s strani narocnika ; stanislava pahole dipl.ekon. tel.st. 03 423 36 84 faks st. 03 423 37 56 elektronska posta stanislava.pahole sb celje.si ponudbe posljite na naslov elektronske poste nabava1 sb celje.si z oznako tehtnica za dojencke 303 2022 do najkasneje 25.05.2022 do 12 ure. priloga obrazec predracuna (obr 2) izjavna o izpolnjevanju tehnicne specifikacije opreme (obr 4) obrazec predracuna obr 2 ponudnik predmet tehtnica za dojencke predracun opis proizvajalec (1) model oz. kataloska stevilka (2) kolicina (3) vrednost brez ddv (4) 1. tehtnica za dojencke 1 kom vrednost opreme v eur brez ddv (1) znesek davka za opremo skupaj vrednost v eur z ddv datum zig in podpis ponudnika sestavni del in priloga ponudbe . obr 4 izjava o izpolnjevanju tehnicne specifikacije opreme ponudnik pod kazensko in materialno odgovornostjo izjavljamo da izpolnjujemo tehnicne zahteve navedene v tem dokumenta ter obr 4 da bomo ponudbi predlozili originalne prospekte proizvajalca ter ostalo originalno dokumentacijo proizvajalca iz katere je razvidna oprema ki je predmet ponudbe da bo izpolnjevanje vseh zahtev iz opisa predmeta narocila mora biti razvidno iz originalnih prospektov proizvajalca ter ostale originalne dokumentacije proizvajalca slednje bomo ustrezno oznacili podcrtali in navedli ustrezno zap. st. ki izhaja iz opisa predmeta narocila otroska tehtnica v skladu z naslednjimi tehnicnimi zahtevami opomba natancnost 5g 7 5g<10g. baterijsko ali omrezno napajanje 220v funkcija tara/ hold / auto hold bmif (merjenje kolicine popite tekocine) overljiva tocnostni razred iii tehtnica odobrena za medicinske namene (m) lcd zaslon velik ergonomski pladenj za varno tehtanje nastavljivo blazenje zmogljivost tehtanja do 20 kg visinomer (smer merjenja horizontalna) kraj in datum zig in podpis ponudnika 10 postopek sp/vh", "ner": [{"TenderOrg": "splosna bolnisnica celje"}, {"TenderTel": "(03) 42 33 000"}, {"TenderFax": "(03) 42 33 757"}, {"TenderNumber": "303"}, {"TenderYear": "2022"}, {"TenderCode": "sp/vh"}, {"TenderDeadline": "25.05.2022"}, {"TenderPerson": "stanislava pahole"}, {"TenderTel": "03 423 36 84"}, {"TenderFax": "03 423 37 56"}, {"TenderType": "m"}], "ner_refine": []}
{"id": "2022_EN_M_589_TENDER", "chunk_id": "0", "input_tokens": 1831, "refiner_input_tokens": 0, "total_output_tokens": 227, "text": "oblakova ulica 5 3000 celje tel (03) 42 33 000 fax (03) 42 33 757 postopek 589 2021 sp/vh povabilo k oddaji ponudbe narocnik vabi ponudnike da v skladu z navodili ponudnikom za izdelavo ponudbe za ogrevalna lucka nad previjalnim pultom mobilna 1 kom splosne zahteve osnova za realizacijo dobave je prejem pisnega narocila strani narocnika. ponudbe zbiramo informativno za predlozitev v presojo odobritve. v kolikor bomo prejeli odobritev s strani pristojnih bomo realizacijo izvedli pri najugodnejsemu ponudniku ki bo izpolnjeval tehnicne zahteve. cena mora vsebovati vse stroske popuste rabate dostavo montazo in davek na dodano vrednost. rok za placilo je 30 dni od prejema racuna. izvajalec mora zagotoviti dostavo blaga ter montazo in namestitev v prostor pri narocniku termin montaze/primopredaje je potrebno uskladiti z narocnikom. obveznost dobavitelja je da bo zagotovil brezplacno oz. na lastne stroske potrebno izvedbo edukacije uporabnikov (normalni uporabniski nivo) s strani narocnika za pravilno ter varno uporabo opreme ter njeno nego. ponudbi predlozite prospekte ter drugo dokumentacijo iz katere je razvidno izpolnjevanje tehnicnih zahtev. kontaktna oseba s strani narocnika ; stanislava pahole hocevar dipl.ekon. tel.st. 03 423 30 84 faks st. 03 423 37 56 elektronska posta stanislava.pahole sb celje.si ponudbe posljite na naslov elektronske poste nabava1 sb celje.si z oznako 589 2022 ogrevalna lucka nad previjalnim pultom mobilna do najkasneje 06.10.2022 do 12 ure.", "ner": [{"TenderTel": "(03) 42 33 000"}, {"TenderFax": "(03) 42 33 757"}, {"TenderNumber": "589"}, {"TenderYear": "2021"}, {"TenderCode": "sp/vh"}, {"TenderPerson": "stanislava pahole hocevar"}, {"TenderTel": "03 423 30 84"}, {"TenderFax": "03 423 37 56"}, {"TenderDeadline": "06.10.2022"}, {"TenderType": "n"}], "ner_refine": []}
{"id": "2022_EN_M_589_TENDER", "chunk_id": "1", "input_tokens": 2181, "refiner_input_tokens": 0, "total_output_tokens": 41, "text": "priloga obrazec predracuna (obr 2) izjavna o izpolnjevanju tehnicne specifikacije opreme (obr 3) izjava o zastopstvu (obr 4) obveznost izbranega ponudnika obrazec predracuna obr 2 ponudnik predmet ogrevalna lucka nad previjalnim pultom mobilna predracun (oprema vzdrzevanje preventivni pregledi opreme za obdobje 7 let ) opis proizvajalec (1) model oz. kataloska stevilka (2) v kolikor proizvajalec na opremi dopusca uporabo aparata drugega proizvajalca vnesite artikel stevilko opis material ter naziv proizvajalca oz oznacite da dopusca kolicina (3) vrednost brez ddv (4) 1.ogrevalna lucka nad previjalnim pultom mobilna 1 kom 2.vrednost preventivnega vzdrzevanje ter redni letni pregled opreme za obdobje 7 let vrednost opreme v eur brez ddv(1) znesek ddv za opremo vrednost preventivnega vzdrzevanja redni letni pregledi opreme v eur brez ddv (3) znesek ddv v eur za preventivno vzdrzevanje redni letni pregled opreme skupaj vrednost v eur za 1+2 v eur z ddv datum zig in podpis ponudnik obr 4 izjava o izpolnjevanju tehnicne specifikacije opreme ponudnik pod kazensko in materialno odgovornostjo izjavljamo da izpolnjujemo tehnicne zahteve navedene v tem dokumentu da bomo ponudbi predlozili originalne prospekte proizvajalca ter ostalo originalno dokumentacijo proizvajalca iz katere je razvidna oprema ki je predmet ponudbe da bo izpolnjevanje vseh zahtev iz opisa predmeta narocila mora biti razvidno iz originalnih prospektov proizvajalca ter ostale originalne dokumentacije proizvajalca slednje bomo ustrezno oznacili podcrtali in navedli ustrezno zap.st. ki izhaja iz opisa predmeta narocila ogrevalna lucka nad previjalnim pultom mobilna v skladu z naslednjimi tehnicnimi zahtevami mobilna nastavljiva temperatura ogrevanja 25 38 c zavora na kolesih alarmi okvara napajanja okvara senzorja okvara sistema utisanje alarma nastavljiv alarm za odstopanje tempertaure vrtljiva glava grelca moznost ciscena z dezinfekcijskimi sredstvi kraj in datum zig in podpis ponudnika obr 4 izjava o zastopstvu ponudnik obvezne priloge v letu 2022 veljavno izjava o zastopstvu lastne blagovne znamke oz. izjava proizvajalca o pooblastilu zastopanja za prodajo tovrstnih aparatov. izjava mora biti potrjena z zigom ter podpisom proizvajalca. v letu 2022 veljavno izjava o zastopstvu lastne blagovne znamke oz. izjava proizvajalca o pooblastilu zastopanja za prodajo originalnega potrosnega materiala potrebnega za delovanje aparatov. izjava mora biti potrjena z zigom ter podpisom proizvajalca. v letu 2022 veljavna pisna pooblastila proizvajalcev ki so proizvedli ponujeno opremo s katerim pooblascajo zgoraj navedeni servis za servisiranje opreme in dobavo rezervnih delov. certifikate o usposobljenosti za brezhibno vzdrzevanje referencne opreme izdane s strani ucnega servisnega centra proizvajalca ki so jih pridobili navedeni serviserji v izjavi iz druge tocke.", "ner": [{"TenderYear": "2022"}, {"TenderType": "m"}], "ner_refine": []}
{"id": "2022_EN_M_667_TENDER", "chunk_id": "0", "input_tokens": 2170, "refiner_input_tokens": 0, "total_output_tokens": 237, "text": "oblakova ulica 5 3000 celje tel (03) 42 33 000 fax (03) 42 33 757 postopek 667 2022 sp/vh povabilo k oddaji ponudbe vabimo vas k oddaji ponudbe za predmet obposteljna servirna mizica 10 kom osnova za realizacijo dobave je prejem pisnega narocila strani narocnika. ponudbe zbiramo informativno za predlozitev v presojo odobritve. v kolikor bomo prejeli odobritev s strani pristojnih bomo realizacijo izvedli pri najugodnejsemu ponudniku ki bo izpolnjeval tehnicne zahteve. cena mora vsebovati vse stroske popuste rabate dostavo montazo in davek na dodano vrednost. rok za placilo je 30 dni od prejema racuna. izvajalec mora zagotoviti dostavo blaga ter montazo in namestitev v prostor pri narocniku. ponudbi predlozite prospekte ter drugo dokumentacijo iz katere je razvidno izpolnjevanje tehnicnih zahtev. kontaktna oseba s strani narocnika ; stanislava pahole hocevar dipl.ekon. tel.st. 03 423 36 84 stanislava.pahole sb celje.si ponudbe posljite na naslov elektronske poste nabava1 sb celje.si z oznako 667 2022 obposteljna servirna mizica do najkasneje 21.11.2022 do 12ure. priloga obrazec predracuna (obr 1) obveznost izbranega ponudnika (obr 2) vodja sluzbe za nabavo medicinske opreme potrosnega materiala in storitev vanja herman gril mag.manag. obrazec predracuna obr 1 ponudnik predmet obposteljna servirna mizica opis proizvajalec (1) model oz. kataloska stevilka (2) kolicina (3) vrednost brez ddv (4) 1. obposteljna servirna mizica 10 kom vrednost opreme v eur brez ddv (1) znesek davka za opremo skupaj vrednost v eur z ddv datum zig in podpis ponudnika obr 2 izjava o izpolnjevanju tehnicne specifikacije opreme ponudnik pod kazensko in materialno odgovornostjo izjavljamo da izpolnjujemo tehnicne zahteve navedene v tem dokumentu da bomo ponudbi predlozili originalne prospekte proizvajalca ter ostalo originalno dokumentacijo proizvajalca iz katere je razvidna oprema ki je predmet ponudbe da bo izpolnjevanje vseh zahtev iz opisa predmeta narocila mora biti razvidno iz originalnih prospektov proizvajalca ter ostale originalne dokumentacije proizvajalca slednje bomo ustrezno oznacili podcrtali in navedli ustrezno zap. st. ki izhaja iz opisa predmeta narocila obposteljna servirna mizica opomba stiri kolesa 50mm z blokado nastavljiva visina s pomocjo plinskega cilindra ogrodje kovinsko mizna ploskev omogoca spreminjanje lege oz. naklona mizna ploskev se mora zloziti kot na sliki mizna ploskev narejena iz abs plastike odporna na praske rahlo poglobljena dimenzije ploskve cca60x40x50/100 omogoceno enostavno ciscenje in dezinfekcija kraj in datum zig in podpis ponudnika", "ner": [{"TenderOrg": "sb celje.si"}, {"TenderTel": "(03) 42 33 000"}, {"TenderFax": "(03) 42 33 757"}, {"TenderNumber": "667"}, {"TenderYear": "2022"}, {"TenderCode": "sp/vh"}, {"TenderDeadline": "21.11.2022"}, {"TenderPerson": "stanislava pahole hocevar"}, {"TenderTel": "03 423 36 84"}, {"TenderPerson": "vanja herman gril"}, {"TenderType": "n"}], "ner_refine": []}
{"id": "2022_EN_M_389_TENDER", "chunk_id": "0", "input_tokens": 1823, "refiner_input_tokens": 0, "total_output_tokens": 228, "text": "oblakova ulica 5 3000 celje tel (03) 42 33 000 fax (03) 42 33 757 postopek 389 2022 kz/vh povabilo k oddaji ponudbe vabimo vas k oddaji ponudbe za predmet hassan trokar za odprti pristop topa konica premera 12mm dolzina 100mm. napredna intra&extra korporalna atraumatska stabilnost v steni z napihljivim balonom in stozcem iz gela za atraumatsko artikulacijo instrumentov. moznost odstranitve vseh membran za lazjo odstranitev tkiva. letna kolicina 10 kos sukcesivna dobava. osnova za realizacijo dobave je prejem pisnega narocila strani narocnika. ponudbe zbiramo informativno za predlozitev v presojo odobritve. v kolikor bomo prejeli odobritev s strani pristojnih bomo realizacijo izvedli pri najugodnejsemu ponudniku. cena mora vsebovati vse stroske popuste rabate in davek na dodano vrednost. izvajalec mora zagotoviti dostavo blaga v skladisce lekarne v delovnem casu za dostavo oz. prevzem blaga (od ponedeljka do petka od 6 00 do 14 ure). rok za placilo je 60 dni od prejema racuna. merilo za izbora najnizja vrednost ponudbe v eur z ddv ob izpolnjevanju tehnicnih zahtev narocnika. kontaktna oseba s strani narocnika ; klavdija zerjav tel. st. 03 423 31 25 elektronska posta klavdija.zerjav sb celje.si ponudbe posljite na naslov elektronske poste nabava1 sb celje.si z oznako 389 2022 hassan trokar do najkasneje 17.06.2022 do 13. ure. vodja sluzbe za nabavo medicinske opreme potrosnega materiala in storitev vanja herman gril dipl. ekon.", "ner": [{"TenderOrg": "sb celje.si", "TenderTel": "(03) 42 33 000"}, {"TenderFax": "(03) 42 33 757"}, {"TenderNumber": "389"}, {"TenderYear": "2022"}, {"TenderCode": "kz/vh"}, {"TenderPerson": "klavdija zerjav"}, {"TenderTel": "03 423 31 25"}, {"TenderDeadline": "17.06.2022"}, {"TenderPerson": "vanja herman gril"}, {"TenderType": "m"}], "ner_refine": []}
{"id": "2022_EN_M_683_TENDER", "chunk_id": "0", "input_tokens": 2105, "refiner_input_tokens": 0, "total_output_tokens": 156, "text": "oblakova ulica 5 3000 celje tel (03) 42 33 000 fax (03) 42 33 757 postopek 683 2022 bg/vh povabilo k oddaji ponudbe narocnik vabi ponudnike da v skladu z navodili ponudnikom izdelajo ponudbo za popravilo ultrazvoka potrebno je popravilo monitorja in linearne sonde la3 16ad. proizvajalec samsung tip 8hm70a inv.st. 00540159 serijska stevilka s0xfm3hja00025v leto nabave 2017 podatki o aparatu (anestezija prebujevalnica 2755). obvezne priloge 1. v letu 2022 veljavna pisna pooblastila proizvajalcev s katerim pooblascajo zgoraj navedeni servis za servisiranje opreme in dobavo rezervnih delov. 2. izjava dana pod kazensko in materialno odgovornostjo z navedbo imen in priimkov serviserjev (pooblasceni servis mora imeti na razpolago vsaj enega serviserja) ki je usposobljen za vzdrzevanje ponujene opreme. serviserji morajo ze v casu oddaje ponudbe imeti s pooblascenim servisom sklenjeno pogodbo o zaposlitvi ali civilnopravno pogodbo o delu ali kaksno drugo civilnopravno pogodbo o sodelovanju v izjavi je potrebno navesti obliko sklenjene pogodbe in cas trajanja te pogodbe. v primeru da gre za redno zaposlenega serviserja pri pooblascenem servisu je potrebno priloziti obrazce m 1/m 2 (prijava odjava iz pokojninskega in invalidskega zavarovanja) ki dokazuje sklenjeno pogodbo o zaposlitvi. 3. certifikati o usposobljenosti za brezhibno vzdrzevanje referencne opreme izdane s strani ucnega servisnega centra proizvajalca ki so jih pridobili navedeni serviserji v izjavi iz druge tocke. pojem referencna oprema si bo narocnik tolmacil iz vidika potrebnega pridobljenega strokovnega znanja usposobljenih oseb za vzdrzevanje opreme ki je primerljiva ponujeni opremi. certifikat ne sme biti starejsi od 24 mesecev (leto izdaje najkasneje 2020). splosne zahteve osnova za realizacijo dobave je prejem pisnega narocila strani narocnika. ponudbe zbiramo informativno za predlozitev v presojo odobritve. v kolikor bomo prejeli odobritev s strani pristojnih bomo realizacijo izvedli pri najugodnejsemu ponudniku ki bo izpolnjeval tehnicne zahteve. cena mora vsebovati vse stroske popuste rabate dostavo montazo in davek na dodano vrednost. ponudbi predlozite prospekte ter drugo dokumentacijo iz katere je razvidno izpolnjevanje zahtev narocnika. rok za placilo je 60 dni od prejema racuna. merilo izbora najnizja vrednost ponudbe v eur z ddv ob izpolnjevanju tehnicnih zahtev narocnika.", "ner": [{"TenderOrg": "oblakova ulica 5 3000 celje"}, {"TenderTel": "(03) 42 33 000"}, {"TenderFax": "(03) 42 33 757"}, {"TenderNumber": "683"}, {"TenderYear": "2022"}, {"TenderCode": "bg/vh"}, {"TenderType": "m"}], "ner_refine": []}
{"id": "2022_EN_M_683_TENDER", "chunk_id": "1", "input_tokens": 1778, "refiner_input_tokens": 0, "total_output_tokens": 202, "text": "4. izvajalec je narocniku po preventivnem in kurativnem vzdrzevalnem posegu na opremi dolzan podati porocilo v obliki delovnega naloga z natancnim opisom izvedenih storitev in o eventualni zamenjavi delov/materiala in sicer stevilo opravljenih ur (redne izredne) naziv aparata inventarna stevilka opreme oziroma aparata serijska stevilka aparata oddelek narocnika (nahajalisce aparata) kolicina in vrsta vgrajenega materiala oz. rezervnih delov cena vgrajenega materiala oz. rezervnih delov velja za popravila ki niso vkljucena v all inclusive vzdrzevanje dolzino garancijskega obdobja za vgrajene rezervne/nadomestne dele/materiala da je aparat brezhiben in varen za uporabo. 5. racun za opravljeno storitev mora vsebovati naziv opreme serijska stevilka inventarna stevilka stevilko narocilnice ter kot prilogo porocilo v obliki delovnega naloga z natancnim opisom izvedenih del. racuni ki ne bodo imeli izkazanega protokola narocila in potrjevanja po tem clenu bodo zavrnjena. kontaktna oseba s strani narocnika; bostjan gajsek tel. st. 030 203 011 elektronska posta bostjan.gajsek sb celje.si matej vidmar tel. st. 030 464 787 elektronska posta matej.vidmar sb celje.si ponudbe posljite na naslov elektronske poste nabava1 sb celje.si z oznako 683 2022 popravilo ultrazvoka 02.12.2022. do 12 ure. vanja herman gril mag. manag. vodja sluzbe za nabavo medicinske opreme potrosnega materiala in storitev", "ner": [{"TenderPerson": "bostjan gajsek"}, {"TenderTel": "030 203 011"}, {"TenderPerson": "matej vidmar"}, {"TenderTel": "030 464 787"}, {"TenderCode": "en"}, {"TenderNumber": "683"}, {"TenderYear": "2022"}, {"TenderDeadline": "02.12.2022"}, {"TenderPerson": "vanja herman gril"}], "ner_refine": []}
{"id": "2022_EN_M_594_TENDER", "chunk_id": "0", "input_tokens": 1900, "refiner_input_tokens": 0, "total_output_tokens": 246, "text": "2 narocnik splosna bolnisnica celje oblakova ulica 5 3000 celje tel (03) 42 33 000 fax (03) 42 33 757 postopek 594 2022 sp/vh povabilo k oddaji ponudbe narocnik vabi ponudnike da v skladu z navodili ponudnikom za izdelavo ponudbe za pripomocek za premescanje pacientov 1 kom splosne zahteve osnova za realizacijo dobave je prejem pisnega narocila strani narocnika. ponudbe zbiramo informativno za predlozitev v presojo odobritve. v kolikor bomo prejeli odobritev s strani pristojnih bomo realizacijo izvedli pri najugodnejsemu ponudniku ki bo izpolnjeval tehnicne zahteve. cena mora vsebovati vse stroske popuste rabate dostavo montazo in davek na dodano vrednost. rok za placilo je 30 dni od prejema racuna. ponudbi predlozite prospekte ter drugo dokumentacijo iz katere je razvidno izpolnjevanje tehnicnih zahtev. kontaktna oseba s strani narocnika ; stanislava pahole dipl.ekon. tel.st. 03 423 30 78 faks st. 03 423 37 56 elektronska posta stanislava.pahole sb celje.si. ponudbe posljite na naslov elektronske poste nabava1 sb celje.si z oznako pripomocek za premescanje pacientov 594 2022 do najkasneje 12.10.2022 do 12 ure. tehnicne specifikacije opreme ponudnik pripomocek za premescanje pacientov v skladu z naslednjimi tehnicnimi zahtevami opomba dolzina 91 x sirina 50 jedro iz ultra lahke pene antibakterijska prevleka negorljiv material vogalniki morajo biti zasciteni za samo nosilnost ter preprecevanje odrgnin pri premescanju nosila za lazjo hrambo omogocati mora ciscenje s sredstvi za dezinfekcijo nosilnost vsaj 180 kg ob ponudbi predlozite tudi prospekt iz katerega je razviden nuden artikel (opis artikla slika). datum zig in podpis ponudnika 10 postopek sp/vh", "ner": [{"TenderOrg": "splosna bolnisnica celje"}, {"TenderTel": "(03) 42 33 000"}, {"TenderFax": "(03) 42 33 757"}, {"TenderNumber": "594"}, {"TenderYear": "2022"}, {"TenderCode": "sp/vh"}, {"TenderPerson": "stanislava pahole"}, {"TenderTel": "03 423 30 78"}, {"TenderFax": "03 423 37 56"}, {"TenderDeadline": "12.10.2022"}, {"TenderType": "m"}], "ner_refine": []}
{"id": "2022_EN_M_105_TENDER", "chunk_id": "0", "input_tokens": 2221, "refiner_input_tokens": 0, "total_output_tokens": 246, "text": "6 narocnik splosna bolnisnica celje oblakova ulica 5 3000 celje tel (03) 42 33 000 fax (03) 42 33 757 postopek 105 2022 mv/vh povabilo k oddaji ponudbe narocnik vabi ponudnike da v skladu z navodili ponudnikom za izdelavo ponudbe za hladilnik za zdravila splosne zahteve osnova za realizacijo dobave je prejem pisnega narocila strani narocnika. ponudbe zbiramo informativno za predlozitev v presojo odobritve. v kolikor bomo prejeli odobritev s strani pristojnih bomo realizacijo izvedli pri najugodnejsemu ponudniku ki bo izpolnjeval tehnicne zahteve. cena mora vsebovati vse stroske popuste rabate dostavo montazo in davek na dodano vrednost. izvajalec mora zagotoviti dostavo blaga ter montazo in namestitev v prostor pri narocniku termin montaze/primopredaje je potrebno uskladiti z narocnikom. obveznost dobavitelja je da bo zagotovil brezplacno oz. na lastne stroske potrebno izvedbo edukacije uporabnikov (normalni uporabniski nivo) s strani narocnika za pravilno ter varno uporabo opreme ter njeno nego. ponudbi predlozite prospekte ter drugo dokumentacijo iz katere je razvidno izpolnjevanje tehnicnih zahtev. dodatne zahteve na medicinski opremi mora biti obvezno prilepljena proizvajalceva nalepka ki mora izkazovati vsaj naslednje podatke ime in tip naprave oznake ce serijska stevilka naprave datum proizvodnje (leto mesec dan) ime proizvajalca drzava proizvajalca na aparatu mora biti obvezno tudi nalepka ki oznacuje termin naslednjega potrebnega preventivnega servisa. kontaktna oseba s strani narocnika ; marusa vodenik dipl.ekon. tel.st. 03 423 31 47 faks st. 03 423 37 56 elektronska posta marusa.vodenik sb celje.si. ponudbe posljite na naslov elektronske poste nabava1 sb celje.si z oznako hladilnik za zdravila 105 2022 do najkasneje 25.02.2022 do 12 ure. priloga obrazec predracuna (obr 2) izjava o zastopstvu (obr 3) izjavna o izpolnjevanju tehnicne specifikacije opreme (obr 4) obveznost izbranega ponudnika obrazec predracuna obr 2 ponudnik predmet hladilnik za zdravila predracun (oprema vzdrzevanje preventivni pregledi opreme za obdobje 7 let ) opis proizvajalec (1) model oz. kataloska stevilka (2) kolicina (3) vrednost brez ddv (4) 1. hladilnik za zdravila 1 kom 2. vrednost kompletnega vzdrzevanja za obdobje 7 let (vrednost mora vkljucevati letne kalibracije meritve nastavitve overitve ves potrosni material ter drug potreben material kakor tudi stroske dela potne stroske dnevnice kilometrine in druge morebitne stroske potrebne za izvedbo potrebnega vzdrzevanja opreme.) cena v eur brez ddv (1) znesek davka za opremo vrednost kompletnega vzdrzevanja in redni letni pregled za obdobje 7 let v eur brez ddv (2) znesek davka v eur za kompletno vzdrzevanje ter redni letni pregled opreme skupaj vrednost v eur z ddv (1+2)", "ner": [{"TenderOrg": "splosna bolnisnica celje"}, {"TenderTel": "(03) 42 33 000"}, {"TenderFax": "(03) 42 33 757"}, {"TenderNumber": "105"}, {"TenderYear": "2022"}, {"TenderCode": "mv/vh"}, {"TenderPerson": "marusa vodenik"}, {"TenderTel": "03 423 31 47"}, {"TenderFax": "03 423 37 56"}, {"TenderDeadline": "25.02.2022"}, {"TenderType": "m"}], "ner_refine": []}
{"id": "2022_EN_M_105_TENDER", "chunk_id": "1", "input_tokens": 2152, "refiner_input_tokens": 0, "total_output_tokens": 41, "text": "datum zig in podpis ponudnika sestavni del in priloga ponudbe . obr 3 izjava o zastopstvu ponudnik obvezne priloge v letu 2022 veljavno izjava o zastopstvu lastne blagovne znamke oz. izjava proizvajalca o pooblastilu zastopanja za prodajo tovrstnih aparatov. izjava mora biti potrjena z zigom ter podpisom proizvajalca. v letu 2022 veljavno izjava o zastopstvu lastne blagovne znamke oz. izjava proizvajalca o pooblastilu zastopanja za prodajo originalnega potrosnega materiala potrebnega za delovanje aparatov. izjava mora biti potrjena z zigom ter podpisom proizvajalca. v letu 2022 veljavna pisna pooblastila proizvajalcev ki so proizvedli ponujeno opremo s katerim pooblascajo zgoraj navedeni servis za servisiranje opreme in dobavo rezervnih delov. certifikate o usposobljenosti za brezhibno vzdrzevanje referencne opreme izdane s strani ucnega servisnega centra proizvajalca ki so jih pridobili navedeni serviserji v izjavi iz druge tocke. pojem referencna oprema si bo narocnik tolmacil iz vidika potrebnega pridobljenega strokovnega znanja usposobljenih oseb za vzdrzevanje opreme ki je primerljiva ponujeni opremi. kraj in datum zig in podpis ponudnika obr 4 izjava o izpolnjevanju tehnicne specifikacije opreme ponudnik pod kazensko in materialno odgovornostjo izjavljamo da izpolnjujemo tehnicne zahteve navedene v tem dokumenta ter obr 4 da bomo ponudbi predlozili originalne prospekte proizvajalca ter ostalo originalno dokumentacijo proizvajalca iz katere je razvidna oprema ki je predmet ponudbe da bo izpolnjevanje vseh zahtev iz opisa predmeta narocila mora biti razvidno iz originalnih prospektov proizvajalca ter ostale originalne dokumentacije proizvajalca slednje bomo ustrezno oznacili podcrtali in navedli ustrezno zap.st. ki izhaja iz opisa predmeta narocila hladilnik za zdravila v skladu z naslednjimi tehnicnimi zahtevami opomba temperaturno obmocje od 2 do 8 oc vrata z zaklepanjem steklena zunanji lcd zaslon odprtina za zunanjo/neodvisno sondo za belezenje temperature alarm ob odprtih vratih zunanji javljalnik izpada elektricne energije (zvocno in vidno opozorilo) 4 police mreza notranja osvetlitev mapiranje hladilnika izvedeno mora biti po instalaciji za prazen in poln hladilnik. temperaturno ovrednotenje mora biti izvedeno v 9 tockah hladilnika (na zgornji polici v sredini in na spodnji polici). (pri temperaturi 6 c) volumen cca. 560l (+/ 5%) zunanje dimenzije hladilnika cca. 700/800/2000 mm kraj in datum zig in podpis ponudnika i. obvezna dokumentacija ob dobavi opreme informacija ponudniku.dokumente ne prilagate ponudbi. seznam spremne dokumentacije skrbnik spremne dokumentacije medicinskega aparata obkrozi ustrezno. 1. prevod navodil v slovenskem jeziku za uporabo ter o nacinu preizkusanja in vzdrzevanja sipv oddelek 2.", "ner": [{"TenderYear": "2022"}], "ner_refine": []}
{"id": "2022_EN_M_360_TENDER", "chunk_id": "0", "input_tokens": 1916, "refiner_input_tokens": 0, "total_output_tokens": 246, "text": "oblakova ulica 5 3000 celje tel (03) 42 33 000 fax (03) 42 33 757 postopek 360 2022 sp/vh povabilo k oddaji ponudbe narocnik vabi ponudnike da v skladu z navodili ponudnikom za izdelavo ponudbe za mobilna operacijska miza za ginekoloske operacije 1 kom splosne zahteve osnova za realizacijo dobave je prejem pisnega narocila strani narocnika. ponudbe zbiramo informativno za predlozitev v presojo odobritve. v kolikor bomo prejeli odobritev s strani pristojnih bomo realizacijo izvedli pri najugodnejsemu ponudniku ki bo izpolnjeval tehnicne zahteve. cena mora vsebovati vse stroske popuste rabate dostavo montazo in davek na dodano vrednost. rok placila 60 dni. izvajalec mora zagotoviti dostavo blaga ter montazo in namestitev v prostor pri narocniku termin montaze/primopredaje je potrebno uskladiti z narocnikom (kontaktna oseba narocnika stanislava pahole) obveznost dobavitelja je da bo zagotovil brezplacno oz. na lastne stroske potrebno izvedbo edukacije uporabnikov (normalni uporabniski nivo) s strani narocnika za pravilno ter varno uporabo opreme ter njeno nego. ce je za ustrezno pridobitev znanja potrebno opraviti vec locenih edukacij je dobavitelj dolzan vsa ta solanja organizirati v smislu te tocke. ponudbi predlozite prospekte ter drugo dokumentacijo iz katere je razvidno izpolnjevanje tehnicnih zahtev. kontaktna oseba s strani narocnika ; stanislava pahole dipl.ekon. tel.st. 03 423 36 84 faks st. 03 423 37 56 ponudbe posljite na naslov elektronske poste nabava1 sb celje.si z oznako mobilna operacijska miza za ginekoloske operacije 360 2022 do najkasneje 23.06.2022 do 12 ure. priloga obrazec predracuna (obr 2) i. specifikacija vzdrzevanja izjava o zastopstvu (obr 3) izjavna o izpolnjevanju tehnicne specifikacije opreme (obr 4) ii.", "ner": [{"TenderOrg": "splosna bolnisnica celje"}, {"TenderTel": "(03) 42 33 000"}, {"TenderFax": "(03) 42 33 757"}, {"TenderNumber": "360"}, {"TenderYear": "2022"}, {"TenderCode": "sp/vh"}, {"TenderPerson": "stanislava pahole"}, {"TenderTel": "03 423 36 84"}, {"TenderFax": "03 423 37 56"}, {"TenderDeadline": "23.06.2022"}, {"TenderType": "m"}], "ner_refine": []}
{"id": "2022_EN_M_360_TENDER", "chunk_id": "1", "input_tokens": 2183, "refiner_input_tokens": 0, "total_output_tokens": 23, "text": "obveznost izbranega ponudnika brazec predracuna obr 2 ponudnik predmet mobilna operacijska miza za ginekoloske operacije predracun (oprema vzdrzevanje preventivni pregledi opreme za obdobje 7 let ) opis proizvajalec (1) model oz. kataloska stevilka (2) kolicina (3) vrednost brez ddv (4) mobilna operacijska miza za ginekoloske operacije kom vzdrzevanje all inclusive za obdobje 7 let vrednost opreme v eur brez ddv(1) znesek ddv za opremo vrednost kompletnega vzdrzevanj za obdobje 7 let (2) znesek ddv v eur za kompletno vzdrzevanje za obdobje 7 let skupaj vrednost v eur za 1+2 v eur z ddv kraj in datum zig in podpis ponudnika i. specifikacija vzdrzevanja kompletno vzdrzevanje v celotnem obdobju vzdrzevanja zajema naslednje vrste del ki so vkljucene v ceno vzdrzevalnine preventivno kurativno in programirano vzdrzevanje (vkljucno potrosni material ali drug material potreben za storitev kakor tudi stroski dela potni stroski stroski bivanja vzdrzevalcev dnevnice kilometrine transport dajatve davscine in drugi morebitni stroski potrebni za izvedbo vzdrzevanja opreme) z namenom ohranjanja stopnje funkcionalnosti sistemov in naprav ob nakupu oz. pravilnega in brezhibnega delovanja opreme; zamenjava vseh okvarjenih in izrabljenih originalnih rezervnih/nadomestnih delov ter potrosnega in drugega materiala ki so se izrabili oz. okvarili pri normalni in pravilni uporabi velja tako za kurativno vzdrzevanje kot tudi za preventivno vzdrzevanje po casovni dinamiki in obsegu ki je predpisan z navodili proizvajalca za vzdrzevanje opreme; redne preventivne kontrole nastavitve meritve po casovni dinamiki in obsegu ki je predpisan z navodili proizvajalca za vzdrzevanje opreme (vkljucno z delom in materialom po navodilih proizvajalca); nastavitve sistema po potrebi; pripravljenost ter stroske dela za popravila okvar ki nastanejo izven rednega delovnega casa; letne kalibracije meritve nastavitve overitve ves potrosni material ter drug potreben material za izvedbo vzdrzevanja po navodilih proizvajalca; nujne nadgradnje in zamenjave (programske in strojne opreme) za ohranitev funkcionalnosti sistema ob zagonu (kot npr. update i ipd.) (v skladu z zahtevo proizvajalca); nujne nadgradnje in zamenjave (programske in strojne) za povecanje funkcionalnosti sistema od nakupa (v skladu z zahtevo proizvajalca); odpravo nepravilnega delovanja ali okvare sistema ki niso posledica nepravilne uporabe na strani narocnika; daljinski nadzor in servis; kontrole inspekcije certificiranje in zagotovitev kakovosti opremljanje z oznacbami (nalepkami na opremi) o izvedenem vzdrzevanju; optimiranje funkcijskih parametrov delovanja; zagotovitev pravice k produktivni nadgradnji ki predstavlja zamenjavo/posodobitev/nadgradnjo obstojecih verzij programske opreme ki v celoti nadomestijo licencirano verzijo programskih licenc; druge stroske ki niso posebej specificirani so pa potrebni za funkcionalno zagotovitev delovanja aparata.", "ner": [], "ner_refine": []}
{"id": "2022_EN_M_094_TENDER", "chunk_id": "0", "input_tokens": 2232, "refiner_input_tokens": 0, "total_output_tokens": 257, "text": "oblakova ulica 5 3000 celje tel (03) 42 33 000 fax (03) 42 33 757 postopek 94 2022 vh/vh povabilo k oddaji ponudbe narocnik vabi ponudnike da v skladu z navodili ponudnikom za izdelavo ponudbe za lutka za reanimacijo novorojencka 1 kom splosne zahteve osnova za realizacijo dobave je prejem pisnega narocila strani narocnika. ponudbe zbiramo informativno za predlozitev v presojo odobritve. v kolikor bomo prejeli odobritev s strani pristojnih bomo realizacijo izvedli pri najugodnejsemu ponudniku ki bo izpolnjeval tehnicne zahteve. cena mora vsebovati vse stroske popuste rabate dostavo montazo in davek na dodano vrednost. rok za placilo je 60 dni od prejema racuna izvajalec mora zagotoviti dostavo blaga ter montazo in namestitev v prostor pri narocniku termin montaze/primopredaje je potrebno uskladiti z narocnikom (kontaktna oseba narocnika vanja herman gril) obveznost dobavitelja je da bo zagotovil brezplacno oz. na lastne stroske potrebno izvedbo edukacije uporabnikov (normalni uporabniski nivo) s strani narocnika za pravilno ter varno uporabo opreme ter njeno nego. ce je za ustrezno pridobitev znanja potrebno opraviti vec locenih edukacij je dobavitelj dolzan vsa ta solanja organizirati v smislu te tocke. ponudbi predlozite prospekte ter drugo dokumentacijo iz katere je razvidno izpolnjevanje tehnicnih zahtev. kontaktna oseba s strani narocnika ; stanislava pahole dipl.ekon. tel.st. 03 423 36 84 faks st. 03 423 37 56 elektronska posta stanislava.pahole sb celje.si. ponudbe posljite na naslov elektronske poste nabava1 sb celje.si z oznako lutka za reanimacijo novorojencka 94 do najkasneje 18.02.2022 do 12 ure. priloga izjavna o izpolnjevanju tehnicne specifikacije opreme (obr 4) obr 4 izjava o izpolnjevanju tehnicne specifikacije opreme ponudnik pod kazensko in materialno odgovornostjo izjavljamo da izpolnjujemo tehnicne zahteve navedene v tem dokumenta ter obr 4 da bomo ponudbi predlozili originalne prospekte proizvajalca ter ostalo originalno dokumentacijo proizvajalca iz katere je razvidna oprema ki je predmet ponudbe da bo izpolnjevanje vseh zahtev iz opisa predmeta narocila mora biti razvidno iz originalnih prospektov proizvajalca ter ostale originalne dokumentacije proizvajalca slednje bomo ustrezno oznacili podcrtali in navedli ustrezno zap.st. ki izhaja iz opisa predmeta narocila predmet lutka za renaimacijo novorojencka 1 kom v skladu z naslednjimi tehnicnimi zahtevami model novorojencka ali nedonosencka model naj bo v obliki celega telesa sklepi naj bodo gibljivi telo upogljivo oskrba dihalne poti lutka naj omogoca vstavitev ustno zrelnega tubusa in nosnozrelnega tubusa aspiracijo dihalne poti vstavitev supragloticnih pripomockov endotrahealno intubacijo umetno dihanje lutka naj omogoca aplikacijo kisika ventilacijo z dihalnim balonom in masko ali preko tubusa omogoca naj predihavanje z ventilatorjem", "ner": [{"TenderOrg": "sb celje"}, {"TenderTel": "(03) 42 33 000"}, {"TenderFax": "(03) 42 33 757"}, {"TenderNumber": "94"}, {"TenderYear": "2022"}, {"TenderCode": "vh/vh"}, {"TenderDeadline": "18.02.2022"}, {"TenderPerson": "vanja herman gril"}, {"TenderPerson": "stanislava pahole"}, {"TenderTel": "03 423 36 84"}, {"TenderFax": "03 423 37 56"}, {"TenderType": "m"}], "ner_refine": []}
{"id": "2022_EN_M_008_TENDER", "chunk_id": "0", "input_tokens": 2253, "refiner_input_tokens": 0, "total_output_tokens": 244, "text": "4 narocnik splosna bolnisnica celje oblakova ulica 5 3000 celje tel (03) 42 33 000 fax (03) 42 33 757 postopek 8 2022 sp/vh povabilo k oddaji ponudbe narocnik vabi ponudnike da v skladu z navodili ponudnikom za izdelavo ponudbe za laboratorijske zamrzovalne omare splosne zahteve osnova za realizacijo dobave je prejem pisnega narocila strani narocnika. ponudbe zbiramo informativno za predlozitev v presojo odobritve. v kolikor bomo prejeli odobritev s strani pristojnih bomo realizacijo izvedli pri najugodnejsemu ponudniku ki bo izpolnjeval tehnicne zahteve. cena mora vsebovati vse stroske popuste rabate dostavo montazo in davek na dodano vrednost. izvajalec mora zagotoviti dostavo blaga ter montazo in namestitev v prostor pri narocniku termin montaze/primopredaje je potrebno uskladiti z narocnikom (kontaktna oseba narocnika vanja herman gril) obveznost dobavitelja je da bo zagotovil brezplacno oz. na lastne stroske potrebno izvedbo edukacije uporabnikov (normalni uporabniski nivo) s strani narocnika za pravilno ter varno uporabo opreme ter njeno nego. ce je za ustrezno pridobitev znanja potrebno opraviti vec locenih edukacij je dobavitelj dolzan vsa ta solanja organizirati v smislu te tocke. ponudbi predlozite prospekte ter drugo dokumentacijo iz katere je razvidno izpolnjevanje tehnicnih zahtev. kontaktna oseba s strani narocnika ; stanislava.pahole dipl.ekon. tel.st. 03 423 36 84 faks st. 03 423 37 56 elektronska posta stanislava.pahole sb celje.si. ponudbe posljite na naslov elektronske poste nabava1 sb celje.si z oznako laboratorijske zamrzovalne omare 8 2022 do najkasneje 11.01.2022 do 12ure. priloga obrazec predracuna (obr 2) izjava o zastopstvu (obr 3) izjavna o izpolnjevanju tehnicne specifikacije opreme (obr 4) obveznost izbranega ponudnika obrazec predracuna obr 2 ponudnik predmet laboratorijske zamrzovalne omare predracun (oprema vzdrzevanje preventivni pregledi opreme za obdobje 7 let ) opis proizvajalec (1) model oz. kataloska stevilka (2) kolicina (3) vrednost brez ddv (4) 1. laboratorijske zamrzovalne omare 2 kom 2. vrednost kompletnega vzdrzevanja za obdobje 7 let (vrednost mora vkljucevati letne kalibracije meritve nastavitve overitve ves potrosni material ter drug potreben material kakor tudi stroske dela potne stroske dnevnice kilometrine in druge morebitne stroske potrebne za izvedbo potrebnega vzdrzevanja opreme.) 2 kom znesek opreme v eur brez ddv za 1 kom (1) znesek davka za opremo za 1 kom vrednost preventivnega vzdrzevanja ter redni letni pregled za obdobje 7 let v eur brez ddv za 1 kom (2) znesek davka v eur za preventivno vzdrzevanje ter redni letni pregled opreme 1 kom v eur brez ddv skupaj vrednost v eur z ddv 2 kom omar + vzdrzevanje 2 kom(1+2) datum zig in podpis ponudnika sestavni del in priloga ponudbe .", "ner": [{"TenderOrg": "splosna bolnisnica celje"}, {"TenderTel": "(03) 42 33 000"}, {"TenderFax": "(03) 42 33 757"}, {"TenderNumber": "8"}, {"TenderYear": "2022"}, {"TenderCode": "sp/vh"}, {"TenderTel": "03 423 36 84"}, {"TenderFax": "03 423 37 56"}, {"TenderPerson": "stanislava pahole"}, {"TenderDeadline": "11.01.2022"}, {"TenderType": "m"}], "ner_refine": []}
{"id": "2022_EN_M_008_TENDER", "chunk_id": "1", "input_tokens": 2097, "refiner_input_tokens": 0, "total_output_tokens": 41, "text": "predracun (oprema vzdrzevanje preventivni pregledi opreme za obdobje 7 let ) opis proizvajalec (1) model oz. kataloska stevilka (2) kolicina (3) vrednost brez ddv (4) 1. laboratorijske zamrzovalne omare 1 kom 2. vrednost kompletnega vzdrzevanja za obdobje 7 let (vrednost mora vkljucevati letne kalibracije meritve nastavitve overitve ves potrosni material ter drug potreben material kakor tudi stroske dela potne stroske dnevnice kilometrine in druge morebitne stroske potrebne za izvedbo potrebnega vzdrzevanja opreme.) 1 kom znesek opreme v eur brez ddv za 1 kom (1) znesek davka za opremo za 1 kom vrednost preventivnega vzdrzevanja ter redni letni pregled za obdobje 7 let v eur brez ddv za 1 kom (2) znesek davka v eur za preventivno vzdrzevanje ter redni letni pregled opreme 1 kom v eur brez ddv skupaj vrednost v eur z ddv (1+2) datum zig in podpis ponudnika sestavni del in priloga ponudbe . obr 3 izjava o zastopstvu ponudnik obvezne priloge v letu 2022 veljavno izjava o zastopstvu lastne blagovne znamke oz. izjava proizvajalca o pooblastilu zastopanja za prodajo tovrstnih aparatov. izjava mora biti potrjena z zigom ter podpisom proizvajalca. v letu 2022 veljavno izjava o zastopstvu lastne blagovne znamke oz. izjava proizvajalca o pooblastilu zastopanja za prodajo originalnega potrosnega materiala potrebnega za delovanje aparatov. izjava mora biti potrjena z zigom ter podpisom proizvajalca. v letu 2022 veljavna pisna pooblastila proizvajalcev ki so proizvedli ponujeno opremo s katerim pooblascajo zgoraj navedeni servis za servisiranje opreme in dobavo rezervnih delov. certifikate o usposobljenosti za brezhibno vzdrzevanje referencne opreme izdane s strani ucnega servisnega centra proizvajalca ki so jih pridobili navedeni serviserji v izjavi iz druge tocke. pojem referencna oprema si bo narocnik tolmacil iz vidika potrebnega pridobljenega strokovnega znanja usposobljenih oseb za vzdrzevanje opreme ki je primerljiva ponujeni opremi. kraj in datum zig in podpis ponudnika obr 4 izjava o izpolnjevanju tehnicne specifikacije opreme ponudnik pod kazensko in materialno odgovornostjo izjavljamo da izpolnjujemo tehnicne zahteve navedene v tem dokumenta ter obr 4 da bomo ponudbi predlozili originalne prospekte proizvajalca ter ostalo originalno dokumentacijo proizvajalca iz katere je razvidna oprema ki je predmet ponudbe da bo izpolnjevanje vseh zahtev iz opisa predmeta narocila mora biti razvidno iz originalnih prospektov proizvajalca ter ostale originalne dokumentacije proizvajalca slednje bomo ustrezno oznacili podcrtali in navedli ustrezno zap.st.", "ner": [], "ner_refine": []}
{"id": "2022_EN_M_149_TENDER", "chunk_id": "0", "input_tokens": 2166, "refiner_input_tokens": 0, "total_output_tokens": 246, "text": "6 narocnik splosna bolnisnica celje oblakova ulica 5 3000 celje tel (03) 42 33 000 fax (03) 42 33 757 postopek 149 2022 mv/vh povabilo k oddaji ponudbe narocnik vabi ponudnike da v skladu z navodili ponudnikom za izdelavo ponudbe za grelna omara 1 kom splosne zahteve osnova za realizacijo dobave je prejem pisnega narocila strani narocnika. ponudbe zbiramo informativno za predlozitev v presojo odobritve. v kolikor bomo prejeli odobritev s strani pristojnih bomo realizacijo izvedli pri najugodnejsemu ponudniku ki bo izpolnjeval tehnicne zahteve. cena mora vsebovati vse stroske popuste rabate dostavo montazo in davek na dodano vrednost. izvajalec mora zagotoviti dostavo blaga ter montazo in namestitev v prostor pri narocniku termin montaze/primopredaje je potrebno uskladiti z narocnikom. obveznost dobavitelja je da bo zagotovil brezplacno oz. na lastne stroske potrebno izvedbo edukacije uporabnikov (normalni uporabniski nivo) s strani narocnika za pravilno ter varno uporabo opreme ter njeno nego. ponudbi predlozite prospekte ter drugo dokumentacijo iz katere je razvidno izpolnjevanje tehnicnih zahtev. dodatne zahteve na medicinski opremi mora biti obvezno prilepljena proizvajalceva nalepka ki mora izkazovati vsaj naslednje podatke ime in tip naprave oznake ce serijska stevilka naprave datum proizvodnje (leto mesec dan) ime proizvajalca drzava proizvajalca na aparatu mora biti obvezno tudi nalepka ki oznacuje termin naslednjega potrebnega preventivnega servisa. kontaktna oseba s strani narocnika ; stanislava pahole dipl.ekon. tel.st. 03 423 36 84 faks st. 03 423 37 56 elektronska posta stanislava.pahole sb celje.si. ponudbe posljite na naslov elektronske poste nabava1 sb celje.si z oznako grelma omara 149 2022 do najkasneje 24.03.2022 do 12 ure. priloga obrazec predracuna (obr 2) izjava o zastopstvu (obr 3) izjavna o izpolnjevanju tehnicne specifikacije opreme (obr 4) obveznost izbranega ponudnika obrazec predracuna obr 2 ponudnik predmet grelna omara predracun (oprema vzdrzevanje preventivni pregledi opreme za obdobje 7 let ) opis proizvajalec (1) model oz. kataloska stevilka (2) kolicina (3) vrednost brez ddv (4) 1. grelna omara 1 kom 2. vrednost kompletnega vzdrzevanja za obdobje 7 let cena v eur brez ddv (1) znesek davka za opremo vrednost kompletnega vzdrzevanja in redni letni pregled za obdobje 7 let v eur brez ddv (2) znesek davka v eur za kompletno vzdrzevanje ter redni letni pregled opreme skupaj vrednost v eur z ddv (1+2) datum zig in podpis ponudnika sestavni del in priloga ponudbe .", "ner": [{"TenderOrg": "splosna bolnisnica celje"}, {"TenderTel": "(03) 42 33 000"}, {"TenderFax": "(03) 42 33 757"}, {"TenderNumber": "149"}, {"TenderYear": "2022"}, {"TenderCode": "mv/vh"}, {"TenderPerson": "stanislava pahole"}, {"TenderTel": "03 423 36 84"}, {"TenderFax": "03 423 37 56"}, {"TenderDeadline": "24.03.2022"}, {"TenderType": "m"}], "ner_refine": []}
{"id": "2022_EN_M_149_TENDER", "chunk_id": "1", "input_tokens": 2174, "refiner_input_tokens": 0, "total_output_tokens": 23, "text": "i. specifikacija vzdrzevanja kompletno vzdrzevanje v celotnem obdobju vzdrzevanja zajema naslednje vrste del ki so vkljucene v ceno vzdrzevalnine preventivno kurativno in programirano vzdrzevanje (vkljucno potrosni material ali drug material potreben za storitev kakor tudi stroski dela potni stroski stroski bivanja vzdrzevalcev dnevnice kilometrine transport dajatve davscine in drugi morebitni stroski potrebni za izvedbo vzdrzevanja opreme) z namenom ohranjanja stopnje funkcionalnosti sistemov in naprav ob nakupu oz. pravilnega in brezhibnega delovanja opreme; zamenjava vseh okvarjenih in izrabljenih originalnih rezervnih/nadomestnih delov ter potrosnega in drugega materiala ki so se izrabili oz. okvarili pri normalni in pravilni uporabi velja tako za kurativno vzdrzevanje kot tudi za preventivno vzdrzevanje po casovni dinamiki in obsegu ki je predpisan z navodili proizvajalca za vzdrzevanje opreme; redne preventivne kontrole nastavitve meritve po casovni dinamiki in obsegu ki je predpisan z navodili proizvajalca za vzdrzevanje opreme (vkljucno z delom in materialom po navodilih proizvajalca); nastavitve sistema po potrebi; pripravljenost ter stroske dela za popravila okvar ki nastanejo izven rednega delovnega casa; letne kalibracije meritve nastavitve overitve ves potrosni material ter drug potreben material za izvedbo vzdrzevanja po navodilih proizvajalca; nujne nadgradnje in zamenjave (programske in strojne opreme) za ohranitev funkcionalnosti sistema ob zagonu (kot npr. update i ipd.) (v skladu z zahtevo proizvajalca); nujne nadgradnje in zamenjave (programske in strojne) za povecanje funkcionalnosti sistema od nakupa (v skladu z zahtevo proizvajalca); odpravo nepravilnega delovanja ali okvare sistema ki niso posledica nepravilne uporabe na strani narocnika; daljinski nadzor in servis; kontrole inspekcije certificiranje in zagotovitev kakovosti opremljanje z oznacbami (nalepkami na opremi) o izvedenem vzdrzevanju; optimiranje funkcijskih parametrov delovanja; zagotovitev pravice k produktivni nadgradnji ki predstavlja zamenjavo/posodobitev/nadgradnjo obstojecih verzij programske opreme ki v celoti nadomestijo licencirano verzijo programskih licenc; druge stroske ki niso posebej specificirani so pa potrebni za funkcionalno zagotovitev delovanja aparata. v ceno vzdrzevalnine po tej ponudbi niso vkljucena sledeca dela in material ki jih narocnik po ustreznem postopku loceno naroci in obracuna delo pri odpravi napak ki so nastale zaradi nepravilne uporabe v tem primeru znasa cena delovne ure brez ddv dodatno narocene spremembe programske opreme ki niso povezane z vzdrzevanjem nadgradnje in zamenjave (programske in strojne opreme) za povecanje funkcionalnosti od nakupa odprava napak ki so nastale zaradi posegov nepooblascenih oseb odprava napak nastalih zaradi atmosferskih razelektrenj (strela) odprava napak nastalih zaradi visje sile (poplave potres pozar ipd.) izvedba fizicnih prestavitev opreme.", "ner": [], "ner_refine": []}
{"id": "2022_EN_M_646_TENDER", "chunk_id": "0", "input_tokens": 2220, "refiner_input_tokens": 0, "total_output_tokens": 240, "text": "6 narocnik splosna bolnisnica celje oblakova ulica 5 3000 celje tel (03) 42 33 000 fax (03) 42 33 757 postopek 656 2022 sp/vh povabilo k oddaji ponudbe narocnik vabi ponudnike da v skladu z navodili ponudnikom za izdelavo ponudbe za brezplacna uporaba dializnih aparatov z vzdrzevanjem ter nakupom potrosnega materiala splosne zahteve osnova za realizacijo dobave je prejem pisnega narocila strani narocnika. ponudbe zbiramo informativno za predlozitev v presojo odobritve. v kolikor bomo prejeli odobritev s strani pristojnih bomo realizacijo izvedli pri najugodnejsemu ponudniku ki bo izpolnjeval tehnicne zahteve. cena mora vsebovati vse stroske popuste rabate dostavo montazo in davek na dodano vrednost. rok za placilo je 30 dni od prejema racuna. izvajalec mora zagotoviti dostavo blaga ter montazo in namestitev v prostor pri narocniku. termin montaze/primopredaje je potrebno uskladiti z narocnikom. obveznost dobavitelja je da bo zagotovil brezplacno oz. na lastne stroske potrebno izvedbo edukacije uporabnikov (normalni uporabniski nivo) s strani narocnika za pravilno ter varno uporabo opreme ter njeno nego. ponudbi predlozite prospekte ter drugo dokumentacijo iz katere je razvidno izpolnjevanje tehnicnih zahtev. dodatne zahteve na medicinski opremi mora biti obvezno prilepljena proizvajalceva nalepka ki mora izkazovati vsaj naslednje podatke ime in tip naprave oznake ce serijska stevilka naprave datum proizvodnje (leto mesec dan) ime proizvajalca drzava proizvajalca na aparatu mora biti obvezno tudi nalepka ki oznacuje termin naslednjega potrebnega preventivnega servisa. kontaktna oseba s strani narocnika ; vanja herman gril mag. manag. tel.st. 03 423 36 84 faks st. 03 423 37 56 elektronska posta vanja.herman sb celje.si. ponudbe posljite na naslov elektronske poste nabava1 sb celje.si z oznako 646 2022 brezplacna uporaba dializnih aparatov z vzdrzevanjem ter nakupom potrosnega materiala do najkasneje 10.11.2022 do 12 ure. priloga obrazec predracuna rekapitulacija (obr 1) obrazec predracuna podrobni ponudbeni predracun (obr 1/1) specifikacija potrosnega material (obr 12) vzorec pogodbe (obr 2) izjava o zastopstvu vzdrzevanju medicinske opreme (obr 3) obrazec predracuna rekapitulacija obr 1 ponudnik evidencno narocilo brezplacna uporaba dializnih aparatov z vzdrzevanjem ter nakupom potrosnega materiala skupaj pogodbena vrednost za potrosni material za obdobje enega leta vrednost v eur z ddv skupaj vrednost za obdobje enega leta v eur z ddv *v ponudbeni ceni so zajeti tudi stroski za brezplacno uporabo aparata za ves cas trajanja pogodbe ter vsi stroski povezani z all inclusive vzdrzevanjem za obdobje 1 leta. v ceni so zajeti vsi stroski vkljucno s prevozom in drugimi odvisnimi stroski fco sedez narocnika.", "ner": [{"TenderOrg": "splosna bolnisnica celje"}, {"TenderTel": "(03) 42 33 000"}, {"TenderFax": "(03) 42 33 757"}, {"TenderNumber": "656"}, {"TenderYear": "2022"}, {"TenderCode": "sp/vh"}, {"TenderTel": "03 423 36 84"}, {"TenderFax": "03 423 37 56"}, {"TenderPerson": "vanja herman gril"}, {"TenderDeadline": "10.11.2022"}, {"TenderType": "m"}], "ner_refine": []}
{"id": "2022_EN_M_646_TENDER", "chunk_id": "1", "input_tokens": 2234, "refiner_input_tokens": 0, "total_output_tokens": 23, "text": "veljavnost ponudbe je 30 dni po datumu dolocenem za odpiranje ponudb. datum zig in podpis ponudnika obrazec predracuna podrobni ponudbeni predracun obr 1 /1 ponudnik evidencno narocilo brezplacna uporaba dializnih aparatov z vzdrzevanjem ter nakupom potrosnega materiala ponudnik ponuja naslednjo opremo (ponudnik predlozi zahtevane podatke in v ponudbi predlozi tehnicno dokumentacijo s katero izkazuje da ponujena oprema ustreza tehnicnih zahtevam dolocenimi v navodili ponudnikom) opis proizvajalec model oz. kataloska stevilka kolicina 1.dializni aparat kot npr. braun tip dialog plus adimea fresenius tip aparata 5008 nipro tip aparat surdial x 3 kom obr 1/2 ponudnik mora v ponudbi predloziti specifikacijo originalnega potrosnega materiala za delovanje nudene opreme iz obr 5 (potrosni material potreben za izvedbo postopka ter drugo potrebno za delovanje opreme) vrsta procedure dvoigelna letno predvideno stevilo postopkov 1600 zap.st. artikel st. (1) opis naziv artikla (1) kolicina potrosnega materiala potrebna za izvedbo 1 postopka (2) cena na enoto brez ddv za postopek(3) vrednost ddv v eur na enoto mere (4) cena na enoto (za postopek) v eur z ddv (5) ocenjena kolicina postopkov za obdobje enega leta (6) 1600 skupaj cena v eur z ddv za obdobje enega leta (7=5x6) vnesite potrebno stevilo dodatnih vrstic za vnos vseh artiklov potrebnih za delovanje aparata iz obr 5 in so potrebni za izvedbo postopkov iz obr 1/1 v kolikor narocnik ugotovi da izbrani ponudnik pri pripravi specifikacije potrosnega materiala ni zavedel vseh potrebnih artiklov bo moral izvajalec brezpogojno in brezplacno dobaviti dodatnih artiklov oz. vec potrosnega materiala v nasprotnem primeru bo narocnik izvrsil dejanja dolocena za primer nespostovanja pogodbe. datum zig in podpis ponudnika obr 2 vzorec pogodbe splosna bolnisnica celje oblakova ulica 5 3000 celje (v nadaljevanju narocnik) ki jo zastopa direktor aleksander svetelsek mag. id stevilka za ddv si 42119022 in (v nadaljevanju izvajalec) id stevilka za ddv sklepata pogodba o brezplacni uporabi dializnih aparatov z vzdrzevanjem ter nakupom potrosnega materiala vrednost pogodbe eur z ddv 1. predmet pogodbe 1.1 predmet pogodbe je obveznost izvajalca da bo narocniku izrocil v razpolaganje in brezplacno uporabo novo in nerabljeno opremo vkljucno z montazo dializni aparat 3 kom proizvajalca model oz. kataloska stevilka da bo v obdobju 1 .leta od dneva podpisa zapisnika s katerim se je aparat predal v brezplacno uporabo vzdrzeval aparat na lastne stroske vzdrzevanje je za narocnika brezplacno da bo dobavljal potrosni material na podlagi vsakokratnega narocila narocnika po dogovorjenih cenah. pri navedeni opremi je sestavni del tudi vsa strojna programska in druga oprema kot tudi vse drugo kar izhaja iz izvajalceve ponudbe st. z dne (ponudba je sestavni del te pogodbe). obveznosti v zvezi z brezplacno predajo aparat v uporabo 1.2.", "ner": [], "ner_refine": []}
{"id": "2022_EN_N_476_TENDER", "chunk_id": "0", "input_tokens": 2159, "refiner_input_tokens": 0, "total_output_tokens": 243, "text": "oblakova ulica 5 3000 celje tel (03) 42 33 000 fax (03) 42 33 757 postopek 476 2022 sp/vh povabilo k oddaji ponudbe narocnik vabi ponudnike da v skladu z navodili ponudnikom za izdelavo ponudbe za pregradna stena zlozljiva 1 kom splosne zahteve osnova za realizacijo dobave je prejem pisnega narocila strani narocnika. ponudbe zbiramo informativno za predlozitev v presojo odobritve. v kolikor bomo prejeli odobritev s strani pristojnih bomo realizacijo izvedli pri najugodnejsemu ponudniku ki bo izpolnjeval tehnicne zahteve. cena mora vsebovati vse stroske popuste rabate dostavo montazo in davek na dodano vrednost. rok za placilo je 60 dni od prejema racuna izvajalec mora zagotoviti dostavo blaga ponudbi predlozite prospekte ter drugo dokumentacijo iz katere je razvidno izpolnjevanje tehnicnih zahtev. kontaktna oseba s strani narocnika ; stanislava pahole dipl.ekon. tel.st. 03 423 36 84 faks st. 03 423 37 56 elektronska posta stanislava.pahole sb celje.si. ponudbe posljite na naslov elektronske poste nabava1 sb celje.si z oznako pregradna stena zlozljiva 476 do najkasneje 28.07.2022 do 12 ure. priloga obrazec predracuna (obr 2) izjavna o izpolnjevanju tehnicne specifikacije opreme (obr 3) obrazec predracuna obr 2 ponudnik predmet zlozljiva pregradna stena predracun opis proizvajalec (1) model oz. kataloska stevilka (2) kolicina (3) vrednost brez ddv (4) 1. zlozljiva pregradna stena 1 kom cena za kom v eur brez ddv skupaj vrednost v eur z ddv datum zig in podpis ponudnik obr 3 izjava o izpolnjevanju tehnicne specifikacije opreme ponudnik pod kazensko in materialno odgovornostjo izjavljamo da izpolnjujemo tehnicne zahteve navedene v tem dokumentu da bomo ponudbi predlozili originalne prospekte proizvajalca ter ostalo originalno dokumentacijo proizvajalca iz katere je razvidna oprema ki je predmet ponudbe da bo izpolnjevanje vseh zahtev iz opisa predmeta narocila mora biti razvidno iz originalnih prospektov proizvajalca ter ostale originalne dokumentacije proizvajalca slednje bomo ustrezno oznacili podcrtali in navedli ustrezno zap. st. ki izhaja iz opisa predmeta narocila pregradna stena zlozljiva v skladu z naslednjimi tehnicnimi zahtevami opomba mobilna na kolesih na zavoro zlozljiva (na tri razdelke) dolzina 200cm do max. 220 visina 150cm (vkljucno s kolesi max 170cm) laminat ali drug obstojni material ne platno ali drug vpojni material povrsina primerna za dezinfekcijo razkuzevanje ali vlazno ciscenje barvo bo uporabnik izbral naknadno kraj in datum zig in podpis ponudnika", "ner": [{"TenderOrg": "sb celje.si"}, {"TenderTel": "(03) 42 33 000"}, {"TenderFax": "(03) 42 33 757"}, {"TenderNumber": "476"}, {"TenderYear": "2022"}, {"TenderCode": "sp/vh"}, {"TenderPerson": "stanislava pahole"}, {"TenderTel": "03 423 36 84"}, {"TenderFax": "03 423 37 56"}, {"TenderDeadline": "28.07.2022"}, {"TenderType": "n"}], "ner_refine": []}
{"id": "2022_EN_M_469_TENDER", "chunk_id": "0", "input_tokens": 2180, "refiner_input_tokens": 0, "total_output_tokens": 246, "text": "4 narocnik splosna bolnisnica celje oblakova ulica 5 3000 celje tel (03) 42 33 000 fax (03) 42 33 757 postopek 469 2022 sp/vh povabilo k oddaji ponudbe narocnik vabi ponudnike da v skladu z navodili ponudnikom za izdelavo ponudbe za pregledovalna miza na kolesih 1 kom splosne zahteve osnova za realizacijo dobave je prejem pisnega narocila strani narocnika. ponudbe zbiramo informativno za predlozitev v presojo odobritve. v kolikor bomo prejeli odobritev s strani pristojnih bomo realizacijo izvedli pri najugodnejsemu ponudniku ki bo izpolnjeval tehnicne zahteve. cena mora vsebovati vse stroske popuste rabate dostavo montazo in davek na dodano vrednost. izvajalec mora zagotoviti dostavo blaga ter montazo in namestitev v prostor pri narocniku termin montaze/primopredaje je potrebno uskladiti z narocnikom (kontaktna oseba narocnika stanislava pahole) obveznost dobavitelja je da bo zagotovil brezplacno oz. na lastne stroske potrebno izvedbo edukacije uporabnikov (normalni uporabniski nivo) s strani narocnika za pravilno ter varno uporabo opreme ter njeno nego. ce je za ustrezno pridobitev znanja potrebno opraviti vec locenih edukacij je dobavitelj dolzan vsa ta solanja organizirati v smislu te tocke. ponudbi predlozite prospekte ter drugo dokumentacijo iz katere je razvidno izpolnjevanje tehnicnih zahtev. kontaktna oseba s strani narocnika ; stanislava pahole dipl.ekon. tel.st. 03 423 36 84 faks st. 03 423 37 56 stanislava.pahole sb celje.si ponudbe posljite na naslov elektronske poste nabava1 sb celje.si z oznako 469 pregledovalna miza na kolesih 2022 do najkasneje 21.07.2022 do 12 ure. priloga obrazec predracuna (obr 2) obveznost izbranega ponudnika (obr 3) obrazec predracuna obr 2 ponudnik predmet pregledovalna miza na kolesih opis n119139 proizvajalec (1) model oz. kataloska stevilka (2) kolicina (3) vrednost brez ddv (4) 1. pregledovalna miza na kolesih 1 kom vrednost opreme v eur brez ddv (1) znesek davka za opremo skupaj vrednost v eur z ddv datum zig in podpis ponudnika obr 3 izjava o izpolnjevanju tehnicne specifikacije opreme ponudnik pod kazensko in materialno odgovornostjo izjavljamo da izpolnjujemo tehnicne zahteve navedene v tem dokumenta ter obr 3 da bomo ponudbi predlozili originalne prospekte proizvajalca ter ostalo originalno dokumentacijo proizvajalca iz katere je razvidna oprema ki je predmet ponudbe da bo izpolnjevanje vseh zahtev iz opisa predmeta narocila mora biti razvidno iz originalnih prospektov proizvajalca ter ostale originalne dokumentacije proizvajalca slednje bomo ustrezno oznacili podcrtali in navedli ustrezno zap.st.", "ner": [{"TenderOrg": "splosna bolnisnica celje"}, {"TenderTel": "(03) 42 33 000"}, {"TenderFax": "(03) 42 33 757"}, {"TenderNumber": "469"}, {"TenderYear": "2022"}, {"TenderCode": "sp/vh"}, {"TenderPerson": "stanislava pahole"}, {"TenderTel": "03 423 36 84"}, {"TenderFax": "03 423 37 56"}, {"TenderDeadline": "21.07.2022"}, {"TenderType": "m"}], "ner_refine": []}
{"id": "2022_EN_N_010_TENDER", "chunk_id": "0", "input_tokens": 2029, "refiner_input_tokens": 0, "total_output_tokens": 210, "text": "splosna bolnisnica celje oblakova ulica 5 3000 celje tel (03) 42 33 000 fax (03) 42 33 757 postopek n 10 2022 kt/ms povabilo k oddaji ponudbe v abimo vas k oddaji ponudbe za predmet vabimo vas k oddaji ponudbe za predmet kasetni in vrecasti filtri zahteve in pogoji za dobavo kasetnih in vrecastih filtrov 1. kasete in vrece morajo biti mersko skladne s podano specifikacijo v obrazcu predracuna. 2. filtrski materiali kasetnih in vrecastih filtrov morajo ustrezati zahtevani kakovosti oziroma filtrimemu razredu ter stopnji propustnosti. kasete in filtri morajo biti kot celota kompaktni in kvalitetno izdelani. 4. kasetni filtri z robom 25 mm morajo biti kvalitetno okvirjeni! da ne pride do izpadanja filterskih materialov. w 5. vrece morajo biti kvalitetno izdelane z okvirji sirokimi 2 cm kjerje to zahtevano. 6. ponudnik mora ponuditi vse razpisane artikle skladno z zahtevano kolicino in kvaliteto in dimenzijami. 7. vsi artikli morajo biti ob dobavi ustrezno deklarirani in oznaceni. 8. kasetni in vrecasti filtri morajo biti ob dobavi pakirani in vidno''oznaceni po posameznih klimatsko prezracevalnih napravah kot je razvidno iz prilozene specifikacije popisa po prilozeni specifikaciji. 9. ponudnik zagotavlja dostavo fco. splosna bolnisnica celje. 10. ponudnik mora na zeljo narocnika predloziti vzorce posameznih artiklov. 11. ponudba mora vkljucevati vse stroske popuste vkljucno z prevzemom in odvozom izrabljenih filterskih materialov !! rok za placilo je 60 dni od prejema racuna. merilo za izbora najnizja vrednost ponudbe v eur z ddv ob izpolnjevanju tehnicnih zahtev narocnika. predviden rok realizacije 3.03.2022 kontaktna oseba s strani narocnika ; stane mulej dipl.ekon. tel.st. 03 423 31 45 faks st. 03 423 37 56 elektronska posta stane.mulej() sb celje.si. ponudbe posljite na naslov elektronske poste nabava2 sb celje.si narocnik splosna bolnisnica celje z oznako n 10 kasetni in vrecasi filtri 2022 do najkasneje 3.2.2022 do 12 ure. vodja nabavne sluzbe matjaz stinek univ.dipl.ekon. postopek kt/ms", "ner": [{"TenderOrg": "splosna bolnisnica celje"}, {"TenderTel": "(03) 42 33 000"}, {"TenderFax": "(03) 42 33 757"}, {"TenderType": "n"}, {"TenderNumber": "10"}, {"TenderYear": "2022"}, {"TenderCode": "kt/ms"}, {"TenderDeadline": "03.02.2022"}, {"TenderPerson": "stane mulej"}, {"TenderPerson": "matjaz stinek"}], "ner_refine": []}
{"id": "2022_EN_N_009_TENDER", "chunk_id": "0", "input_tokens": 1901, "refiner_input_tokens": 0, "total_output_tokens": 244, "text": "splosna bolnisnica celje oblakova ulica 5 3000 celje tel (03) 42 33 000 fax (03) 42 33 757 postopek n 9 2022 kt/ms povabilo k oddaji ponudbe narocnik vabi ponudnike da v skladu z navodili ponudnikom za izdelavo ponudbe za parnokonvekcijska pec z dvema kuhalnima komorama 1kom splosne zahteve osnova za realizacijo dobave je prejem pisnega narocila strani narocnika. ponudbe zbiramo informativno za predlozitev v presojo odobritve. v kolikor bomo prejeli odobritev s strani pristojnih bomo realizacijo izvedli pri najugodnejsemu ponudniku ki bo izpolnjeval tehnicne zahteve. cena mora vsebovati vse stroske popuste rabate dostavo montazo in davek na dodano vrednost. izvajalec mora zagotoviti dostavo blaga namestitev montazo s prikljucitvijo na ustrezne prikljucke ki jih pripravi narocnik ter funkcionalni zagon. termin montaze/primopredaje je potrebno uskladiti z narocnikom (kontaktna oseba narocnika klavdija trunki). obveznost dobavitelja je da bo zagotovil brezplacno oz. na lastne stroske potrebno izvedbo edukacije uporabnikov (normalni uporabniski nivo) s strani narocnika za pravilno ter varno uporabo opreme ter njeno nego. ce je za ustrezno pridobitev znanja potrebno opraviti vec locenih edukacij je dobavitelj dolzan vsa ta solanja organizirati v smislu te tocke. ponudbi predlozite prospekte ter drugo dokumentacijo iz katere je razvidno izpolnjevanje tehnicnih zahtev. kontaktna oseba s strani narocnika ; klavdija trunkl uni. dipl.ekon. tel.st. 03 423 35 35 faks st. 03 423 37 56 elektronska posta klavdija.trunkl sb celje.si ponudbe posljite na naslov elektronske poste nabava2 sb celje.si z oznako n parnokonvekcijska pec z dvema kuhalnima komorama 9 2022 do najkasneje 9.2.2022 do 12 ure.", "ner": [{"TenderOrg": "splosna bolnisnica celje"}, {"TenderTel": "(03) 42 33 000"}, {"TenderFax": "(03) 42 33 757"}, {"TenderType": "n"}, {"TenderNumber": "9"}, {"TenderYear": "2022"}, {"TenderCode": "kt/ms"}, {"TenderDeadline": "09.02.2022"}, {"TenderPerson": "klavdija trunkl"}, {"TenderTel": "03 423 35 35"}, {"TenderFax": "03 423 37 56"}], "ner_refine": []}
{"id": "2022_EN_N_009_TENDER", "chunk_id": "1", "input_tokens": 2237, "refiner_input_tokens": 0, "total_output_tokens": 62, "text": "priloga 1. obrazec predracuna (obr 2) 2. izjavna o izpolnjevanju tehnicne specifikacije opreme (obr 3) 3. izjava o zastopstvu (obr 4) 4. obveznost izbranega ponudnika narocnik splosna bolnisnica celje postopek kt/ms obrazec predracuna ponudnik predmet parno konvekcijska pec predracun (oprema vzdrzevanje preventivni pregledi opreme za obdobje 7 let ) obr 2 opis proizvajalec (1) model oz. kolicina (3) v rednost brez ddv (4) kataloska stevilka q) 1. parnokonvekcijska pec z 1 kom dvema kuhalnima komorama 2.v rednost preventivnega vzdrzevanje ter redni letni pregled opreme za obdobje 7 let v rednost opreme v eur brez ddv (1) znesek ddv za opremo v rednost preventivnega vzdrzevanja redni letni pregledi opreme v eur brez ddv (3) narocnik splosna bolnisnica celje znesek ddv v eur za preventivno vzdrzevanje redni letni pregled opreme skupaj vrednost v eur za 142 v eur z ddv datum zig in podpis ponudnik postopek kt/ms obr 4 izjava o izpolnjevanju tehnicne specifikacije opreme ponudnik pod kazensko in materialno odgovornostjo izjavljamo da izpolnjujemo tehnicne zahteve navedene v tem dokumentu da bomo ponudbi predlozili originalne prospekte proizvajalca ter ostalo originalno dokumentacijo proizvajalca iz katere je razvidna oprema ki je predmet ponudbe da bo izpolnjevanje vseh zahtev iz opisa predmeta narocila mora biti razvidno iz originalnih prospektov proizvajalca ter ostale originalne dokumentacije proizvajalca slednje bomo ustrezno oznacili podcrtali in navedli ustrezno zap.st. ki izhaja iz opisa predmeta narocila parno konvekcijska pec v obkrozite ustrezno opomba skladu z naslednjimi tehnicnimi zahtevami da oprema izpolnjuje tehnicne zahteve ne oprema ne izpolnjuje tehnicne zahteve 1. dva locena prostora za da ne pecenje ki delujeta neodvisno drug od drugega 2. kapaciteta ene komore 6x da ne gn 1/1 3. sirina max 550 mm da ne 4. globina max 780 mm da ne 5. visina max 1.815 mm da ne 6. moznost dveh nacinov da ne hkratnega kuhanja 7. upravljanje preko barvnega | da ne zaslona na dotik 8. higienska vrata komore da ne trojno zastekljena 9. integrirana led osvetlitev da ne higienskih vrat kuharske komore 10. 12 nacinov kuhanja da ne e soft uparjanje 30%c do 99c e parni nacin 100c narocnik splosna bolnisnica celje 6 e expres uparjanje 101c do 130c e konvekcija 30c do 300c e combi uparjanje 30c do 250c e popolnost 30%c do 180c nizkotemperaturno kuhanje delta t kuhanje sous vide vlaznost 30c do 220c peka 30c do 220c funkcija pocitka 1 . do 20 programskih korakov | da ne ki jih je mogoce individualno kombinirati 12. prikaz porabe energije da ne 13. v grajena temperaturna da ne sonda za merjenje sredice 14. prikljucna moc 2x7 8 kw da", "ner": [], "ner_refine": []}
{"id": "2022_EN_N_052_TENDER", "chunk_id": "0", "input_tokens": 1853, "refiner_input_tokens": 0, "total_output_tokens": 304, "text": "ci splosna bolnisnica celje oblakova ulica 5 3000 celje tel (03) 42 33 000 fax (8) 4233 757 postopek n 52 2022 sl/ms povabilo k oddaji ponudbe predmet evidencnega narocila kombinirani cistilni stroj za potrebe sb celje vas vabimo k oddaji ponudbe za kombinirani cistilni stroj in sicer za 1kom (opis in tehnicni podatki v prilogd. osnova za realizacijo dobave je prejem pisnega narocila s strani narocnika. ponudbe zbiramo informativno za predlozitev v presojo odobritve. v kolikor bomo prejeli odobritev s strani pristojnih bomo realizacijo izvedli pri najugodnejsemu ponudniku. cena mora vsebovati vse stroske popuste rabate in davek na dodano vrednost. izvajalec mora zagotoviti dostavo blaga v skladisce nabavne sluzbe v delovnem casu za dostavo oz. prevzem blaga (od ponedeljka do petka od 6 00 do 14 00 ure). rok za placilo je 60 dni od prejema racuna. merilo za izbor najnizja vrednost ponudbe v eur z ddv ob izpolnjevanju tehnicnih zahtev narocnika. kontaktna oseba s strani narocnika sandi luzar dipl. ing. log. (un) tel.st. 03 423 35 34 faks st. 03 423 37 56 elektronska posta sandi.luzar sb celje.si stane mulej dipl.ekon. tel.st. 03 423 31 45 elektronska posta stane.mulej() sb celje.si ponudbe posljite na naslov elektronske poste nabava2(0 sb celje.si z oznako n 52 kombinirani cistilni stroj 22 do najkasneje 27.06.2022 do bure narocnik splosna bolnisnica celje 2 vodja nabavne sluzbe matjaz stinek univ.dipl.ekon. postopek ms/ms", "ner": [{"TenderOrg": "splosna bolnisnica celje"}, {"TenderTel": "(03) 42 33 000"}, {"TenderFax": "(8) 4233 757"}, {"TenderNumber": "52"}, {"TenderYear": "2022"}, {"TenderCode": "sl/ms"}, {"TenderPerson": "sandi luzar"}, {"TenderTel": "03 423 35 34"}, {"TenderFax": "03 423 37 56"}, {"TenderPerson": "stane mulej"}, {"TenderTel": "03 423 31 45"}, {"TenderDeadline": "27.06.2022"}, {"TenderPerson": "matjaz stinek"}, {"TenderType": "n"}], "ner_refine": []}
{"id": "2022_EN_N_092_TENDER", "chunk_id": "0", "input_tokens": 2006, "refiner_input_tokens": 0, "total_output_tokens": 235, "text": "cl splosna bolnisnica celje oblakova ulica 5 3000 celje tel (03) 42 33 000 postopek n 92 2022 sl/ms povabilo k oddaji ponudbe vabimo vas k oddaji ponudbe za predmet kasetni in vrecasti filtri zahteve in pogoji za dobavo kasetnih in vrecastih filtrov 1. kasete in vrece morajo biti mersko skladne s podano specifikacijo v obrazcu predracuna. 2. filterski materiali kasetnih in vrecastih filtrov morajo ustrezati zahtevani kakovosti oziroma filtrirmemu razredu ter stopnji propustnosti. 3. kasete in filtri morajo biti kot celota kompaktni in kvalitetno izdelani. 4. kasetni filtri z robom 25 mm morajo biti kvalitetno okvirjeni! da ne pride do izpadanja filterskih materialov. 5. vrece morajo biti kvalitetno izdelane z okvirji sirokimi 2 cm kjerje to zahtevano. 6. ponudnik mora ponuditi vse razpisane artikle skladno z zahtevano kolicino in kvaliteto in dimenzijami. 7 v si artikli morajo biti ob dobavi ustrezno deklarirani in oznaceni. 8. kasetni in vrecasti filtri morajo biti ob dobavi pakirani in vidno''oznaceni po posameznih klimatsko prezracevalnih napravah kot je razvidno iz prilozene specifikacije popisa po prilozeni specifikaciji. 9. ponudnik zagotavlja dostavo fco. splosna bolnisnica celje. 10. ponudnik mora na zeljo narocnika predloziti vzorce posameznih artiklov. 11. ponudba mora vkljucevati vse stroske popuste vkljucno s prevzemom in odvozom izrabljenih filterskih materialov |! rok za placilo je 60 dni od prejema racuna. merilo za izbora najnizja vrednost ponudbe v eur z ddv ob izpolnjevanju tehnicnih zahtev narocnika. predviden rok realizacije konec novembra 2022 narocnik splosna bolnisnica celje kontaktna oseba s strani narocnika sandi luzar dipl. ing. log. (un) tel.st. 03 423 35 34 faks st. 03 423 37 56 elektronska posta sandi.luzar sb celje.si ponudbe posljite na naslov elektronske poste nabava2 sb celje.si z oznako n 92 kasetni in vreeasti filtri 2022 do najkasneje 26.10.2022 do 12 ure . vodja nabavne sluzbe matjaz stinek univ.dipl.ekon. postopek sl/ms", "ner": [{"TenderOrg": "splosna bolnisnica celje"}, {"TenderTel": "(03) 42 33 000"}, {"TenderNumber": "92"}, {"TenderYear": "2022"}, {"TenderCode": "sl/ms"}, {"TenderType": "n"}, {"TenderPerson": "sandi luzar"}, {"TenderTel": "03 423 35 34"}, {"TenderFax": "03 423 37 56"}, {"TenderDeadline": "26.10.2022"}, {"TenderPerson": "matjaz stinek"}], "ner_refine": []}
{"id": "2022_EN_N_035_TENDER", "chunk_id": "0", "input_tokens": 2012, "refiner_input_tokens": 0, "total_output_tokens": 235, "text": "cl splosna bolnisnica celje oblakova ulica 5 3000 celje tel (03) 42 33 000 postopek n 35 2022 sl/ms povabilo k oddaji ponudbe vabimo vas k oddaji ponudbe za predmet kasetni in vrecasti filtri zahteve in pogoji za dobavo kasetnih in vrecastih filtrov 1. kasete in vrece morajo biti mersko skladne s podano specifikacijo v obracu predracuna. 2. filterski materiali kasetnih in vrecastih filtrov morajo ustrezati zahtevani kakovosti oziroma filtrirmemu razredu ter stopnji propustnosti. 3. kasete in filtri morajo biti kot celota kompaktni in kvalitetno izdelani. 4. kasetni filtri z robom 25 mm morajo biti kvalitetno okvirjeni! da ne pride do izpadanja filterskih materialov. 3. vrece morajo biti kvalitetno izdelane z okvirji sirokimi 2 cm kjerje to zahtevano. 6. ponudnik mora ponuditi vse razpisane artikle skladno z zahtevano kolicino in kvaliteto in dimenzijami. 7. vsi artikli morajo biti ob dobavi ustrezno deklarirani in oznaceni. 8. kasetni in vrecasti filtri morajo biti ob dobavi pakirani in vidno\"\"oznaceni po posameznih klimatsko prezracevalnih napravah kot je razvidno iz prilozene specifikacije popisa po prilozeni specifikaciji. 9. ponudnik zagotavlja dostavo fco. splosna bolnisnica celje. 10. ponudnik mora na zeljo narocnika predloziti vzorce posameznih artiklov. 11. ponudba mora vkljucevati vse stroske popuste vkljucno z prevzemom in odvozom izrabljenih filterskih materialov !! rok za placilo je 60 dni od prejema racuna. merilo za izbora najnizja vrednost ponudbe v eur z ddv ob izpolnjevanju tehnicnih zahtev narocnika. predviden rok realizacije 18.05.2022 narocnik splosna bolnisnica celje 2 kontaktna oseba s strani narocnika sandi luzar dipl. ing. log. (un) tel.st. 03 423 35 34 faks st. 03 423 37 56 elektronska posta sandi.luzar sb celje.si ponudbe posljite na naslov elektronske poste nabava2(0 sb celje.si z oznako n 35 2022 kasetni in vrecasti filtri do najkasneje 22.04.2022 do 12 ure. vodja nabavne sluzbe matjaz stinek univ.dipl.ekon. postopek sl/ms", "ner": [{"TenderOrg": "splosna bolnisnica celje"}, {"TenderTel": "(03) 42 33 000"}, {"TenderNumber": "35"}, {"TenderYear": "2022"}, {"TenderCode": "sl/ms"}, {"TenderDeadline": "22.04.2022"}, {"TenderPerson": "sandi luzar"}, {"TenderTel": "03 423 35 34"}, {"TenderFax": "03 423 37 56"}, {"TenderPerson": "matjaz stinek"}, {"TenderType": "n"}], "ner_refine": []}
{"id": "2022_EN_N_044_TENDER", "chunk_id": "0", "input_tokens": 2034, "refiner_input_tokens": 0, "total_output_tokens": 236, "text": "ci splosna bolnisnica celje oblakova ulica 5 3000 celje tel (03) 42 33 000 fax (8) 4233 757 postopek n 44 2022 sl/ms povabilo k oddaji ponudbe predmet evidencnega narocila krmilnik unitronics z hmi panelom (model us7 b10 ra28) za potrebe sb celje vas vabimo k oddaji ponudbe za krmilnik z hmi panelom (unitronics unistream 7\" hmi pro panel us7 b10 ra28) (potrebujemo 1 kom) kateri ima naslednje specifikacije 7\" barvni zaslon na dotik 800x 480 razsiritev do 2048 vhodno izhodnih signalov predvajanje mpeg 4 gif pdf datotek a udio web server sol client grafi pid podatkovne tabele data sampling dragadrop interface udeb kreiranje uporabniskih blokov za nadaljnjo uporabo rs485% ca nopen\" unican modbus ip/rtu ethernetip oddaljen dostop preko pc ja tablice pametnega telefona ipd. 14di 2 hsc 2 al 0 10v/0 20ma 12 bitni 2a pt100/1000 ni 100/1000 8ro 2a 0 0 10v/0 20ma /4 20ma navodila za uporabo v slo rok dobave 3 delovne dni od dneva narocila. narocnik splosna bolnisnica celje 2 osnova za realizacijo dobave je prejem pisnega narocila s strani narocnika. ponudbe zbiramo informativno za predlozitev v presojo odobritve. v kolikor bomo prejeli odobritev s strani pristojnih bomo realizacijo izvedli pri najugodnejsemu ponudniku. cena mora vsebovati vse stroske popuste rabate in davek na dodano vrednost. izvajalec mora zagotoviti dostavo blaga v skladisce nabavne sluzbe v delovnem casu za dostavo oz. prevzem blaga (od ponedeljka do petka od 6 00 do 14 00 ure). rok za placilo je 60 dni od prejema racuna. merilo za izbor najnizja vrednost ponudbe v eur z ddv ob izpolnjevanju tehnicnih zahtev narocnika. kontaktna oseba s strani narocnika ; sandi luzar dipl. ing. log. (un) tel.st. 03 423 35 34 faks st. 03 423 37 56 elektronska posta sandi.luzar sb celje.si ponudbe posljite na naslov elektronske poste nabava2 sb celje.si vodja nabavne sluzbe matjaz stinek univ.dipl.ekon. postopek sl/ms", "ner": [{"TenderOrg": "splosna bolnisnica celje"}, {"TenderTel": "(03) 42 33 000"}, {"TenderFax": "(8) 4233 757"}, {"TenderNumber": "44"}, {"TenderYear": "2022"}, {"TenderCode": "sl/ms"}, {"TenderPerson": "sandi luzar"}, {"TenderTel": "03 423 35 34"}, {"TenderFax": "03 423 37 56"}, {"TenderPerson": "matjaz stinek"}, {"TenderType": "n"}], "ner_refine": []}
{"id": "2022_EN_N_047_TENDER", "chunk_id": "0", "input_tokens": 1859, "refiner_input_tokens": 0, "total_output_tokens": 282, "text": "ci splosna bolnisnica celje oblakova ulica 5 3000 celje tel (03) 42 33 000 fax (03) 42 33 757 postopek n 47 2022 sl/ms povabilo k oddaji ponudbe predmet evidencnega narocila les mizarski za potrebe sb celje vas vabimo k oddaji ponudbe za les miza rski kot sledi v opisu naziv artikla m/3 1 ; lessmreka debelina 5 cm robljeno 1 2 | les hrast debelina 5 cm nerobljeno 0 5 zahteve suseno (7 10% ) prva klasa. osnova za realizacijo dobave je prejem pisnega narocila s strani narocnika. ponudbe zbiramo informativno za predlozitev v presojo odobritve. v kolikor bomo prejeli odobritev s strani pristojnih bomo realizacijo izvedli pri najugodnejsemu ponudniku. cena mora vsebovati vse stroske popuste rabate in davek na dodano vrednost. izvajalec mora zagotoviti dostavo blaga v skladisce nabavne sluzbe v delovnem casu za dostavo oz. prevzem blaga (od ponedeljka do petka od 6 00 do 14 00 ure). rok za placilo je 60 dni od prejema racuna. merilo za izbor najnizja vrednost ponudbe v eur z ddv ob izpolnjevanju tehnicnih zahtev narocnika. narocnik splosna bolnisnica celje 2 kontaktna oseba s strani narocnika ; sandi luzar dipl. ing. log. (un) tel.st. 03 423 35 34 faks st. 03 423 37 56 elektronska posta sandi luzan0 sb celje.si stane mulej dipl.ekon. tel.st. 03 423 31 45 elektronska posta stane.mulej() sb celje.si ponudbe posljite na naslov elektronske poste nabava2(0 sb celje.si vodja nabavne sluzbe matjaz stinek univ.dipl.ekon. postopek ms/ms", "ner": [{"TenderOrg": "splosna bolnisnica celje"}, {"TenderTel": "(03) 42 33 000"}, {"TenderFax": "(03) 42 33 757"}, {"TenderNumber": "47"}, {"TenderYear": "2022"}, {"TenderCode": "sl/ms"}, {"TenderPerson": "sandi luzar"}, {"TenderTel": "03 423 35 34"}, {"TenderFax": "03 423 37 56"}, {"TenderPerson": "stane mulej"}, {"TenderTel": "03 423 31 45"}, {"TenderPerson": "matjaz stinek"}, {"TenderType": "n"}], "ner_refine": []}
{"id": "2022_EN_N_060_TENDER", "chunk_id": "0", "input_tokens": 1884, "refiner_input_tokens": 0, "total_output_tokens": 244, "text": "splosna bolnisnica celje oblakova ulica 5 3000 celje tel (03) 42 33 000 fax (03) 42 33 757 postopek n 60 2022 kt/ms povabilo k oddaj i ponudbe v abimo vas k oddaji ponudbe za predmet potrosni material za likalno linijo t igla 026.797/1 300 kom filc molton 3 6 x 5 7m 900g/m 3kom ponudnik mora ponuditi vse artikle. osnova za realizacijo dobave je prejem pisnega narocila s strani narocnika. ponudbe zbiramo informativno za predlozitev v presojo odobritve. v kolikor bomo prejeli odobritev s strani pristojnih bomo realizacijo izvedli pri najugodnejsemu ponudniku. cena mora vsebovati vse stroske popuste rabate in davek na dodano vrednost. v ceni mora biti zajeta kompletna dobava in montaza ter vsi zakljucki. izvajalec mora zagotoviti dostavo blaga ter montazo in namestitev v prostor pri narocniku v delovnem casu za dostavo oz. prevzem blaga (od ponedeljka do petka od 6 00 do 14 ure). za termin montaze se je potrebno dogovoriti z narocnikom (kontaktna oseba narocnika klavdija trunkl) rok za placilo je 60 dni od prejema racuna. merilo izbora najnizja vrednost ponudbe v eur z ddv ob izpolnjevanju tehnicnih zahtev narocnika. narocnik splosna bolnisnica celje 2 kontaktna oseba s strani narocnika klavdija trunkl uni.dipl.ekon. tel.st. 03 423 35 35 faks st. 03 423 37 56 elektronska posta klavdija.trunkl sb celje.si ponudbe posljite na naslov elektronske poste nabava2 sb celje.si z oznako n 60 2022 potrosni material za likalno linijo do najkasneje 20.07.2022 do ture vodja nabavne sluzbe matjaz stinek univ.dipl.ekon. postopek kt/ms", "ner": [{"TenderOrg": "splosna bolnisnica celje"}, {"TenderTel": "(03) 42 33 000"}, {"TenderFax": "(03) 42 33 757"}, {"TenderType": "n"}, {"TenderNumber": "60"}, {"TenderYear": "2022"}, {"TenderCode": "kt/ms"}, {"TenderDeadline": "20.07.2022"}, {"TenderPerson": "matjaz stinek"}, {"TenderTel": "03 423 35 35"}, {"TenderFax": "03 423 37 56"}], "ner_refine": []}
{"id": "2022_EN_N_106_TENDER", "chunk_id": "0", "input_tokens": 1847, "refiner_input_tokens": 0, "total_output_tokens": 263, "text": "splosna bolnisnica celje oblakova ulica 5 3000 celje tel (03) 42 33000 fax (03) 42 33 757 postopek n 106 2022 kt/ms povabilo k oddaj i ponudbe vabimo vas k oddaji ponudbe za predmet nastavki za palicni mesalnik nastavek za mesanje master mixer tool m ac500 nastavek | 1 kom za mesanje s palicnim mesalcem dynamic serije master dolzine 500 mm emulgacijski nastavek blender master aco70 za palicni 1 kom mesalec dynamic serije master. 410 mm nastavek za pire ricer/mash potato tool ac004 za palitni | 1 kom mesalec dynamic serije master. 420 mm garancija 12 mesecev pomudba naj vsebuje vse navedene pozicije. osnova za realizacijo dobave je prejem pisnega narocila strani narocnika. ponudbe zbiramo informativno za predlozitev v presojo odobritve. v kolikor bomo prejeli odobritev s strani pristojnih bomo realizacijo izvedli pri najugodnejsemu ponudniku. cena mora vsebovati vse stroske popuste rabate in davek na dodano vrednost. rok za placilo je 60 dni od prejema racuna. merilo za izbora najnizja vrednost ponudbe v eur z ddv ob izpolnjevanju tehnicnih zahtev narocnika. kontaktna oseba s strani narocnika ; klavdija trunkl uni. dipl.ekon. tel.st. 03 423 35 35 faks st. 03 423 37 56 elektronska posta klavdija.trunkl sb celje.si ponudbe posljite na naslov elektronske poste nabava2 sb celje.si z oznako n 106 nastavki za palicni mesalec 2022 do najkasneje 6.2.2022 do 2. wre. vodja nabavne sluzbe matjaz stinek univ.dipl.ekon. narocnik splosna bolnisnica celje postopek kt/ms", "ner": [{"TenderOrg": "splosna bolnisnica celje"}, {"TenderTel": "(03) 42 33000"}, {"TenderFax": "(03) 42 33 757"}, {"TenderType": "n"}, {"TenderNumber": "106"}, {"TenderYear": "2022"}, {"TenderCode": "kt/ms"}, {"TenderDeadline": "06.02.2022"}, {"TenderPerson": "klavdija trunkl"}, {"TenderTel": "03 423 35 35"}, {"TenderFax": "03 423 37 56"}, {"TenderPerson": "matjaz stinek"}], "ner_refine": []}
{"id": "2022_EN_N_079_TENDER", "chunk_id": "0", "input_tokens": 1822, "refiner_input_tokens": 0, "total_output_tokens": 262, "text": "splosna bolnisnica celje oblakova ulica 5 3000 celje tel (03) 42 33 000 fax (03) 42 33 757 postopek n 79 2022 sl/ms povabilo k oddaj i ponudbe v abimo vas k oddaji ponudbe za predmet potrosni material za likalno linijo t igla 026.797/1 300 kom filc molton 3 6 x 5 7m 900g/m 3kom. ponudnik mora ponuditi vse artikle. osnova za realizacijo dobave je prejem pisnega narocila s strani narocnika. ponudbe zbiramo informativno za predlozitev v presojo odobritve. v kolikor bomo prejeli odobritev s strani pristojnih bomo realizacijo izvedli pri najugodnejsemu ponudniku. cena mora vsebovati vse stroske popuste rabate in davek na dodano vrednost. v ceni mora biti zajeta kompletna dobava. izvajalec mora zagotoviti dostavo blaga v delovnem casu za dostavo oz. prevzem blaga (od ponedeljka do petka od 6 00 do 14 00 ure). rok za placilo je 60 dni od prejema racuna. merilo izbora najnizja vrednost ponudbe v eur z ddv ob izpolnjevanju tehnicnih zahtev narocnika. kontaktna oseba s strani narocnika sandi luzar dipl ing. log. (un) tel.st. 03 423 35 34 faks st. 03 423 37 56 elektronska posta sandi luzar0 sb celje.si ponudbe posljite na naslov elektronske poste nabava2(0 sb celje.si z oznako n 79 potrosni material za likalno linijo 222 do najkasneje 27.09.2022 do 12.ure vodja nabavne sluzbe matjaz stinek univ.dipl.ekon.", "ner": [{"TenderOrg": "splosna bolnisnica celje"}, {"TenderTel": "(03) 42 33 000"}, {"TenderFax": "(03) 42 33 757"}, {"TenderType": "n"}, {"TenderNumber": "79"}, {"TenderYear": "2022"}, {"TenderCode": "sl/ms"}, {"TenderTel": "03 423 35 34"}, {"TenderFax": "03 423 37 56"}, {"TenderPerson": "sandi luzar"}, {"TenderDeadline": "27.09.2022"}, {"TenderPerson": "matjaz stinek"}], "ner_refine": []}
{"id": "2022_EN_N_109_TENDER", "chunk_id": "0", "input_tokens": 2091, "refiner_input_tokens": 0, "total_output_tokens": 263, "text": "splosna bolnisnica celje oblakova ulica 5 3000 celje tel (03) 42 33000 fax (03) 42 33 757 postopek n 109 kt/ms povabilo k oddaj i ponudbe vabimo vas k oddaji ponudbe za predmet hladilna omara 1 kom v sestavu in opisu kot sledi v nadaljevanju dimenzije cca 70 x 80 x 200 cm (sxgxv) prostornina cca. 700 litrov temperaturno obmocje 2'/ 8' c enojna vrata po visini nastavljive nogice elektronsko upravljanje avtomatsko odtajanje iz nerjavece plocevine kompresor in izmenjevalec toplote namescen na zgornji strani hladilnika wondhrpwne splosne zahteve 1. ponudbi predlozite prospekte ter drugo dokumentacijo iz katere je razvidno izpolnjevanje tehnicnih zahtev. 2. obvezna spremna dokumentacija ob dobavi opreme je prevod navodil v slovenskem jeziku originalno navodilo za uporabo (user book) ce oznacba po moznosti pritrjena tudi na opremo. kontakt pooblascenega serviserja garancija najmanj 12 mesecev osnova za realizacijo dobave je prejem pisnega narocila strani narocnika. ponudbe zbiramo informativno za predlozitev v presojo odobritve. v kolikor bomo prejeli odobritev s strani pristojnih bomo realizacijo izvedli pri najugodnejsemu ponudniku. narocnik je v specifikacijah zahtev navedel tip opreme izkljucno z namenom da se doloci zahtevana raven kakovosti. v ponudbi lahko ponudite tudi opremo drugih proizvajalcev vendar mora biti le ta tehnicno najmanj enakovredna opremi navedeni v specifikaciji zahtev narocnika. narocnik splosna bolnisnica celje 2 cena mora vsebovati vse stroske popuste rabate in davek na dodano vrednost. izvajalec mora zagotoviti dostavo blaga skladisce nabavne sluzbe v delovnem casu za dostavo oz. prevzem blaga (od ponedeljka do petka od 6 00 do 14 ure). rok za placilo je 60 dni od prejema racuna. merilo za izbora najnizja vrednost ponudbe v eur z ddv ob izpolnjevanju tehnicnih zahtev narocnika. kontaktna oseba s strani narocnika ; klavdija trunkl uni. dipl.ekon. tel.st. 03 423 35 35 faks st. 03 423 37 56 elektronska posta klavdija.trunkl sb celje.si ponudbe posljite na naslov elektronske poste nabava2 sb celje.si z oznako n 109 hladilna omara 2022 do najkasneje 6.12.2022 do 12 ure. vodja nabavne sluzbe matjaz stinek univ.dipl.ekon postopek kt/ms narocnik splosna bolnisnica celje postopek kt/ms", "ner": [{"TenderOrg": "splosna bolnisnica celje"}, {"TenderTel": "(03) 42 33000"}, {"TenderFax": "(03) 42 33 757"}, {"TenderType": "n"}, {"TenderNumber": "109"}, {"TenderCode": "kt/ms"}, {"TenderDeadline": "06.12.2022"}, {"TenderPerson": "klavdija trunkl"}, {"TenderTel": "03 423 35 35"}, {"TenderFax": "03 423 37 56"}, {"TenderPerson": "matjaz stinek"}, {"TenderYear": "2022"}], "ner_refine": []}
{"id": "2022_EN_N_026_TENDER", "chunk_id": "0", "input_tokens": 1834, "refiner_input_tokens": 0, "total_output_tokens": 261, "text": "splosna bolnisnica celje oblakova ulica 5 3000 celje tel (03) 42 33000 fax (03) 42 33 757 postopek n 26 2022 kt/ms povabilo k oddaj i ponudbe vabimo vas k oddaji ponudbe za predmet ogrevani vozicek za gn posode bain marie na premicnem podstavku spodnja polica 2 kolesi z moznostjo fiksiranja kapaciteta 4 x gn 1/1 20 cm prikljucek 230 v / 2 8kw mere 65 x 170 x 90 cm (sxgxv) osnova za realizacijo dobave je prejem pisnega narocila strani narocnika. ponudbe zbiramo informativno za predlozitev v presojo odobritve. v kolikor bomo prejeli odobritev s strani pristojnih bomo realizacijo izvedli pri najugodnejsemu ponudniku. cena mora vsebovati vse stroske popuste rabate in davek na dodano vrednost. izvajalec mora zagotoviti dostavo blaga skladisce nabavne sluzbe v delovnem casu za dostavo oz. prevzem blaga (od ponedeljka do petka od 6 00 do 14 ure). rok za placilo je 60 dni od prejema racuna. merilo za izbora najnizja vrednost ponudbe v eur z ddv ob izpolnjevanju tehnicnih zahtev narocnika. kontaktna oseba s strani narocnika ; klavdija trunkl uni. dipl.ekon. tel.st. 03 423 35 35 faks st. 03 423 37 56 elektronska posta klavdija.trunkl sb celje.si ponudbe posljite na naslov elektronske poste nabava2 sb celje.si z oznako n 26 ogrevani vozicek za gn posode bain marie 2022 do najkasneje 25.3.2022 do 12 ure vodja nabavne sluzbe matjaz stinek univ.dipl.ekon.", "ner": [{"TenderOrg": "splosna bolnisnica celje"}, {"TenderTel": "(03) 42 33000"}, {"TenderFax": "(03) 42 33 757"}, {"TenderType": "n"}, {"TenderNumber": "26"}, {"TenderYear": "2022"}, {"TenderCode": "kt/ms"}, {"TenderPerson": "klavdija trunkl"}, {"TenderTel": "03 423 35 35"}, {"TenderFax": "03 423 37 56"}, {"TenderDeadline": "25.3.2022"}, {"TenderPerson": "matjaz stinek"}], "ner_refine": []}
{"id": "2022_EN_N_049_TENDER", "chunk_id": "0", "input_tokens": 1965, "refiner_input_tokens": 0, "total_output_tokens": 239, "text": "splosna bolnisnica celje oblakova ulica 5 3000 celje tel (03) 42 33000 fax ((b) 2 33 57 postopek n 49 2022 sl/ms povabilo k oddaj i ponudbe predmet evidencnega narocila mesoreznica miska22 za potrebe sb celje vas vabimo k oddaji ponudbe za mesoreznica miska 22 in sicer za 1 kom katera ustreza naslednjemu opisu motor 230/380 v moc 1500w (2 km) kapaciteta mletja do 300 kg na uro masa 38 kg zobniski prenos moci reduktor samobrusni sistem nozev enterprice zunanje mere; d440 x s200 x v 480 mm globina pulta min. 370 mm ohisje ulito iz aluminija in obleceno v inox mlevna glava iz inox a snemljiva opcija; nadomestno sito 22 ( h/82 ) nadomestni noz 22 ( h/82 ) narocnik splosna bolnisnica celje 2 osnova za realizacijo dobave je prejem pisnega narocila s strani narocnika. ponudbe zbiramo informativno za predlozitev v presojo odobritve. v kolikor bomo prejeli odobritev s strani pristojnih bomo realizacijo izvedli pri najugodnejsemu ponudniku. cena mora vsebovati vse stroske popuste rabate in davek na dodano vrednost. izvajalec mora zagotoviti dostavo blaga v skladisce nabavne sluzbe v delovnem casu za dostavo oz. prevzem blaga (od ponedeljka do petka od 6 00 do 14 00 ure). rok za placilo je 60 dni od prejema racuna. merilo za izbor najnizja vrednost ponudbe v eur z ddv ob izpolnjevanju tehnicnih zahtev narocnika. kontaktna oseba s strani narocnika ; sandi luzar dipl. ing. log. (un) tel.st. 03 423 35 34 faks st. 03 423 37 56 elektronska posta sandi.luzar sb celje.si ponudbe posljite na naslov elektronske poste nabava2(0 sb celje.si z oznako n 49 mesoreznica miska22 2(22 do najkasneje 16.06.2022 do 12 ure . vodja nabavne sluzbe matjaz stinek univ.dipl.ekon. postopek kt/ms", "ner": [{"TenderOrg": "splosna bolnisnica celje"}, {"TenderTel": "(03) 42 33000"}, {"TenderFax": "(03) 42 33"}, {"TenderNumber": "49"}, {"TenderYear": "2022"}, {"TenderCode": "sl/ms"}, {"TenderTel": "03 423 35 34"}, {"TenderFax": "03 423 37 56"}, {"TenderDeadline": "16.06.2022"}, {"TenderPerson": "matjaz stinek"}, {"TenderType": "n"}], "ner_refine": []}
{"id": "2022_EN_N_030_TENDER", "chunk_id": "0", "input_tokens": 1927, "refiner_input_tokens": 0, "total_output_tokens": 278, "text": "splosna bolnisnica celje oblakova ulica 5 3000 celje tel (03) 42 33000 fax (03) 42 33 757 postopek n 30 2022 sl/ms povabilo k oddaj i ponudbe v abimo vas k oddaji ponudbe za predmet potrosni material za likalno linijo ' cistilna krpa zicnata sirina 150 cm 1 kom t igla 026.797/1 300 kom filc molton 3 6x 5 7m 900g/m 3 kom trak vodilni za likalno linijo tip mb/s 80802 10 kom. ponudnik mora ponuditi vse artikle. osnova za realizacijo dobave je prejem pisnega narocila s strani narocnika. ponudbe zbiramo informativno za predlozitev v presojo odobritve. v kolikor bomo prejeli odobritev s strani pristojnih bomo realizacijo izvedli pri najugodnejsemu ponudniku. cena mora vsebovati vse stroske popuste rabate in davek na dodano vrednost. v ceni mora biti zajeta kompletna dobava in montaza ter vsi zakljucki. izvajalec mora zagotoviti dostavo blaga ter montazo in namestitev v prostor pri narocniku v delovnem casu za dostavo oz. prevzem blaga (od ponedeljka do petka od 6 00 do 14 ure). za termin montaze se je potrebno dogovoriti z narocnikom (kontaktna oseba narocnika sandi luzar) rok za placilo je 60 dni od prejema racuna. merilo izbora najnizja vrednost ponudbe v eur z ddv ob izpolnjevanju tehnicnih zahtev narocnika. kontaktna oseba s strani narocnika sandi luzar dipl ing. log. (un) tel.st. 03 423 35 34 faks st. 03 423 37 56 elektronska posta sandi luzar0 sb celje.si narocnik splosna bolnisnica celje 2 ponudbe posljite na naslov elektronske poste nabava2(0 sb celje.si z oznako n 30 2022 potrosni material za likalno linijo do najkasneje 05.04.2022 do ture vodja nabavne sluzbe matjaz stinek univ.dipl.ekon. postopek kt/ms", "ner": [{"TenderOrg": "splosna bolnisnica celje"}, {"TenderTel": "(03) 42 33000"}, {"TenderFax": "(03) 42 33 757"}, {"TenderType": "n"}, {"TenderNumber": "30"}, {"TenderYear": "2022"}, {"TenderCode": "sl/ms"}, {"TenderPerson": "sandi luzar"}, {"TenderTel": "03 423 35 34"}, {"TenderFax": "03 423 37 56"}, {"TenderDeadline": "05.04.2022"}, {"TenderPerson": "matjaz stinek"}, {"TenderCode": "kt/ms"}], "ner_refine": []}
{"id": "2022_EN_N_024_TENDER", "chunk_id": "0", "input_tokens": 1961, "refiner_input_tokens": 0, "total_output_tokens": 236, "text": "ci splosna bolnisnica celje oblakova ulica 5 3000 celje tel (03) 42 33 000 fax (8) 4233 757 postopek n 24 2022 sm/ms povabilo k oddaji ponudbe predmet evidencnega narocila pozivnik za sistem tihega alarmiranja za ekipe nmp za potrebe sb celje vas vabimo k oddaji ponudbe za pozivnik za sistem tihega alarmiranja za ekipe nmp pager swissphone s.ouad x15 kateri ima naslednje specifikacije 16 naslovov (ric) s stirimi podnaslovi graficno dodelan visokolocljivostni zaslon za do 200 karakterjev na stran povezava z drugimi napravami prek povezave bluetooth integriran rfid cip izjemen sprejem z 2.5 uv/m pri 1 200 bit/s zelo glasen; glasnost 95 db(a) na razdalji 30 cm ekstremno robusten (2 m testni padec) slovenski jezik vodoodporen in prahoodporen po standardu ip67 teza 108g dimenzije 81 x 64x 22 mm rok dobave 3 delovne dni od dneva narocila. osnova za realizacijo dobave je prejem pisnega narocila s strani narocnika. ponudbe zbiramo informativno za predlozitev v presojo odobritve. v kolikor bomo prejeli odobritev s strani pristojnih bomo realizacijo izvedli pri najugodnejsemu ponudniku. narocnik splosna bolnisnica celje 2 cena mora vsebovati vse stroske popuste rabate in davek na dodano vrednost. izvajalec mora zagotoviti dostavo blaga v skladisce nabavne sluzbe v delovnem casu za dostavo oz. prevzem blaga (od ponedeljka do petka od 6 00 do 14 00 ure). rok za placilo je 60 dni od prejema racuna. merilo za izbor najnizja vrednost ponudbe v eur z ddv ob izpolnjevanju tehnicnih zahtev narocnika. kontaktna oseba s strani narocnika ; sandi luzar dipl. ing. log. (un) tel.st. 03 423 35 34 faks st. 03 423 37 56 elektronska posta sandi.luzar sb celje.si ponudbe posljite na naslov elektronske poste nabava2 sb celje.si vodja nabavne sluzbe matjaz stinek univ.dipl.ekon. postopek ms/ms", "ner": [{"TenderOrg": "splosna bolnisnica celje"}, {"TenderTel": "(03) 42 33 000"}, {"TenderFax": "(8) 4233 757"}, {"TenderNumber": "24"}, {"TenderYear": "2022"}, {"TenderCode": "sm/ms"}, {"TenderPerson": "sandi luzar"}, {"TenderTel": "03 423 35 34"}, {"TenderFax": "03 423 37 56"}, {"TenderPerson": "matjaz stinek"}, {"TenderType": "n"}], "ner_refine": []}
{"id": "2022_EN_N_095_TENDER", "chunk_id": "0", "input_tokens": 1921, "refiner_input_tokens": 0, "total_output_tokens": 314, "text": "splosna bolnisnica celje oblakova ulica 5 3000 celje tel (03) 42 33 000 fax (03) 42 33 757 postopek n 95 2022 sl/ ms povabilo k oddaji ponudbe vabimo vas k oddaji ponudbe za predmet tokovne klesce a1502 v sebina narocila mini fleksibilne tokovne klesce a1502 4 kom specifikacije 1 fazne mini fleksibilne tokovne klesce oznake a 1502 3000/300/30 a /1v dolzina senzorja 48 cm. osnova za realizacijo dobave je prejem pisnega narocila s strani narocnika. ponudbe zbiramo informativno za predlozitev v presojo odobritve. v kolikor bomo prejeli odobritev s strani pristojnih bomo realizacijo izvedli pri najugodnejsemu ponudniku. cena mora vsebovati vse stroske popuste rabate in davek na dodano vrednost. izvajalec mora zagotoviti dostavo blaga v skladisce nabavne sluzbe v delovnem casu za dostavo oz. prevzem blaga (od ponedeljka do petka od 6 00 do 14 00 ure). rok za placilo je 60 dni od prejema racuna. merilo za izbora najnizja vrednost ponudbe v eur z ddv ob izpolnjevanju tehnicnih zahtev narocnika. narocnik splosna bolnisnica celje kontaktna oseba s strani narocnika matjaz stinek uni. dipl.ekon. tel.st. 03 423 30 76 faks st. 03 423 37 56 elektronska posta matjaz.stinek sb celje.si sandi luzar dipl. ing. log. (un) tel.st. 03 423 35 34 faks st. 03 423 37 56 elektronska posta sandi.luzar sb celje.si ponudbe posljite na naslov elektronske poste nabava2(0 sb celje.si z oznako n 95 tokovne klesce a1502 2022 do najkasneje 07.11.2022 do 12 ure . vodja nabavne sluzbe matjaz stinek univ.dipl.ekon. postopek sl/ms", "ner": [{"TenderOrg": "splosna bolnisnica celje"}, {"TenderTel": "(03) 42 33 000"}, {"TenderFax": "(03) 42 33 757"}, {"TenderType": "n"}, {"TenderNumber": "95"}, {"TenderYear": "2022"}, {"TenderCode": "sl/ms"}, {"TenderDeadline": "07.11.2022"}, {"TenderPerson": "matjaz stinek"}, {"TenderTel": "03 423 30 76"}, {"TenderFax": "03 423 37 56"}, {"TenderPerson": "sandi luzar"}, {"TenderTel": "03 423 35 34"}], "ner_refine": []}
{"id": "2022_EN_N_042_TENDER", "chunk_id": "0", "input_tokens": 1907, "refiner_input_tokens": 0, "total_output_tokens": 253, "text": "ci splosna bolnisnica celje oblakova ulica 5 3000 celje tel (03) 42 33 000 fax (8) 4233 757 postopek n 42 2022 sl/ms povabilo k oddaji ponudbe predmet evidencnega narocila knauf gradbeni material 4 potrosni material za potrebe sb celje vas vabimo k oddaji ponudbe za knauf gradbeni material potrosni material . potrebujemo torej sledece gibs plosca 1250 x 2000 x 12.5 mm 50 kom uw profil za stene 75 x 40x 0 6 10kom cw profil za stene pokoncni 75 x 40x 0 6 42 kom samovrezni vijak tn25 3000 kom univerzalni zidni vlozek z vijakom 6x 40 100 kom volna steklena v roli 48m rok dobave 3 delovne dni od dneva narocila. osnova za realizacijo dobave je prejem pisnega narocila s strani narocnika. ponudbe zbiramo informativno za predlozitev v presojo odobritve. v kolikor bomo prejeli odobritev s strani pristojnih bomo realizacijo izvedli pri najugodnejsemu ponudniku. cena mora vsebovati vse stroske popuste rabate in davek na dodano vrednost. izvajalec mora zagotoviti dostavo blaga v skladisce nabavne sluzbe v delovnem casu za dostavo oz. prevzem blaga (od ponedeljka do petka od 6 00 do 14 00 ure). rok za placilo je 60 dni od prejema racuna. narocnik splosna bolnisnica celje 2 merilo za izbor najnizja vrednost ponudbe v eur z ddv ob izpolnjevanju tehnicnih zahtev narocnika. kontaktna oseba s strani narocnika ; sandi luzar dipl. ing. log. (un) tel.st. 03 423 35 34 faks st. 03 423 37 56 elektronska posta sandi.luzar sb celje.si ponudbe posljite na naslov elektronske poste nabava2 sb celje.si vodja nabavne sluzbe matjaz stinek univ.dipl.ekon. postopek ms/ms", "ner": [{"TenderOrg": "splosna bolnisnica celje"}, {"TenderTel": "(03) 42 33 000"}, {"TenderFax": "(8) 4233 757"}, {"TenderNumber": "42"}, {"TenderYear": "2022"}, {"TenderCode": "sl/ms"}, {"TenderPerson": "sandi luzar"}, {"TenderTel": "03 423 35 34"}, {"TenderFax": "03 423 37 56"}, {"TenderPerson": "matjaz stinek"}, {"TenderCode": "ms/ms"}, {"TenderType": "n"}], "ner_refine": []}
{"id": "2022_EN_N_045_TENDER", "chunk_id": "0", "input_tokens": 1988, "refiner_input_tokens": 0, "total_output_tokens": 233, "text": "cs splosna bolnisnica celje oblakova ulica 5 3000 celje tel (03) 42 33000 fax (b 4233757 postopek n 45 2022 sl/ms povabilo k oddaji ponudbe predmet evidencnega narocila brusilni stroj femi art. 405 4 namenski podstavek femi art. 303 za potrebe sb celje vas vabimo k oddaji ponudbe za brusilni stroj femi art. 405 profesionalni dvokolutni 4 namenski podstavek femi art. 303 za brusilni stroj femi art.405 in sicer 1 kom kateri ima naslednje tehnicne lastnosti brusilni stroj femi art. 405 zanesljiv in tih indukcijski motor 1f/500w v kompletu z 2x brusno kolo fi220 2800 obratov/min teza 15kg. narocnik splosna bolnisnica celje 2 namenski podstavek femi art. 303 za brusilni stroj femi art. 405 trden in stabilen podstavek s posodo za vodo za hlajenje orodja dimenzije 370x 370x700 mm rok dobave 3 delovne dni od dneva narocila. osnova za realizacijo dobave je prejem pisnega narocila s strani narocnika. ponudbe zbiramo informativno za predlozitev v presojo odobritve. v kolikor bomo prejeli odobritev s strani pristojnih bomo realizacijo izvedli pri najugodnejsemu ponudniku. cena mora vsebovati vse stroske popuste rabate in davek na dodano vrednost. izvajalec mora zagotoviti dostavo blaga v skladisce nabavne sluzbe v delovnem casu za dostavo oz. prevzem blaga (od ponedeljka do petka od 6 00 do 14 00 ure). rok za placilo je 60 dni od prejema racuna. merilo za izbor najnizja vrednost ponudbe v eur z ddv ob izpolnjevanju tehnicnih zahtev narocnika. postopek ms/ms narocnik splosna bolnisnica celje 3 kontaktna oseba s strani narocnika ; sandi luzar dipl. ing. log. (un) tel.st. 03 423 35 34 faks st. 03 423 37 56 elektronska posta sandi.luzar sb celje.si ponudbe posljite na naslov elektronske poste nabava2 sb celje.si vodja nabavne sluzbe matjaz stinek univ.dipl.ekon. postopek ms/ms", "ner": [{"TenderOrg": "splosna bolnisnica celje"}, {"TenderTel": "(03) 42 33000"}, {"TenderFax": "(b 4233757"}, {"TenderNumber": "45"}, {"TenderYear": "2022"}, {"TenderCode": "sl/ms"}, {"TenderPerson": "sandi luzar"}, {"TenderTel": "03 423 35 34"}, {"TenderFax": "03 423 37 56"}, {"TenderPerson": "matjaz stinek"}, {"TenderType": "n"}], "ner_refine": []}
{"id": "2022_EN_N_004_TENDER", "chunk_id": "0", "input_tokens": 1913, "refiner_input_tokens": 0, "total_output_tokens": 253, "text": "ci splosna bolnisnica celje oblakova ulica 5 3000 celje tel (03) 42 33000 fax (03) 42 33 757 postopek n 4 2022 sm/ms povabilo k oddaji ponudbe predmet evidencnega narocila akumulatorski udarni vrtalnik dewalt dcd 796 p2 za potrebe sb celje vas vabimo k oddaji ponudbe za akumulatorski udarni vrtalnik dewalt dcd 796 p2 kateri ima naslednje tehnicne lastnosti in sicer blagovna znamka dewalt stevilo vrtljajev 2000 vrt/min moc 460 w hitrost 0 550/2000/min tip glave hitrovpenjalna kapaciteta baterije 5ah z indikatorjem napolnjenosti pakiranje kovcek napetost baterije 18 v xr ll ion velikost glave 1 13mm stevilo baterij 2 kom polnilnik hitri xr polnilnik rok dobave 3 delovne dni od dneva narocila. osnova za realizacijo dobave je prejem pisnega narocila s strani narocnika. ponudbe zbiramo informativno za predlozitev v presojo odobritve. v kolikor bomo prejeli odobritev s strani pristojnih bomo realizacijo izvedli pri najugodnejsemu ponudniku. cena mora vsebovati vse stroske popuste rabate in davek na dodano vrednost. izvajalec mora zagotoviti dostavo blaga v skladisce nabavne sluzbe v delovnem casu za dostavo oz. prevzem blaga (od ponedeljka do petka od 6 00 do 14 00 ure). rok za placilo je 60 dni od prejema racuna. narocnik splosna bolnisnica celje 2 merilo za izbor najnizja vrednost ponudbe v eur z ddv ob izpolnjevanju tehnicnih zahtev narocnika. kontaktna oseba s strani narocnika ; stane mulej dipl.ekon. tel.st. 03 423 31 45 faks st. 03 423 37 56 elektronska posta stane.mulej sb celje.si ponudbe posljite na naslov elektronske poste nabava2 sb celje.si vodja nabavne sluzbe matjaz stinek univ.dipl.ekon. postopek ms/ms", "ner": [{"TenderOrg": "splosna bolnisnica celje"}, {"TenderTel": "(03) 42 33000"}, {"TenderFax": "(03) 42 33 757"}, {"TenderNumber": "4"}, {"TenderYear": "2022"}, {"TenderCode": "sm/ms"}, {"TenderType": "n"}, {"TenderPerson": "stane mulej"}, {"TenderTel": "03 423 31 45"}, {"TenderFax": "03 423 37 56"}, {"TenderPerson": "matjaz stinek"}, {"TenderCode": "ms/ms"}], "ner_refine": []}
{"id": "2022_EN_N_005_TENDER", "chunk_id": "0", "input_tokens": 1929, "refiner_input_tokens": 0, "total_output_tokens": 256, "text": "cc splosna bolnisnica celje oblakova ulica 5 3000 celje tel (03) 42 33000 fax (b 4233757 postopek n 5 2022 kt/ms povabilo k oddaj i ponudbe vabimo vas k oddaji ponudbe za predmet kovinska arhivska omara s krilnimi vrati e arhivska omara sps 02 a e dvokrilna vrata e varjena izvedba (dodatna montaza ni potrebna) ( stabilna konstrukcija e zaklepanje z rocajno kljucavnico e prestavljive police e nosilnost police 60 kg e standardna barva svetlo siva zunanje mere (vxsxg mm) 1950 x 800 x 400 police 4 osnova za realizacijo dobave je prejem pisnega narocila strani narocnika. ponudbe zbiramo informativno za predlozitev v presojo odobritve. v kolikor bomo prejeli odobritev s strani pristojnih bomo realizacijo izvedli pri najugodnejsemu ponudniku. cena mora vsebovati vse stroske popuste rabate in davek na dodano vrednost. v ceni mora biti zajeta kompletna dobava in montaza ter vsi zakljucki. izvajalec mora zagotoviti dostavo blaga ter montazo in namestitev v prostor pri narocniku v delovnem casu za dostavo oz. narocnik splosna bolnisnica celje 2 prevzem blaga (od ponedeljka do petka od 6 00 do 14 ure). termin montaze je potrebno dogovoriti z narocnikom (kontaktna oseba narocnika klavdija trunkl) rok za placilo je 60 dni od prejema racuna. merilo za izbora najnizja vrednost ponudbe v eur z ddv ob izpolnjevanju tehnicnih zahtev narocnika. kontaktna oseba s strani narocnika ; klavdija trunkl uni. dipl.ekon. tel.st. 03 423 35 35 faks st. 03 423 37 56 elektronska posta klavdija.trunkl sb celje.si ponudbe posljite na naslov elektronske poste nabava2 sb celje.si z oznako n 5 kovinska arhivska omara 2022 do najkasneje 18.1.2022 do 12 ure vodja nabavne sluzbe matjaz stinek univ.dipl.ekon. postopek kt/ms", "ner": [{"TenderOrg": "splosna bolnisnica celje"}, {"TenderTel": "(03) 42 33000"}, {"TenderFax": "(b 4233757"}, {"TenderNumber": "5"}, {"TenderYear": "2022"}, {"TenderCode": "kt/ms"}, {"TenderDeadline": "18.1.2022"}, {"TenderPerson": "matjaz stinek"}, {"TenderPerson": "klavdija trunkl"}, {"TenderTel": "03 423 35 35"}, {"TenderFax": "03 423 37 56"}, {"TenderType": "n"}], "ner_refine": []}
